Workbook
Name Stock: 'CEK CICI'!$A:$N
Name kirim: '2_Barang MJD'!$A$2:$G$78
Name NamedRange1: 'CEK CICI'!$1:$2800
Name BGI: Sheet23!$A:$U
Name hpp: HAJIKUMEDIUM!$A$1:$C$546
Name Stock: 'Current Stock'!$A:$M
Name Tugas: 'TUGAS DAILY'!$A:$G
Name stockKJD: 'Current Stock'!$A$3:$I$2096
Name StockAll: 'Current Stock'!$A$1:$M$2105
Name Penjualan: PENJUALAN!$A$4:$I$11356
Name StockAll: 'CEK CICI'!$A$1:$N$2075
Name stockKJD: 'CEK CICI'!$A$3:$J$2066
Name NamedRange1: 'Current Stock'!$1:$2833

Sheet Current Stock
A1: 4
A2: Kode Barang | B2: Kode Mobil | C2: Tipe Mobil | D2: Part | E2: Merk | F2: Aksesoris | G2: Masuk | H2: Keluar | I2: Stok Akhir | J2: Rak | K2: SO | L2: Alert | M2: Lain - Lain
A3: =CONCATENATE(B3,E3) -> OTH-SEALANTXYG | B3: OTH-SEALANT | C3: Sealant Polyurethane XYG Tube | D3: OTH | E3: XYG | G3: =SUMIFS(X!$F$5:$F$3100,X!$D$5:$D$3100,'Current Stock'!A3) -> 1067 | H3: =SUMIFS(PENJUALAN!$E$4:$E$11000,PENJUALAN!$C$4:$C$11000,'Current Stock'!A3) -> 271 | I3: =G3-H3 -> 796 | L3: 10
A4: =CONCATENATE(B4,E4) -> OTH-PETIKAYU | B4: OTH-PETI | C4: Peti Kayu | D4: OTH | E4: KAYU | G4: =SUMIFS(X!$F$5:$F$2005,X!$D$5:$D$2005,'Current Stock'!A4) -> 32 | H4: =SUMIFS(PENJUALAN!$E$4:$E$11000,PENJUALAN!$C$4:$C$11000,'Current Stock'!A4) -> 211 | I4: =G4-H4 -> -179 | L4: 10
A5: =CONCATENATE(B5,E5) -> LFW-ALTIS18RSXYG | B5: LFW-ALTIS18RS | C5: Toyota Altis 18- E210 12th Gen | D5: LFW | E5: XYG | F5: X/MB/RS/List | G5: =SUMIFS(X!$F$5:$F$2005,X!$D$5:$D$2005,'Current Stock'!A5) -> 1 | H5: =SUMIFS(PENJUALAN!$E$4:$E$11000,PENJUALAN!$C$4:$C$11000,'Current Stock'!A5) -> 1 | I5: =G5-H5 -> 0
A6: =CONCATENATE(B6,E6) -> OTH-SERSK | B6: OTH-SER | C6: 255 Ultra + Actv-100 Application | D6: OTH | E6: SK | G6: =SUMIFS(X!$F$5:$F$2005,X!$D$5:$D$2005,'Current Stock'!A6) -> 0 | H6: =SUMIFS(PENJUALAN!$E$4:$E$11000,PENJUALAN!$C$4:$C$11000,'Current Stock'!A6) -> 0 | I6: =G6-H6 -> 0
A7: =CONCATENATE(B7,E7) -> OTH-SERBY | B7: OTH-SER | C7: 501 Sealant Application | D7: OTH | E7: BY | G7: =SUMIFS(X!$F$5:$F$2005,X!$D$5:$D$2005,'Current Stock'!A7) -> 780 | H7: =SUMIFS(PENJUALAN!$E$4:$E$11000,PENJUALAN!$C$4:$C$11000,'Current Stock'!A7) -> 156 | I7: =G7-H7 -> 624
A8: =CONCATENATE(B8,E8) -> OTH-SERTRANSPORT | B8: OTH-SER | C8: Transport | D8: OTH | E8: TRANSPORT | G8: =SUMIFS(X!$F$5:$F$2005,X!$D$5:$D$2005,'Current Stock'!A8) -> 0 | H8: =SUMIFS(PENJUALAN!$E$4:$E$11000,PENJUALAN!$C$4:$C$11000,'Current Stock'!A8) -> 358 | I8: =G8-H8 -> -358
A9: =CONCATENATE(B9,E9) -> OTH-LIST04TOYDAI | B9: OTH-LIST04 | C9: List Kaca Depan Code 04 | D9: OTH | E9: TOYDAI | G9: =SUMIFS(X!$F$5:$F$2005,X!$D$5:$D$2005,'Current Stock'!A9) -> 60 | H9: =SUMIFS(PENJUALAN!$E$4:$E$11000,PENJUALAN!$C$4:$C$11000,'Current Stock'!A9) -> 58 | I9: =G9-H9 -> 2 | L9: 2
A10: =CONCATENATE(B10,E10) -> OTH-LIST11TOYDAI | B10: OTH-LIST11 | C10: List Kaca Depan Code 11 | D10: OTH | E10: TOYDAI | G10: =SUMIFS(X!$F$5:$F$2005,X!$D$5:$D$2005,'Current Stock'!A10) -> 37 | H10: =SUMIFS(PENJUALAN!$E$4:$E$11000,PENJUALAN!$C$4:$C$11000,'Current Stock'!A10) -> 32 | I10: =G10-H10 -> 5 | L10: 2
A11: =CONCATENATE(B11,E11) -> OTH-LISTINVTOY | B11: OTH-LISTINV | C11: List Kaca Depan INV | D11: OTH | E11: TOY | G11: =SUMIFS(X!$F$5:$F$2005,X!$D$5:$D$2005,'Current Stock'!A11) -> 30 | H11: =SUMIFS(PENJUALAN!$E$4:$E$11000,PENJUALAN!$C$4:$C$11000,'Current Stock'!A11) -> 27 | I11: =G11-H11 -> 3 | L11: 2
A12: =CONCATENATE(B12,E12) -> TRW-DMAX1MSG | B12: TRW-DMAX1 | C12: Isuzu D-Max 02-12 1st Gen | D12: TRW | E12: MSG | G12: =SUMIFS(X!$F$5:$F$2005,X!$D$5:$D$2005,'Current Stock'!A12) -> 2 | H12: =SUMIFS(PENJUALAN!$E$4:$E$11000,PENJUALAN!$C$4:$C$11000,'Current Stock'!A12) -> 2 | I12: =G12-H12 -> 0 | J12: B1T4
A13: =CONCATENATE(B13,E13) -> FDR-DMAX1MSG | B13: FDR-DMAX1 | C13: Isuzu D-Max 02-12 1st Gen | D13: FDR | E13: MSG | G13: =SUMIFS(X!$F$5:$F$2005,X!$D$5:$D$2005,'Current Stock'!A13) -> 1 | H13: =SUMIFS(PENJUALAN!$E$4:$E$11000,PENJUALAN!$C$4:$C$11000,'Current Stock'!A13) -> 1 | I13: =G13-H13 -> 0
A14: =CONCATENATE(B14,E14) -> RDL-DMAX1MSG | B14: RDL-DMAX1 | C14: Isuzu D-Max 02-12 1st Gen | D14: RDL | E14: MSG | G14: =SUMIFS(X!$F$5:$F$2005,X!$D$5:$D$2005,'Current Stock'!A14) -> 2 | H14: =SUMIFS(PENJUALAN!$E$4:$E$11000,PENJUALAN!$C$4:$C$11000,'Current Stock'!A14) -> 1 | I14: =G14-H14 -> 1 | J14: A9T4
A15: =CONCATENATE(B15,E15) -> OTH-RPLXLFW | B15: OTH-RPLX | C15: Pemasangan Kaca Mobil Depan | D15: OTH | E15: LFW | G15: =SUMIFS(X!$F$5:$F$2005,X!$D$5:$D$2005,'Current Stock'!A15) -> 0 | H15: =SUMIFS(PENJUALAN!$E$4:$E$11000,PENJUALAN!$C$4:$C$11000,'Current Stock'!A15) -> 101 | I15: =G15-H15 -> -101 | L15: 100
A16: =CONCATENATE(B16,E16) -> OTH-RPLXTRW | B16: OTH-RPLX | C16: Pemasangan Kaca Mobil Belakang | D16: OTH | E16: TRW | G16: =SUMIFS(X!$F$5:$F$2005,X!$D$5:$D$2005,'Current Stock'!A16) -> 0 | H16: =SUMIFS(PENJUALAN!$E$4:$E$11000,PENJUALAN!$C$4:$C$11000,'Current Stock'!A16) -> 26 | I16: =G16-H16 -> -26 | L16: 100
A17: =CONCATENATE(B17,E17) -> OTH-RPLXSIDE | B17: OTH-RPLX | C17: Pemasangan Kaca Mobil Samping | D17: OTH | E17: SIDE | G17: =SUMIFS(X!$F$5:$F$2005,X!$D$5:$D$2005,'Current Stock'!A17) -> 0 | H17: =SUMIFS(PENJUALAN!$E$4:$E$11000,PENJUALAN!$C$4:$C$11000,'Current Stock'!A17) -> 12 | I17: =G17-H17 -> -12 | L17: 100
A18: =CONCATENATE(B18,E18) -> OTH-SERLMB | B18: OTH-SER | C18: Lembur | D18: OTH | E18: LMB | G18: =SUMIFS(X!$F$5:$F$2005,X!$D$5:$D$2005,'Current Stock'!A18) -> 0 | H18: =SUMIFS(PENJUALAN!$E$4:$E$11000,PENJUALAN!$C$4:$C$11000,'Current Stock'!A18) -> 37 | I18: =G18-H18 -> -37
A19: =CONCATENATE(B19,E19) -> FILM-40STD | B19: FILM-40 | C19: Automotive Film Standard - Black 40% | D19: FILM | E19: STD | G19: =SUMIFS(X!$F$5:$F$2005,X!$D$5:$D$2005,'Current Stock'!A19) -> 0 | H19: =SUMIFS(PENJUALAN!$E$4:$E$11000,PENJUALAN!$C$4:$C$11000,'Current Stock'!A19) -> 17 | I19: =G19-H19 -> -17
A20: =CONCATENATE(B20,E20) -> FILM-60STD | B20: FILM-60 | C20: Automotive Film Standard - Black 60% | D20: FILM | E20: STD | G20: =SUMIFS(X!$F$5:$F$2005,X!$D$5:$D$2005,'Current Stock'!A20) -> 0 | H20: =SUMIFS(PENJUALAN!$E$4:$E$11000,PENJUALAN!$C$4:$C$11000,'Current Stock'!A20) -> 29 | I20: =G20-H20 -> -29
A21: =CONCATENATE(B21,E21) -> FILM-80STD | B21: FILM-80 | C21: Automotive Film Standard - Black 80% | D21: FILM | E21: STD | G21: =SUMIFS(X!$F$5:$F$2005,X!$D$5:$D$2005,'Current Stock'!A21) -> 0 | H21: =SUMIFS(PENJUALAN!$E$4:$E$11000,PENJUALAN!$C$4:$C$11000,'Current Stock'!A21) -> 9 | I21: =G21-H21 -> -9
A22: =CONCATENATE(B22,E22) -> TRW-AVANZA03HAUTO | B22: TRW-AVANZA03H | C22: Toyota Avanza / Xenia 03-11 1st Gen | D22: TRW | E22: AUTO | F22: X/H | G22: =SUMIFS(X!$F$5:$F$2005,X!$D$5:$D$2005,'Current Stock'!A22) -> 0 | H22: =SUMIFS(PENJUALAN!$E$4:$E$11000,PENJUALAN!$C$4:$C$11000,'Current Stock'!A22) -> 0 | I22: =G22-H22 -> 0
A23: =CONCATENATE(B23,E23) -> RDR-CRV12SG | B23: RDR-CRV12 | C23: Honda CR-V 12-16 4th Gen | D23: RDR | E23: SG | G23: =SUMIFS(X!$F$5:$F$2005,X!$D$5:$D$2005,'Current Stock'!A23) -> 0 | H23: =SUMIFS(PENJUALAN!$E$4:$E$11000,PENJUALAN!$C$4:$C$11000,'Current Stock'!A23) -> 0 | I23: =G23-H23 -> 0
A24: =CONCATENATE(B24,E24) -> LFW-ALPHARD08RSPIL | B24: LFW-ALPHARD08RS | C24: Toyota Alphard 08-15 ANH20 2nd Gen | D24: LFW | E24: PIL | F24: X/MB/RS | G24: =SUMIFS(X!$F$5:$F$2005,X!$D$5:$D$2005,'Current Stock'!A24) -> 0 | H24: =SUMIFS(PENJUALAN!$E$4:$E$11000,PENJUALAN!$C$4:$C$11000,'Current Stock'!A24) -> 0 | I24: =G24-H24 -> 0
A25: =CONCATENATE(B25,E25) -> LFW-JAZZ07AGC | B25: LFW-JAZZ07 | C25: Honda Jazz 07-13 2nd Gen (Honda) | D25: LFW | E25: AGC | F25: X/MB/Logo | G25: =SUMIFS(X!$F$5:$F$2005,X!$D$5:$D$2005,'Current Stock'!A25) -> 1 | H25: =SUMIFS(PENJUALAN!$E$4:$E$11000,PENJUALAN!$C$4:$C$11000,'Current Stock'!A25) -> 1 | I25: =G25-H25 -> 0
A26: =CONCATENATE(B26,E26) -> RDR-AVANZA11ASH | B26: RDR-AVANZA11 | C26: Toyota Avanza / Xenia 11-15 2nd Gen | D26: RDR | E26: ASH | G26: =SUMIFS(X!$F$5:$F$2005,X!$D$5:$D$2005,'Current Stock'!A26) -> 10 | H26: =SUMIFS(PENJUALAN!$E$4:$E$11000,PENJUALAN!$C$4:$C$11000,'Current Stock'!A26) -> 9 | I26: =G26-H26 -> 1 | J26: A13T3
A27: =CONCATENATE(B27,E27) -> RDL-AGYA13ASH | B27: RDL-AGYA13 | C27: Toyota Agya/Ayla 13-22 1st Gen | D27: =LEFT(A27,FIND("-",A27) - 1) -> RDL | E27: ASH | G27: =SUMIFS(X!$F$5:$F$2005,X!$D$5:$D$2005,'Current Stock'!A27) -> 5 | H27: =SUMIFS(PENJUALAN!$E$4:$E$11000,PENJUALAN!$C$4:$C$11000,'Current Stock'!A27) -> 4 | I27: =G27-H27 -> 1 | J27: A13T4
A28: =CONCATENATE(B28,E28) -> TRW-AVANZA11ORI | B28: TRW-AVANZA11 | C28: Toyota Avanza / Xenia 11-15 2nd Gen/3rd Gen | D28: TRW | E28: ORI | F28: X/Logo | G28: =SUMIFS(X!$F$5:$F$2005,X!$D$5:$D$2005,'Current Stock'!A28) -> 0 | H28: =SUMIFS(PENJUALAN!$E$4:$E$11000,PENJUALAN!$C$4:$C$11000,'Current Stock'!A28) -> 0 | I28: =G28-H28 -> 0
A29: =CONCATENATE(B29,E29) -> RDL-AVANZA11ORI | B29: RDL-AVANZA11 | C29: Toyota Avanza / Xenia 11-15 2nd Gen/3rd Gen | D29: RDL | E29: ORI | G29: =SUMIFS(X!$F$5:$F$2005,X!$D$5:$D$2005,'Current Stock'!A29) -> 0 | H29: =SUMIFS(PENJUALAN!$E$4:$E$11000,PENJUALAN!$C$4:$C$11000,'Current Stock'!A29) -> 0 | I29: =G29-H29 -> 0
A30: =CONCATENATE(B30,E30) -> RDR-AVANZA11ORI | B30: RDR-AVANZA11 | C30: Toyota Avanza / Xenia 11-15 2nd Gen/3rd Gen | D30: RDR | E30: ORI | G30: =SUMIFS(X!$F$5:$F$2005,X!$D$5:$D$2005,'Current Stock'!A30) -> 0 | H30: =SUMIFS(PENJUALAN!$E$4:$E$11000,PENJUALAN!$C$4:$C$11000,'Current Stock'!A30) -> 0 | I30: =G30-H30 -> 0
A31: =CONCATENATE(B31,E31) -> FDL-AVANZA11ORI | B31: FDL-AVANZA11 | C31: Toyota Avanza / Xenia 11-15 2nd Gen/3rd Gen | D31: FDL | E31: ORI | G31: =SUMIFS(X!$F$5:$F$2005,X!$D$5:$D$2005,'Current Stock'!A31) -> 0 | H31: =SUMIFS(PENJUALAN!$E$4:$E$11000,PENJUALAN!$C$4:$C$11000,'Current Stock'!A31) -> 0 | I31: =G31-H31 -> 0
A32: =CONCATENATE(B32,E32) -> FDR-AVANZA11ORI | B32: FDR-AVANZA11 | C32: Toyota Avanza / Xenia 11-15 2nd Gen/3rd Gen | D32: FDR | E32: ORI | G32: =SUMIFS(X!$F$5:$F$2005,X!$D$5:$D$2005,'Current Stock'!A32) -> 0 | H32: =SUMIFS(PENJUALAN!$E$4:$E$11000,PENJUALAN!$C$4:$C$11000,'Current Stock'!A32) -> 0 | I32: =G32-H32 -> 0
A33: =CONCATENATE(B33,E33) -> LFW-ETIOSASH | B33: LFW-ETIOS | C33: Toyota Etios 10- 1st Gen Sedan | D33: LFW | E33: ASH | F33: X | G33: =SUMIFS(X!$F$5:$F$2005,X!$D$5:$D$2005,'Current Stock'!A33) -> 0 | H33: =SUMIFS(PENJUALAN!$E$4:$E$11000,PENJUALAN!$C$4:$C$11000,'Current Stock'!A33) -> 0 | I33: =G33-H33 -> 0 | L33: 1
A34: =CONCATENATE(B34,E34) -> TRW-XPANDERAGC | B34: TRW-XPANDER | C34: Mitsubishi Xpander 17-21 / Livina 19- 2nd Gen (Mitsubishi) | D34: TRW | E34: AGC | F34: X/Hole | G34: =SUMIFS(X!$F$5:$F$2005,X!$D$5:$D$2005,'Current Stock'!A34) -> 6 | H34: =SUMIFS(PENJUALAN!$E$4:$E$11000,PENJUALAN!$C$4:$C$11000,'Current Stock'!A34) -> 5 | I34: =G34-H34 -> 1 | J34: B10T3
A35: =CONCATENATE(B35,E35) -> SWR-RAIZEORI | B35: SWR-RAIZE | C35: Toyota Raize / Daihatsu Rocky 20- | D35: SWR | E35: ORI | F35: X | G35: =SUMIFS(X!$F$5:$F$2005,X!$D$5:$D$2005,'Current Stock'!A35) -> 0 | H35: =SUMIFS(PENJUALAN!$E$4:$E$11000,PENJUALAN!$C$4:$C$11000,'Current Stock'!A35) -> 0 | I35: =G35-H35 -> 0 | L35: 1
A36: =CONCATENATE(B36,E36) -> TRW-BRV16HONDA | B36: TRW-BRV16 | C36: Honda BR-V 16- Genuine | D36: TRW | E36: HONDA | F36: X/H/Logo | G36: =SUMIFS(X!$F$5:$F$2005,X!$D$5:$D$2005,'Current Stock'!A36) -> 0 | H36: =SUMIFS(PENJUALAN!$E$4:$E$11000,PENJUALAN!$C$4:$C$11000,'Current Stock'!A36) -> 0 | I36: =G36-H36 -> 0 | L36: 1
A37: =CONCATENATE(B37,E37) -> LFW-AUDIB8FY | B37: LFW-AUDIB8 | C37: Audi A4 08-15 B8 | D37: LFW | E37: FY | F37: X/RS/List | G37: =SUMIFS(X!$F$5:$F$2005,X!$D$5:$D$2005,'Current Stock'!A37) -> 0 | H37: =SUMIFS(PENJUALAN!$E$4:$E$11000,PENJUALAN!$C$4:$C$11000,'Current Stock'!A37) -> 0 | I37: =G37-H37 -> 0
A38: =CONCATENATE(B38,E38) -> TRW-AUDIB8FY | B38: TRW-AUDIB8 | C38: Audi A4 08-15 B8 | D38: TRW | E38: FY | F38: X/H/A | G38: =SUMIFS(X!$F$5:$F$2005,X!$D$5:$D$2005,'Current Stock'!A38) -> 0 | H38: =SUMIFS(PENJUALAN!$E$4:$E$11000,PENJUALAN!$C$4:$C$11000,'Current Stock'!A38) -> 0 | I38: =G38-H38 -> 0
A39: =CONCATENATE(B39,E39) -> LFW-AUDIC7FY | B39: LFW-AUDIC7 | C39: Audi A6 11-18 C7 | D39: LFW | E39: FY | F39: X/RS/List | G39: =SUMIFS(X!$F$5:$F$2005,X!$D$5:$D$2005,'Current Stock'!A39) -> 0 | H39: =SUMIFS(PENJUALAN!$E$4:$E$11000,PENJUALAN!$C$4:$C$11000,'Current Stock'!A39) -> 0 | I39: =G39-H39 -> 0
A40: =CONCATENATE(B40,E40) -> TRW-AUDIC7FY | B40: TRW-AUDIC7 | C40: Audi A6 11-18 C7 | D40: TRW | E40: FY | F40: X/H/List | G40: =SUMIFS(X!$F$5:$F$2005,X!$D$5:$D$2005,'Current Stock'!A40) -> 0 | H40: =SUMIFS(PENJUALAN!$E$4:$E$11000,PENJUALAN!$C$4:$C$11000,'Current Stock'!A40) -> 0 | I40: =G40-H40 -> 0
A41: =CONCATENATE(B41,E41) -> LFW-E30FY | B41: LFW-E30 | C41: BMW 3 Series 82-94 E30 | D41: LFW | E41: FY | G41: =SUMIFS(X!$F$5:$F$2005,X!$D$5:$D$2005,'Current Stock'!A41) -> 0 | H41: =SUMIFS(PENJUALAN!$E$4:$E$11000,PENJUALAN!$C$4:$C$11000,'Current Stock'!A41) -> 0 | I41: =G41-H41 -> 0
A42: =CONCATENATE(B42,E42) -> TRW-E30FY | B42: TRW-E30 | C42: BMW 3 Series 82-94 E30 | D42: TRW | E42: FY | F42: H | G42: =SUMIFS(X!$F$5:$F$2005,X!$D$5:$D$2005,'Current Stock'!A42) -> 0 | H42: =SUMIFS(PENJUALAN!$E$4:$E$11000,PENJUALAN!$C$4:$C$11000,'Current Stock'!A42) -> 0 | I42: =G42-H42 -> 0
A43: =CONCATENATE(B43,E43) -> LFW-E36FY | B43: LFW-E36 | C43: BMW 3 Series 90-99 E36 | D43: LFW | E43: FY | F43: X/MB | G43: =SUMIFS(X!$F$5:$F$2005,X!$D$5:$D$2005,'Current Stock'!A43) -> 0 | H43: =SUMIFS(PENJUALAN!$E$4:$E$11000,PENJUALAN!$C$4:$C$11000,'Current Stock'!A43) -> 0 | I43: =G43-H43 -> 0
A44: =CONCATENATE(B44,E44) -> TRW-E36FY | B44: TRW-E36 | C44: BMW 3 Series 90-99 E36 | D44: TRW | E44: FY | F44: X/H | G44: =SUMIFS(X!$F$5:$F$2005,X!$D$5:$D$2005,'Current Stock'!A44) -> 0 | H44: =SUMIFS(PENJUALAN!$E$4:$E$11000,PENJUALAN!$C$4:$C$11000,'Current Stock'!A44) -> 0 | I44: =G44-H44 -> 0
A45: =CONCATENATE(B45,E45) -> FDL-E36FY | B45: FDL-E36 | C45: BMW 3 Series 90-99 E36 | D45: FD/L | E45: FY | G45: =SUMIFS(X!$F$5:$F$2005,X!$D$5:$D$2005,'Current Stock'!A45) -> 0 | H45: =SUMIFS(PENJUALAN!$E$4:$E$11000,PENJUALAN!$C$4:$C$11000,'Current Stock'!A45) -> 0 | I45: =G45-H45 -> 0
A46: =CONCATENATE(B46,E46) -> FDR-E36FY | B46: FDR-E36 | C46: BMW 3 Series 90-99 E36 | D46: FD/R | E46: FY | G46: =SUMIFS(X!$F$5:$F$2005,X!$D$5:$D$2005,'Current Stock'!A46) -> 0 | H46: =SUMIFS(PENJUALAN!$E$4:$E$11000,PENJUALAN!$C$4:$C$11000,'Current Stock'!A46) -> 0 | I46: =G46-H46 -> 0
A47: =CONCATENATE(B47,E47) -> RDL-E36FY | B47: RDL-E36 | C47: BMW 3 Series 90-99 E36 | D47: RD/L | E47: FY | G47: =SUMIFS(X!$F$5:$F$2005,X!$D$5:$D$2005,'Current Stock'!A47) -> 0 | H47: =SUMIFS(PENJUALAN!$E$4:$E$11000,PENJUALAN!$C$4:$C$11000,'Current Stock'!A47) -> 0 | I47: =G47-H47 -> 0
A48: =CONCATENATE(B48,E48) -> RDR-E36FY | B48: RDR-E36 | C48: BMW 3 Series 90-99 E36 | D48: RD/R | E48: FY | G48: =SUMIFS(X!$F$5:$F$2005,X!$D$5:$D$2005,'Current Stock'!A48) -> 0 | H48: =SUMIFS(PENJUALAN!$E$4:$E$11000,PENJUALAN!$C$4:$C$11000,'Current Stock'!A48) -> 0 | I48: =G48-H48 -> 0
A49: =CONCATENATE(B49,E49) -> LFW-E46RSFY | B49: LFW-E46RS | C49: BMW 3 Series 98-06 E46 | D49: LFW | E49: FY | F49: X/MB/RS | G49: =SUMIFS(X!$F$5:$F$2005,X!$D$5:$D$2005,'Current Stock'!A49) -> 0 | H49: =SUMIFS(PENJUALAN!$E$4:$E$11000,PENJUALAN!$C$4:$C$11000,'Current Stock'!A49) -> 0 | I49: =G49-H49 -> 0
A50: =CONCATENATE(B50,E50) -> LFW-E46FY | B50: LFW-E46 | C50: BMW 3 Series 98-06 E46 | D50: LFW | E50: FY | F50: X/MB | G50: =SUMIFS(X!$F$5:$F$2005,X!$D$5:$D$2005,'Current Stock'!A50) -> 0 | H50: =SUMIFS(PENJUALAN!$E$4:$E$11000,PENJUALAN!$C$4:$C$11000,'Current Stock'!A50) -> 0 | I50: =G50-H50 -> 0
A51: =CONCATENATE(B51,E51) -> TRW-E46FY | B51: TRW-E46 | C51: BMW 3 Series 98-06 E46 | D51: TRW | E51: FY | F51: X/H | G51: =SUMIFS(X!$F$5:$F$2005,X!$D$5:$D$2005,'Current Stock'!A51) -> 2 | H51: =SUMIFS(PENJUALAN!$E$4:$E$11000,PENJUALAN!$C$4:$C$11000,'Current Stock'!A51) -> 0 | I51: =G51-H51 -> 2 | J51: A4T3
A52: =CONCATENATE(B52,E52) -> FDL-E46FY | B52: FDL-E46 | C52: BMW 3 Series 98-06 E46 | D52: FD/L | E52: FY | F52: 2Hole | G52: =SUMIFS(X!$F$5:$F$2005,X!$D$5:$D$2005,'Current Stock'!A52) -> 0 | H52: =SUMIFS(PENJUALAN!$E$4:$E$11000,PENJUALAN!$C$4:$C$11000,'Current Stock'!A52) -> 0 | I52: =G52-H52 -> 0
A53: =CONCATENATE(B53,E53) -> FDR-E46FY | B53: FDR-E46 | C53: BMW 3 Series 98-06 E46 | D53: FD/R | E53: FY | F53: 2Hole | G53: =SUMIFS(X!$F$5:$F$2005,X!$D$5:$D$2005,'Current Stock'!A53) -> 0 | H53: =SUMIFS(PENJUALAN!$E$4:$E$11000,PENJUALAN!$C$4:$C$11000,'Current Stock'!A53) -> 0 | I53: =G53-H53 -> 0
A54: =CONCATENATE(B54,E54) -> RDL-E46FY | B54: RDL-E46 | C54: BMW 3 Series 98-06 E46 | D54: RD/L | E54: FY | F54: 1Hole | G54: =SUMIFS(X!$F$5:$F$2005,X!$D$5:$D$2005,'Current Stock'!A54) -> 0 | H54: =SUMIFS(PENJUALAN!$E$4:$E$11000,PENJUALAN!$C$4:$C$11000,'Current Stock'!A54) -> 0 | I54: =G54-H54 -> 0
A55: =CONCATENATE(B55,E55) -> RDR-E46FY | B55: RDR-E46 | C55: BMW 3 Series 98-06 E46 | D55: RD/R | E55: FY | F55: 1Hole | G55: =SUMIFS(X!$F$5:$F$2005,X!$D$5:$D$2005,'Current Stock'!A55) -> 0 | H55: =SUMIFS(PENJUALAN!$E$4:$E$11000,PENJUALAN!$C$4:$C$11000,'Current Stock'!A55) -> 0 | I55: =G55-H55 -> 0
A56: =CONCATENATE(B56,E56) -> LFW-E46RS2DOORFY | B56: LFW-E46RS2DOOR | C56: BMW 3 Series 98-06 E46 (2-Door Coupe) | D56: LFW | E56: FY | F56: X/MB | G56: =SUMIFS(X!$F$5:$F$2005,X!$D$5:$D$2005,'Current Stock'!A56) -> 0 | H56: =SUMIFS(PENJUALAN!$E$4:$E$11000,PENJUALAN!$C$4:$C$11000,'Current Stock'!A56) -> 0 | I56: =G56-H56 -> 0
A57: =CONCATENATE(B57,E57) -> LFW-E90RSFY | B57: LFW-E90RS | C57: BMW 3 Series 05-12 E90 | D57: LFW | E57: FY | F57: X/MB/RS | G57: =SUMIFS(X!$F$5:$F$2005,X!$D$5:$D$2005,'Current Stock'!A57) -> 0 | H57: =SUMIFS(PENJUALAN!$E$4:$E$11000,PENJUALAN!$C$4:$C$11000,'Current Stock'!A57) -> 0 | I57: =G57-H57 -> 0
A58: =CONCATENATE(B58,E58) -> LFW-E90FY | B58: LFW-E90 | C58: BMW 3 Series 05-12 E90 | D58: LFW | E58: FY | F58: X/MB | G58: =SUMIFS(X!$F$5:$F$2005,X!$D$5:$D$2005,'Current Stock'!A58) -> 0 | H58: =SUMIFS(PENJUALAN!$E$4:$E$11000,PENJUALAN!$C$4:$C$11000,'Current Stock'!A58) -> 0 | I58: =G58-H58 -> 0
A59: =CONCATENATE(B59,E59) -> TRW-E90FY | B59: TRW-E90 | C59: BMW 3 Series 05-12 E90 | D59: TRW | E59: FY | F59: X/H | G59: =SUMIFS(X!$F$5:$F$2005,X!$D$5:$D$2005,'Current Stock'!A59) -> 0 | H59: =SUMIFS(PENJUALAN!$E$4:$E$11000,PENJUALAN!$C$4:$C$11000,'Current Stock'!A59) -> 0 | I59: =G59-H59 -> 0
A60: =CONCATENATE(B60,E60) -> FDL-E90FY | B60: FDL-E90 | C60: BMW 3 Series 05-12 E90 | D60: FD/L | E60: FY | F60: 2Hole | G60: =SUMIFS(X!$F$5:$F$2005,X!$D$5:$D$2005,'Current Stock'!A60) -> 0 | H60: =SUMIFS(PENJUALAN!$E$4:$E$11000,PENJUALAN!$C$4:$C$11000,'Current Stock'!A60) -> 0 | I60: =G60-H60 -> 0
A61: =CONCATENATE(B61,E61) -> FDR-E90FY | B61: FDR-E90 | C61: BMW 3 Series 05-12 E90 | D61: FD/R | E61: FY | F61: 2Hole | G61: =SUMIFS(X!$F$5:$F$2005,X!$D$5:$D$2005,'Current Stock'!A61) -> 0 | H61: =SUMIFS(PENJUALAN!$E$4:$E$11000,PENJUALAN!$C$4:$C$11000,'Current Stock'!A61) -> 0 | I61: =G61-H61 -> 0
A62: =CONCATENATE(B62,E62) -> RDL-E90FY | B62: RDL-E90 | C62: BMW 3 Series 05-12 E90 | D62: RD/L | E62: FY | F62: 1Hole | G62: =SUMIFS(X!$F$5:$F$2005,X!$D$5:$D$2005,'Current Stock'!A62) -> 0 | H62: =SUMIFS(PENJUALAN!$E$4:$E$11000,PENJUALAN!$C$4:$C$11000,'Current Stock'!A62) -> 0 | I62: =G62-H62 -> 0
A63: =CONCATENATE(B63,E63) -> RDR-E90FY | B63: RDR-E90 | C63: BMW 3 Series 05-12 E90 | D63: RD/R | E63: FY | F63: 1Hole | G63: =SUMIFS(X!$F$5:$F$2005,X!$D$5:$D$2005,'Current Stock'!A63) -> 0 | H63: =SUMIFS(PENJUALAN!$E$4:$E$11000,PENJUALAN!$C$4:$C$11000,'Current Stock'!A63) -> 0 | I63: =G63-H63 -> 0
A64: =CONCATENATE(B64,E64) -> LFW-F30FY | B64: LFW-F30 | C64: BMW 3 Series 12-18 F30/F35 | D64: LFW | E64: FY | F64: X/RS/List | G64: =SUMIFS(X!$F$5:$F$2005,X!$D$5:$D$2005,'Current Stock'!A64) -> 1 | H64: =SUMIFS(PENJUALAN!$E$4:$E$11000,PENJUALAN!$C$4:$C$11000,'Current Stock'!A64) -> 0 | I64: =G64-H64 -> 1 | J64: A8T2
A65: =CONCATENATE(B65,E65) -> LFW-W222XYG | B65: LFW-W222 | C65: Mers-Benz S-Class 13-20 W222 4D | D65: LFW | E65: XYG | F65: X/H/A/3S/List | G65: =SUMIFS(X!$F$5:$F$2005,X!$D$5:$D$2005,'Current Stock'!A65) -> 1 | H65: =SUMIFS(PENJUALAN!$E$4:$E$11000,PENJUALAN!$C$4:$C$11000,'Current Stock'!A65) -> 1 | I65: =G65-H65 -> 0
A66: =CONCATENATE(B66,E66) -> FDL-F30FY | B66: FDL-F30 | C66: BMW 3 Series 12-18 F30/F35 | D66: FD/L | E66: FY | F66: 2Hole | G66: =SUMIFS(X!$F$5:$F$2005,X!$D$5:$D$2005,'Current Stock'!A66) -> 0 | H66: =SUMIFS(PENJUALAN!$E$4:$E$11000,PENJUALAN!$C$4:$C$11000,'Current Stock'!A66) -> 0 | I66: =G66-H66 -> 0
A67: =CONCATENATE(B67,E67) -> FDR-F30FY | B67: FDR-F30 | C67: BMW 3 Series 12-18 F30/F35 | D67: FD/R | E67: FY | F67: 2Hole | G67: =SUMIFS(X!$F$5:$F$2005,X!$D$5:$D$2005,'Current Stock'!A67) -> 0 | H67: =SUMIFS(PENJUALAN!$E$4:$E$11000,PENJUALAN!$C$4:$C$11000,'Current Stock'!A67) -> 0 | I67: =G67-H67 -> 0
A68: =CONCATENATE(B68,E68) -> RDL-F30FY | B68: RDL-F30 | C68: BMW 3 Series 12-18 F30/F35 | D68: RD/L | E68: FY | F68: 1Hole | G68: =SUMIFS(X!$F$5:$F$2005,X!$D$5:$D$2005,'Current Stock'!A68) -> 0 | H68: =SUMIFS(PENJUALAN!$E$4:$E$11000,PENJUALAN!$C$4:$C$11000,'Current Stock'!A68) -> 0 | I68: =G68-H68 -> 0
A69: =CONCATENATE(B69,E69) -> RDR-F30FY | B69: RDR-F30 | C69: BMW 3 Series 12-18 F30/F35 | D69: RD/R | E69: FY | F69: 1Hole | G69: =SUMIFS(X!$F$5:$F$2005,X!$D$5:$D$2005,'Current Stock'!A69) -> 0 | H69: =SUMIFS(PENJUALAN!$E$4:$E$11000,PENJUALAN!$C$4:$C$11000,'Current Stock'!A69) -> 0 | I69: =G69-H69 -> 0
A70: =CONCATENATE(B70,E70) -> LFW-E60RSKFY | B70: LFW-E60RSK | C70: BMW 5 Series 03-10 E60 (1 Sensor / [] ) | D70: LFW | E70: FY | F70: X/MB/RS | G70: =SUMIFS(X!$F$5:$F$2005,X!$D$5:$D$2005,'Current Stock'!A70) -> 0 | H70: =SUMIFS(PENJUALAN!$E$4:$E$11000,PENJUALAN!$C$4:$C$11000,'Current Stock'!A70) -> 0 | I70: =G70-H70 -> 0
A71: =CONCATENATE(B71,E71) -> LFW-E60RSOFY | B71: LFW-E60RSO | C71: BMW 5 Series 03-10 E60 (1 Sensor / O) | D71: LFW | E71: FY | F71: X/MB/RS | G71: =SUMIFS(X!$F$5:$F$2005,X!$D$5:$D$2005,'Current Stock'!A71) -> 0 | H71: =SUMIFS(PENJUALAN!$E$4:$E$11000,PENJUALAN!$C$4:$C$11000,'Current Stock'!A71) -> 0 | I71: =G71-H71 -> 0
A72: =CONCATENATE(B72,E72) -> TRW-E60FY | B72: TRW-E60 | C72: BMW 5 Series 03-10 E60 | D72: TRW | E72: FY | F72: X/H | G72: =SUMIFS(X!$F$5:$F$2005,X!$D$5:$D$2005,'Current Stock'!A72) -> 0 | H72: =SUMIFS(PENJUALAN!$E$4:$E$11000,PENJUALAN!$C$4:$C$11000,'Current Stock'!A72) -> 0 | I72: =G72-H72 -> 0
A73: =CONCATENATE(B73,E73) -> FDL-E60FY | B73: FDL-E60 | C73: BMW 5 Series 03-10 E60 | D73: FD/L | E73: FY | G73: =SUMIFS(X!$F$5:$F$2005,X!$D$5:$D$2005,'Current Stock'!A73) -> 0 | H73: =SUMIFS(PENJUALAN!$E$4:$E$11000,PENJUALAN!$C$4:$C$11000,'Current Stock'!A73) -> 0 | I73: =G73-H73 -> 0
A74: =CONCATENATE(B74,E74) -> FDR-E60FY | B74: FDR-E60 | C74: BMW 5 Series 03-10 E60 | D74: FD/R | E74: FY | G74: =SUMIFS(X!$F$5:$F$2005,X!$D$5:$D$2005,'Current Stock'!A74) -> 0 | H74: =SUMIFS(PENJUALAN!$E$4:$E$11000,PENJUALAN!$C$4:$C$11000,'Current Stock'!A74) -> 0 | I74: =G74-H74 -> 0
A75: =CONCATENATE(B75,E75) -> RDL-E60FY | B75: RDL-E60 | C75: BMW 5 Series 03-10 E60 | D75: RD/L | E75: FY | F75: 1Hole | G75: =SUMIFS(X!$F$5:$F$2005,X!$D$5:$D$2005,'Current Stock'!A75) -> 0 | H75: =SUMIFS(PENJUALAN!$E$4:$E$11000,PENJUALAN!$C$4:$C$11000,'Current Stock'!A75) -> 0 | I75: =G75-H75 -> 0
A76: =CONCATENATE(B76,E76) -> RDR-E60FY | B76: RDR-E60 | C76: BMW 5 Series 03-10 E60 | D76: RD/R | E76: FY | F76: 1Hole | G76: =SUMIFS(X!$F$5:$F$2005,X!$D$5:$D$2005,'Current Stock'!A76) -> 0 | H76: =SUMIFS(PENJUALAN!$E$4:$E$11000,PENJUALAN!$C$4:$C$11000,'Current Stock'!A76) -> 0 | I76: =G76-H76 -> 0
A77: =CONCATENATE(B77,E77) -> LFW-F10FY | B77: LFW-F10 | C77: BMW 5 Series 10-16 F10 (1 Sensor / ꓳ Tengah) | D77: LFW | E77: FY | F77: X/MB/RS | G77: =SUMIFS(X!$F$5:$F$2005,X!$D$5:$D$2005,'Current Stock'!A77) -> 0 | H77: =SUMIFS(PENJUALAN!$E$4:$E$11000,PENJUALAN!$C$4:$C$11000,'Current Stock'!A77) -> 0 | I77: =G77-H77 -> 0
A78: =CONCATENATE(B78,E78) -> FDL-F10FY | B78: FDL-F10 | C78: BMW 5 Series 10-16 F10 | D78: FD/L | E78: FY | F78: 2Hole | G78: =SUMIFS(X!$F$5:$F$2005,X!$D$5:$D$2005,'Current Stock'!A78) -> 0 | H78: =SUMIFS(PENJUALAN!$E$4:$E$11000,PENJUALAN!$C$4:$C$11000,'Current Stock'!A78) -> 0 | I78: =G78-H78 -> 0
A79: =CONCATENATE(B79,E79) -> FDR-F10FY | B79: FDR-F10 | C79: BMW 5 Series 10-16 F10 | D79: FD/R | E79: FY | F79: 2Hole | G79: =SUMIFS(X!$F$5:$F$2005,X!$D$5:$D$2005,'Current Stock'!A79) -> 0 | H79: =SUMIFS(PENJUALAN!$E$4:$E$11000,PENJUALAN!$C$4:$C$11000,'Current Stock'!A79) -> 0 | I79: =G79-H79 -> 0
A80: =CONCATENATE(B80,E80) -> RDL-F10FY | B80: RDL-F10 | C80: BMW 5 Series 10-16 F10 | D80: RD/L | E80: FY | F80: 1Hole | G80: =SUMIFS(X!$F$5:$F$2005,X!$D$5:$D$2005,'Current Stock'!A80) -> 0 | H80: =SUMIFS(PENJUALAN!$E$4:$E$11000,PENJUALAN!$C$4:$C$11000,'Current Stock'!A80) -> 0 | I80: =G80-H80 -> 0
A81: =CONCATENATE(B81,E81) -> RDR-F10FY | B81: RDR-F10 | C81: BMW 5 Series 10-16 F10 | D81: RD/R | E81: FY | F81: 1Hole | G81: =SUMIFS(X!$F$5:$F$2005,X!$D$5:$D$2005,'Current Stock'!A81) -> 0 | H81: =SUMIFS(PENJUALAN!$E$4:$E$11000,PENJUALAN!$C$4:$C$11000,'Current Stock'!A81) -> 0 | I81: =G81-H81 -> 0
A82: =CONCATENATE(B82,E82) -> LFW-E84FY | B82: LFW-E84 | C82: BMW X1 Series 09-14 E84 (1 Sensor / [] ) | D82: LFW | E82: FY | F82: X/MB/RS | G82: =SUMIFS(X!$F$5:$F$2005,X!$D$5:$D$2005,'Current Stock'!A82) -> 0 | H82: =SUMIFS(PENJUALAN!$E$4:$E$11000,PENJUALAN!$C$4:$C$11000,'Current Stock'!A82) -> 0 | I82: =G82-H82 -> 0
A83: =CONCATENATE(B83,E83) -> TRW-E84FY | B83: TRW-E84 | C83: BMW X1 Series 09-14 E84 | D83: TRW | E83: FY | F83: X/H | G83: =SUMIFS(X!$F$5:$F$2005,X!$D$5:$D$2005,'Current Stock'!A83) -> 0 | H83: =SUMIFS(PENJUALAN!$E$4:$E$11000,PENJUALAN!$C$4:$C$11000,'Current Stock'!A83) -> 0 | I83: =G83-H83 -> 0
A84: =CONCATENATE(B84,E84) -> LFW-F48FY | B84: LFW-F48 | C84: BMW X1 Series 15- F48 | D84: LFW | E84: FY | F84: X/RS | G84: =SUMIFS(X!$F$5:$F$2005,X!$D$5:$D$2005,'Current Stock'!A84) -> 0 | H84: =SUMIFS(PENJUALAN!$E$4:$E$11000,PENJUALAN!$C$4:$C$11000,'Current Stock'!A84) -> 0 | I84: =G84-H84 -> 0
A85: =CONCATENATE(B85,E85) -> LFW-E53FY | B85: LFW-E53 | C85: BMW X5 Series 00-06 E53 | D85: LFW | E85: FY | F85: X/MB/RS | G85: =SUMIFS(X!$F$5:$F$2005,X!$D$5:$D$2005,'Current Stock'!A85) -> 0 | H85: =SUMIFS(PENJUALAN!$E$4:$E$11000,PENJUALAN!$C$4:$C$11000,'Current Stock'!A85) -> 0 | I85: =G85-H85 -> 0
A86: =CONCATENATE(B86,E86) -> TRW-E53BLACKFY | B86: TRW-E53BLACK | C86: BMW X5 Series 00-06 E53 (Hitam) | D86: TRW | E86: FY | F86: X/H/A/1hole | G86: =SUMIFS(X!$F$5:$F$2005,X!$D$5:$D$2005,'Current Stock'!A86) -> 0 | H86: =SUMIFS(PENJUALAN!$E$4:$E$11000,PENJUALAN!$C$4:$C$11000,'Current Stock'!A86) -> 0 | I86: =G86-H86 -> 0
... A116: =CONCATENATE(B116,E116) -> LFW-ORLANDOFY | B116: LFW-ORLANDO | C116: Chevrolet Orlando 12- 1st Gen | D116: LFW | E116: FY | F116: X/MB | G116: =SUMIFS(X!$F$5:$F$2005,X!$D$5:$D$2005,'Current Stock'!A116) -> 0 | H116: =SUMIFS(PENJUALAN!$E$4:$E$11000,PENJUALAN!$C$4:$C$11000,'Current Stock'!A116) -> 0 | I116: =G116-H116 -> 0
A117: =CONCATENATE(B117,E117) -> FDR-ORLANDOFY | B117: FDR-ORLANDO | C117: Chevrolet Orlando 12- 1st Gen | D117: FD/R | E117: FY | G117: =SUMIFS(X!$F$5:$F$2005,X!$D$5:$D$2005,'Current Stock'!A117) -> 0 | H117: =SUMIFS(PENJUALAN!$E$4:$E$11000,PENJUALAN!$C$4:$C$11000,'Current Stock'!A117) -> 0 | I117: =G117-H117 -> 0
A118: =CONCATENATE(B118,E118) -> RDL-ORLANDOFY | B118: RDL-ORLANDO | C118: Chevrolet Orlando 12- 1st Gen | D118: RD/L | E118: FY | G118: =SUMIFS(X!$F$5:$F$2005,X!$D$5:$D$2005,'Current Stock'!A118) -> 0 | H118: =SUMIFS(PENJUALAN!$E$4:$E$11000,PENJUALAN!$C$4:$C$11000,'Current Stock'!A118) -> 0 | I118: =G118-H118 -> 0
A119: =CONCATENATE(B119,E119) -> LFW-SPARK98FY | B119: LFW-SPARK98 | C119: Chevrolet Spark 98-05 M100 1stGen (800cc) | D119: LFW | E119: FY | F119: X/MB | G119: =SUMIFS(X!$F$5:$F$2005,X!$D$5:$D$2005,'Current Stock'!A119) -> 0 | H119: =SUMIFS(PENJUALAN!$E$4:$E$11000,PENJUALAN!$C$4:$C$11000,'Current Stock'!A119) -> 0 | I119: =G119-H119 -> 0
A120: =CONCATENATE(B120,E120) -> TRW-SPARK98FY | B120: TRW-SPARK98 | C120: Chevrolet Spark 98-05 M100 1stGen (800cc) | D120: TRW | E120: FY | F120: X/H | G120: =SUMIFS(X!$F$5:$F$2005,X!$D$5:$D$2005,'Current Stock'!A120) -> 0 | H120: =SUMIFS(PENJUALAN!$E$4:$E$11000,PENJUALAN!$C$4:$C$11000,'Current Stock'!A120) -> 0 | I120: =G120-H120 -> 0
A121: =CONCATENATE(B121,E121) -> LFW-SPARK05FY | B121: LFW-SPARK05 | C121: Chevrolet Spark 05-09 M200 2nd Gen (1000cc) | D121: LFW | E121: FY | F121: X/MB | G121: =SUMIFS(X!$F$5:$F$2005,X!$D$5:$D$2005,'Current Stock'!A121) -> 0 | H121: =SUMIFS(PENJUALAN!$E$4:$E$11000,PENJUALAN!$C$4:$C$11000,'Current Stock'!A121) -> 0 | I121: =G121-H121 -> 0
A122: =CONCATENATE(B122,E122) -> TRW-SPARK05FY | B122: TRW-SPARK05 | C122: Chevrolet Spark 05-09 M200 2nd Gen (1000cc) | D122: TRW | E122: FY | F122: X/H | G122: =SUMIFS(X!$F$5:$F$2005,X!$D$5:$D$2005,'Current Stock'!A122) -> 0 | H122: =SUMIFS(PENJUALAN!$E$4:$E$11000,PENJUALAN!$C$4:$C$11000,'Current Stock'!A122) -> 0 | I122: =G122-H122 -> 0
A123: =CONCATENATE(B123,E123) -> FDL-SPARK05FY | B123: FDL-SPARK05 | C123: Chevrolet Spark 05-09 M200 2nd Gen (1000cc) | D123: FD/L | E123: FY | F123: 2Hole | G123: =SUMIFS(X!$F$5:$F$2005,X!$D$5:$D$2005,'Current Stock'!A123) -> 0 | H123: =SUMIFS(PENJUALAN!$E$4:$E$11000,PENJUALAN!$C$4:$C$11000,'Current Stock'!A123) -> 0 | I123: =G123-H123 -> 0
A124: =CONCATENATE(B124,E124) -> FDR-SPARK05FY | B124: FDR-SPARK05 | C124: Chevrolet Spark 05-09 M200 2nd Gen (1000cc) | D124: FD/R | E124: FY | F124: 2Hole | G124: =SUMIFS(X!$F$5:$F$2005,X!$D$5:$D$2005,'Current Stock'!A124) -> 0 | H124: =SUMIFS(PENJUALAN!$E$4:$E$11000,PENJUALAN!$C$4:$C$11000,'Current Stock'!A124) -> 0 | I124: =G124-H124 -> 0
A125: =CONCATENATE(B125,E125) -> RDR-SPARK05FY | B125: RDR-SPARK05 | C125: Chevrolet Spark 05-09 M200 2nd Gen (1000cc) | D125: RD/R | E125: FY | G125: =SUMIFS(X!$F$5:$F$2005,X!$D$5:$D$2005,'Current Stock'!A125) -> 0 | H125: =SUMIFS(PENJUALAN!$E$4:$E$11000,PENJUALAN!$C$4:$C$11000,'Current Stock'!A125) -> 0 | I125: =G125-H125 -> 0
A126: =CONCATENATE(B126,E126) -> LFW-SPARK10FY | B126: LFW-SPARK10 | C126: Chevrolet Spark 10-15 M300 3rd Gen (1200cc) | D126: LFW | E126: FY | F126: X/MB | G126: =SUMIFS(X!$F$5:$F$2005,X!$D$5:$D$2005,'Current Stock'!A126) -> 0 | H126: =SUMIFS(PENJUALAN!$E$4:$E$11000,PENJUALAN!$C$4:$C$11000,'Current Stock'!A126) -> 0 | I126: =G126-H126 -> 0
A127: =CONCATENATE(B127,E127) -> TRW-SPARK10FY | B127: TRW-SPARK10 | C127: Chevrolet Spark 10-15 M300 3rd Gen (1200cc) | D127: TRW | E127: FY | F127: X/H | G127: =SUMIFS(X!$F$5:$F$2005,X!$D$5:$D$2005,'Current Stock'!A127) -> 0 | H127: =SUMIFS(PENJUALAN!$E$4:$E$11000,PENJUALAN!$C$4:$C$11000,'Current Stock'!A127) -> 0 | I127: =G127-H127 -> 0
A128: =CONCATENATE(B128,E128) -> FDL-SPARK10FY | B128: FDL-SPARK10 | C128: Chevrolet Spark 10-15 M300 3rd Gen (1200cc) | D128: FD/L | E128: FY | F128: 2Hole | G128: =SUMIFS(X!$F$5:$F$2005,X!$D$5:$D$2005,'Current Stock'!A128) -> 0 | H128: =SUMIFS(PENJUALAN!$E$4:$E$11000,PENJUALAN!$C$4:$C$11000,'Current Stock'!A128) -> 0 | I128: =G128-H128 -> 0
A129: =CONCATENATE(B129,E129) -> FDR-SPARK10FY | B129: FDR-SPARK10 | C129: Chevrolet Spark 10-15 M300 3rd Gen (1200cc) | D129: FD/R | E129: FY | F129: 2Hole | G129: =SUMIFS(X!$F$5:$F$2005,X!$D$5:$D$2005,'Current Stock'!A129) -> 0 | H129: =SUMIFS(PENJUALAN!$E$4:$E$11000,PENJUALAN!$C$4:$C$11000,'Current Stock'!A129) -> 0 | I129: =G129-H129 -> 0
...

Sheet LIST KACA PINDAHAN 
B1: Kode Barang | C1: Rak | D1: Jumlah masuk peti | E1: Peti | F1: SISA DIRAK | G1: Current Stok LIVE | H1: Keterangan
A2: 1 | B2: LFW-DATSUNGOMU | C2: B8T2 | D2: 10 | E2: 1 | F2: 0 | G2: =IFERROR(VLOOKUP(A2,Oktober25,9,FALSE),"") -> #ERROR! | K2: SWR-KAPSUL02LONGASH 3PC | N2: SWR-KAPSUL02LONGASH 4PC
A3: 2 | B3: LFW-JUKEXYG | C3: B9T2 | D3: 0 | E3: 1 | F3: 0 | K3: SFL-HIACEXYG 2PC | N3: SFL-HIACEXYG 2PC
A4: 3 | B4: LFW-CONFEROMU | C4: A8T1 | D4: 1 | E4: 1 | F4: 0 | G4: DIRUKO BARU 1PC | K4: RDL-PICANTO04FY 1PC | N4: RDL-PICANTO04FY 1PC
A5: 4 | B5: LFW-AVANZA11MU | C5: A5T1 | D5: 0 | E5: 2 | F5: 1 | H5: KACA FILM | K5: RDR-PICANTO04FY 1PC | N5: RDR-PICANTO04FY 1PC
A6: 5 | B6: LFW-KAPSUL02XYG | C6: A5T2 | D6: 2 | E6: 2 | F6: 0 | G6: DIRUKO BARU | K6: RDR-FORTUNER05XYG 2PC | N6: RDR-FORTUNER05XYG 2PC
A7: 6 | B7: LFW-FORTUNER15AGC | C7: B3T2 | D7: 0 | E7: 2 | F7: 1 | G7: DIRUKO BARU | K7: RDL-FORTUNER05XYG 2PC | N7: RDL-FORTUNER05XYG 2PC
A8: 7 | B8: LFW-FORTUNER05MSG | C8: A2T2 | D8: 0 | E8: 2 | F8: 1 | G8: DIRUKO BARU | K8: RDR-HILUX05ASH 1PC | N8: RDR-HILUX05ASH 1PC
A9: 9 | B9: LFW-KAPSUL97XYG | C9: A5T2 | D9: 0 | E9: 2 | F9: 0 | G9: DIRUKO BARU | K9: RDR-INNOVA04ASH 1PC | N9: RDR-GRANMAXASH 2PC
A10: 10 | B10: LFW-AVANZA16MU | C10: B2T1 | D10: 0 | E10: 2 | F10: 0 | G10: DIRUKO BARU | K10: RDL-AVANZA21ASH 3PC | N10: RDL-GRANMAXASH 2PC
A11: 11 | B11: LFW-AVANZA03MU | C11: B2T1 | D11: 0 | E11: 2 | F11: 2 | G11: DIRUKO BARU | K11: RDR-AVANZA21ASH 2PC | N11: RDR-INNOVA04ASH 1PC
A12: 12 | B12: LFW-CAMRY02XYG | C12: A1T2 | D12: 2 | E12: 3 | F12: 0 | K12: RDR-CRV02ASH 1PC | N12: RDL-INNOVA04ASH 1PC
A13: 13 | B13: LFW-CAMRY96XYG | C13: A1T2 | D13: 1 | E13: 3 | F13: 0 | K13: RDL-AVANZA11ASH 2PC | N13: RDL-AVANZA111ASH 2PC
A14: 14 | B14: LFW-CAMRY11NORSXYG | C14: A1T2 | D14: 1 | E14: 3 | F14: 0 | K14: RDR-AVANZA11ASH 2PC | N14: RDR-AVANZA11ASH 2PC
A15: 15 | B15: LFW-CAMRY06XYG | C15: A1T2 | D15: 1 | E15: 3 | F15: 0 | K15: RDL-INNOVA04ASH 1PC | N15: RDL-AVANZA21ASH 3PC
A16: 16 | B16: LFW-CAMRY06RSXYG | C16: A1T2 | D16: 0 | E16: 3 | F16: 0 | K16: RDL-HILUX15XYG 1PC | N16: RDR-CRV02ASH 1PC
A17: 17 | B17: LFW-CAMRY11XYG | C17: A1T2 | D17: 1 | E17: 3 | F17: 0 | K17: RDR-HILUX15XYG 0PC | N17: RDL-HILUX15XYG 1PC
A18: 18 | B18: LFW-ALTIS13RSXYG | C18: A1T2 | D18: 1 | E18: 3 | F18: 0 | K18: RDL-AVANZA03ASH 2PC | N18: RDR-HILUX15XYG 1PC
A19: 19 | B19: LFW-RANGER11RSXYG | C19: A3T2 | D19: 2 | E19: 3 | F19: 0 | K19: RDR-AVANZA03ASH 2PC | N19: RDL-AVANZA03ASH 2PC
A20: 20 | B20: LFW-RANGER11MU | C20: A3T2 | D20: 1 | E20: 3 | F20: 0 | K20: RDR-GRANMAXASH 2PC | N20: RDR-AVANZA03ASH 2PC
A21: 21 | B21: LFW-ALTIS00XYG | C21: A1T2 | D21: 1 | E21: 3 | F21: 0 | K21: RDL-GRANMAXASH 2PC | N21: RDR-RUSH17ASH 1PC
A22: 22 | B22: LFW-FIESTAMU | C22: A3T1 | D22: 2 | E22: 4 | F22: 0 | G22: KIRIM 11/11/25 | K22: RDR-RUSH17ASH 1PC | N22: RDL-RUSH17ASH 1PC
A23: 23 | B23: LFW-C26XYG | C23: A1T1 | D23: 0 | E23: 4 | F23: 0 | G23: KIRIM 11/11/25 | K23: RDL-RUSH17ASH 1PC | N23: RDR-LIVINAO07ASH 1PC
A24: 24 | B24: LFW-ALPHARD08RSFR | C24: A1T1 | D24: 1 | E24: 4 | F24: 0 | G24: KIRIM 11/11/25 | K24: RDR-LIVINAO07ASH 1PC | N24: RDL-LIVINA07ASH 1PC
A25: 25 | B25: LFW-ALPHARD08XYG | C25: A1T1 | D25: 1 | E25: 4 | F25: 0 | G25: KIRIM 11/11/25 | K25: RDL-LIVINA07ASH 1PC | N25: RDR-FORTUNER15ASH 1PC
A26: 26 | B26: LFW-VOXY17XYG | C26: A1T2 | D26: 1 | E26: 4 | F26: 0 | G26: KIRIM 11/11/25 | K26: RDR-FORTUNER15ASH 1PC | N26: RDL-TRITON05ASH 1PC
A27: 27 | B27: LFW-VOXY22RSFR | C27: A1T2 | D27: 1 | E27: 4 | F27: 0 | G27: KIRIM 11/11/25 | K27: RDL-TRITON05ASH 1PC | N27: RDR-PAJERO16AGC 1PC
A28: 28 | B28: LFW-W203RS1XYG | C28: A9T2 | D28: 2 | E28: 5 | F28: 0 | G28: KIRIM 11/11/25 | K28: RDR-PAJERO16AGC 1PC | N28: RDL-AGYA13ASH 2PC
A29: 29 | B29: LFW-W204RSFR | C29: A8T2 | D29: 2 | E29: 5 | F29: 0 | G29: KIRIM 11/11/25 | K29: RDL-AGYA13ASH 2PC | N29: RDR-AGYA13ASH 2PC
A30: 30 | B30: LFW-F30XYG | C30: A8T2 | D30: 1 | E30: 5 | F30: 0 | G30: KIRIM 11/11/25 | K30: RDR-AGYA13ASH 2PC | N30: RDL-XPANDERASH 1PC
A31: 31 | B31: LFW-MAZDA214RS1XYG | C31: A4T1 | D31: 0 | E31: 5 | F31: 0 | G31: KIRIM 11/11/25 | K31: RDL-XPANDERASH 1PC | N31: SWR-PANTHER00ASH 2PC
A32: 32 | B32: LFW-MAZDA214RS3XYG | C32: A4T1 | D32: 1 | E32: 5 | F32: 0 | G32: KIRIM 11/11/25 | K32: FDR-ERTIGA12ASH 5PC | N32: FDR-ERTIGA12ASH 5PC
A33: 33 | B33: LFW-CX5GEN1RSXYG | C33: A4T1 | D33: 1 | E33: 5 | F33: 0 | G33: KIRIM 11/11/25 | K33: SWR-PANTHER00ASH 2PC | N33: FDR-L300ASH 5PC
A34: 34 | B34: LFW-CX5GEN1RS2XYG | C34: A4T1 | D34: 1 | E34: 5 | F34: 0 | G34: KIRIM 11/11/25 | N34: FDL-L300ASH 1PC
A35: 35 | B35: LFW-MAZDA209XYG | C35: A4T1 | D35: 1 | E35: 5 | F35: 0 | G35: KIRIM 11/11/25 | N35: RDR-ERTIGA18MU 3PC
A36: 36 | B36: LFW-PAJERO16AGC | C36: A4T2 | D36: 2 | E36: 5 | F36: 2 | G36: KIRIM 11/11/25 | N36: SWL-GRANMAXASH 2PC
A37: 37 | B37: LFW-CIVICESTXYG | C37: B5T2 | D37: 1 | E37: 6 | F37: 0 | G37: DIRUKO BARU | N37: FDR-GRANMAXASH 2PC
A38: 38 | B38: LFW-CIVIC11XYG | C38: B7T1 | D38: 1 | E38: 6 | F38: 0 | G38: DIRUKO BARU | N38: FDL-HRV14PIL 1PC
A39: 39 | B39: LFW-CIVIC05PIL | C39: B7T1 | D39: 2 | E39: 6 | F39: 0 | G39: DIRUKO BARU | N39: RDL-PAJERO16AGC 1PC
A40: 40 | B40: LFW-CIVIC16RSXYG | C40: B7T1 | D40: 1 | E40: 6 | F40: 0 | G40: DIRUKO BARU | N40: FDL-AGYA13ASH 2PC
A41: 41 | B41: LFW-CIVICGENIOXYG | C41: B5T2 | D41: 2 | E41: 6 | F41: 0 | G41: DIRUKO BARU | N41: FDR-AGYA13ASH 1PC
A42: 42 | B42: LFW-BALENO08XYG | C42: B9T1 | D42: 1 | E42: 6 | F42: 0 | G42: DIRUKO BARU | N42: FDL-GRANMAXASH 1PC
A43: 43 | B43: LFW-BALENO15XYG | C43: B9T1 | D43: 1 | E43: 6 | F43: 0 | G43: DIRUKO BARU | N43: RDL-AVANZA11ASH 1PC
A44: 44 | B44: LFW-BALENO96MU | C44: B11T2 | D44: 2 | E44: 6 | F44: 0 | G44: DIRUKO BARU | N44: FDR-AVANZA11ASH 2PC
A45: 45 | B45: LFW-COROLLA95MU | C45: A5T2 | D45: 1 | E45: 6 | F45: 0 | G45: DIRUKO BARU | N45: SWL-APVASH 1PC
... A57: 57 | B57: LFW-PICANTO04HTMXYG | C57: A8T1 | D57: 3 | E57: 7 | F57: 0 | G57: DIRUKO BARU | N57: FDR-YARIS05ASH 1PC
A58: 58 | B58: LFW-PANTHER00ASH | C58: A13T2 | D58: 3 | E58: 8 | F58: 0 | G58: DIRUKO BARU
A59: 59 | B59: LFW-ALMAZRSXYG | C59: A9T1 | D59: 0 | E59: 8 | F59: 0 | G59: DIRUKO BARU
A60: 60 | B60: LFW-CAPTIVAXYG | C60: A9T1 | D60: 1 | E60: 8 | F60: 0 | G60: DIRUKO BARU
A61: 61 | B61: LFW-CAPTIVARSFR | C61: A9T1 | D61: 1 | E61: 8 | F61: 0 | G61: DIRUKO BARU
A62: 62 | B62: LFW-SPINXYG | C62: A9T2 | D62: 0 | E62: 8 | F62: 0 | G62: DIRUKO BARU
A63: 63 | B63: LFW-CRETAXYG | C63: A10T2 | D63: 1 | E63: 8 | F63: 0 | G63: DIRUKO BARU
A64: 64 | B64: LFW-STARGAZERXYG | C64: A10T2 | D64: 1 | E64: 8 | F64: 0 | G64: DIRUKO BARU
A65: 65 | B65: LFW-STARGAZERRSXYG | C65: A10T2 | D65: 1 | E65: 8 | F65: 0 | G65: DIRUKO BARU
A66: 66 | B66: LFW-LIVINA07MU | C66: B8T2 | D66: 2 | E66: 8 | F66: 0 | G66: DIRUKO BARU
A67: 67 | B67: LFW-CITY02XYG | C67: B5T1 | D67: 1 | E67: 8 | F67: 0 | G67: DIRUKO BARU
A68: 68 | B68: LFW-DMAX1MU | C68: A12T2 | D68: 1 | E68: 8 | F68: 0 | G68: DIRUKO BARU
A69: 69 | B69: LFW-MARCHXYG | C69: B10T2 | D69: 1 | E69: 9 | F69: 0 | G69: DIRUKO BARU
... A75: 75 | B75: LFW-MIRAGEXYG | C75: B13T2 | D75: 1 | E75: 9 | F75: 0 | G75: DIRUKO BARU
A76: 76 | B76: LFW-CRV95XYG | C76: B7T2 | D76: 1 | E76: 9 | F76: 0 | G76: DIRUKO BARU | K76: LIST RAK SEMENTARA
A77: 77 | B77: LFW-CRV05XYG | C77: B5T2 | D77: 1 | E77: 9 | F77: 0 | G77: DIRUKO BARU | K77: A2T1
A78: 78 | B78: LFW-YARIS05MU | C78: B3T1 | D78: 1 | E78: 9 | F78: 1 | G78: DIRUKO BARU | K78: LFW-CARRY19XYG 1PC
A79: 79 | B79: LFW-STREAM00NOXYG | C79: B7T1 | D79: 1 | E79: 9 | F79: 0 | G79: DIRUKO BARU
A80: 80 | B80: LFW-STREAM00MBXYG | C80: B7T1 | D80: 0 | E80: 9 | F80: 0 | G80: DIRUKO BARU
A81: 81 | B81: LFW-CORTEZASH | C81: A7T1 | D81: 0 | E81: 10 | F81: 0 | K81: A3T2
A82: 82 | B82: LFW-OUTLANDERXYG | C82: B13T2 | D82: 0 | E82: 10 | F82: 0 | G82: psg 12/11/25 | K82: TRW-YARIS17XYG
A83: 83 | B83: LFW-APVXYG | C83: B12T1 | D83: 1 | E83: 10 | F83: 0
A84: 84 | B84: LFW-ERTIGA12MU | C84: B11T1 | D84: 2 | E84: 10 | F84: 0
A85: 85 | B85: LFW-ERTIGA18MU | C85: B11T1 | D85: 1 | E85: 10 | F85: 0 | K85: A6T1
A86: 86 | B86: LFW-T30MU | C86: B9T1 | D86: 1 | E86: 10 | F86: 0 | K86: TRW-CRV17PIL
A87: 87 | B87: LFW-ACCORD93XYG | C87: B7T1 | D87: 1 | E87: 10 | F87: 0
A88: 88 | B88: LFW-CRV95XYG | C88: B7T1 | D88: 1 | E88: 10 | F88: 0 | K88: A7T1
A89: 89 | B89: LFW-HRV22PIL | C89: B7T2 | D89: 1 | E89: 10 | F89: 1 | K89: LFW FREEDXYG 2PC
A90: 90 | B90: LFW-CRV17XYG | C90: B5T2 | D90: 1 | E90: 10 | F90: 0 | K90: LFW XPANDERAGC 2PC
A91: 91 | B91: LFW-ACCORD98XYG | C91: B5T2 | D91: 1 | E91: 10 | F91: 0 | K91: LFW XPANDER MU 1PC
A92: 92 | B92: LFW-SIENTAXYG | C92: A1T1 | D92: 1 | E92: 10 | F92: 0
A93: 93 | B93: LFW-HIACEPIL | C93: A11T1 - T2 | D93: 6 | E93: 11 | F93: 0 | G93: KIRIM 11/11/25 | K93: A8T2
A94: 94 | B94: LFW-HIACE19XYG | C94: A12T1 | D94: 0 | E94: 11 | F94: 0 | G94: KIRIM 11/11/25 | K94: LFW-W204RSXYG 2PC
A95: 95 | B95: LFW-ELFNMRXYG | C95: A13T1 | D95: 0 | E95: 11 | F95: 0 | G95: KIRIM 11/11/25
A96: 96 | B96: LFW-ELFNKRXYG | C96: A13T1 | D96: 3 | E96: 11 | F96: 0 | G96: KIRIM 11/11/25 | K96: A9 T1
A97: 97 | B97: LFW-PANTHER91MU | D97: 2 | E97: 12 | F97: 0
A98: 98 | B98: LFW-CARRYASH | D98: 2 | E98: 12 | F98: 0 | K98: LFW TA11 MU 3 PC
A99: 99 | B99: LFW-L300MU | D99: 0 | E99: 12 | F99: 0 | K99: LFW TA15 MU 1 PC
A100: 100 | B100: LFW-FE700MU | D100: 2 | E100: 12 | F100: 0 | K100: LFW TA04 MU 2 PC
A101: 101 | B101: LFW-FE700XYG | D101: 1 | E101: 12 | F101: 0 | K101: LFW SIGRA MU 6 PC
A102: 102 | B102: LFW-TRAGAMU | D102: 0 | E102: 12 | F102: 0 | K102: LFW-JAZZ01MU 1PC
A103: 103 | B103: LFW-FE300MU | D103: 2 | E103: 12 | F103: 0
B104: LFW-DYNAMU | D104: 0 | E104: 12 | F104: 0
B105: LFW-CARRYFUTURAMU | D105: 1 | E105: 12 | F105: 0 | K105: A9T2
B106: LFW-CARRY19XYG | D106: 0 | E106: 12 | F106: 0 | K106: LFW-TRAGAMU 2PC
B107: LFW-ODYSSEY99XYG | C107: B6T2 | D107: 2 | E107: 13 | F107: 0 | K107: LFW-L300MU 1PC
B108: LFW-HRV22PIL | D108: 1 | E108: 13 | F108: 0
B109: LFW-CRV17PIL | D109: 1 | E109: 13 | F109: 0 | K109: A10 T1
B110: LFW-HRV14XYG | D110: 0 | E110: 13 | F110: 0
B111: LFW-HRV14PIL | D111: 1 | E111: 13 | F111: 0 | K111: LFW-BRIOAGC 1PC
B112: LFW-JAZZ13XYG | D112: 0 | E112: 13 | F112: 0 | K112: LFW AGYA 13 MU 2 PC
B113: LFW-JAZZ07MU | D113: 1 | E113: 13 | F113: 0 | K113: LFW AGYA 23 MU 1 PC
B114: TRW-ALPHARD02FR | D114: 1 | E114: 14 | F114: 0 | K114: LFW TERIOS 06 MU 3 PC
B115: TRW-ALPHARD08BLACKXYG | D115: 1 | E115: 14 | F115: 0 | K115: LFW RUSH 17 MU 2 PC
B116: TRW-ALPHARD15BLACKXYG | D116: 1 | E116: 14 | F116: 0 | K116: LFW RUSH17 XYG 1 PC
...

Sheet ASAHIMAS SBY
A1: SWR-KAPSUL02LONGASH 4PC | D1: RDL-AVANZA03ASH 2PC
A2: SFL-HIACEXYG 2PC | D2: RDR-AVANZA03ASH 2PC
A3: RDL-PICANTO04FY 1PC | D3: RDR-GRANMAXASH 2PC
A4: RDR-PICANTO04FY 1PC | D4: RDL-GRANMAXASH 2PC
A5: RDR-FORTUNER05XYG 2PC | D5: RDR-RUSH17ASH 1PC
A6: RDL-FORTUNER05XYG 2PC | D6: RDL-RUSH17ASH 1PC
A7: RDR-HILUX05ASH 1PC | D7: RDR-LIVINAO07ASH 1PC
A8: RDR-INNOVA04ASH 1PC | D8: RDL-LIVINA07ASH 1PC
A9: RDL-AVANZA21ASH 3PC | D9: RDR-FORTUNER15ASH 1PC
A10: RDR-AVANZA21ASH 2PC | D10: RDL-TRITON05ASH 1PC
A11: RDR-CRV02ASH 1PC | D11: RDR-PAJERO16AGC 1PC
A12: RDL-AVANZA11ASH 2PC | D12: RDL-AGYA13ASH 2PC
... A16: RDR-HILUX15XYG 1PC | D16: SWR-PANTHER00ASH 2PC
A21: STOK ASAHIMAS 07/03/2026
A23: Stok asahimas sby | E23: Stok kosong/habis
A25: MERK | B25: JUMLAH | C25: RAK | E25: MERK | F25: JUMLAH | G25: RAK | H25: Order
A26: SWR-KAPSUL02LONGASH | B26: 3 | E26: FDR-LOUHANASH | F26: 0 | H26: ada mu
A27: FDR-JAZZ01ASH | B27: 5 | E27: TRW-KIJANGK125PUASH | F27: 0
A28: FDL-TERIOS06ASH | B28: 5 | E28: FDR-DYNAASH | F28: 0 | H28: 5 | I28: 46094
A29: FDR-ELFNMRASH | B29: 5 | E29: FDL-FE700ASH | F29: 1 | H29: 5 | I29: x
A30: FDR-QUESTERASH | B30: 5 | E30: TRW-AVANZA21ASH | F30: 0 | H30: 5 | I30: x
A31: TRW-KAPSUL02ASH | B31: 5 | E31: FDL-ERTIGA12ASH | F31: 1 | H31: 5 | I31: 46094
A32: FDR-L300ASH | B32: 5 | E32: FDL-GRANMAXASH | F32: 1 | H32: 5 | I32: 46094
A33: SWL-INNOVA04ASH | B33: 5 | E33: FDR-GRANMAXASH | F33: 1 | H33: 5 | I33: 46094
A34: SWR-FORTUNER15ASH | B34: 5 | E34: FDL-VIOS13ASH | F34: 0
A35: FDR-ERTIGA12ASH | B35: 4 | E35: FDR-VIOS13ASH | F35: 0
A36: TRW-AVANZA21HASH | B36: 4 | E36: FDL-FREEDASH | F36: 0
A37: FDL-CARRYFUTURAASH | B37: 5 | E37: FDR-VIOS07ASH | F37: 0
A38: SWR-AVANZA03ASH | B38: 5 | E38: FDR-DATSUNASH | F38: 0
A39: SWL-AVANZA11ASH | B39: 5 | E39: RDR-MOBILIOASH | F39: 0
A40: SWR-AVANZA11ASH | B40: 3 | E40: RDL-CRV02ASH | F40: 0
A41: RDL-AVANZA21ASH | B41: 3 | E41: LFW-BRV22ASH | F41: 0 | H41: 5 | I41: x
A42: FDL-JAZZ01ASH | B42: 5 | E42: RDR-YARIS13ASH | F42: 0 | H42: 5 | I42: x | J42: 3TYR4M-3RDRTA0N
A43: FDR-SIGRA16ASH | B43: 5 | E43: SWR-AVANZA21ASH | F43: 1
E44: - | F44: 0
E45: FDL-RUSH17ASH | F45: 0 | H45: 5 | I45: x
E46: FDR-AVANZA21 | F46: 0 | H46: 5 | I46: x
E47: FDL-DYNAASH | F47: 0 | H47: 5 | I47: x
E48: FDL-ELFNMRASH | F48: 0 | H48: 5 | I48: x
E49: FDL-FORTUNER15ASH | F49: 0 | H49: 5 | I49: x | J49: 3TNF6M-AFDLTA0N
E50: RDL-FORTUNER15ASH | F50: 0 | H50: 5 | I50: x | J50: 3TNF6M-3RDLTT0N
E51: RDR-CRV12ASH | F51: 0
E52: TRW-FUTURAMBASH | F52: 0
E53: FDL-FE300ASH | F53: 0 | H53: 5 | I53: x | J53: 3FE44M-4FDLTT1
E54: LFW-CORTEZASH | F54: 0
E55: RDR-ERTIGA12ASH | F55: 0 | H55: 5 | I55: 46094
E56: FDR-FV100ASH | F56: 0
E57: FDL-RUSH17ASH | F57: 0 | H57: 5 | I57: 46094

Sheet Uang setoran
A1: Tanggal | B1: Nomor Inovice | C1: Total Cash | D1: Total Cash di Setor | E1: Sisa Uang Setor | F1: Ambil cash untuk petty cash | G1: Keterangan | H1: SETOR by LIA
A2: 46070 | B2: B260052 Rp1,350,000 | C2: 1350000 | D2: 1350000 | E2: Rp.70.000 | G2: Sisa tunai Sebelumnya Rp,70.000 | H2: Sudah
A3: 46071 | B3: B260055 Rp.1.000.000 | C3: 1000000 | D3: Rp.4,849,000 + Rp.51.000 (Sisa tunai) = Rp.4.900.000 | E3: 19000 | G3: Sisa tunai Rp.19.000 | H3: Sudah
A4: 46071 | B4: B260056 Rp.3.299.000 | C4: 3299000 | F4: Rp,500.000 | H4: Sudah
A5: 46071 | B5: B260057 Rp.550.000 | C5: 550000 | H5: Sudah
A6: 46073 | B6: B260063 Rp.2.025.000 | C6: Rp.2.025.000 | D6: Rp.2.020.000 | E6: 5000 | G6: Sisa Tunai Rp.24.000 | H6: Belum
A7: 46073 | B7: B260065 Rp.480.00 | C7: 480000 | D7: 480000 | H7: Belum

Sheet PENJUALAN
A1: PENJUALAN
A2: TANGGAL | B2: INV | C2: PRODUK | E2: PC | F2: Penjualan | K2: DAniel SunyotoD | P2: Sales via | Q2: Pembayaran | V2: Input By | W2: KO YAN | X2: Check CICI
C3: KODE | D3: NAMA | F3: Satuan | G3: Jumlah | H3: Diskon | I3: Nett | J3: Jumlah | K3: Nama | L3: No Telp | M3: Email | N3: No Pol | O3: Alamat | Q3: TUNAI | R3: TRANSFER | S3: TOKPED | T3: POTONG | U3: Kembali
A4: 45353 | B4: B240001 | C4: LFW-INNOVA04MSG | D4: =IFERROR(VLOOKUP(C4,Stock,3,FALSE),"") -> Toyota Innova 04-15 1st Gen | E4: 1 | F4: 1625000 | G4: =E4*F4 -> 1625000 | I4: =G4-H4 -> 1625000 | J4: =I4 -> 1625000 | K4: Hari Yulianto | L4: +62 812-3459-2545 | P4: Tokopedia | Q4: 1650000 | V4: CM | X4: done TF AW33
A5: 45356 | B5: C240002 | C5: LFW-JAZZ01MU | D5: =IFERROR(VLOOKUP(C5,Stock,3,FALSE),"") -> Honda Jazz 01-07 1st Gen | E5: 1 | F5: 1698000 | G5: =E5*F5 -> 1698000 | I5: =G5-H5 -> 1698000 | J5: =I5 -> 1698000 | K5: Wahyu | L5: 6282132792913 | P5: Tokopedia | R5: 350000 | S5: 1348000 | T5: 51224 | V5: CM
A6: 45357 | B6: C240003 | C6: LFW-AVANZA16MU | D6: =IFERROR(VLOOKUP(C6,Stock,3,FALSE),"") -> Toyota Avanza / Xenia 15-21 3rd Gen | E6: 3 | F6: 880000 | G6: =E6*F6 -> 2640000 | H6: 264000 | I6: =G6-H6 -> 2376000 | J6: =I6 -> 2376000 | K6: Manuju Jaya (BMJ) | L6: 082199055555 | P6: Tokopedia | R6: 2376000 | V6: CM
A7: 45357 | B7: C240003 | C7: LFW-FJ40MU | D7: =IFERROR(VLOOKUP(C7,Stock,3,FALSE),"") -> Toyota LandCruiser 74- FJ40 / Jeep Hardtop | E7: 1 | F7: 889000 | G7: =E7*F7 -> 889000 | H7: 8900 | I7: =G7-H7 -> 880100 | J7: =I7 -> 880100 | K7: Manuju Jaya | L7: 082199055555 | P7: Tokopedia | R7: 880100 | V7: CM
A8: 45357 | B8: C240003 | C8: OTH-PETIKAYU | D8: =IFERROR(VLOOKUP(C8,Stock,3,FALSE),"") -> Peti Kayu | E8: 1 | F8: 160000 | G8: =E8*F8 -> 160000 | I8: =G8-H8 -> 160000 | J8: =I8 -> 160000 | K8: Manuju Jaya | L8: 082199055555 | P8: Tokopedia | R8: 160000 | V8: CM
A9: 45358 | B9: C240004 | C9: TRW-SIGRA16MU | D9: =IFERROR(VLOOKUP(C9,Stock,3,FALSE),"") -> Toyota Calya / Sigra 16- | E9: 1 | F9: 748000 | G9: =E9*F9 -> 748000 | I9: =G9-H9 -> 748000 | J9: =I9 -> 748000 | K9: Dian Rini | L9: 6282234837411 | N9: - | O9: - | P9: Tokopedia | S9: 748000 | T9: 14960 | V9: CM
A10: 45358 | B10: C240005 | C10: LFW-CX5GEN1RSXYG | D10: =IFERROR(VLOOKUP(C10,Stock,3,FALSE),"") -> Mazda CX-5 .12-14 1st Gen KE Pre - (1 Sensor/ □ ) | E10: 1 | F10: 3666000 | G10: =E10*F10 -> 3666000 | I10: =G10-H10 -> 3666000 | J10: =I10 -> 3666000 | K10: Ricky | L10: +62 811-369-885 | P10: Tokopedia | R10: =J10 -> 3666000 | V10: CM
A11: 45360 | B11: C240006 | C11: TRW-T32XYG | D11: =IFERROR(VLOOKUP(C11,Stock,3,FALSE),"") -> Nissan X-Trail 13- T32 | E11: 1 | F11: 2782000 | G11: =E11*F11 -> 2782000 | I11: =G11-H11 -> 2782000 | J11: =I11 -> 2782000 | K11: Tommy Okan | L11: 6281280000460 | O11: Wonokromo | P11: Tokopedia | R11: 350000 | S11: 2432000 | T11: 92416 | V11: CM
A12: 45360 | B12: C240007 | C12: LFW-JUKEFR | D12: =IFERROR(VLOOKUP(C12,Stock,3,FALSE),"") -> Nissan Juke 11- | E12: 1 | F12: 1782000 | G12: =E12*F12 -> 1782000 | I12: =G12-H12 -> 1782000 | J12: =I12 -> 1782000 | K12: Buddy Tjoanda | L12: 081332154567 | O12: Maluku | P12: Sentra Bekasi | R12: 300000 | V12: CM
A13: 45360 | B13: C240007 | C13: OTH-PETIKAYU | D13: =IFERROR(VLOOKUP(C13,Stock,3,FALSE),"") -> Peti Kayu | E13: 1 | F13: 160000 | G13: =E13*F13 -> 160000 | I13: =G13-H13 -> 160000 | J13: =I13 -> 160000 | K13: Buddy Tjoanda | L13: 081332154567 | O13: Maluku | P13: Sentra Bekasi | V13: CM
A14: 45360 | B14: C240007 | C14: OTH-SERTRANSPORT | D14: =IFERROR(VLOOKUP(C14,Stock,3,FALSE),"") -> Transport | E14: 1 | F14: 250000 | G14: =E14*F14 -> 250000 | I14: =G14-H14 -> 250000 | J14: =I14 -> 250000 | K14: Buddy Tjoanda | L14: 081332154567 | O14: Maluku | P14: Sentra Bekasi | V14: CM
A15: 45363 | B15: C240008 | C15: LFW-CITY96XYG | D15: =IFERROR(VLOOKUP(C15,Stock,3,FALSE),"") -> Honda City 96-02 3rdGen (City Z) | E15: 1 | F15: 1248000 | G15: =E15*F15 -> 1248000 | I15: =G15-H15 -> 1248000 | J15: =I15 -> 1248000 | K15: Budi | L15: +62 813-3140-5595 | O15: Surabaya | P15: Tokopedia | R15: 1248000 | V15: CM
A16: 45363 | B16: C240008 | C16: OTH-SERTRANSPORT | D16: =IFERROR(VLOOKUP(C16,Stock,3,FALSE),"") -> Transport | E16: 1 | F16: 100000 | G16: =E16*F16 -> 100000 | I16: =G16-H16 -> 100000 | J16: =I16 -> 100000 | K16: Budi | L16: +62 813-3140-5595 | O16: Surabaya | P16: Tokopedia | R16: 100000 | V16: CM
A17: 45364 | B17: C240009 | C17: TRW-ALPHARD08BLACKFR | D17: =IFERROR(VLOOKUP(C17,Stock,3,FALSE),"") -> Toyota Alphard 08-15 ANH20 2nd Gen (Hitam) | E17: 1 | F17: 2748000 | G17: =E17*F17 -> 2748000 | I17: =G17-H17 -> 2748000 | J17: =I17 -> 2748000 | K17: Alfian | L17: 6281351878653 | O17: Banjar, KalSel | P17: Tokopedia | S17: 2748000 | T17: 111624 | V17: CM
A18: 45364 | B18: C240009 | C18: OTH-PETIKAYU | D18: =IFERROR(VLOOKUP(C18,Stock,3,FALSE),"") -> Peti Kayu | E18: 1 | F18: 160000 | G18: =E18*F18 -> 160000 | I18: =G18-H18 -> 160000 | J18: =I18 -> 160000 | K18: Alfian | L18: 6281351878653 | O18: Banjar, KalSel | P18: Tokopedia | S18: 160000 | V18: CM
A19: 45364 | B19: C240010 | C19: TRW-ERTIGA12XYG | D19: =IFERROR(VLOOKUP(C19,Stock,3,FALSE),"") -> Suzuki Ertiga 12-18 1st Gen MPV | E19: 1 | F19: 1099000 | G19: =E19*F19 -> 1099000 | I19: =G19-H19 -> 1099000 | J19: =I19 -> 1099000 | K19: Zudi | L19: +62 856-4505-2349 | O19: Lamongan | P19: Bandung | Q19: 1099000 | V19: RA | X19: done tf 33 - 1,100,000
A20: 45364 | B20: C240011 | C20: LFW-INNOVA04XYG | D20: =IFERROR(VLOOKUP(C20,Stock,3,FALSE),"") -> Toyota Innova 04-15 1st Gen | E20: 1 | F20: 1150000 | G20: =E20*F20 -> 1150000 | I20: =G20-H20 -> 1150000 | J20: =I20 -> 1150000 | K20: Indra | L20: 6282228898164 | O20: Surabaya | P20: Tokopedia | R20: 1150000 | V20: RA
A21: 45364 | B21: C240011 | C21: OTH-SERTRANSPORT | D21: =IFERROR(VLOOKUP(C21,Stock,3,FALSE),"") -> Transport | E21: 1 | F21: 100000 | G21: =E21*F21 -> 100000 | I21: =G21-H21 -> 100000 | J21: =I21 -> 100000 | K21: Indra | L21: 6282228898164 | O21: Surabaya | P21: Tokopedia | R21: 100000 | V21: RA
A22: 45364 | B22: C240011 | C22: OTH-PETIKAYU | D22: =IFERROR(VLOOKUP(C22,Stock,3,FALSE),"") -> Peti Kayu | E22: 1 | F22: 160000 | G22: =E22*F22 -> 160000 | I22: =G22-H22 -> 160000 | J22: =I22 -> 160000 | K22: Indra | L22: 6282228898164 | O22: Surabaya | P22: Tokopedia | R22: 160000 | V22: RA
A23: 45364 | B23: C240012 | C23: SWL-ALPHARD08HITAMXYG | D23: =IFERROR(VLOOKUP(C23,Stock,3,FALSE),"") -> Toyota Alphard 08-15 ANH20 2nd Gen (Hitam) | E23: 1 | F23: 3416000 | G23: =E23*F23 -> 3416000 | I23: =G23-H23 -> 3416000 | J23: =I23 -> 3416000 | K23: Daniel Sunyoto | L23: +62 817-399-777 | N23: L 1810 KB | O23: Surabaya | P23: Tokopedia | R23: 100000 | V23: RA | X23: SL-00001
A24: 45365 | B24: C240013 | C24: LFW-PICANTO11PIL | D24: =IFERROR(VLOOKUP(C24,Stock,3,FALSE),"") -> Kia Picanto 11-16 2nd Gen | E24: 1 | F24: 2200000 | G24: =E24*F24 -> 2200000 | I24: =G24-H24 -> 2200000 | J24: =I24 -> 2200000 | L24: +62 895-4025-29766 | O24: Surabaya | P24: Tokopedia | R24: 2200000 | V24: CM
A25: 45366 | B25: C240014 | C25: LFW-T30XYG | D25: =IFERROR(VLOOKUP(C25,Stock,3,FALSE),"") -> Nissan X-Trail 01-07 T30 | E25: 1 | F25: 1971000 | G25: =E25*F25 -> 1971000 | I25: =G25-H25 -> 1971000 | J25: =I25 -> 1971000 | K25: Zainal Arif | L25: +62 813-3678-3983 | N25: L 1884 ABP | O25: Surabaya | P25: Tokopedia | Q25: 2071000 | V25: CM | X25: 19/3/24 terima cash 2071rb
A26: 45366 | B26: C240014 | C26: OTH-SERTRANSPORT | D26: =IFERROR(VLOOKUP(C26,Stock,3,FALSE),"") -> Transport | E26: 1 | F26: 100000 | G26: =E26*F26 -> 100000 | I26: =G26-H26 -> 100000 | J26: =I26 -> 100000 | K26: Zainal Arif | L26: +62 813-3678-3983 | N26: L 1884 ABP | O26: Surabaya | P26: Tokopedia | R26: 100000 | V26: CM
A27: 45366 | B27: C240015 | C27: LFW-HRV14XYG | D27: =IFERROR(VLOOKUP(C27,Stock,3,FALSE),"") -> Honda HR-V 14-21 5D SUV | E27: 1 | F27: 2156000 | G27: =E27*F27 -> 2156000 | I27: =G27-H27 -> 2156000 | J27: =I27 -> 2156000 | K27: Chia | L27: 082139961863 | N27: S 1664 ES | O27: Gubeng, Surabaya | P27: Tokopedia | R27: 400000 | S27: 1756000 | T27: 66728 | V27: CM
A28: 45367 | B28: C240016 | C28: LFW-CITY02MU | D28: =IFERROR(VLOOKUP(C28,Stock,3,FALSE),"") -> Honda City 02-08 4th Gen Idsi GD8 | E28: 1 | F28: 2148000 | G28: =E28*F28 -> 2148000 | I28: =G28-H28 -> 2148000 | J28: =I28 -> 2148000 | K28: Jakasakti | L28: +62 812-3329-7656 | N28: N 1728 EN | O28: Lawang | P28: Tokopedia | Q28: 748000 | R28: 1400000 | V28: CM | X28: 16/3/24 tf 2jt ke aw11, sisa 600rb untuk petty cash
A29: 45367 | B29: C240017 | C29: LFW-SWIFT11MU | D29: =IFERROR(VLOOKUP(C29,Stock,3,FALSE),"") -> Suzuki Swift 11-17 2nd Gen | E29: 1 | F29: 1748000 | G29: =E29*F29 -> 1748000 | I29: =G29-H29 -> 1748000 | J29: =I29 -> 1748000 | K29: Anang | L29: +62 812-3099-1982 | N29: W 1404 QR | P29: Tokopedia | Q29: 1748000 | V29: CM | X29: 16/3/24 tf 2jt ke aw11, sisa 600rb untuk petty cash
A30: 45367 | B30: C240018 | C30: LFW-ELFNMRXYG | D30: =IFERROR(VLOOKUP(C30,Stock,3,FALSE),"") -> Isuzu Elf 17- New NMR NLR | E30: 1 | F30: 1664000 | G30: =E30*F30 -> 1664000 | I30: =G30-H30 -> 1664000 | J30: =I30 -> 1664000 | K30: Agus | L30: +62 857-4236-4861 | N30: S 8115 WM | P30: Ruko | R30: 1664000 | V30: CM
A31: 45367 | B31: C240018 | C31: OTH-SERTRANSPORT | D31: =IFERROR(VLOOKUP(C31,Stock,3,FALSE),"") -> Transport | E31: 1 | F31: 100000 | G31: =E31*F31 -> 100000 | I31: =G31-H31 -> 100000 | J31: =I31 -> 100000 | K31: Agus | L31: +62 857-4236-4861 | N31: S 8115 WM | P31: Ruko | R31: 100000 | V31: CM
A32: 45369 | B32: C240019 | C32: TRW-BRV16XYG | D32: =IFERROR(VLOOKUP(C32,Stock,3,FALSE),"") -> Honda BR-V 16- | E32: 1 | F32: 1259000 | G32: =E32*F32 -> 1259000 | I32: =G32-H32 -> 1259000 | J32: =I32 -> 1259000 | K32: Muhammad Sabirin | L32: 6281349006066 | O32: Banjarbaru | P32: Tokopedia | S32: 1259000 | T32: 55042 | V32: CM
A33: 45369 | B33: C240019 | C33: OTH-PETIKAYU | D33: =IFERROR(VLOOKUP(C33,Stock,3,FALSE),"") -> Peti Kayu | E33: 1 | F33: 160000 | G33: =E33*F33 -> 160000 | I33: =G33-H33 -> 160000 | J33: =I33 -> 160000 | K33: Muhammad Sabirin | L33: 6281349006066 | O33: Banjarbaru | P33: Tokopedia | S33: 160000 | V33: CM
A34: 45370 | B34: C240020 | C34: LFW-VIOS07MU | D34: =IFERROR(VLOOKUP(C34,Stock,3,FALSE),"") -> Toyota Vios 07-13 XP90 2nd Gen | E34: 1 | F34: 1133000 | G34: =E34*F34 -> 1133000 | I34: =G34-H34 -> 1133000 | J34: =I34 -> 1133000 | K34: Mahendra | L34: 6281349006066 | O34: Surabaya | P34: Ruko | Q34: 1133000 | V34: CM | X34: 19/3/24 terima cash 1133rb, masuk petty cash
A35: 45370 | B35: C240020 | C35: TRW-VIOS07XYG | D35: =IFERROR(VLOOKUP(C35,Stock,3,FALSE),"") -> Toyota Vios 07-13 XP90 2nd Gen | E35: 1 | F35: 1354000 | G35: =E35*F35 -> 1354000 | I35: =G35-H35 -> 1354000 | J35: =I35 -> 1354000 | K35: Mahendra | L35: 6281349006066 | O35: Surabaya | P35: Ruko | Q35: 1354000 | V35: CM | X35: 19/3/24 terima cash 1354rb, masuk petty cash
A36: 45371 | B36: C240021 | C36: OTH-SERTRANSPORT | D36: =IFERROR(VLOOKUP(C36,Stock,3,FALSE),"") -> Transport | E36: 1 | F36: 100000 | G36: =E36*F36 -> 100000 | I36: =G36-H36 -> 100000 | J36: =I36 -> 100000 | K36: Agus | L36: +62 857-4236-4861 | N36: S 8115 WM | P36: Ruko | Q36: 100000 | V36: CM | X36: 20/3/24 terima cash 100rb, masuk petty cash
A37: 45371 | B37: C240022 | C37: LFW-TERIOS06MU | D37: =IFERROR(VLOOKUP(C37,Stock,3,FALSE),"") -> Toyota Rush / Terios 06-17 | E37: 1 | F37: 1149000 | G37: =E37*F37 -> 1149000 | I37: =G37-H37 -> 1149000 | J37: =I37 -> 1149000 | K37: cevan missa | L37: 6282146315512 | N37: - | O37: Kupang | P37: Tokopedia | S37: 1149000 | T37: 50862 | V37: CM
A38: 45371 | B38: C240022 | C38: OTH-PETIKAYU | D38: =IFERROR(VLOOKUP(C38,Stock,3,FALSE),"") -> Peti Kayu | E38: 1 | F38: 160000 | G38: =E38*F38 -> 160000 | I38: =G38-H38 -> 160000 | J38: =I38 -> 160000 | K38: cevan missa | L38: 6282146315512 | N38: - | O38: Kupang | P38: Tokopedia | S38: 160000 | V38: CM
A39: 45372 | B39: C240022 | C39: LFW-CITY02MU | D39: =IFERROR(VLOOKUP(C39,Stock,3,FALSE),"") -> Honda City 02-08 4th Gen Idsi GD8 | E39: 1 | F39: 605616 | G39: =E39*F39 -> 605616 | I39: =G39-H39 -> 605616 | J39: =I39 -> 605616 | K39: PECAH | V39: CM
A40: 45372 | B40: C240022 | C40: TRW-YARIS17XYG | D40: =IFERROR(VLOOKUP(C40,Stock,3,FALSE),"") -> Toyota Yaris 18- 3rd Gen (Lampu -) XP151 | E40: 1 | K40: PECAH | V40: CM
A41: 45374 | B41: C240023 | C41: TRW-INNOVA04HXYG | D41: =IFERROR(VLOOKUP(C41,Stock,3,FALSE),"") -> Toyota Innova 04-15 1st Gen | E41: 1 | F41: 1589000 | G41: =E41*F41 -> 1589000 | I41: =G41-H41 -> 1589000 | J41: =I41 -> 1589000 | K41: Sukatno | L41: +62 821-3141-7782 | N41: W 1254 CG | O41: Gresik | P41: Sentra Bekasi | R41: 1589000 | V41: CM
A42: 45374 | B42: C240024 | C42: LFW-VIOS07MU | D42: =IFERROR(VLOOKUP(C42,Stock,3,FALSE),"") -> Toyota Vios 07-13 XP90 2nd Gen | E42: 1 | F42: 616842 | G42: =E42*F42 -> 616842 | I42: =G42-H42 -> 616842 | J42: =I42 -> 616842 | K42: WISMAN PECAH | N42: - | V42: CM
A43: 45374 | B43: C240025 | C43: LFW-JAZZ13PIL | D43: =IFERROR(VLOOKUP(C43,Stock,3,FALSE),"") -> Honda Jazz 13- 3rd Gen (Honda) | E43: 1 | F43: 2540000 | G43: =E43*F43 -> 2540000 | I43: =G43-H43 -> 2540000 | J43: =I43 -> 2540000 | K43: Angga Abdi Putra | L43: +62 822-4446-8618 | P43: Sentra Bekasi | R43: 2540000 | V43: CM
A44: 45377 | B44: C240026 | C44: OTH-RPLXLFW | D44: =IFERROR(VLOOKUP(C44,Stock,3,FALSE),"") -> Pemasangan Kaca Mobil Depan | E44: 1 | F44: 400000 | G44: =E44*F44 -> 400000 | I44: =G44-H44 -> 400000 | J44: =I44 -> 400000 | K44: Yayan | N44: L 1820 ADQ | O44: Surabaya | P44: Tokopedia | Q44: 400000 | V44: CM | X44: 26/3/24 terima cash 400rb masuk petty cash
A45: 45378 | B45: C240027 | C45: TRW-HILUX05XYG | D45: =IFERROR(VLOOKUP(C45,Stock,3,FALSE),"") -> Toyota Hilux Pickup 05-15 | E45: 1 | F45: 1069000 | G45: =E45*F45 -> 1069000 | H45: 5000 | I45: =G45-H45 -> 1064000 | J45: =I45 -> 1064000 | K45: Bpk. M. Mansyur | L45: 082302024464 | N45: A 8149 TX | O45: Surabaya | P45: Marketplace | R45: 1069000 | V45: CM
A46: 45378 | B46: C240028 | C46: LFW-BRV16XYG | D46: =IFERROR(VLOOKUP(C46,Stock,3,FALSE),"") -> Honda BR-V 16- | E46: 1 | F46: 1382000 | G46: =E46*F46 -> 1382000 | I46: =G46-H46 -> 1382000 | J46: =I46 -> 1382000 | K46: Kristi Tumpil | L46: 6281240173075 | N46: - | O46: Surabaya | P46: Tokopedia | S46: 1382000 | T46: 39490 | V46: CM
A47: 45378 | B47: C240028 | C47: OTH-SEALANTXYG | D47: =IFERROR(VLOOKUP(C47,Stock,3,FALSE),"") -> Sealant Polyurethane XYG Tube | E47: 2 | F47: 75000 | G47: =E47*F47 -> 150000 | I47: =G47-H47 -> 150000 | J47: =I47 -> 150000 | K47: Kristi Tumpil | L47: 6281240173075 | N47: - | O47: Surabaya | P47: Tokopedia | S47: 150000 | V47: CM
A48: 45378 | B48: C240028 | C48: OTH-PETIKAYU | D48: =IFERROR(VLOOKUP(C48,Stock,3,FALSE),"") -> Peti Kayu | E48: 1 | F48: 160000 | G48: =E48*F48 -> 160000 | I48: =G48-H48 -> 160000 | J48: =I48 -> 160000 | K48: Kristi Tumpil | L48: 6281240173075 | N48: - | O48: Surabaya | P48: Tokopedia | S48: 160000 | V48: CM
A49: 45379 | B49: C240029 | C49: LFW-AUDIQ508XYG | D49: =IFERROR(VLOOKUP(C49,Stock,3,FALSE),"") -> Audi Q5 08-17 | E49: 1 | F49: 6671000 | G49: =E49*F49 -> 6671000 | I49: =G49-H49 -> 6671000 | J49: =I49 -> 6671000 | K49: Autohaus | L49: +62 812-3546-923 | N49: L 1657 WS | O49: Surabaya | P49: Sentra Bekasi | R49: 7321000 | V49: CM | X49: lunas 28/3/24
A50: 45379 | B50: C240029 | C50: OTH-PETIKAYU | D50: =IFERROR(VLOOKUP(C50,Stock,3,FALSE),"") -> Peti Kayu | E50: 1 | F50: 300000 | G50: =E50*F50 -> 300000 | I50: =G50-H50 -> 300000 | J50: =I50 -> 300000 | K50: Autohaus | L50: +62 812-3546-923 | O50: Surabaya | P50: Sentra Bekasi | V50: CM
A51: 45379 | B51: C240029 | C51: OTH-SERTRANSPORT | D51: =IFERROR(VLOOKUP(C51,Stock,3,FALSE),"") -> Transport | E51: 1 | F51: 350000 | G51: =E51*F51 -> 350000 | I51: =G51-H51 -> 350000 | K51: Autohaus | L51: +62 812-3546-923 | O51: Surabaya | P51: Sentra Bekasi | V51: CM
A52: 45379 | B52: C240030 | C52: LFW-BRIOMU | D52: =IFERROR(VLOOKUP(C52,Stock,3,FALSE),"") -> Honda Brio 10- / Mobilio 11- | E52: 1 | F52: 1199000 | G52: =E52*F52 -> 1199000 | I52: =G52-H52 -> 1199000 | J52: =I52 -> 1199000 | K52: Hasim | L52: 085233443451 | O52: Surabaya | P52: Tokopedia | V52: CM
A53: 45379 | B53: C240031 | C53: TRW-NAV07XYG | D53: =IFERROR(VLOOKUP(C53,Stock,3,FALSE),"") -> Toyota NAV1/Noah 07-17 | E53: 1 | F53: 3281000 | G53: =E53*F53 -> 3281000 | I53: =G53-H53 -> 3281000 | J53: =I53 -> 3281000 | K53: Bpk. Koeswanto | L53: +62 811-3609-140/koes1to@yahoo.com | N53: L 1349 YC | O53: Surabaya | P53: MJD | Q53: 200000 | R53: 3081000 | V53: CM | X53: 28/3/24 terima cash 200rb dp masuk petty cash
A54: 45380 | B54: C240032 | C54: LFW-TERIOS06MU | D54: =IFERROR(VLOOKUP(C54,Stock,3,FALSE),"") -> Toyota Rush / Terios 06-17 | E54: 1 | F54: 1599000 | G54: =E54*F54 -> 1599000 | I54: =G54-H54 -> 1599000 | J54: =I54 -> 1599000 | K54: Ngudi Budianto | L54: +62 821-4080-2377 | O54: Blitar | P54: MJD | R54: 1599000 | V54: CM
A55: 45380 | B55: C240032 | C55: OTH-SERTRANSPORT | D55: =IFERROR(VLOOKUP(C55,Stock,3,FALSE),"") -> Transport | E55: 1 | F55: 1200000 | G55: =E55*F55 -> 1200000 | I55: =G55-H55 -> 1200000 | J55: =I55 -> 1200000 | K55: Ngudi Budianto | L55: +62 821-4080-2377 | O55: Blitar | P55: MJD | Q55: 1200000 | V55: CM | X55: tf
A56: 45380 | B56: C240032 | C56: OTH-LIST04TOYDAI | D56: =IFERROR(VLOOKUP(C56,Stock,3,FALSE),"") -> List Kaca Depan Code 04 | E56: 1 | F56: 315000 | G56: =E56*F56 -> 315000 | I56: =G56-H56 -> 315000 | J56: =I56 -> 315000 | K56: Ngudi Budianto | L56: +62 821-4080-2377 | O56: Blitar | P56: MJD | Q56: 315000 | V56: CM | X56: tf
A57: 45383 | B57: D240001 | C57: TRW-JAZZ07XYG | D57: =IFERROR(VLOOKUP(C57,Stock,3,FALSE),"") -> Honda Jazz 07-13 2nd Gen | E57: 1 | F57: 1188000 | G57: =E57*F57 -> 1188000 | I57: =G57-H57 -> 1188000 | J57: =I57 -> 1188000 | K57: Sutapa | L57: 6281216909525 | O57: Bitung | P57: Tokopedia | S57: 1188000 | V57: CM
A58: 45383 | B58: D240001 | C58: OTH-PETIKAYU | D58: =IFERROR(VLOOKUP(C58,Stock,3,FALSE),"") -> Peti Kayu | E58: 1 | F58: 160000 | G58: =E58*F58 -> 160000 | I58: =G58-H58 -> 160000 | J58: =I58 -> 160000 | K58: Sutapa | L58: 6281216909525 | O58: Bitung | P58: Tokopedia | R58: 160000 | V58: CM
A59: 45383 | B59: SJLD240001 | C59: RDL-HIACE19FR | D59: =IFERROR(VLOOKUP(C59,Stock,3,FALSE),"") -> Toyota Hi-Ace 19- Premio | F59: 0 | G59: =E59*F59 -> 0 | I59: =G59-H59 -> 0 | J59: =I59 -> 0 | K59: RJG | P59: RETUR | V59: CM
A60: 45383 | B60: SJLD240001 | C60: RDR-HIACE19FR | D60: =IFERROR(VLOOKUP(C60,Stock,3,FALSE),"") -> Toyota Hi-Ace 19- Premio | F60: 0 | G60: =E60*F60 -> 0 | I60: =G60-H60 -> 0 | J60: =I60 -> 0 | K60: RJG | P60: RETUR | V60: CM
A61: 45383 | B61: SJLD240001 | C61: SRR-HIACE19FR | D61: =IFERROR(VLOOKUP(C61,Stock,3,FALSE),"") -> Toyota Hi-Ace 19- Premio | F61: 0 | G61: =E61*F61 -> 0 | I61: =G61-H61 -> 0 | J61: =I61 -> 0 | K61: RJG | P61: RETUR | V61: CM
A62: 45383 | B62: SJLD240001 | C62: SRL-HIACE19FR | D62: =IFERROR(VLOOKUP(C62,Stock,3,FALSE),"") -> Toyota Hi-Ace 19- Premio | F62: 0 | G62: =E62*F62 -> 0 | I62: =G62-H62 -> 0 | J62: =I62 -> 0 | K62: RJG | P62: RETUR | V62: CM
A63: 45383 | B63: SJLD240001 | C63: SRR-HIACEFFR | D63: =IFERROR(VLOOKUP(C63,Stock,3,FALSE),"") -> Toyota Hi-Ace 04-20 Commuter With Frame | F63: 0 | G63: =E63*F63 -> 0 | I63: =G63-H63 -> 0 | J63: =I63 -> 0 | K63: RJG | P63: RETUR | V63: CM
A64: 45383 | B64: SJLD240001 | C64: SRR-HIACEFBLACKFR | D64: =IFERROR(VLOOKUP(C64,Stock,3,FALSE),"") -> Toyota Hi-Ace 04-20 Commuter With Frame (Hitam) | F64: 0 | G64: =E64*F64 -> 0 | I64: =G64-H64 -> 0 | J64: =I64 -> 0 | K64: RJG | P64: RETUR | V64: CM
A65: 45384 | B65: D240002 | C65: LFW-SIGRA16MU | D65: =IFERROR(VLOOKUP(C65,Stock,3,FALSE),"") -> Toyota Calya / Sigra 16- | E65: 1 | F65: 929000 | G65: =E65*F65 -> 929000 | I65: =G65-H65 -> 929000 | J65: =I65 -> 929000 | K65: Anto | L65: 085106096699 | O65: Jugrug | P65: Tokopedia | Q65: 1000000 | V65: CM
A66: 45384 | B66: D240002 | C66: OTH-RPLXLFW | D66: =IFERROR(VLOOKUP(C66,Stock,3,FALSE),"") -> Pemasangan Kaca Mobil Depan | E66: 1 | F66: 50000 | G66: =E66*F66 -> 50000 | I66: =G66-H66 -> 50000 | J66: =I66 -> 50000 | K66: Anto | L66: 085106096699 | O66: Jugrug | P66: Tokopedia | V66: CM
A67: 45385 | B67: D240003 | C67: TRW-INNOVA15XYG | D67: =IFERROR(VLOOKUP(C67,Stock,3,FALSE),"") -> Toyota Innova 15- 2nd Gen | E67: 1 | F67: 969000 | G67: =E67*F67 -> 969000 | I67: =G67-H67 -> 969000 | J67: =I67 -> 969000 | O67: HMG | P67: Handi | R67: 969000 | V67: CM
A68: 45385 | B68: D240003 | C68: OTH-SERTRANSPORT | D68: =IFERROR(VLOOKUP(C68,Stock,3,FALSE),"") -> Transport | E68: 1 | F68: 50000 | G68: =E68*F68 -> 50000 | I68: =G68-H68 -> 50000 | J68: =I68 -> 50000 | O68: HMG | P68: Handi | R68: 50000 | V68: CM
A69: 45386 | B69: D240004 | C69: LFW-ELFNKRXYG | D69: =IFERROR(VLOOKUP(C69,Stock,3,FALSE),"") -> Isuzu Elf 93- NKR NHR | E69: 1 | F69: 1500000 | G69: =E69*F69 -> 1500000 | H69: 75000 | I69: =G69-H69 -> 1425000 | J69: =I69 -> 1425000 | K69: PT. Nilam Port Terminal Indonesia | L69: +62 812-3456-8122 | N69: L 8027 BZ | O69: Perak | P69: Google Ads | R69: 1425000 | V69: CM
A70: 45387 | B70: D240005 | C70: LFW-SIGRA16MU | D70: =IFERROR(VLOOKUP(C70,Stock,3,FALSE),"") -> Toyota Calya / Sigra 16- | E70: 1 | F70: 1179000 | G70: =E70*F70 -> 1179000 | I70: =G70-H70 -> 1179000 | J70: =I70 -> 1179000 | K70: Stanley | L70: +62 812-1739-369 | O70: Darmo | P70: Google Ads | R70: 1179000 | V70: CM
A71: 45388 | B71: D240006 | C71: LFW-HILUX15MU | D71: =IFERROR(VLOOKUP(C71,Stock,3,FALSE),"") -> Toyota Hilux Pickup 15- (Revo) | E71: 1 | F71: 1599000 | G71: =E71*F71 -> 1599000 | I71: =G71-H71 -> 1599000 | J71: =I71 -> 1599000 | K71: Husin | L71: 0811378928 | P71: Tokopedia | R71: 1599000
A72: 45388 | B72: D240006 | C72: OTH-PETIKAYU | D72: =IFERROR(VLOOKUP(C72,Stock,3,FALSE),"") -> Peti Kayu | E72: 1 | F72: 160000 | G72: =E72*F72 -> 160000 | I72: =G72-H72 -> 160000 | J72: =I72 -> 160000 | K72: Husin | L72: 0811378928 | P72: Tokopedia | R72: 160000
A73: 45388 | B73: D240006 | C73: OTH-SEALANTXYG | D73: =IFERROR(VLOOKUP(C73,Stock,3,FALSE),"") -> Sealant Polyurethane XYG Tube | E73: 2 | F73: 75000 | G73: =E73*F73 -> 150000 | I73: =G73-H73 -> 150000 | J73: =I73 -> 150000 | K73: Husin | L73: 0811378928 | P73: Tokopedia | R73: 150000
A74: 45388 | B74: D240007 | C74: LFW-INNOVA15PIL | D74: =IFERROR(VLOOKUP(C74,Stock,3,FALSE),"") -> Toyota Innova 15- 2nd Gen | E74: 1 | F74: 2900000 | G74: =E74*F74 -> 2900000 | H74: 150000 | I74: =G74-H74 -> 2750000 | J74: =I74 -> 2750000 | K74: Auda Fardin Akbironi Fabian | L74: +62 812-2223-8884 | N74: S 1788 XM | P74: Google Ads | R74: 2750000
A75: 45388 | B75: D240008 | C75: TRW-AVANZA03XYG | D75: =IFERROR(VLOOKUP(C75,Stock,3,FALSE),"") -> Toyota Avanza / Xenia 03-11 1st Gen | E75: 1 | F75: 680000 | G75: =E75*F75 -> 680000 | I75: =G75-H75 -> 680000 | J75: =I75 -> 680000 | P75: Google Ads | R75: 680000
A76: 45388 | B76: D240009 | C76: TRW-ERTIGA12XYG | D76: =IFERROR(VLOOKUP(C76,Stock,3,FALSE),"") -> Suzuki Ertiga 12-18 1st Gen MPV | E76: 1 | F76: 1099000 | G76: =E76*F76 -> 1099000 | I76: =G76-H76 -> 1099000 | J76: =I76 -> 1099000 | N76: L 1906 GH | P76: Google Ads | R76: 1174000
A77: 45397 | B77: D240010 | C77: LFW-INNOVA15PIL | D77: =IFERROR(VLOOKUP(C77,Stock,3,FALSE),"") -> Toyota Innova 15- 2nd Gen | E77: 1 | F77: 2900000 | G77: =E77*F77 -> 2900000 | H77: 150000 | I77: =G77-H77 -> 2750000 | J77: =I77 -> 2750000 | K77: Ina | L77: +62 812-3040-970 | M77: Akmalghifari0@gmail.com | N77: L 1076 HS | P77: Google Ads | R77: 2750000
A78: 45397 | B78: D240011 | C78: TRW-PAJERO16XYG | D78: =IFERROR(VLOOKUP(C78,Stock,3,FALSE),"") -> Mitsubishi Pajero 16- | E78: 1 | F78: 1686000 | G78: =E78*F78 -> 1686000 | I78: =G78-H78 -> 1686000 | J78: =I78 -> 1686000 | K78: Bpk. Sawung | P78: Google Ads | R78: 1761000
A79: 45397 | B79: D240012 | C79: LFW-SWIFT11MU | D79: =IFERROR(VLOOKUP(C79,Stock,3,FALSE),"") -> Suzuki Swift 11-17 2nd Gen | E79: 1 | F79: 1748000 | G79: =E79*F79 -> 1748000 | H79: 48000 | I79: =G79-H79 -> 1700000 | J79: =I79 -> 1700000 | K79: Taufik | L79: +62 877-8883-8585 | M79: taufikhidayah692@gmail.com | N79: W 1895 NH | P79: Google Ads | R79: 1700000
A80: 45397 | B80: D240013 | C80: LFW-BRIOMU | D80: =IFERROR(VLOOKUP(C80,Stock,3,FALSE),"") -> Honda Brio 10- / Mobilio 11- | E80: 1 | F80: 1448000 | G80: =E80*F80 -> 1448000 | I80: =G80-H80 -> 1448000 | J80: =I80 -> 1448000 | K80: Heris | L80: +62 811-3431-633 | M80: herizmiko@gmail.com | N80: S 1310 NH | O80: Gresik | P80: Google Ads | R80: 1448000
A81: 45398 | B81: D240014 | C81: TRW-CRV12NONPXYG | D81: =IFERROR(VLOOKUP(C81,Stock,3,FALSE),"") -> Honda CR-V 12-16 4th Gen [Rata] | E81: 1 | F81: 1646000 | G81: =E81*F81 -> 1646000 | I81: =G81-H81 -> 1646000 | J81: =I81 -> 1646000 | K81: Park Moonki | L81: 08111368837 | M81: mkpark@apluslogistik.com | N81: B 1979 UJI | P81: Tokopedia | R81: 1646000
A82: 45398 | B82: D240015 | C82: LFW-TIMORMU | D82: =IFERROR(VLOOKUP(C82,Stock,3,FALSE),"") -> Kia Timor 95-98 / Sephia 94-05 | E82: 1 | F82: 1749000 | G82: =E82*F82 -> 1749000 | I82: =G82-H82 -> 1749000 | J82: =I82 -> 1749000 | K82: Ibnu Zuber | L82: +62 812-3030-0618 | N82: W 1003 BC | P82: MJD | Q82: 1750000
A83: 45398 | B83: D240016 | C83: LFW-JAZZ13MU | D83: =IFERROR(VLOOKUP(C83,Stock,3,FALSE),"") -> Honda Jazz 13- 3rd Gen | E83: 1 | F83: 1318000 | G83: =E83*F83 -> 1318000 | I83: =G83-H83 -> 1318000 | J83: =I83 -> 1318000 | K83: Anak Agung Bagus Dwi Ramarkandya | L83: 6281239329539 | P83: Tokopedia | S83: 1318000
A84: 45398 | B84: D240016 | C84: OTH-PETIKAYU | D84: =IFERROR(VLOOKUP(C84,Stock,3,FALSE),"") -> Peti Kayu | E84: 1 | F84: 160000 | G84: =E84*F84 -> 160000 | I84: =G84-H84 -> 160000 | J84: =I84 -> 160000 | K84: Anak Agung Bagus Dwi Ramarkandya | L84: 6281239329539 | P84: Tokopedia | S84: 160000
A85: 45399 | B85: D240017 | C85: TRW-HILUX05XYG | D85: =IFERROR(VLOOKUP(C85,Stock,3,FALSE),"") -> Toyota Hilux Pickup 05-15 | E85: 1 | F85: 895000 | G85: =E85*F85 -> 895000 | I85: =G85-H85 -> 895000 | J85: =I85 -> 895000 | K85: Sabiq | L85: +62 812-1696-0177 | M85: khoirunsabiq@gmail.com | N85: L 8609 BAC | P85: Google Ads | R85: 895000
A86: 45399 | B86: D240017 | C86: OTH-RPLXLFW | D86: =IFERROR(VLOOKUP(C86,Stock,3,FALSE),"") -> Pemasangan Kaca Mobil Depan | E86: 1 | F86: 50000 | G86: =E86*F86 -> 50000 | I86: =G86-H86 -> 50000 | J86: =I86 -> 50000 | K86: Sabiq | L86: +62 812-1696-0177 | M86: khoirunsabiq@gmail.com | N86: L 8609 BAC | P86: Google Ads | R86: 50000
A87: 45399 | B87: D240018 | C87: TRW-AGYA13ASH | D87: =IFERROR(VLOOKUP(C87,Stock,3,FALSE),"") -> Toyota Agya/Ayla | E87: 1 | F87: 819000 | G87: =E87*F87 -> 819000 | I87: =G87-H87 -> 819000 | J87: =I87 -> 819000 | K87: Muhammad Abdus Basid | L87: 083853141710 | M87: abdulbasid571@gmail.com | P87: Ruko | Q87: 900000
A88: 45399 | B88: D240018 | C88: OTH-SEALANTXYG | D88: =IFERROR(VLOOKUP(C88,Stock,3,FALSE),"") -> Sealant Polyurethane XYG Tube | E88: 1 | F88: 75000 | G88: =E88*F88 -> 75000 | I88: =G88-H88 -> 75000 | J88: =I88 -> 75000 | K88: Muhammad Abdus Basid | L88: 083853141710 | M88: abdulbasid571@gmail.com | P88: Ruko
A89: 45399 | B89: D240019 | C89: LFW-ELFNMRXYG | D89: =IFERROR(VLOOKUP(C89,Stock,3,FALSE),"") -> Isuzu Elf 17- New NMR NLR | E89: 1 | F89: 1464000 | G89: =E89*F89 -> 1464000 | I89: =G89-H89 -> 1464000 | J89: =I89 -> 1464000 | L89: +62 838-4508-7293 | N89: L 8256 ND | P89: Google Ads | Q89: 1500000
A90: 45400 | B90: D240020 | C90: TRW-AVANZA11MU | D90: =IFERROR(VLOOKUP(C90,Stock,3,FALSE),"") -> Toyota Avanza / Xenia 11-15 2nd Gen / 15-21 3rd Gen | E90: 1 | F90: 900000 | G90: =E90*F90 -> 900000 | I90: =G90-H90 -> 900000 | J90: =I90 -> 900000 | K90: Hari Purwanto | L90: +62 822-3091-2453 | N90: W 1357 TT | P90: Sentra Bekasi | Q90: 900000
A91: 45400 | B91: D240021 | C91: LFW-CROSSXYG | D91: =IFERROR(VLOOKUP(C91,Stock,3,FALSE),"") -> Toyota Corolla Cross 21- | E91: 1 | F91: 3199000 | G91: =E91*F91 -> 3199000 | I91: =G91-H91 -> 3199000 | J91: =I91 -> 3199000 | K91: Raven Delano Simon | L91: 081217429823 | O91: Malang | P91: Google Ads | R91: 3199000
A92: 45400 | B92: D240021 | C92: OTH-PETIKAYU | D92: =IFERROR(VLOOKUP(C92,Stock,3,FALSE),"") -> Peti Kayu | E92: 1 | F92: 160000 | G92: =E92*F92 -> 160000 | I92: =G92-H92 -> 160000 | J92: =I92 -> 160000 | K92: Raven Delano Simon | L92: 081217429823 | O92: Malang | P92: Google Ads | R92: 160000
A93: 45400 | B93: D240022 | C93: LFW-GRANMAXMU | D93: =IFERROR(VLOOKUP(C93,Stock,3,FALSE),"") -> Daihatsu Gran Max / Luxio 07- | E93: 1 | F93: 988000 | G93: =E93*F93 -> 988000 | I93: =G93-H93 -> 988000 | J93: =I93 -> 988000 | K93: Azzikra | L93: +62 822-4040-8485 | M93: azzik29@gmail.com | N93: N 8772 BD | P93: Tokopedia | Q93: 1000000
A94: 45402 | B94: D240023 | C94: TRW-SIGRA16MU | D94: =IFERROR(VLOOKUP(C94,Stock,3,FALSE),"") -> Toyota Calya / Sigra 16- | E94: 1 | F94: 948000 | G94: =E94*F94 -> 948000 | I94: =G94-H94 -> 948000 | J94: =I94 -> 948000 | K94: Najib | L94: +62 877-5268-1169 | O94: Waru | P94: Google Ads | Q94: 1100000
A95: 45402 | B95: D240023 | C95: OTH-SERTRANSPORT | D95: =IFERROR(VLOOKUP(C95,Stock,3,FALSE),"") -> Transport | E95: 1 | F95: 150000 | G95: =E95*F95 -> 150000 | I95: =G95-H95 -> 150000 | J95: =I95 -> 150000 | K95: Najib | L95: +62 877-5268-1169 | O95: Waru | P95: Google Ads
A96: 45402 | B96: D240024 | C96: LFW-AVANZA16MU | D96: =IFERROR(VLOOKUP(C96,Stock,3,FALSE),"") -> Toyota Avanza / Xenia 15-21 3rd Gen | E96: 1 | F96: 1079000 | G96: =E96*F96 -> 1079000 | I96: =G96-H96 -> 1079000 | J96: =I96 -> 1079000 | K96: Fendi | L96: +62 856-4807-6245 | M96: efendyachg@gmail.com | N96: M 1214 HC | P96: Google Ads | Q96: 1100000
A97: 45402 | B97: D240025 | C97: LFW-FREEDXYG | D97: =IFERROR(VLOOKUP(C97,Stock,3,FALSE),"") -> Honda Freed 08-16 1st gen | E97: 1 | F97: 1918000 | G97: =E97*F97 -> 1918000 | I97: =G97-H97 -> 1918000 | J97: =I97 -> 1918000 | K97: Rendy Alfi | L97: +62 819-1391-8272 | O97: Sidoarjo | P97: Google Ads | Q97: 1918000
A98: 45402 | B98: D240025 | C98: OTH-SERTRANSPORT | D98: =IFERROR(VLOOKUP(C98,Stock,3,FALSE),"") -> Transport | E98: 1 | F98: 150000 | G98: =E98*F98 -> 150000 | I98: =G98-H98 -> 150000 | J98: =I98 -> 150000 | K98: Rendy Alfi | L98: +62 819-1391-8272 | O98: Sidoarjo | P98: Google Ads | Q98: 150000
A99: 45403 | B99: D240026 | C99: LFW-BRIOMU | D99: =IFERROR(VLOOKUP(C99,Stock,3,FALSE),"") -> Honda Brio 10- / Mobilio 11- | E99: 1 | F99: 1448000 | G99: =E99*F99 -> 1448000 | I99: =G99-H99 -> 1448000 | J99: =I99 -> 1448000 | K99: Malika | L99: +62 813-3202-1118 | M99: malikaalula@gmail.com | N99: N 1888 XS | P99: Google Ads | R99: 1448000
A100: 45403 | B100: D240027 | C100: LFW-SIGRA16MU | D100: =IFERROR(VLOOKUP(C100,Stock,3,FALSE),"") -> Toyota Calya / Sigra 16- | E100: 1 | F100: 1149000 | G100: =E100*F100 -> 1149000 | H100: 49000 | I100: =G100-H100 -> 1100000 | J100: =I100 -> 1100000 | K100: Ali Duro | L100: +62 819-3829-9520 | O100: Madura | P100: Google Ads | Q100: 200000 | R100: 1000000
...

Sheet INV TTD A4 2
A1: SENTRA AUTOGLASS SURABAYA | J1: Tanggal | L1: 46139
A2: Jl. Bratang Gede No.138, Ngagelrejo, Kec. Wonokromo, Surabaya, Jawa Timur 60245 | J2: Kepada Yth.
A3: (+62) 81288009878 | sentraautoglass.sby@gmail.com | J3: Auto77
J4: +62 856-0608-8887
J5: Surabaya
D7: NOTA PENJUALAN
A9: INV | B9: D260092 | J9: NO POL
A10: No | B10: Kode | C10: =IFERROR(VLOOKUP(B10,Stock,3,FALSE),"") | H10: Qty | J10: Harga Satuan | L10: Jumlah
A11: 1 | B11: OTH-RPLXTRW | C11: =IFERROR(VLOOKUP(B11,Stock,3,FALSE),"") -> Pemasangan Kaca Mobil Belakang | H11: 1 | I11: PC | J11: 450000 | L11: =H11*J11 -> 450000
C12: =IFERROR(VLOOKUP(B12,Stock,3,FALSE),"") | L12: =H12*J12 -> 0
C13: =IFERROR(VLOOKUP(B13,Stock,3,FALSE),"") | L13: =H13*J13 -> 0
C14: =IFERROR(VLOOKUP(B14,Stock,3,FALSE),"") | L14: =H14*J14 -> 0
C15: =IFERROR(VLOOKUP(B15,Stock,3,FALSE),"") | L15: =H15*J15 -> 0
C16: =IFERROR(VLOOKUP(B16,Stock,3,FALSE),"") | L16: =H16*J16 -> 0
B17: BCA 6041794388 an Alvin Wijaya | L17: =H17*J17 -> 0
K18: TOTAL | L18: =SUM(L11:L17) -> 450000
D19: Penerima | F19: Kaca yang sudah dipesan/dipasang tidak dapat dibatalkan/dikembalikan. Tidak ada garansi kaca. | K19: DP
K20: NETTO | L20: =L18-L19 -> 450000
K22: Ket
A23: Trust the Experts, Drive Safer and Clearer | D23: .................... | K23: JASA BONGKAR
A29: SENTRA AUTOGLASS SURABAYA | J29: Tanggal | L29: =L1 -> 46139
A30: =A2 -> Jl. Bratang Gede No.138, Ngagelrejo, Kec. Wonokromo, Surabaya, Jawa Timur 60245 | J30: Kepada Yth.
A31: (+62) 81288009878 | sentraautoglass.sby@gmail.com | J31: =J3 -> Auto77
J32: =J4 -> +62 856-0608-8887
J33: =J5 -> Surabaya
D35: NOTA PENJUALAN
A37: INV | B37: =B9 -> D260092 | J37: NO POL | L37: =L9
A38: No | B38: Kode | C38: Nama Barang | H38: Qty | J38: Harga Satuan | L38: Jumlah
A39: 1 | B39: =B11 -> OTH-RPLXTRW | C39: =IFERROR(VLOOKUP(B39,Stock,3,FALSE),"") -> Pemasangan Kaca Mobil Belakang | H39: =H11 -> 1 | I39: PC | J39: =J11 -> 450000 | L39: =H39*J39 -> 450000
A40: =A12 | B40: =B12 | C40: =IFERROR(VLOOKUP(B40,Stock,3,FALSE),"") | H40: =H12 | I40: =I12 | J40: =J12 | L40: =H40*J40 -> 0
A41: =A13 | B41: =B13 | C41: =IFERROR(VLOOKUP(B41,Stock,3,FALSE),"") | H41: =H13 | I41: =I13 | J41: =J13 | L41: =H41*J41 -> 0
A42: =A14 | B42: =B14 | C42: =IFERROR(VLOOKUP(B42,Stock,3,FALSE),"") | H42: =H14 | I42: =I14 | J42: =J14 | L42: =H42*J42 -> 0
A43: =A15 | B43: =B15 | C43: =IFERROR(VLOOKUP(B43,Stock,3,FALSE),"") | H43: =H15 | I43: =I15 | J43: =J15 | L43: =H43*J43 -> 0
L44: =H44*J44 -> 0
A45: =A17 | B45: =B17 -> BCA 6041794388 an Alvin Wijaya | I45: =I17 | J45: =J17 | L45: =L17 -> 0
K46: TOTAL | L46: =L18 -> 450000
D47: Penerima | F47: Kaca yang sudah dipesan/dipasang tidak dapat dibatalkan/dikembalikan. Tidak ada garansi kaca. | K47: =K19 -> DP | L47: =L19
K48: NETTO | L48: =L20 -> 450000
K50: Ket
A51: Trust the Experts, Drive Safer and Clearer | D51: .................... | K51: =K23 -> JASA BONGKAR
K52: =K24

Sheet INV TTD A4 3
A1: SENTRA AUTOGLASS SURABAYA | J1: Tanggal | L1: 46139
A2: Jl. Bratang Gede No.138, Ngagelrejo, Kec. Wonokromo, Surabaya, Jawa Timur 60245 | J2: Kepada Yth.
A3: (+62) 81288009878 | sentraautoglass.sby@gmail.com | J3: Bpk Piter candra
J4: +62 818-542-003
J5: Surabaya
D7: NOTA PENJUALAN
A9: INV | B9: D260092 | J9: NO POL
A10: No | B10: Kode | C10: Nama Barang | H10: Qty | J10: Harga Satuan | L10: Jumlah
A11: 1 | B11: LFW-TERRA18RSXYG | C11: =IFERROR(VLOOKUP(B11,Stock,3,FALSE),"") -> Nissan Terra 18- | H11: 1 | I11: PC | J11: 3000000 | L11: =H11*J11 -> 3000000
A12: 2 | B12: OTH-PETIKAYU | C12: =IFERROR(VLOOKUP(B12,Stock,3,FALSE),"") -> Peti Kayu | H12: 1 | I12: X | J12: 200000 | L12: =H12*J12 -> 200000
C13: =IFERROR(VLOOKUP(B13,Stock,3,FALSE),"") | L13: =H13*J13 -> 0
C14: =IFERROR(VLOOKUP(B14,Stock,3,FALSE),"") | L14: =H14*J14 -> 0
C15: =IFERROR(VLOOKUP(B15,Stock,3,FALSE),"") | L15: =H15*J15 -> 0
C16: =IFERROR(VLOOKUP(B16,Stock,3,FALSE),"") | L16: =H16*J16 -> 0
C17: =IFERROR(VLOOKUP(B17,Stock,3,FALSE),"")
B18: BCA 6041794388 an Alvin Wijaya | L18: =H18*J18 -> 0
K19: TOTAL | L19: =SUM(L11:L18) -> 3200000
D20: Penerima | F20: Kaca yang sudah dipesan/dipasang tidak dapat dibatalkan/dikembalikan. Tidak ada garansi kaca. | K20: DP | L20: 1600000
K21: NETTO | L21: =L19-L20 -> 1600000
K23: Ket
A24: Trust the Experts, Drive Safer and Clearer | D24: .................... | K24: EXCLUDE BIAYA CARGO
A30: SENTRA AUTOGLASS SURABAYA | J30: Tanggal | L30: =L1 -> 46139
A31: =A2 -> Jl. Bratang Gede No.138, Ngagelrejo, Kec. Wonokromo, Surabaya, Jawa Timur 60245 | J31: Kepada Yth.
A32: (+62) 81288009878 | sentraautoglass.sby@gmail.com | J32: =J3 -> Bpk Piter candra
J33: =J4 -> +62 818-542-003
J34: =J5 -> Surabaya
J35: =J6
D36: NOTA PENJUALAN
A38: INV | B38: =B9 -> D260092 | J38: NO POL | L38: =L9
A39: No | B39: Kode | C39: Nama Barang | H39: Qty | J39: Harga Satuan | L39: Jumlah
A40: =A11 -> 1 | B40: =B11 -> LFW-TERRA18RSXYG | C40: =IFERROR(VLOOKUP(B40,Stock,3,FALSE),"") -> Nissan Terra 18- | H40: =H11 -> 1 | I40: PC | J40: =J11 -> 3000000 | L40: =H40*J40 -> 3000000
A41: =A12 -> 2 | B41: =B12 -> OTH-PETIKAYU | C41: =IFERROR(VLOOKUP(B41,Stock,3,FALSE),"") -> Peti Kayu | H41: =H12 -> 1 | I41: =I12 -> X | J41: =J12 -> 200000 | L41: =H41*J41 -> 200000
A42: =A13 | B42: =B13 | C42: =IFERROR(VLOOKUP(B42,Stock,3,FALSE),"") | H42: =H13 | I42: =I13 | J42: =J13 | L42: =H42*J42 -> 0
A43: =A14 | B43: =B14 | C43: =IFERROR(VLOOKUP(B43,Stock,3,FALSE),"") | H43: =H14 | I43: =I14 | J43: =J14 | L43: =H43*J43 -> 0
A44: =A15 | B44: =B15 | C44: =IFERROR(VLOOKUP(B44,Stock,3,FALSE),"") | H44: =H15 | I44: =I15 | J44: =J15 | L44: =H44*J44 -> 0
B45: =B16 | L45: =H45*J45 -> 0
A46: =A18 | B46: =B18 -> BCA 6041794388 an Alvin Wijaya | I46: =I18 | J46: =J18 | L46: =L18 -> 0
K47: TOTAL | L47: =L19 -> 3200000
D48: Penerima | F48: Kaca yang sudah dipesan/dipasang tidak dapat dibatalkan/dikembalikan. Tidak ada garansi kaca. | K48: =K20 -> DP | L48: =L20 -> 1600000
K49: NETTO | L49: =L21 -> 1600000
K51: Ket
A52: Trust the Experts, Drive Safer and Clearer | D52: .................... | K52: =K24 -> EXCLUDE BIAYA CARGO
K53: =K25

Sheet  INV TTD A4 1 PDF
B1: SENTRA AUTOGLASS SURABAYA | K1: Tanggal | M1: 46139
B2: Jl. Bratang Gede No.138, Ngagelrejo, Kec. Wonokromo, Surabaya, Jawa Timur 60245 | K2: Kepada Yth.
B3: (+62) 81288009878 | sentraautoglass.sby@gmail.com | K3: P. David
K4: +62 857-3050-8510
K5: Surabaya
E7: NOTA PENJUALAN
B9: INV | C9: D260094 | K9: NO POL
B10: No | C10: Kode | D10: Nama Barang | I10: Qty | K10: Harga Satuan | M10: Jumlah
B11: 1 | C11: LFW-T30MU | D11: =IFERROR(VLOOKUP(C11,Stock,3,FALSE),"") -> Nissan X-Trail 01-07 T30 | I11: 1 | J11: PC | K11: 1521000 | M11: =I11*K11 -> 1521000
B12: 2 | C12: OTH-PETIKAYU | D12: =IFERROR(VLOOKUP(C12,Stock,3,FALSE),"") -> Peti Kayu | I12: 1 | J12: X | K12: 200000 | M12: =I12*K12 -> 200000
D13: =IFERROR(VLOOKUP(C13,Stock,3,FALSE),"") | M13: =I13*K13 -> 0
D14: =IFERROR(VLOOKUP(C14,Stock,3,FALSE),"") | M14: =I14*K14 -> 0
D15: =IFERROR(VLOOKUP(C15,Stock,3,FALSE),"") | M15: =I15*K15 -> 0
C16: BCA 6041794388 an Alvin Wijaya | M16: =I16*K16 -> 0
L17: TOTAL | M17: =SUM(M11:M16) -> 1721000
E18: Penerima | G18: Kaca yang sudah dipesan/dipasang tidak dapat dibatalkan/dikembalikan. Tidak ada garansi kaca. | L18: DP
L19: NETTO | M19: =M17-M18 -> 1721000
L21: Ket
B22: Trust the Experts, Drive Safer and Clearer | E22: .................... | L22: LUNAS

Sheet INV VIRTUAL
A1: SENTRA AUTOGLASS SURABAYA | J1: Tanggal | L1: 46133
A2: Jl. Bratang Gede No.138, Ngagelrejo, Kec. Wonokromo, Surabaya, Jawa Timur 60245 | J2: Kepada Yth.
A3: (+62) 81288009878 | sentraautoglass.sby@gmail.com | J3: KARMAWAN BAJAWA(Amel)
J4: Surabaya
D7: NOTA PENJUALAN
A9: INV | B9: D260078 | J9: NO POL
A10: No | B10: Kode | C10: Nama Barang | H10: Qty | J10: Harga Satuan | L10: Jumlah
A11: 1 | B11: LFW-CAPTIVAXYG | C11: =IFERROR(VLOOKUP(B11,Stock,3,FALSE),"") -> Chevrolet Captiva 06-18 1st gen C100 | H11: 1 | I11: PC | J11: 1802000 | L11: =H11*J11 -> 1802000
C12: =IFERROR(VLOOKUP(B12,Stock,3,FALSE),"") | L12: =H12*J12 -> 0
C13: =IFERROR(VLOOKUP(B13,Stock,3,FALSE),"") | L13: =H13*J13 -> 0
C14: =IFERROR(VLOOKUP(B14,Stock,3,FALSE),"") | L14: =H14*J14 -> 0
L15: =H15*J15 -> 0
K16: TOTAL | L16: =SUM(L11:L15) -> 1802000
F17: Kaca yang sudah dipesan/dipasang tidak dapat dibatalkan/dikembalikan. Tidak ada garansi kaca. | K17: DP
K18: NETTO | L18: =L16-L17 -> 1802000
K20: Ket
A21: Trust the Experts, Drive Safer and Clearer | K21: KIRIM

Sheet SURAT JALAN
A1: SENTRA AUTOGLASS SURABAYA | I1: Tanggal | L1: 46128
A2: Jl. Bratang Gede No.138, Ngagelrejo, Kec. Wonokromo, Surabaya, Jawa Timur | I2: Kepada Yth.
A3: (+62) 81288009878 | sentraautoglass.sby@gmail.com | I3: Expedisi Karya Bersama(CV Abirama)
I4: Surabaya
D9: SURAT JALAN
A10: NO | B10: D260056
A11: No | B11: Kode | C11: Nama Barang | H11: Keterangan | L11: QTY
A12: 1 | B12: LFW-CARRY19XYG | C12: =IFERROR(VLOOKUP(B12,Stock,3,FALSE),"") -> Suzuki Carry New 19- | L12: 1
C14: =IFERROR(VLOOKUP(B14,Stock,3,FALSE),"")
C15: =IFERROR(VLOOKUP(B15,Stock,3,FALSE),"")
C16: =IFERROR(VLOOKUP(B16,Stock,3,FALSE),"")
K17: Total
E18: Penerima | J18: Kaca yang sudah dipesan tidak dapat dibatalkan/dikembalikan.
B20: Trust the Experts, Drive Safer and Clearer
E21: .................... | K21: KET :
K22: KIRIM

Sheet PO
A1: Order | H1: Terima | K1: DONE
A2: Tanggal | B2: Supplier | C2: Kode | D2: Nama Barang | E2: PC | G2: Keterangan | H2: Tanggal | I2: PC | J2: Keterangan/Nota no
A3: 45784 | B3: BGI | C3: LFW-MAZDA209XYG | D3: =IFERROR(VLOOKUP(C3,Stock,3,FALSE),"") -> Mazda 2 09-14 3rd Gen | E3: 2 | G3: READY SBY | H3: 45785 | I3: 2 | K3: TRUE
A4: 45784 | B4: BGI | C4: LFW-YARIS05MU | D4: =IFERROR(VLOOKUP(C4,Stock,3,FALSE),"") -> Toyota Yaris 05-13 XP90 1st Gen | E4: 2 | G4: READY SBY | H4: 45785 | I4: 2 | K4: TRUE
A5: 45784 | B5: BGI | C5: TRW-JAZZ07XYG | D5: =IFERROR(VLOOKUP(C5,Stock,3,FALSE),"") -> Honda Jazz 07-13 2nd Gen | E5: 2 | G5: READY JKT | K5: FALSE
A6: 45775 | B6: BGI | C6: LFW-CONFEROXYG | D6: =IFERROR(VLOOKUP(C6,Stock,3,FALSE),"") -> Wuling Confero (Tanpa Spionnya) | E6: 2 | G6: READY JKT | K6: FALSE
A7: 45775 | B7: BGI | C7: TRW-RUSH17XYG | D7: =IFERROR(VLOOKUP(C7,Stock,3,FALSE),"") -> Toyota Rush / Terios 18- | E7: 3 | G7: READY JKT | K7: FALSE
A8: 45775 | B8: BGI | C8: TRW-AVANZA03XYG | D8: =IFERROR(VLOOKUP(C8,Stock,3,FALSE),"") -> Toyota Avanza / Xenia 03-11 1st Gen | E8: 5 | G8: READY JKT | K8: FALSE
A9: 45775 | B9: BGI | C9: TRW-YARIS13XYG | D9: =IFERROR(VLOOKUP(C9,Stock,3,FALSE),"") -> Toyota Yaris 13- 2nd Gen (Lampu C) XP150 | E9: 1 | G9: READY JKT | K9: FALSE
A10: 45775 | B10: BGI | C10: TRW-JAZZ01XYG | D10: =IFERROR(VLOOKUP(C10,Stock,3,FALSE),"") -> Honda Jazz 01-07 1st Gen | E10: 1 | G10: READY JKT | K10: FALSE
A11: 45775 | B11: BGI | C11: TRW-BRIO18XYG | D11: =IFERROR(VLOOKUP(C11,Stock,3,FALSE),"") -> Honda Brio 18- | E11: 2 | G11: READY JKT | K11: FALSE
A12: 45775 | B12: BGI | C12: TRW-LIVINA07XYG | D12: =IFERROR(VLOOKUP(C12,Stock,3,FALSE),"") -> Nissan Livina 07-12 L10 (Tanpa Lubang) | E12: 3 | G12: READY JKT | K12: FALSE
A13: 45785 | B13: BGI | C13: LFW-ALTIS06RSXYG | D13: =IFERROR(VLOOKUP(C13,Stock,3,FALSE),"") -> Toyota Altis 06-13 E140 10th Gen | E13: 1 | G13: READY JKT | K13: FALSE
A14: 45786 | B14: BGI | C14: LFW-VIOS13MU | D14: =IFERROR(VLOOKUP(C14,Stock,3,FALSE),"") -> Toyota Yaris 13- 2nd Gen / Vios 14- 3rd Gen | E14: 3 | G14: READY SBY | K14: FALSE
C15: LFW-CX5GEN1RS3XYG | D15: =IFERROR(VLOOKUP(C15,Stock,3,FALSE),"") -> Mazda CX-5 .14-17 1st Gen KE Facelift - (3 Sensor/ /\8 ) | E15: 1 | K15: FALSE
C16: LFW-E84XYG | D16: =IFERROR(VLOOKUP(C16,Stock,3,FALSE),"") -> BMW X1 Series 09-14 E84 (1 Sensor / [] ) | E16: 1 | K16: FALSE
C17: TRW-SIRION1XYG | D17: =IFERROR(VLOOKUP(C17,Stock,3,FALSE),"") -> Daihatsu Sirion 04-10 1st Gen | E17: 1 | K17: FALSE
C18: LFW-ECOSPORTXYG | D18: =IFERROR(VLOOKUP(C18,Stock,3,FALSE),"") -> Ford EcoSport 13- B515 | E18: 1 | K18: FALSE
C19: LFW-CRV17XYG | D19: =IFERROR(VLOOKUP(C19,Stock,3,FALSE),"") -> Honda CR-V 17- 5th Gen | E19: 1 | K19: FALSE
C20: LFW-HRV14XYG | D20: =IFERROR(VLOOKUP(C20,Stock,3,FALSE),"") -> Honda HR-V 14-21 5D SUV | E20: 1 | K20: FALSE
C21: TRW-JAZZ07XYG | D21: =IFERROR(VLOOKUP(C21,Stock,3,FALSE),"") -> Honda Jazz 07-13 2nd Gen | E21: 2 | K21: FALSE
C22: LFW-JAZZ13XYG | D22: =IFERROR(VLOOKUP(C22,Stock,3,FALSE),"") -> Honda Jazz 13- 3rd Gen | E22: 1 | K22: FALSE
C23: LFW-GAVEGAXYG | D23: =IFERROR(VLOOKUP(C23,Stock,3,FALSE),"") -> Hyundai Grand Avega 11-16 RB | E23: 1 | K23: FALSE
C24: LFW-DMAX2XYG | D24: =IFERROR(VLOOKUP(C24,Stock,3,FALSE),"") -> Isuzu D-Max 12-19 2nd Gen | E24: 1 | K24: FALSE
C25: LFW-RIO11XYG | D25: =IFERROR(VLOOKUP(C25,Stock,3,FALSE),"") -> Kia Rio 11-17 UB Hatchback | E25: 1 | K25: FALSE
C26: LFW-SPORTAGE10XYG | D26: =IFERROR(VLOOKUP(C26,Stock,3,FALSE),"") -> Kia Sportage 10-15 SL | E26: 1 | K26: FALSE
... C58: LFW-SPARK10XYG | D58: =IFERROR(VLOOKUP(C58,Stock,3,FALSE),"") -> Chevrolet Spark 10-15 M300 3rd Gen (1200cc) | E58: 1 | K58: FALSE
A59: 45796 | B59: PMK | C59: LFW-FORTUNER15AGC | D59: =IFERROR(VLOOKUP(C59,Stock,3,FALSE),"") -> Toyota Fortuner 15- 2nd Gen (Toyota) | E59: 3 | G59: PO 3-4 HARI | H59: 45798 | I59: 2 | J59: 3pc , lunas | K59: TRUE
A60: 45804 | B60: BGI | C60: LFW-FE700MU | D60: =IFERROR(VLOOKUP(C60,Stock,3,FALSE),"") -> Mitsubishi Canter FE700 01- (PS110,125) | E60: 2 | K60: FALSE
D61: =IFERROR(VLOOKUP(C61,Stock,3,FALSE),"") | K61: FALSE
D62: =IFERROR(VLOOKUP(C62,Stock,3,FALSE),"") | K62: FALSE
D63: =IFERROR(VLOOKUP(C63,Stock,3,FALSE),"") | K63: FALSE
D64: =IFERROR(VLOOKUP(C64,Stock,3,FALSE),"") | K64: FALSE
K65: FALSE
K66: FALSE
K67: FALSE
K68: FALSE
K69: FALSE
K70: FALSE
K71: FALSE
K72: FALSE
K73: FALSE
K74: FALSE
K75: FALSE
K76: FALSE
... K996: FALSE

Sheet  INV POLOS
J1: Tanggal | L1: 46134
J2: Kepada Yth.
J3: P. Tasman
J4: +62 813-3530-5670
J5: Sidoarjo
D7: NOTA PENJUALAN
A9: INV | B9: D260079 | J9: NO POL
A10: No | B10: Kode | C10: Nama Barang | H10: Qty | J10: Harga Satuan | L10: Jumlah
A11: 1 | B11: LFW-CAMRY06RSXYG | C11: =IFERROR(VLOOKUP(B11,Stock,3,FALSE),"") -> Toyota Camry 06-11 XV40 4th Gen | H11: 1 | I11: PC | J11: 3223000 | L11: =H11*J11 -> 3223000
C12: =IFERROR(VLOOKUP(B12,Stock,3,FALSE),"") | L12: =H12*J12 -> 0
C13: =IFERROR(VLOOKUP(B13,Stock,3,FALSE),"") | L13: =H13*J13 -> 0
C14: =IFERROR(VLOOKUP(B14,Stock,3,FALSE),"") | L14: =H14*J14 -> 0
L15: =H15*J15 -> 0
K17: TOTAL | L17: =SUM(L11:L16) -> 3223000
C18: Penerima | F18: Kaca yang sudah dipesan/dipasang tidak dapat dibatalkan/dikembalikan. Tidak ada garansi kaca. | K18: DEPOSIT
K19: NETTO | L19: =L17-L18 -> 3223000
C21: ................... | K21: Ket

Sheet INV TTD A4 KF
A1: SENTRA AUTOGLASS SURABAYA | J1: Tanggal | L1: 45740
A2: Jalan Simo Jawar No. 108, Simomulyo Baru, Sukomanunggal, Surabaya | J2: Kepada Yth.
A3: (+62) 81288009878 | sentraautoglass.sby@gmail.com | J3: P. Deny
J4: +62 877-6251-4735
J5: Surabaya
D7: NOTA PENJUALAN
A9: INV | B9: C250081 | J9: NO POL
A10: No | B10: Kode | C10: Nama Barang | H10: Qty | J10: Harga Satuan | L10: Jumlah
A11: 1 | B11: LFW-AVANZA16MU | C11: =IFERROR(VLOOKUP(B11,Stock,3,FALSE),"") -> Toyota Avanza / Xenia 15-21 3rd Gen | H11: 1 | I11: PC | J11: 1050000 | L11: =H11*J11 -> 1050000
A12: 2 | B12: FILM-40STD | C12: =IFERROR(VLOOKUP(B12,Stock,3,FALSE),"") -> Automotive Film Standard - Black 40% | H12: 1 | I12: X | J12: 350000 | L12: =H12*J12 -> 350000
C13: =IFERROR(VLOOKUP(B13,Stock,3,FALSE),"") | L13: =H13*J13 -> 0
C14: =IFERROR(VLOOKUP(B14,Stock,3,FALSE),"") | L14: =H14*J14 -> 0
C15: =IFERROR(VLOOKUP(B15,Stock,3,FALSE),"") | L15: =H15*J15 -> 0
L16: =H16*J16 -> 0
B17: BCA 6041794388 an Alvin Wijaya | L17: =H17*J17 -> 0
K18: TOTAL | L18: =SUM(L11:L17) -> 1400000
D19: Penerima | F19: Kaca yang sudah dipesan/dipasang tidak dapat dibatalkan/dikembalikan. | K19: DISKON | L19: 150000
K20: NETTO | L20: =L18-L19 -> 1250000
K22: Ket
A23: Trust the Experts, Drive Safer and Clearer | D23: ....................
A31: SENTRA AUTOGLASS SURABAYA | J31: Tanggal | L31: =L1 -> 45740
A32: Jalan Simo Jawar No. 108, Simomulyo Baru, Sukomanunggal, Surabaya | J32: Kepada Yth.
A33: (+62) 81288009878 | sentraautoglass.sby@gmail.com | J33: =J3 -> P. Deny
J34: =J4 -> +62 877-6251-4735
J35: =J5 -> Surabaya
D37: NOTA PENJUALAN
A39: INV | B39: =B9 -> C250081 | J39: NO POL | L39: =L9
A40: No | B40: Kode | C40: Nama Barang | H40: Qty | J40: Harga Satuan | L40: Jumlah
A41: 1 | B41: =B11 -> LFW-AVANZA16MU | C41: =C11 -> Toyota Avanza / Xenia 15-21 3rd Gen | H41: =H11 -> 1 | I41: =I11 -> PC | J41: =J11 -> 1050000 | L41: =H41*J41 -> 1050000
A42: =A12 -> 2 | B42: =B12 -> FILM-40STD | C42: =IFERROR(VLOOKUP(B42,Stock,3,FALSE),"") -> Automotive Film Standard - Black 40% | H42: =H12 -> 1 | I42: =I12 -> X | J42: =J12 -> 350000 | L42: =L12 -> 350000
A43: =A13 | B43: =B13 | C43: =IFERROR(VLOOKUP(B43,Stock,3,FALSE),"") | H43: =H13 | I43: =I13 | J43: =J13 | L43: =L13 -> 0
A44: =A14 | B44: =B14 | C44: =IFERROR(VLOOKUP(B44,Stock,3,FALSE),"") | H44: =H14 | I44: =I14 | J44: =J14 | L44: =L14 -> 0
A45: =A15 | B45: =B15 | C45: =IFERROR(VLOOKUP(B45,Stock,3,FALSE),"") | H45: =H15 | I45: =I15 | J45: =J15 | L45: =L15 -> 0
A46: =A16 | B46: =B16 | C46: =IFERROR(VLOOKUP(B46,Stock,3,FALSE),"") | H46: =H16 | I46: =I16 | J46: =J16 | L46: =L16 -> 0
A47: =A17 | B47: =B17 -> BCA 6041794388 an Alvin Wijaya | H47: =H17 | I47: =I17 | J47: =J17 | L47: =L17 -> 0
K48: TOTAL | L48: =L18 -> 1400000
D49: Penerima | F49: Kaca yang sudah dipesan/dipasang tidak dapat dibatalkan/dikembalikan. | K49: DISKON | L49: =L19 -> 150000
K50: NETTO | L50: =L20 -> 1250000
K52: Ket
A53: Trust the Experts, Drive Safer and Clearer | D53: .................... | K53: =K23

Sheet CEK CICI
A2: Kode Barang | B2: Kode Mobil | C2: Tipe Mobil | D2: Part | E2: Merk | F2: Aksesoris | G2: ORDER | H2: Masuk | I2: Keluar | J2: Stok Akhir | K2: Rak | L2: SO | M2: Alert | N2: Lain - Lain
A3: =CONCATENATE(B3,E3) -> OTH-SEALANTXYG | B3: OTH-SEALANT | C3: Sealant Polyurethane XYG Tube | D3: OTH | E3: XYG | H3: =SUMIFS(X!$F$5:$F$2005,X!$D$5:$D$2005,'CEK CICI'!A3) -> 1067 | I3: =SUMIFS(PENJUALAN!$E$4:$E$4288,PENJUALAN!$C$4:$C$4288,'CEK CICI'!A3) -> 271 | J3: =H3-I3 -> 796 | M3: 10
A4: =CONCATENATE(B4,E4) -> OTH-PETIKAYU | B4: OTH-PETI | C4: Peti Kayu | D4: OTH | E4: KAYU | H4: =SUMIFS(X!$F$5:$F$2005,X!$D$5:$D$2005,'CEK CICI'!A4) -> 32 | I4: =SUMIFS(PENJUALAN!$E$4:$E$4288,PENJUALAN!$C$4:$C$4288,'CEK CICI'!A4) -> 211 | J4: =H4-I4 -> -179 | M4: 10
A5: =CONCATENATE(B5,E5) -> OTH-SERTR | B5: OTH-SER | C5: 9092 Sealant Application | D5: OTH | E5: TR | H5: =SUMIFS(X!$F$5:$F$2005,X!$D$5:$D$2005,'CEK CICI'!A5) -> 20 | I5: =SUMIFS(PENJUALAN!$E$4:$E$4288,PENJUALAN!$C$4:$C$4288,'CEK CICI'!A5) -> 18 | J5: =H5-I5 -> 2
A6: =CONCATENATE(B6,E6) -> OTH-SERBY | B6: OTH-SER | C6: 501 Sealant Application | D6: OTH | E6: BY | H6: =SUMIFS(X!$F$5:$F$2005,X!$D$5:$D$2005,'CEK CICI'!A6) -> 780 | I6: =SUMIFS(PENJUALAN!$E$4:$E$4288,PENJUALAN!$C$4:$C$4288,'CEK CICI'!A6) -> 156 | J6: =H6-I6 -> 624
A7: =CONCATENATE(B7,E7) -> OTH-SERTRANSPORT | B7: OTH-SER | C7: Transport | D7: OTH | E7: TRANSPORT | H7: =SUMIFS(X!$F$5:$F$2005,X!$D$5:$D$2005,'CEK CICI'!A7) -> 0 | I7: =SUMIFS(PENJUALAN!$E$4:$E$4288,PENJUALAN!$C$4:$C$4288,'CEK CICI'!A7) -> 358 | J7: =H7-I7 -> -358
A8: =CONCATENATE(B8,E8) -> OTH-LIST04TOYDAI | B8: OTH-LIST04 | C8: List Kaca Depan Code 04 | D8: OTH | E8: TOYDAI | H8: =SUMIFS(X!$F$5:$F$2005,X!$D$5:$D$2005,'CEK CICI'!A8) -> 60 | I8: =SUMIFS(PENJUALAN!$E$4:$E$4288,PENJUALAN!$C$4:$C$4288,'CEK CICI'!A8) -> 58 | J8: =H8-I8 -> 2 | M8: 2
A9: =CONCATENATE(B9,E9) -> OTH-LIST11TOYDAI | B9: OTH-LIST11 | C9: List Kaca Depan Code 11 | D9: OTH | E9: TOYDAI | H9: =SUMIFS(X!$F$5:$F$2005,X!$D$5:$D$2005,'CEK CICI'!A9) -> 37 | I9: =SUMIFS(PENJUALAN!$E$4:$E$4288,PENJUALAN!$C$4:$C$4288,'CEK CICI'!A9) -> 32 | J9: =H9-I9 -> 5 | M9: 2
A10: =CONCATENATE(B10,E10) -> OTH-LISTINVTOY | B10: OTH-LISTINV | C10: List Kaca Depan INV | D10: OTH | E10: TOY | H10: =SUMIFS(X!$F$5:$F$2005,X!$D$5:$D$2005,'CEK CICI'!A10) -> 30 | I10: =SUMIFS(PENJUALAN!$E$4:$E$4288,PENJUALAN!$C$4:$C$4288,'CEK CICI'!A10) -> 27 | J10: =H10-I10 -> 3 | M10: 2
A11: =CONCATENATE(B11,E11) -> OTH-LISTWSERT12SGP | B11: OTH-LISTWSERT12 | C11: List Kaca Depan Ertiga 2012-2018 SGP | D11: OTH | E11: SGP | H11: =SUMIFS(X!$F$5:$F$2005,X!$D$5:$D$2005,'CEK CICI'!A11) -> 2 | I11: =SUMIFS(PENJUALAN!$E$4:$E$4288,PENJUALAN!$C$4:$C$4288,'CEK CICI'!A11) -> 2 | J11: =H11-I11 -> 0
A12: =CONCATENATE(B12,E12) -> OTH-LISTPJR16MIT | B12: OTH-LISTPJR16 | C12: List Kaca Depan Mitsubishi Pajero 16- / Triton 16- | D12: OTH | E12: MIT | H12: =SUMIFS(X!$F$5:$F$2005,X!$D$5:$D$2005,'CEK CICI'!A12) -> 2 | I12: =SUMIFS(PENJUALAN!$E$4:$E$4288,PENJUALAN!$C$4:$C$4288,'CEK CICI'!A12) -> 1 | J12: =H12-I12 -> 1
A13: =CONCATENATE(B13,E13) -> OTH-RPLXLFW | B13: OTH-RPLX | C13: Pemasangan Kaca Mobil Depan | D13: OTH | E13: LFW | H13: =SUMIFS(X!$F$5:$F$2005,X!$D$5:$D$2005,'CEK CICI'!A13) -> 0 | I13: =SUMIFS(PENJUALAN!$E$4:$E$4288,PENJUALAN!$C$4:$C$4288,'CEK CICI'!A13) -> 101 | J13: =H13-I13 -> -101 | M13: 100
A14: =CONCATENATE(B14,E14) -> OTH-RPLXTRW | B14: OTH-RPLX | C14: Pemasangan Kaca Mobil Belakang | D14: OTH | E14: TRW | H14: =SUMIFS(X!$F$5:$F$2005,X!$D$5:$D$2005,'CEK CICI'!A14) -> 0 | I14: =SUMIFS(PENJUALAN!$E$4:$E$4288,PENJUALAN!$C$4:$C$4288,'CEK CICI'!A14) -> 26 | J14: =H14-I14 -> -26 | M14: 100
A15: =CONCATENATE(B15,E15) -> OTH-RPLXSIDE | B15: OTH-RPLX | C15: Pemasangan Kaca Mobil Samping | D15: OTH | E15: SIDE | H15: =SUMIFS(X!$F$5:$F$2005,X!$D$5:$D$2005,'CEK CICI'!A15) -> 0 | I15: =SUMIFS(PENJUALAN!$E$4:$E$4288,PENJUALAN!$C$4:$C$4288,'CEK CICI'!A15) -> 12 | J15: =H15-I15 -> -12 | M15: 100
A16: =CONCATENATE(B16,E16) -> OTH-SERLMB | B16: OTH-SER | C16: Lembur | D16: OTH | E16: LMB | H16: =SUMIFS(X!$F$5:$F$2005,X!$D$5:$D$2005,'CEK CICI'!A16) -> 0 | I16: =SUMIFS(PENJUALAN!$E$4:$E$4288,PENJUALAN!$C$4:$C$4288,'CEK CICI'!A16) -> 37 | J16: =H16-I16 -> -37
A17: =CONCATENATE(B17,E17) -> FILM-40STD | B17: FILM-40 | C17: Automotive Film Standard - Black 40% | D17: FILM | E17: STD | H17: =SUMIFS(X!$F$5:$F$2005,X!$D$5:$D$2005,'CEK CICI'!A17) -> 0 | I17: =SUMIFS(PENJUALAN!$E$4:$E$4288,PENJUALAN!$C$4:$C$4288,'CEK CICI'!A17) -> 17 | J17: =H17-I17 -> -17
A18: =CONCATENATE(B18,E18) -> TRW-AVANZA03HAUTO | B18: TRW-AVANZA03H | C18: Toyota Avanza / Xenia 03-11 1st Gen | D18: TRW | E18: AUTO | F18: X/H | H18: =SUMIFS(X!$F$5:$F$2005,X!$D$5:$D$2005,'CEK CICI'!A18) -> 0 | I18: =SUMIFS(PENJUALAN!$E$4:$E$4288,PENJUALAN!$C$4:$C$4288,'CEK CICI'!A18) -> 0 | J18: =H18-I18 -> 0
A19: =CONCATENATE(B19,E19) -> RDR-CRV12SG | B19: RDR-CRV12 | C19: Honda CR-V 12-16 4th Gen | D19: RDR | E19: SG | H19: =SUMIFS(X!$F$5:$F$2005,X!$D$5:$D$2005,'CEK CICI'!A19) -> 0 | I19: =SUMIFS(PENJUALAN!$E$4:$E$4288,PENJUALAN!$C$4:$C$4288,'CEK CICI'!A19) -> 0 | J19: =H19-I19 -> 0
A20: =CONCATENATE(B20,E20) -> LFW-ALPHARD08RSPIL | B20: LFW-ALPHARD08RS | C20: Toyota Alphard 08-15 ANH20 2nd Gen | D20: LFW | E20: PIL | F20: X/MB/RS | H20: =SUMIFS(X!$F$5:$F$2005,X!$D$5:$D$2005,'CEK CICI'!A20) -> 0 | I20: =SUMIFS(PENJUALAN!$E$4:$E$4288,PENJUALAN!$C$4:$C$4288,'CEK CICI'!A20) -> 0 | J20: =H20-I20 -> 0
A21: =CONCATENATE(B21,E21) -> RDL-AVANZA03ASH | B21: RDL-AVANZA03 | C21: Toyota Avanza / Xenia 03-11 1st Gen | D21: RDL | E21: ASH | H21: =SUMIFS(X!$F$5:$F$2005,X!$D$5:$D$2005,'CEK CICI'!A21) -> 5 | I21: =SUMIFS(PENJUALAN!$E$4:$E$4288,PENJUALAN!$C$4:$C$4288,'CEK CICI'!A21) -> 3 | J21: =H21-I21 -> 2 | K21: A13T4
A22: =CONCATENATE(B22,E22) -> RDR-AVANZA11ASH | B22: RDR-AVANZA11 | C22: Toyota Avanza / Xenia 11-15 2nd Gen | D22: RDR | E22: ASH | H22: =SUMIFS(X!$F$5:$F$2005,X!$D$5:$D$2005,'CEK CICI'!A22) -> 10 | I22: =SUMIFS(PENJUALAN!$E$4:$E$4288,PENJUALAN!$C$4:$C$4288,'CEK CICI'!A22) -> 9 | J22: =H22-I22 -> 1 | K22: A14T3
A23: =CONCATENATE(B23,E23) -> RDL-AVANZA11ASH | B23: RDL-AVANZA11 | C23: Toyota Avanza / Xenia 11-15 2nd Gen | D23: RDL | E23: ASH | H23: =SUMIFS(X!$F$5:$F$2005,X!$D$5:$D$2005,'CEK CICI'!A23) -> 5 | I23: =SUMIFS(PENJUALAN!$E$4:$E$4288,PENJUALAN!$C$4:$C$4288,'CEK CICI'!A23) -> 3 | J23: =H23-I23 -> 2 | K23: A14T3
A24: =CONCATENATE(B24,E24) -> TRW-AVANZA11ORI | B24: TRW-AVANZA11 | C24: Toyota Avanza / Xenia 11-15 2nd Gen/3rd Gen | D24: TRW | E24: ORI | F24: X/Logo | H24: =SUMIFS(X!$F$5:$F$2005,X!$D$5:$D$2005,'CEK CICI'!A24) -> 0 | I24: =SUMIFS(PENJUALAN!$E$4:$E$4288,PENJUALAN!$C$4:$C$4288,'CEK CICI'!A24) -> 0 | J24: =H24-I24 -> 0
A25: =CONCATENATE(B25,E25) -> RDL-AVANZA11ORI | B25: RDL-AVANZA11 | C25: Toyota Avanza / Xenia 11-15 2nd Gen/3rd Gen | D25: RDL | E25: ORI | H25: =SUMIFS(X!$F$5:$F$2005,X!$D$5:$D$2005,'CEK CICI'!A25) -> 0 | I25: =SUMIFS(PENJUALAN!$E$4:$E$4288,PENJUALAN!$C$4:$C$4288,'CEK CICI'!A25) -> 0 | J25: =H25-I25 -> 0
A26: =CONCATENATE(B26,E26) -> RDR-AVANZA11ORI | B26: RDR-AVANZA11 | C26: Toyota Avanza / Xenia 11-15 2nd Gen/3rd Gen | D26: RDR | E26: ORI | H26: =SUMIFS(X!$F$5:$F$2005,X!$D$5:$D$2005,'CEK CICI'!A26) -> 0 | I26: =SUMIFS(PENJUALAN!$E$4:$E$4288,PENJUALAN!$C$4:$C$4288,'CEK CICI'!A26) -> 0 | J26: =H26-I26 -> 0
A27: =CONCATENATE(B27,E27) -> FDL-AVANZA11ORI | B27: FDL-AVANZA11 | C27: Toyota Avanza / Xenia 11-15 2nd Gen/3rd Gen | D27: FDL | E27: ORI | H27: =SUMIFS(X!$F$5:$F$2005,X!$D$5:$D$2005,'CEK CICI'!A27) -> 0 | I27: =SUMIFS(PENJUALAN!$E$4:$E$4288,PENJUALAN!$C$4:$C$4288,'CEK CICI'!A27) -> 0 | J27: =H27-I27 -> 0
A28: =CONCATENATE(B28,E28) -> FDR-AVANZA11ORI | B28: FDR-AVANZA11 | C28: Toyota Avanza / Xenia 11-15 2nd Gen/3rd Gen | D28: FDR | E28: ORI | H28: =SUMIFS(X!$F$5:$F$2005,X!$D$5:$D$2005,'CEK CICI'!A28) -> 0 | I28: =SUMIFS(PENJUALAN!$E$4:$E$4288,PENJUALAN!$C$4:$C$4288,'CEK CICI'!A28) -> 0 | J28: =H28-I28 -> 0
A29: =CONCATENATE(B29,E29) -> LFW-ETIOSASH | B29: LFW-ETIOS | C29: Toyota Etios 10- 1st Gen Sedan | D29: LFW | E29: ASH | F29: X | H29: =SUMIFS(X!$F$5:$F$2005,X!$D$5:$D$2005,'CEK CICI'!A29) -> 0 | I29: =SUMIFS(PENJUALAN!$E$4:$E$4288,PENJUALAN!$C$4:$C$4288,'CEK CICI'!A29) -> 0 | J29: =H29-I29 -> 0 | M29: 1
A30: =CONCATENATE(B30,E30) -> TRW-LUXIODAIHATSU | B30: TRW-LUXIO | C30: Daihatsu Luxio 07- | D30: TRW | E30: DAIHATSU | F30: X/Logo | H30: =SUMIFS(X!$F$5:$F$2005,X!$D$5:$D$2005,'CEK CICI'!A30) -> 12 | I30: =SUMIFS(PENJUALAN!$E$4:$E$4288,PENJUALAN!$C$4:$C$4288,'CEK CICI'!A30) -> 7 | J30: =H30-I30 -> 5 | K30: B8T3 | M30: 1
A31: =CONCATENATE(B31,E31) -> SWR-RAIZEORI | B31: SWR-RAIZE | C31: Toyota Raize / Daihatsu Rocky 20- | D31: SWR | E31: ORI | F31: X | H31: =SUMIFS(X!$F$5:$F$2005,X!$D$5:$D$2005,'CEK CICI'!A31) -> 0 | I31: =SUMIFS(PENJUALAN!$E$4:$E$4288,PENJUALAN!$C$4:$C$4288,'CEK CICI'!A31) -> 0 | J31: =H31-I31 -> 0 | M31: 1
A32: =CONCATENATE(B32,E32) -> TRW-BRV16HONDA | B32: TRW-BRV16 | C32: Honda BR-V 16- Genuine | D32: TRW | E32: HONDA | F32: X/H/Logo | H32: =SUMIFS(X!$F$5:$F$2005,X!$D$5:$D$2005,'CEK CICI'!A32) -> 0 | I32: =SUMIFS(PENJUALAN!$E$4:$E$4288,PENJUALAN!$C$4:$C$4288,'CEK CICI'!A32) -> 0 | J32: =H32-I32 -> 0 | M32: 1
A33: =CONCATENATE(B33,E33) -> LFW-AUDIB8FY | B33: LFW-AUDIB8 | C33: Audi A4 08-15 B8 | D33: LFW | E33: FY | F33: X/RS/List | H33: =SUMIFS(X!$F$5:$F$2005,X!$D$5:$D$2005,'CEK CICI'!A33) -> 0 | I33: =SUMIFS(PENJUALAN!$E$4:$E$4288,PENJUALAN!$C$4:$C$4288,'CEK CICI'!A33) -> 0 | J33: =H33-I33 -> 0
A34: =CONCATENATE(B34,E34) -> TRW-AUDIB8FY | B34: TRW-AUDIB8 | C34: TRW-AUDIB8 | D34: TRW | E34: FY | F34: X/H/A | H34: =SUMIFS(X!$F$5:$F$2005,X!$D$5:$D$2005,'CEK CICI'!A34) -> 0 | I34: =SUMIFS(PENJUALAN!$E$4:$E$4288,PENJUALAN!$C$4:$C$4288,'CEK CICI'!A34) -> 0 | J34: =H34-I34 -> 0
A35: =CONCATENATE(B35,E35) -> LFW-AUDIC7FY | B35: LFW-AUDIC7 | C35: Audi A6 11-18 C7 | D35: LFW | E35: FY | F35: X/RS/List | H35: =SUMIFS(X!$F$5:$F$2005,X!$D$5:$D$2005,'CEK CICI'!A35) -> 0 | I35: =SUMIFS(PENJUALAN!$E$4:$E$4288,PENJUALAN!$C$4:$C$4288,'CEK CICI'!A35) -> 0 | J35: =H35-I35 -> 0
A36: =CONCATENATE(B36,E36) -> TRW-AUDIC7FY | B36: TRW-AUDIC7 | C36: Audi A6 11-18 C7 | D36: TRW | E36: FY | F36: X/H/List | H36: =SUMIFS(X!$F$5:$F$2005,X!$D$5:$D$2005,'CEK CICI'!A36) -> 0 | I36: =SUMIFS(PENJUALAN!$E$4:$E$4288,PENJUALAN!$C$4:$C$4288,'CEK CICI'!A36) -> 0 | J36: =H36-I36 -> 0
A37: =CONCATENATE(B37,E37) -> LFW-E30FY | B37: LFW-E30 | C37: BMW 3 Series 82-94 E30 | D37: LFW | E37: FY | H37: =SUMIFS(X!$F$5:$F$2005,X!$D$5:$D$2005,'CEK CICI'!A37) -> 0 | I37: =SUMIFS(PENJUALAN!$E$4:$E$4288,PENJUALAN!$C$4:$C$4288,'CEK CICI'!A37) -> 0 | J37: =H37-I37 -> 0
A38: =CONCATENATE(B38,E38) -> TRW-E30FY | B38: TRW-E30 | C38: BMW 3 Series 82-94 E30 | D38: TRW | E38: FY | F38: H | H38: =SUMIFS(X!$F$5:$F$2005,X!$D$5:$D$2005,'CEK CICI'!A38) -> 0 | I38: =SUMIFS(PENJUALAN!$E$4:$E$4288,PENJUALAN!$C$4:$C$4288,'CEK CICI'!A38) -> 0 | J38: =H38-I38 -> 0
A39: =CONCATENATE(B39,E39) -> LFW-E36FY | B39: LFW-E36 | C39: BMW 3 Series 90-99 E36 | D39: LFW | E39: FY | F39: X/MB | H39: =SUMIFS(X!$F$5:$F$2005,X!$D$5:$D$2005,'CEK CICI'!A39) -> 0 | I39: =SUMIFS(PENJUALAN!$E$4:$E$4288,PENJUALAN!$C$4:$C$4288,'CEK CICI'!A39) -> 0 | J39: =H39-I39 -> 0
A40: =CONCATENATE(B40,E40) -> TRW-E36FY | B40: TRW-E36 | C40: BMW 3 Series 90-99 E36 | D40: TRW | E40: FY | F40: X/H | H40: =SUMIFS(X!$F$5:$F$2005,X!$D$5:$D$2005,'CEK CICI'!A40) -> 0 | I40: =SUMIFS(PENJUALAN!$E$4:$E$4288,PENJUALAN!$C$4:$C$4288,'CEK CICI'!A40) -> 0 | J40: =H40-I40 -> 0
A41: =CONCATENATE(B41,E41) -> FDL-E36FY | B41: FDL-E36 | C41: BMW 3 Series 90-99 E36 | D41: FD/L | E41: FY | H41: =SUMIFS(X!$F$5:$F$2005,X!$D$5:$D$2005,'CEK CICI'!A41) -> 0 | I41: =SUMIFS(PENJUALAN!$E$4:$E$4288,PENJUALAN!$C$4:$C$4288,'CEK CICI'!A41) -> 0 | J41: =H41-I41 -> 0
A42: =CONCATENATE(B42,E42) -> FDR-E36FY | B42: FDR-E36 | C42: BMW 3 Series 90-99 E36 | D42: FD/R | E42: FY | H42: =SUMIFS(X!$F$5:$F$2005,X!$D$5:$D$2005,'CEK CICI'!A42) -> 0 | I42: =SUMIFS(PENJUALAN!$E$4:$E$4288,PENJUALAN!$C$4:$C$4288,'CEK CICI'!A42) -> 0 | J42: =H42-I42 -> 0
A43: =CONCATENATE(B43,E43) -> RDL-E36FY | B43: RDL-E36 | C43: BMW 3 Series 90-99 E36 | D43: RD/L | E43: FY | H43: =SUMIFS(X!$F$5:$F$2005,X!$D$5:$D$2005,'CEK CICI'!A43) -> 0 | I43: =SUMIFS(PENJUALAN!$E$4:$E$4288,PENJUALAN!$C$4:$C$4288,'CEK CICI'!A43) -> 0 | J43: =H43-I43 -> 0
A44: =CONCATENATE(B44,E44) -> RDR-E36FY | B44: RDR-E36 | C44: BMW 3 Series 90-99 E36 | D44: RD/R | E44: FY | H44: =SUMIFS(X!$F$5:$F$2005,X!$D$5:$D$2005,'CEK CICI'!A44) -> 0 | I44: =SUMIFS(PENJUALAN!$E$4:$E$4288,PENJUALAN!$C$4:$C$4288,'CEK CICI'!A44) -> 0 | J44: =H44-I44 -> 0
A45: =CONCATENATE(B45,E45) -> LFW-E46RSFY | B45: LFW-E46RS | C45: BMW 3 Series 98-06 E46 | D45: LFW | E45: FY | F45: X/MB/RS | H45: =SUMIFS(X!$F$5:$F$2005,X!$D$5:$D$2005,'CEK CICI'!A45) -> 0 | I45: =SUMIFS(PENJUALAN!$E$4:$E$4288,PENJUALAN!$C$4:$C$4288,'CEK CICI'!A45) -> 0 | J45: =H45-I45 -> 0
A46: =CONCATENATE(B46,E46) -> LFW-E46FY | B46: LFW-E46 | C46: BMW 3 Series 98-06 E46 | D46: LFW | E46: FY | F46: X/MB | H46: =SUMIFS(X!$F$5:$F$2005,X!$D$5:$D$2005,'CEK CICI'!A46) -> 0 | I46: =SUMIFS(PENJUALAN!$E$4:$E$4288,PENJUALAN!$C$4:$C$4288,'CEK CICI'!A46) -> 0 | J46: =H46-I46 -> 0
A47: =CONCATENATE(B47,E47) -> TRW-E46FY | B47: TRW-E46 | C47: BMW 3 Series 98-06 E46 | D47: TRW | E47: FY | F47: X/H | H47: =SUMIFS(X!$F$5:$F$2005,X!$D$5:$D$2005,'CEK CICI'!A47) -> 2 | I47: =SUMIFS(PENJUALAN!$E$4:$E$4288,PENJUALAN!$C$4:$C$4288,'CEK CICI'!A47) -> 0 | J47: =H47-I47 -> 2 | K47: A4T3
A48: =CONCATENATE(B48,E48) -> FDL-E46FY | B48: FDL-E46 | C48: BMW 3 Series 98-06 E46 | D48: FD/L | E48: FY | F48: 2Hole | H48: =SUMIFS(X!$F$5:$F$2005,X!$D$5:$D$2005,'CEK CICI'!A48) -> 0 | I48: =SUMIFS(PENJUALAN!$E$4:$E$4288,PENJUALAN!$C$4:$C$4288,'CEK CICI'!A48) -> 0 | J48: =H48-I48 -> 0
A49: =CONCATENATE(B49,E49) -> FDR-E46FY | B49: FDR-E46 | C49: BMW 3 Series 98-06 E46 | D49: FD/R | E49: FY | F49: 2Hole | H49: =SUMIFS(X!$F$5:$F$2005,X!$D$5:$D$2005,'CEK CICI'!A49) -> 0 | I49: =SUMIFS(PENJUALAN!$E$4:$E$4288,PENJUALAN!$C$4:$C$4288,'CEK CICI'!A49) -> 0 | J49: =H49-I49 -> 0
A50: =CONCATENATE(B50,E50) -> RDL-E46FY | B50: RDL-E46 | C50: BMW 3 Series 98-06 E46 | D50: RD/L | E50: FY | F50: 1Hole | H50: =SUMIFS(X!$F$5:$F$2005,X!$D$5:$D$2005,'CEK CICI'!A50) -> 0 | I50: =SUMIFS(PENJUALAN!$E$4:$E$4288,PENJUALAN!$C$4:$C$4288,'CEK CICI'!A50) -> 0 | J50: =H50-I50 -> 0
A51: =CONCATENATE(B51,E51) -> RDR-E46FY | B51: RDR-E46 | C51: BMW 3 Series 98-06 E46 | D51: RD/R | E51: FY | F51: 1Hole | H51: =SUMIFS(X!$F$5:$F$2005,X!$D$5:$D$2005,'CEK CICI'!A51) -> 0 | I51: =SUMIFS(PENJUALAN!$E$4:$E$4288,PENJUALAN!$C$4:$C$4288,'CEK CICI'!A51) -> 0 | J51: =H51-I51 -> 0
A52: =CONCATENATE(B52,E52) -> LFW-E46RS2DOORFY | B52: LFW-E46RS2DOOR | C52: BMW 3 Series 98-06 E46 (2-Door Coupe) | D52: LFW | E52: FY | F52: X/MB | H52: =SUMIFS(X!$F$5:$F$2005,X!$D$5:$D$2005,'CEK CICI'!A52) -> 0 | I52: =SUMIFS(PENJUALAN!$E$4:$E$4288,PENJUALAN!$C$4:$C$4288,'CEK CICI'!A52) -> 0 | J52: =H52-I52 -> 0
A53: =CONCATENATE(B53,E53) -> LFW-E90RSFY | B53: LFW-E90RS | C53: BMW 3 Series 05-12 E90 | D53: LFW | E53: FY | F53: X/MB/RS | H53: =SUMIFS(X!$F$5:$F$2005,X!$D$5:$D$2005,'CEK CICI'!A53) -> 0 | I53: =SUMIFS(PENJUALAN!$E$4:$E$4288,PENJUALAN!$C$4:$C$4288,'CEK CICI'!A53) -> 0 | J53: =H53-I53 -> 0
A54: =CONCATENATE(B54,E54) -> LFW-E90FY | B54: LFW-E90 | C54: BMW 3 Series 05-12 E90 | D54: LFW | E54: FY | F54: X/MB | H54: =SUMIFS(X!$F$5:$F$2005,X!$D$5:$D$2005,'CEK CICI'!A54) -> 0 | I54: =SUMIFS(PENJUALAN!$E$4:$E$4288,PENJUALAN!$C$4:$C$4288,'CEK CICI'!A54) -> 0 | J54: =H54-I54 -> 0
A55: =CONCATENATE(B55,E55) -> TRW-E90FY | B55: TRW-E90 | C55: BMW 3 Series 05-12 E90 | D55: TRW | E55: FY | F55: X/H | H55: =SUMIFS(X!$F$5:$F$2005,X!$D$5:$D$2005,'CEK CICI'!A55) -> 0 | I55: =SUMIFS(PENJUALAN!$E$4:$E$4288,PENJUALAN!$C$4:$C$4288,'CEK CICI'!A55) -> 0 | J55: =H55-I55 -> 0
A56: =CONCATENATE(B56,E56) -> FDL-E90FY | B56: FDL-E90 | C56: BMW 3 Series 05-12 E90 | D56: FD/L | E56: FY | F56: 2Hole | H56: =SUMIFS(X!$F$5:$F$2005,X!$D$5:$D$2005,'CEK CICI'!A56) -> 0 | I56: =SUMIFS(PENJUALAN!$E$4:$E$4288,PENJUALAN!$C$4:$C$4288,'CEK CICI'!A56) -> 0 | J56: =H56-I56 -> 0
A57: =CONCATENATE(B57,E57) -> FDR-E90FY | B57: FDR-E90 | C57: BMW 3 Series 05-12 E90 | D57: FD/R | E57: FY | F57: 2Hole | H57: =SUMIFS(X!$F$5:$F$2005,X!$D$5:$D$2005,'CEK CICI'!A57) -> 0 | I57: =SUMIFS(PENJUALAN!$E$4:$E$4288,PENJUALAN!$C$4:$C$4288,'CEK CICI'!A57) -> 0 | J57: =H57-I57 -> 0
A58: =CONCATENATE(B58,E58) -> RDL-E90FY | B58: RDL-E90 | C58: BMW 3 Series 05-12 E90 | D58: RD/L | E58: FY | F58: 1Hole | H58: =SUMIFS(X!$F$5:$F$2005,X!$D$5:$D$2005,'CEK CICI'!A58) -> 0 | I58: =SUMIFS(PENJUALAN!$E$4:$E$4288,PENJUALAN!$C$4:$C$4288,'CEK CICI'!A58) -> 0 | J58: =H58-I58 -> 0
A59: =CONCATENATE(B59,E59) -> RDR-E90FY | B59: RDR-E90 | C59: BMW 3 Series 05-12 E90 | D59: RD/R | E59: FY | F59: 1Hole | H59: =SUMIFS(X!$F$5:$F$2005,X!$D$5:$D$2005,'CEK CICI'!A59) -> 0 | I59: =SUMIFS(PENJUALAN!$E$4:$E$4288,PENJUALAN!$C$4:$C$4288,'CEK CICI'!A59) -> 0 | J59: =H59-I59 -> 0
A60: =CONCATENATE(B60,E60) -> LFW-F30FY | B60: LFW-F30 | C60: BMW 3 Series 12-18 F30/F35 | D60: LFW | E60: FY | F60: X/RS/List | H60: =SUMIFS(X!$F$5:$F$2005,X!$D$5:$D$2005,'CEK CICI'!A60) -> 1 | I60: =SUMIFS(PENJUALAN!$E$4:$E$4288,PENJUALAN!$C$4:$C$4288,'CEK CICI'!A60) -> 0 | J60: =H60-I60 -> 1
A61: =CONCATENATE(B61,E61) -> TRW-F30FY | B61: TRW-F30 | C61: BMW 3 Series 12-18 F30/F35 | D61: TRW | E61: FY | F61: X/H | H61: =SUMIFS(X!$F$5:$F$2005,X!$D$5:$D$2005,'CEK CICI'!A61) -> 2 | I61: =SUMIFS(PENJUALAN!$E$4:$E$4288,PENJUALAN!$C$4:$C$4288,'CEK CICI'!A61) -> 2 | J61: =H61-I61 -> 0 | K61: A1T3
A62: =CONCATENATE(B62,E62) -> FDL-F30FY | B62: FDL-F30 | C62: BMW 3 Series 12-18 F30/F35 | D62: FD/L | E62: FY | F62: 2Hole | H62: =SUMIFS(X!$F$5:$F$2005,X!$D$5:$D$2005,'CEK CICI'!A62) -> 0 | I62: =SUMIFS(PENJUALAN!$E$4:$E$4288,PENJUALAN!$C$4:$C$4288,'CEK CICI'!A62) -> 0 | J62: =H62-I62 -> 0
A63: =CONCATENATE(B63,E63) -> FDR-F30FY | B63: FDR-F30 | C63: BMW 3 Series 12-18 F30/F35 | D63: FD/R | E63: FY | F63: 2Hole | H63: =SUMIFS(X!$F$5:$F$2005,X!$D$5:$D$2005,'CEK CICI'!A63) -> 0 | I63: =SUMIFS(PENJUALAN!$E$4:$E$4288,PENJUALAN!$C$4:$C$4288,'CEK CICI'!A63) -> 0 | J63: =H63-I63 -> 0
A64: =CONCATENATE(B64,E64) -> RDL-F30FY | B64: RDL-F30 | C64: BMW 3 Series 12-18 F30/F35 | D64: RD/L | E64: FY | F64: 1Hole | H64: =SUMIFS(X!$F$5:$F$2005,X!$D$5:$D$2005,'CEK CICI'!A64) -> 0 | I64: =SUMIFS(PENJUALAN!$E$4:$E$4288,PENJUALAN!$C$4:$C$4288,'CEK CICI'!A64) -> 0 | J64: =H64-I64 -> 0
A65: =CONCATENATE(B65,E65) -> RDR-F30FY | B65: RDR-F30 | C65: BMW 3 Series 12-18 F30/F35 | D65: RD/R | E65: FY | F65: 1Hole | H65: =SUMIFS(X!$F$5:$F$2005,X!$D$5:$D$2005,'CEK CICI'!A65) -> 0 | I65: =SUMIFS(PENJUALAN!$E$4:$E$4288,PENJUALAN!$C$4:$C$4288,'CEK CICI'!A65) -> 0 | J65: =H65-I65 -> 0
A66: =CONCATENATE(B66,E66) -> LFW-E60RSKFY | B66: LFW-E60RSK | C66: BMW 5 Series 03-10 E60 (1 Sensor / [] ) | D66: LFW | E66: FY | F66: X/MB/RS | H66: =SUMIFS(X!$F$5:$F$2005,X!$D$5:$D$2005,'CEK CICI'!A66) -> 0 | I66: =SUMIFS(PENJUALAN!$E$4:$E$4288,PENJUALAN!$C$4:$C$4288,'CEK CICI'!A66) -> 0 | J66: =H66-I66 -> 0
A67: =CONCATENATE(B67,E67) -> LFW-E60RSOFY | B67: LFW-E60RSO | C67: BMW 5 Series 03-10 E60 (1 Sensor / O) | D67: LFW | E67: FY | F67: X/MB/RS | H67: =SUMIFS(X!$F$5:$F$2005,X!$D$5:$D$2005,'CEK CICI'!A67) -> 0 | I67: =SUMIFS(PENJUALAN!$E$4:$E$4288,PENJUALAN!$C$4:$C$4288,'CEK CICI'!A67) -> 0 | J67: =H67-I67 -> 0
A68: =CONCATENATE(B68,E68) -> TRW-E60FY | B68: TRW-E60 | C68: BMW 5 Series 03-10 E60 | D68: TRW | E68: FY | F68: X/H | H68: =SUMIFS(X!$F$5:$F$2005,X!$D$5:$D$2005,'CEK CICI'!A68) -> 0 | I68: =SUMIFS(PENJUALAN!$E$4:$E$4288,PENJUALAN!$C$4:$C$4288,'CEK CICI'!A68) -> 0 | J68: =H68-I68 -> 0
A69: =CONCATENATE(B69,E69) -> FDL-E60FY | B69: FDL-E60 | C69: BMW 5 Series 03-10 E60 | D69: FD/L | E69: FY | H69: =SUMIFS(X!$F$5:$F$2005,X!$D$5:$D$2005,'CEK CICI'!A69) -> 0 | I69: =SUMIFS(PENJUALAN!$E$4:$E$4288,PENJUALAN!$C$4:$C$4288,'CEK CICI'!A69) -> 0 | J69: =H69-I69 -> 0
A70: =CONCATENATE(B70,E70) -> FDR-E60FY | B70: FDR-E60 | C70: BMW 5 Series 03-10 E60 | D70: FD/R | E70: FY | H70: =SUMIFS(X!$F$5:$F$2005,X!$D$5:$D$2005,'CEK CICI'!A70) -> 0 | I70: =SUMIFS(PENJUALAN!$E$4:$E$4288,PENJUALAN!$C$4:$C$4288,'CEK CICI'!A70) -> 0 | J70: =H70-I70 -> 0
A71: =CONCATENATE(B71,E71) -> RDL-E60FY | B71: RDL-E60 | C71: BMW 5 Series 03-10 E60 | D71: RD/L | E71: FY | F71: 1Hole | H71: =SUMIFS(X!$F$5:$F$2005,X!$D$5:$D$2005,'CEK CICI'!A71) -> 0 | I71: =SUMIFS(PENJUALAN!$E$4:$E$4288,PENJUALAN!$C$4:$C$4288,'CEK CICI'!A71) -> 0 | J71: =H71-I71 -> 0
A72: =CONCATENATE(B72,E72) -> RDR-E60FY | B72: RDR-E60 | C72: BMW 5 Series 03-10 E60 | D72: RD/R | E72: FY | F72: 1Hole | H72: =SUMIFS(X!$F$5:$F$2005,X!$D$5:$D$2005,'CEK CICI'!A72) -> 0 | I72: =SUMIFS(PENJUALAN!$E$4:$E$4288,PENJUALAN!$C$4:$C$4288,'CEK CICI'!A72) -> 0 | J72: =H72-I72 -> 0
A73: =CONCATENATE(B73,E73) -> LFW-F10FY | B73: LFW-F10 | C73: BMW 5 Series 10-16 F10 (1 Sensor / ꓳ Tengah) | D73: LFW | E73: FY | F73: X/MB/RS | H73: =SUMIFS(X!$F$5:$F$2005,X!$D$5:$D$2005,'CEK CICI'!A73) -> 0 | I73: =SUMIFS(PENJUALAN!$E$4:$E$4288,PENJUALAN!$C$4:$C$4288,'CEK CICI'!A73) -> 0 | J73: =H73-I73 -> 0
A74: =CONCATENATE(B74,E74) -> FDL-F10FY | B74: FDL-F10 | C74: BMW 5 Series 10-16 F10 | D74: FD/L | E74: FY | F74: 2Hole | H74: =SUMIFS(X!$F$5:$F$2005,X!$D$5:$D$2005,'CEK CICI'!A74) -> 0 | I74: =SUMIFS(PENJUALAN!$E$4:$E$4288,PENJUALAN!$C$4:$C$4288,'CEK CICI'!A74) -> 0 | J74: =H74-I74 -> 0
A75: =CONCATENATE(B75,E75) -> FDR-F10FY | B75: FDR-F10 | C75: BMW 5 Series 10-16 F10 | D75: FD/R | E75: FY | F75: 2Hole | H75: =SUMIFS(X!$F$5:$F$2005,X!$D$5:$D$2005,'CEK CICI'!A75) -> 0 | I75: =SUMIFS(PENJUALAN!$E$4:$E$4288,PENJUALAN!$C$4:$C$4288,'CEK CICI'!A75) -> 0 | J75: =H75-I75 -> 0
A76: =CONCATENATE(B76,E76) -> RDL-F10FY | B76: RDL-F10 | C76: BMW 5 Series 10-16 F10 | D76: RD/L | E76: FY | F76: 1Hole | H76: =SUMIFS(X!$F$5:$F$2005,X!$D$5:$D$2005,'CEK CICI'!A76) -> 0 | I76: =SUMIFS(PENJUALAN!$E$4:$E$4288,PENJUALAN!$C$4:$C$4288,'CEK CICI'!A76) -> 0 | J76: =H76-I76 -> 0
A77: =CONCATENATE(B77,E77) -> RDR-F10FY | B77: RDR-F10 | C77: BMW 5 Series 10-16 F10 | D77: RD/R | E77: FY | F77: 1Hole | H77: =SUMIFS(X!$F$5:$F$2005,X!$D$5:$D$2005,'CEK CICI'!A77) -> 0 | I77: =SUMIFS(PENJUALAN!$E$4:$E$4288,PENJUALAN!$C$4:$C$4288,'CEK CICI'!A77) -> 0 | J77: =H77-I77 -> 0
A78: =CONCATENATE(B78,E78) -> LFW-E84FY | B78: LFW-E84 | C78: BMW X1 Series 09-14 E84 (1 Sensor / [] ) | D78: LFW | E78: FY | F78: X/MB/RS | H78: =SUMIFS(X!$F$5:$F$2005,X!$D$5:$D$2005,'CEK CICI'!A78) -> 0 | I78: =SUMIFS(PENJUALAN!$E$4:$E$4288,PENJUALAN!$C$4:$C$4288,'CEK CICI'!A78) -> 0 | J78: =H78-I78 -> 0
A79: =CONCATENATE(B79,E79) -> TRW-E84FY | B79: TRW-E84 | C79: BMW X1 Series 09-14 E84 | D79: TRW | E79: FY | F79: X/H | H79: =SUMIFS(X!$F$5:$F$2005,X!$D$5:$D$2005,'CEK CICI'!A79) -> 0 | I79: =SUMIFS(PENJUALAN!$E$4:$E$4288,PENJUALAN!$C$4:$C$4288,'CEK CICI'!A79) -> 0 | J79: =H79-I79 -> 0
A80: =CONCATENATE(B80,E80) -> LFW-F48FY | B80: LFW-F48 | C80: BMW X1 Series 15- F48 | D80: LFW | E80: FY | F80: X/RS | H80: =SUMIFS(X!$F$5:$F$2005,X!$D$5:$D$2005,'CEK CICI'!A80) -> 0 | I80: =SUMIFS(PENJUALAN!$E$4:$E$4288,PENJUALAN!$C$4:$C$4288,'CEK CICI'!A80) -> 0 | J80: =H80-I80 -> 0
A81: =CONCATENATE(B81,E81) -> LFW-E53FY | B81: LFW-E53 | C81: BMW X5 Series 00-06 E53 | D81: LFW | E81: FY | F81: X/MB/RS | H81: =SUMIFS(X!$F$5:$F$2005,X!$D$5:$D$2005,'CEK CICI'!A81) -> 0 | I81: =SUMIFS(PENJUALAN!$E$4:$E$4288,PENJUALAN!$C$4:$C$4288,'CEK CICI'!A81) -> 0 | J81: =H81-I81 -> 0
A82: =CONCATENATE(B82,E82) -> TRW-E53BLACKFY | B82: TRW-E53BLACK | C82: BMW X5 Series 00-06 E53 (Hitam) | D82: TRW | E82: FY | F82: X/H/A/1hole | H82: =SUMIFS(X!$F$5:$F$2005,X!$D$5:$D$2005,'CEK CICI'!A82) -> 0 | I82: =SUMIFS(PENJUALAN!$E$4:$E$4288,PENJUALAN!$C$4:$C$4288,'CEK CICI'!A82) -> 0 | J82: =H82-I82 -> 0
... A112: =CONCATENATE(B112,E112) -> LFW-ORLANDOFY | B112: LFW-ORLANDO | C112: Chevrolet Orlando 12- 1st Gen | D112: LFW | E112: FY | F112: X/MB | H112: =SUMIFS(X!$F$5:$F$2005,X!$D$5:$D$2005,'CEK CICI'!A112) -> 0 | I112: =SUMIFS(PENJUALAN!$E$4:$E$4288,PENJUALAN!$C$4:$C$4288,'CEK CICI'!A112) -> 0 | J112: =H112-I112 -> 0
A113: =CONCATENATE(B113,E113) -> FDR-ORLANDOFY | B113: FDR-ORLANDO | C113: Chevrolet Orlando 12- 1st Gen | D113: FD/R | E113: FY | H113: =SUMIFS(X!$F$5:$F$2005,X!$D$5:$D$2005,'CEK CICI'!A113) -> 0 | I113: =SUMIFS(PENJUALAN!$E$4:$E$4288,PENJUALAN!$C$4:$C$4288,'CEK CICI'!A113) -> 0 | J113: =H113-I113 -> 0
A114: =CONCATENATE(B114,E114) -> RDL-ORLANDOFY | B114: RDL-ORLANDO | C114: Chevrolet Orlando 12- 1st Gen | D114: RD/L | E114: FY | H114: =SUMIFS(X!$F$5:$F$2005,X!$D$5:$D$2005,'CEK CICI'!A114) -> 0 | I114: =SUMIFS(PENJUALAN!$E$4:$E$4288,PENJUALAN!$C$4:$C$4288,'CEK CICI'!A114) -> 0 | J114: =H114-I114 -> 0
A115: =CONCATENATE(B115,E115) -> LFW-SPARK98FY | B115: LFW-SPARK98 | C115: Chevrolet Spark 98-05 M100 1stGen (800cc) | D115: LFW | E115: FY | F115: X/MB | H115: =SUMIFS(X!$F$5:$F$2005,X!$D$5:$D$2005,'CEK CICI'!A115) -> 0 | I115: =SUMIFS(PENJUALAN!$E$4:$E$4288,PENJUALAN!$C$4:$C$4288,'CEK CICI'!A115) -> 0 | J115: =H115-I115 -> 0
A116: =CONCATENATE(B116,E116) -> TRW-SPARK98FY | B116: TRW-SPARK98 | C116: Chevrolet Spark 98-05 M100 1stGen (800cc) | D116: TRW | E116: FY | F116: X/H | H116: =SUMIFS(X!$F$5:$F$2005,X!$D$5:$D$2005,'CEK CICI'!A116) -> 0 | I116: =SUMIFS(PENJUALAN!$E$4:$E$4288,PENJUALAN!$C$4:$C$4288,'CEK CICI'!A116) -> 0 | J116: =H116-I116 -> 0
A117: =CONCATENATE(B117,E117) -> LFW-SPARK05FY | B117: LFW-SPARK05 | C117: Chevrolet Spark 05-09 M200 2nd Gen (1000cc) | D117: LFW | E117: FY | F117: X/MB | H117: =SUMIFS(X!$F$5:$F$2005,X!$D$5:$D$2005,'CEK CICI'!A117) -> 0 | I117: =SUMIFS(PENJUALAN!$E$4:$E$4288,PENJUALAN!$C$4:$C$4288,'CEK CICI'!A117) -> 0 | J117: =H117-I117 -> 0
A118: =CONCATENATE(B118,E118) -> TRW-SPARK05FY | B118: TRW-SPARK05 | C118: Chevrolet Spark 05-09 M200 2nd Gen (1000cc) | D118: TRW | E118: FY | F118: X/H | H118: =SUMIFS(X!$F$5:$F$2005,X!$D$5:$D$2005,'CEK CICI'!A118) -> 0 | I118: =SUMIFS(PENJUALAN!$E$4:$E$4288,PENJUALAN!$C$4:$C$4288,'CEK CICI'!A118) -> 0 | J118: =H118-I118 -> 0
A119: =CONCATENATE(B119,E119) -> FDL-SPARK05FY | B119: FDL-SPARK05 | C119: Chevrolet Spark 05-09 M200 2nd Gen (1000cc) | D119: FD/L | E119: FY | F119: 2Hole | H119: =SUMIFS(X!$F$5:$F$2005,X!$D$5:$D$2005,'CEK CICI'!A119) -> 0 | I119: =SUMIFS(PENJUALAN!$E$4:$E$4288,PENJUALAN!$C$4:$C$4288,'CEK CICI'!A119) -> 0 | J119: =H119-I119 -> 0
A120: =CONCATENATE(B120,E120) -> FDR-SPARK05FY | B120: FDR-SPARK05 | C120: Chevrolet Spark 05-09 M200 2nd Gen (1000cc) | D120: FD/R | E120: FY | F120: 2Hole | H120: =SUMIFS(X!$F$5:$F$2005,X!$D$5:$D$2005,'CEK CICI'!A120) -> 0 | I120: =SUMIFS(PENJUALAN!$E$4:$E$4288,PENJUALAN!$C$4:$C$4288,'CEK CICI'!A120) -> 0 | J120: =H120-I120 -> 0
A121: =CONCATENATE(B121,E121) -> RDR-SPARK05FY | B121: RDR-SPARK05 | C121: Chevrolet Spark 05-09 M200 2nd Gen (1000cc) | D121: RD/R | E121: FY | H121: =SUMIFS(X!$F$5:$F$2005,X!$D$5:$D$2005,'CEK CICI'!A121) -> 0 | I121: =SUMIFS(PENJUALAN!$E$4:$E$4288,PENJUALAN!$C$4:$C$4288,'CEK CICI'!A121) -> 0 | J121: =H121-I121 -> 0
A122: =CONCATENATE(B122,E122) -> LFW-SPARK10FY | B122: LFW-SPARK10 | C122: Chevrolet Spark 10-15 M300 3rd Gen (1200cc) | D122: LFW | E122: FY | F122: X/MB | H122: =SUMIFS(X!$F$5:$F$2005,X!$D$5:$D$2005,'CEK CICI'!A122) -> 0 | I122: =SUMIFS(PENJUALAN!$E$4:$E$4288,PENJUALAN!$C$4:$C$4288,'CEK CICI'!A122) -> 0 | J122: =H122-I122 -> 0
A123: =CONCATENATE(B123,E123) -> TRW-SPARK10FY | B123: TRW-SPARK10 | C123: Chevrolet Spark 10-15 M300 3rd Gen (1200cc) | D123: TRW | E123: FY | F123: X/H | H123: =SUMIFS(X!$F$5:$F$2005,X!$D$5:$D$2005,'CEK CICI'!A123) -> 0 | I123: =SUMIFS(PENJUALAN!$E$4:$E$4288,PENJUALAN!$C$4:$C$4288,'CEK CICI'!A123) -> 0 | J123: =H123-I123 -> 0
A124: =CONCATENATE(B124,E124) -> FDL-SPARK10FY | B124: FDL-SPARK10 | C124: Chevrolet Spark 10-15 M300 3rd Gen (1200cc) | D124: FD/L | E124: FY | F124: 2Hole | H124: =SUMIFS(X!$F$5:$F$2005,X!$D$5:$D$2005,'CEK CICI'!A124) -> 0 | I124: =SUMIFS(PENJUALAN!$E$4:$E$4288,PENJUALAN!$C$4:$C$4288,'CEK CICI'!A124) -> 0 | J124: =H124-I124 -> 0
A125: =CONCATENATE(B125,E125) -> FDR-SPARK10FY | B125: FDR-SPARK10 | C125: Chevrolet Spark 10-15 M300 3rd Gen (1200cc) | D125: FD/R | E125: FY | F125: 2Hole | H125: =SUMIFS(X!$F$5:$F$2005,X!$D$5:$D$2005,'CEK CICI'!A125) -> 0 | I125: =SUMIFS(PENJUALAN!$E$4:$E$4288,PENJUALAN!$C$4:$C$4288,'CEK CICI'!A125) -> 0 | J125: =H125-I125 -> 0
A126: =CONCATENATE(B126,E126) -> RDL-SPARK10FY | B126: RDL-SPARK10 | C126: Chevrolet Spark 10-15 M300 3rd Gen (1200cc) | D126: RD/L | E126: FY | F126: 2Hole | H126: =SUMIFS(X!$F$5:$F$2005,X!$D$5:$D$2005,'CEK CICI'!A126) -> 0 | I126: =SUMIFS(PENJUALAN!$E$4:$E$4288,PENJUALAN!$C$4:$C$4288,'CEK CICI'!A126) -> 0 | J126: =H126-I126 -> 0
A127: =CONCATENATE(B127,E127) -> RDR-SPARK10FY | B127: RDR-SPARK10 | C127: Chevrolet Spark 10-15 M300 3rd Gen (1200cc) | D127: RD/R | E127: FY | F127: 2Hole | H127: =SUMIFS(X!$F$5:$F$2005,X!$D$5:$D$2005,'CEK CICI'!A127) -> 0 | I127: =SUMIFS(PENJUALAN!$E$4:$E$4288,PENJUALAN!$C$4:$C$4288,'CEK CICI'!A127) -> 0 | J127: =H127-I127 -> 0
A128: =CONCATENATE(B128,E128) -> LFW-SPINFY | B128: LFW-SPIN | C128: Chevrolet Spin 12- | D128: LFW | E128: FY | F128: X/MB | H128: =SUMIFS(X!$F$5:$F$2005,X!$D$5:$D$2005,'CEK CICI'!A128) -> 0 | I128: =SUMIFS(PENJUALAN!$E$4:$E$4288,PENJUALAN!$C$4:$C$4288,'CEK CICI'!A128) -> 0 | J128: =H128-I128 -> 0
A129: =CONCATENATE(B129,E129) -> RDL-TRAILBLAZERFY | B129: RDL-TRAILBLAZER | C129: Chevrolet TrailBlazer 13- | D129: RD/L | E129: FY | H129: =SUMIFS(X!$F$5:$F$2005,X!$D$5:$D$2005,'CEK CICI'!A129) -> 0 | I129: =SUMIFS(PENJUALAN!$E$4:$E$4288,PENJUALAN!$C$4:$C$4288,'CEK CICI'!A129) -> 0 | J129: =H129-I129 -> 0
A130: =CONCATENATE(B130,E130) -> RDR-TRAILBLAZERFY | B130: RDR-TRAILBLAZER | C130: Chevrolet TrailBlazer 13- | D130: RD/R | E130: FY | H130: =SUMIFS(X!$F$5:$F$2005,X!$D$5:$D$2005,'CEK CICI'!A130) -> 0 | I130: =SUMIFS(PENJUALAN!$E$4:$E$4288,PENJUALAN!$C$4:$C$4288,'CEK CICI'!A130) -> 0 | J130: =H130-I130 -> 0
...

Sheet TANDA TERIMA
A1: SENTRA AUTOGLASS | I1: Tanggal | L1: 08/04/2026
A2: Jalan Simo Jawar No. 108, Simomulyo Baru, Sukomanunggal, Surabaya | I2: Kepada Yth.
A3: (+62) 81288009878 | sentraautoglass.sby@gmail.com | I3: P. Badrus
I4: Surabaya
D7: TANDA TERIMA BARANG
A9: NO | B9: D260002
A10: No | B10: Kode | C10: Nama Barang | H10: Keterangan | L10: QTY
A11: 1 | B11: UIRAN SAMPAH | C11: IURAN SAMPAH BULAN APRIL | L11: 100000
C12: =IFERROR(VLOOKUP(B12,Stock,3,FALSE),"")
C13: =IFERROR(VLOOKUP(B13,Stock,3,FALSE),"")
C14: =IFERROR(VLOOKUP(B14,Stock,3,FALSE),"")
C15: =IFERROR(VLOOKUP(B15,Stock,3,FALSE),"")
K17: total | L17: =SUM(L11:L16) -> 100000
E18: Penerima | J18: Kaca yang sudah dipesan tidak dapat dibatalkan/dikembalikan.
B22: Trust the Experts, Drive Safer and Clearer | E22: ....................

Sheet Sheet23
A1: SBY Code | B1: Merk | C1: Posisi | D1: Pos | E1: Tipe Mobil | F1: Aksesoris | G1: New | H1: FY JKT | I1: FY SBY | J1: XYG JKT | K1: XYG SBY | L1: MUL JKT | M1: MUL SBY | N1: PL Nov22 | O1: MUL JKT - Feb | P1: MUL SBY - Feb | Q1: MUL JKT - Mar | R1: MUL SBY - Mar | S1: XYG JKT Mar | T1: XYG SBY Mar | U1: XYG JKT Mei
A2: AUDI | E2: AUDI
A3: LFW-A396 | B3: - X - | C3: Depan | D3: LFW | E3: Audi A3 96-03 | F3: X/MB/List | G3: - | H3: 0 | I3: 0 | J3: 2 | K3: 0 | L3: 0 | M3: 0 | N3: 4681000 | O3: 0 | P3: 0 | Q3: 0 | R3: 0 | S3: 0 | T3: 0 | U3: 0
A4: LFW-AUDIA304 | B4: - X - | C4: Depan | D4: LFW | E4: Audi A3 04-13 | F4: X/MB/List | G4: - | H4: 0 | I4: 0 | J4: 3 | K4: 0 | L4: 0 | M4: 0 | N4: 4681000 | O4: 0 | P4: 0 | Q4: 0 | R4: 0 | S4: 0 | T4: 0 | U4: 0
A5: LFW-AUDIB6 | B5: - X - | C5: Depan | D5: LFW | E5: Audi A4 01-06 B6 | F5: X/MB | G5: - | H5: 0 | I5: 0 | J5: 5 | K5: 0 | L5: 0 | M5: 0 | N5: 4681000 | O5: 0 | P5: 0 | Q5: 0 | R5: 0 | S5: 0 | T5: 0 | U5: 0
A6: LFW-AUDIB7 | B6: - X - | C6: Depan | D6: LFW | E6: Audi A4 06-08 B7 | F6: X/MB/RS/List | G6: - | H6: 0 | I6: 0 | J6: 1 | K6: 0 | L6: 0 | M6: 0 | N6: 4681000 | O6: 0 | P6: 0 | Q6: 0 | R6: 0 | S6: 0 | T6: 0 | U6: 0
A7: LFW-AUDIB808 | B7: - X - | C7: Depan | D7: LFW | E7: Audi A4 08-15 B8 (08-11 RS Bulat Air Hujan) | F7: X/RS/List | G7: - | H7: 0 | I7: 0 | J7: 3 | K7: 0 | L7: 0 | M7: 0 | N7: 4681000 | O7: 0 | P7: 0 | Q7: 0 | R7: 0 | S7: 0 | T7: 0 | U7: 0
A8: LFW-AUDIB811 | B8: F X - | C8: Depan | D8: LFW | E8: Audi A4 08-15 B8 (11-15 RS Bulat Sempurna) | F8: X/RS/List | G8: - | H8: 0 | I8: 0 | J8: 3 | K8: 0 | L8: 0 | M8: 0 | N8: 4681000 | O8: 0 | P8: 0 | Q8: 0 | R8: 0 | S8: 0 | T8: 0 | U8: 5
A9: TRW-AUDIB8 | B9: F - - | C9: Bagasi | D9: TRW | E9: Audi A4 08-15 B8 | F9: X/Heater/A | G9: - | H9: 10 | I9: 0 | J9: 0 | K9: 0 | L9: 0 | M9: 0 | N9: 3373000 | O9: 0 | P9: 0 | Q9: 0 | R9: 0 | S9: 0 | T9: 0 | U9: 0
A10: LFW-AUDIC6 | B10: - X - | C10: Depan | D10: LFW | E10: Audi A6 04-11 C6 | F10: X/RS | G10: - | H10: 0 | I10: 0 | J10: 4 | K10: 0 | L10: 0 | M10: 0 | N10: 6282000 | O10: 0 | P10: 0 | Q10: 0 | R10: 0 | S10: 0 | T10: 0 | U10: 0
A11: TRW-AUDIC6 | B11: - X - | C11: Bagasi | D11: TRW | E11: Audi A6 04-11 C6 | F11: X/Heater | G11: - | H11: 0 | I11: 0 | J11: 4 | K11: 0 | L11: 0 | M11: 0 | N11: 3300000 | O11: 0 | P11: 0 | Q11: 0 | R11: 0 | S11: 0 | T11: 0 | U11: 0
A12: LFW-AUDIC7 | B12: F X - | C12: Depan | D12: LFW | E12: Audi A6 11-18 C7 (11-13 RS Bulat Air Hujan) | F12: X/RS/List | G12: - | H12: 0 | I12: 0 | J12: 2 | K12: 0 | L12: 0 | M12: 0 | N12: 6282000 | O12: 0 | P12: 0 | Q12: 0 | R12: 0 | S12: 0 | T12: 0 | U12: 0
A13: TRW-AUDIC7 | B13: F - - | C13: Bagasi | D13: TRW | E13: Audi A6 11-18 C7 | F13: X/Heater/List | G13: - | H13: 4 | I13: 0 | J13: 0 | K13: 0 | L13: 0 | M13: 0 | N13: 3373000 | O13: 0 | P13: 0 | Q13: 0 | R13: 0 | S13: 0 | T13: 0 | U13: 0
A14: LFW-AUDIQ312 | B14: - X - | C14: Depan | D14: LFW | E14: Audi Q3 12-17 | F14: X/RS/List | G14: - | H14: 0 | I14: 0 | J14: 4 | K14: 0 | L14: 0 | M14: 0 | N14: 4681000 | O14: 0 | P14: 0 | Q14: 0 | R14: 0 | S14: 0 | T14: 0 | U14: 0
... A18: LFW-AUDIQ716 | B18: - X - | C18: Depan | D18: LFW | E18: Audi Q7 15- | F18: X/RS/List | G18: - | H18: 0 | I18: 0 | J18: 4 | K18: 0 | L18: 0 | M18: 0 | N18: 9853000 | O18: 0 | P18: 0 | Q18: 0 | R18: 0 | S18: 0 | T18: 0 | U18: 0
A19: BMW | E19: BMW
A20: LFW-E30 | B20: F X - | C20: Depan | D20: LFW | E20: BMW 3 Series 82-94 E30 | G20: - | H20: 0 | I20: 0 | J20: 4 | K20: 0 | L20: 0 | M20: 0 | N20: 1457000 | O20: 0 | P20: 0 | Q20: 0 | R20: 0 | S20: 0 | T20: 0 | U20: 0
A21: TRW-E30 | B21: F - - | C21: Bagasi | D21: TRW | E21: BMW 3 Series 82-94 E30 | F21: Heater | G21: - | H21: 4 | I21: 0 | J21: 0 | K21: 0 | L21: 0 | M21: 0 | N21: 1500000 | O21: 0 | P21: 0 | Q21: 0 | R21: 0 | S21: 0 | T21: 0 | U21: 0
A22: LFW-E36 | B22: F X - | C22: Depan | D22: LFW | E22: BMW 3 Series 90-99 E36 | F22: X/MB | G22: - | H22: 0 | I22: 0 | J22: 8 | K22: 9 | L22: 0 | M22: 0 | N22: 1514000 | O22: 0 | P22: 0 | Q22: 0 | R22: 0 | S22: >10 | T22: 10 | U22: >10
A23: TRW-E36 | B23: F X - | C23: Bagasi | D23: TRW | E23: BMW 3 Series 90-99 E36 | F23: X/Heater | G23: - | H23: 0 | I23: 0 | J23: 3 | K23: 1 | L23: 0 | M23: 0 | N23: 2083000 | O23: 0 | P23: 0 | Q23: 0 | R23: 0 | S23: 0 | T23: 0 | U23: 0
A24: FDL-E36 | B24: F X - | C24: Smpg | D24: FD/L | E24: BMW 3 Series 90-99 E36 | G24: - | H24: 0 | I24: 0 | J24: 0 | K24: 0 | L24: 0 | M24: 0 | N24: 725000 | O24: 0 | P24: 0 | Q24: 0 | R24: 0 | S24: 0 | T24: 0 | U24: 0
A25: FDR-E36 | B25: F X - | C25: Smpg | D25: FD/R | E25: BMW 3 Series 90-99 E36 | G25: - | H25: 0 | I25: 0 | J25: 3 | K25: 0 | L25: 0 | M25: 0 | N25: 725000 | O25: 0 | P25: 0 | Q25: 0 | R25: 0 | S25: 0 | T25: 0 | U25: 0
A26: RDL-E36 | B26: F - - | C26: Smpg | D26: RD/L | E26: BMW 3 Series 90-99 E36 | G26: - | H26: 0 | I26: 0 | J26: 0 | K26: 0 | L26: 0 | M26: 0 | N26: 644000 | O26: 0 | P26: 0 | Q26: 0 | R26: 0 | S26: 0 | T26: 0 | U26: 0
A27: RDR-E36 | B27: F - - | C27: Smpg | D27: RD/R | E27: BMW 3 Series 90-99 E36 | G27: - | H27: 6 | I27: 0 | J27: 0 | K27: 0 | L27: 0 | M27: 0 | N27: 644000 | O27: 0 | P27: 0 | Q27: 0 | R27: 0 | S27: 0 | T27: 0 | U27: 0
A28: LFW-E46RS2DOOR | B28: F X - | C28: Depan | D28: LFW | E28: BMW 3 Series 98-06 E46 (2D Coupe / Cabrio) | F28: X/MB | G28: - | H28: 0 | I28: 0 | J28: 4 | K28: 0 | L28: 0 | M28: 0 | N28: 5880000 | O28: 0 | P28: 0 | Q28: 0 | R28: 0 | S28: 0 | T28: 0 | U28: 0
A29: LFW-E46RS | B29: F - - | C29: Depan | D29: LFW | E29: BMW 3 Series 98-06 E46 | F29: X/MB/RS | G29: - | H29: 4 | I29: 0 | J29: 0 | K29: 0 | L29: 0 | M29: 0 | N29: 2241000 | O29: 0 | P29: 0 | Q29: 0 | R29: 0 | S29: 0 | T29: 0 | U29: 0
A30: LFW-E46 | B30: F X - | C30: Depan | D30: LFW | E30: BMW 3 Series 98-06 E46 | F30: X/MB | G30: - | H30: 0 | I30: 0 | J30: 2 | K30: 1 | L30: 0 | M30: 0 | N30: 1805000 | O30: 0 | P30: 0 | Q30: 0 | R30: 0 | S30: >10 | T30: 10 | U30: >10
A31: TRW-E46 | B31: F - - | C31: Bagasi | D31: TRW | E31: BMW 3 Series 98-06 E46 | F31: X/Heater | G31: - | H31: >10 | I31: 0 | J31: 0 | K31: 0 | L31: 0 | M31: 0 | N31: 2142000 | O31: 0 | P31: 0 | Q31: 0 | R31: 0 | S31: 0 | T31: 0 | U31: 0
A32: FDL-E46 | B32: F - - | C32: Smpg | D32: FD/L | E32: BMW 3 Series 98-06 E46 | F32: 2Hole | G32: - | H32: 0 | I32: 0 | J32: 0 | K32: 0 | L32: 0 | M32: 0 | N32: 725000 | O32: 0 | P32: 0 | Q32: 0 | R32: 0 | S32: 0 | T32: 0 | U32: 0
A33: FDR-E46 | B33: F - - | C33: Smpg | D33: FD/R | E33: BMW 3 Series 98-06 E46 | F33: 2Hole | G33: - | H33: >10 | I33: 0 | J33: 0 | K33: 0 | L33: 0 | M33: 0 | N33: 725000 | O33: 0 | P33: 0 | Q33: 0 | R33: 0 | S33: 0 | T33: 0 | U33: 0
A34: RDL-E46 | B34: F - - | C34: Smpg | D34: RD/L | E34: BMW 3 Series 98-06 E46 | F34: 1Hole | G34: - | H34: 7 | I34: 0 | J34: 0 | K34: 0 | L34: 0 | M34: 0 | N34: 644000 | O34: 0 | P34: 0 | Q34: 0 | R34: 0 | S34: 0 | T34: 0 | U34: 0
A35: RDR-E46 | B35: F - - | C35: Smpg | D35: RD/R | E35: BMW 3 Series 98-06 E46 | F35: 1Hole | G35: - | H35: 10 | I35: 0 | J35: 0 | K35: 0 | L35: 0 | M35: 0 | N35: 644000 | O35: 0 | P35: 0 | Q35: 0 | R35: 0 | S35: 0 | T35: 0 | U35: 0
A36: LFW-E90RS | B36: F X - | C36: Depan | D36: LFW | E36: BMW 3 Series 05-12 E90 / E91 | F36: X/MB/RS | G36: - | H36: 0 | I36: 0 | J36: >10 | K36: 4 | L36: 0 | M36: 0 | N36: 2576000 | O36: 0 | P36: 0 | Q36: 0 | R36: 0 | S36: 0 | T36: 0 | U36: 0
A37: LFW-E90 | B37: F X - | C37: Depan | D37: LFW | E37: BMW 3 Series 05-12 E90 | F37: X/MB | G37: - | H37: 0 | I37: 0 | J37: 4 | K37: 0 | L37: 0 | M37: 0 | N37: 2544000 | O37: 0 | P37: 0 | Q37: 0 | R37: 0 | S37: 8 | T37: 2 | U37: 0
A38: TRW-E90 | B38: F - - | C38: Bagasi | D38: TRW | E38: BMW 3 Series 05-12 E90 | F38: X/Heater | G38: - | H38: 1 | I38: 0 | J38: 0 | K38: 0 | L38: 0 | M38: 0 | N38: 2507000 | O38: 0 | P38: 0 | Q38: 0 | R38: 0 | S38: 0 | T38: 0 | U38: 0
A39: TRW-E90A | B39: - X - | C39: Bagasi | D39: TRW | E39: BMW 3 Series 05-12 E90 (Antenna) | F39: X/Heater/A | G39: - | H39: 0 | I39: 0 | J39: 1 | K39: 0 | L39: 0 | M39: 0 | N39: 2570000 | O39: 0 | P39: 0 | Q39: 0 | R39: 0 | S39: 0 | T39: 0 | U39: 0
A40: FDL-E90 | B40: F - - | C40: Smpg | D40: FD/L | E40: BMW 3 Series 05-12 E90 | F40: 2Hole | G40: - | H40: 4 | I40: 0 | J40: 0 | K40: 0 | L40: 0 | M40: 0 | N40: 804000 | O40: 0 | P40: 0 | Q40: 0 | R40: 0 | S40: 0 | T40: 0 | U40: 0
A41: FDR-E90 | B41: F - - | C41: Smpg | D41: FD/R | E41: BMW 3 Series 05-12 E90 | F41: 2Hole | G41: - | H41: 8 | I41: 0 | J41: 0 | K41: 0 | L41: 0 | M41: 0 | N41: 804000 | O41: 0 | P41: 0 | Q41: 0 | R41: 0 | S41: 0 | T41: 0 | U41: 0
A42: RDL-E90 | B42: F - - | C42: Smpg | D42: RD/L | E42: BMW 3 Series 05-12 E90 | F42: 1Hole | G42: - | H42: 4 | I42: 0 | J42: 0 | K42: 0 | L42: 0 | M42: 0 | N42: 804000 | O42: 0 | P42: 0 | Q42: 0 | R42: 0 | S42: 0 | T42: 0 | U42: 0
A43: RDR-E90 | B43: F - - | C43: Smpg | D43: RD/R | E43: BMW 3 Series 05-12 E90 | F43: 1Hole | G43: - | H43: >10 | I43: 0 | J43: 0 | K43: 0 | L43: 0 | M43: 0 | N43: 804000 | O43: 0 | P43: 0 | Q43: 0 | R43: 0 | S43: 0 | T43: 0 | U43: 0
A44: LFW-F30 | B44: F X - | C44: Depan | D44: LFW | E44: BMW 3 Series 12-18 F30/F35 | F44: X/RS/List | G44: - | H44: 0 | I44: 0 | J44: 0 | K44: 0 | L44: 0 | M44: 0 | N44: 4202000 | O44: 0 | P44: 0 | Q44: 0 | R44: 0 | S44: >10 | T44: 2 | U44: 0
A45: TRW-F30 | B45: F - - | C45: Bagasi | D45: TRW | E45: BMW 3 Series 12-18 F30/F35 | F45: X/Heater | G45: - | H45: 0 | I45: 0 | J45: 0 | K45: 0 | L45: 0 | M45: 0 | N45: 2453000 | O45: 0 | P45: 0 | Q45: 0 | R45: 0 | S45: 5 | T45: 0 | U45: 0
A46: FDL-F30 | B46: F X - | C46: Smpg | D46: FD/L | E46: BMW 3 Series 12-18 F30/F35 | F46: 2Hole | G46: - | H46: 0 | I46: 0 | J46: 4 | K46: 0 | L46: 0 | M46: 0 | N46: 804000 | O46: 0 | P46: 0 | Q46: 0 | R46: 0 | S46: 0 | T46: 0 | U46: 0
A47: FDR-F30 | B47: F - - | C47: Smpg | D47: FD/R | E47: BMW 3 Series 12-18 F30/F35 | F47: 2Hole | G47: - | H47: 2 | I47: 0 | J47: 0 | K47: 0 | L47: 0 | M47: 0 | N47: 804000 | O47: 0 | P47: 0 | Q47: 0 | R47: 0 | S47: 0 | T47: 0 | U47: 0
A48: RDL-F30 | B48: F - - | C48: Smpg | D48: RD/L | E48: BMW 3 Series 12-18 F30/F35 | F48: 1Hole | G48: - | H48: 8 | I48: 0 | J48: 0 | K48: 0 | L48: 0 | M48: 0 | N48: 725000 | O48: 0 | P48: 0 | Q48: 0 | R48: 0 | S48: 0 | T48: 0 | U48: 0
A49: RDR-F30 | B49: F - - | C49: Smpg | D49: RD/R | E49: BMW 3 Series 12-18 F30/F35 | F49: 1Hole | G49: - | H49: >10 | I49: 0 | J49: 0 | K49: 0 | L49: 0 | M49: 0 | N49: 725000 | O49: 0 | P49: 0 | Q49: 0 | R49: 0 | S49: 0 | T49: 0 | U49: 0
A50: LFW-G20RS1 | B50: - X - | C50: Depan | D50: LFW | E50: BMW 3 Series 18- G20/G21 (1 Sensor / O ) | F50: X/RS/List | G50: - | H50: 0 | I50: 0 | J50: 4 | K50: 0 | L50: 0 | M50: 0 | N50: 4202000 | O50: 0 | P50: 0 | Q50: 0 | R50: 0 | S50: 0 | T50: 0 | U50: 0
A51: LFW-G20RS2 | B51: - X - | C51: Depan | D51: LFW | E51: BMW 3 Series 18- G20/G21 (2 Sensor / Big /\ O ) | F51: X/RS/List | G51: - | H51: 0 | I51: 0 | J51: 5 | K51: 0 | L51: 0 | M51: 0 | N51: 4202000 | O51: 0 | P51: 0 | Q51: 0 | R51: 0 | S51: 0 | T51: 0 | U51: 0
A52: LFW-E39 | B52: - X - | C52: Depan | D52: LFW | E52: BMW 5 Series 95-03 E39 | F52: X/MB | G52: - | H52: 0 | I52: 0 | J52: 5 | K52: 0 | L52: 0 | M52: 0 | N52: 1848000 | O52: 0 | P52: 0 | Q52: 0 | R52: 0 | S52: 0 | T52: 0 | U52: 0
A53: LFW-E60RSK | B53: F X - | C53: Depan | D53: LFW | E53: BMW 5 Series 03-10 E60 (1 Sensor / [] ) | F53: X/MB/RS | G53: - | H53: 0 | I53: 0 | J53: 2 | K53: 0 | L53: 0 | M53: 0 | N53: 2641000 | O53: 0 | P53: 0 | Q53: 0 | R53: 0 | S53: 0 | T53: 0 | U53: 0
A54: LFW-E60RSO | B54: F X - | C54: Depan | D54: LFW | E54: BMW 5 Series 03-10 E60 (1 Sensor / O) | F54: X/MB/RS | G54: - | H54: 0 | I54: 0 | J54: 4 | K54: 1 | L54: 0 | M54: 0 | N54: 3132000 | O54: 0 | P54: 0 | Q54: 0 | R54: 0 | S54: 0 | T54: 0 | U54: 0
A55: TRW-E60 | B55: F X - | C55: Bagasi | D55: TRW | E55: BMW 5 Series 03-10 E60 | F55: X/Heater | G55: - | H55: 0 | I55: 0 | J55: 4 | K55: 0 | L55: 0 | M55: 0 | N55: 2892000 | O55: 0 | P55: 0 | Q55: 0 | R55: 0 | S55: 0 | T55: 0 | U55: 0
A56: FDL-E60 | B56: F - - | C56: Smpg | D56: FD/L | E56: BMW 5 Series 03-10 E60 | G56: - | H56: >10 | I56: 0 | J56: 0 | K56: 0 | L56: 0 | M56: 0 | N56: 804000 | O56: 0 | P56: 0 | Q56: 0 | R56: 0 | S56: 0 | T56: 0 | U56: 0
A57: FDR-E60 | B57: F - - | C57: Smpg | D57: FD/R | E57: BMW 5 Series 03-10 E60 | G57: - | H57: >10 | I57: 0 | J57: 0 | K57: 0 | L57: 0 | M57: 0 | N57: 804000 | O57: 0 | P57: 0 | Q57: 0 | R57: 0 | S57: 0 | T57: 0 | U57: 0
A58: RDL-E60 | B58: F - - | C58: Smpg | D58: RD/L | E58: BMW 5 Series 03-10 E60 | F58: 1Hole | G58: - | H58: 2 | I58: 0 | J58: 0 | K58: 0 | L58: 0 | M58: 0 | N58: 725000 | O58: 0 | P58: 0 | Q58: 0 | R58: 0 | S58: 0 | T58: 0 | U58: 0
A59: RDR-E60 | B59: F - - | C59: Smpg | D59: RD/R | E59: BMW 5 Series 03-10 E60 | F59: 1Hole | G59: - | H59: 4 | I59: 0 | J59: 0 | K59: 0 | L59: 0 | M59: 0 | N59: 725000 | O59: 0 | P59: 0 | Q59: 0 | R59: 0 | S59: 0 | T59: 0 | U59: 0
A60: LFW-F10 | B60: F X - | C60: Depan | D60: LFW | E60: BMW 5 Series 10-16 F10 (1 Sensor / ꓳ Tengah) | F60: X/MB/RS | G60: - | H60: 0 | I60: 0 | J60: 6 | K60: 1 | L60: 0 | M60: 0 | N60: 3865000 | O60: 0 | P60: 0 | Q60: 0 | R60: 0 | S60: 0 | T60: 0 | U60: 0
A61: LFW-F10RSBWH | B61: - X - | C61: Depan | D61: LFW | E61: BMW 5 Series 10-16 F10 (1 Sensor / ꓳ Bawah) | F61: X/MB/RS/List | G61: - | H61: 0 | I61: 0 | J61: 8 | K61: 1 | L61: 0 | M61: 0 | N61: 3865000 | O61: 0 | P61: 0 | Q61: 0 | R61: 0 | S61: 0 | T61: 0 | U61: 0
A62: TRW-F10 | B62: - X - | C62: Bagasi | D62: TRW | E62: BMW 5 Series 10-16 F10 | F62: X/Heater | G62: - | H62: 0 | I62: 0 | J62: 1 | K62: 0 | L62: 0 | M62: 0 | N62: 2916000 | O62: 0 | P62: 0 | Q62: 0 | R62: 0 | S62: 0 | T62: 0 | U62: 5
A63: FDL-F10 | B63: F - - | C63: Smpg | D63: FD/L | E63: BMW 5 Series 10-16 F10 | F63: 2Hole | G63: - | H63: >10 | I63: 0 | J63: 0 | K63: 0 | L63: 0 | M63: 0 | N63: 884000 | O63: 0 | P63: 0 | Q63: 0 | R63: 0 | S63: 0 | T63: 0 | U63: 0
A64: FDR-F10 | B64: F - - | C64: Smpg | D64: FD/R | E64: BMW 5 Series 10-16 F10 | F64: 2Hole | G64: - | H64: >10 | I64: 0 | J64: 0 | K64: 0 | L64: 0 | M64: 0 | N64: 884000 | O64: 0 | P64: 0 | Q64: 0 | R64: 0 | S64: 0 | T64: 0 | U64: 0
A65: RDL-F10 | B65: F - - | C65: Smpg | D65: RD/L | E65: BMW 5 Series 10-16 F10 | F65: 1Hole | G65: - | H65: 5 | I65: 0 | J65: 0 | K65: 0 | L65: 0 | M65: 0 | N65: 804000 | O65: 0 | P65: 0 | Q65: 0 | R65: 0 | S65: 0 | T65: 0 | U65: 0
A66: RDR-F10 | B66: F - - | C66: Smpg | D66: RD/R | E66: BMW 5 Series 10-16 F10 | F66: 1Hole | G66: - | H66: 2 | I66: 0 | J66: 0 | K66: 0 | L66: 0 | M66: 0 | N66: 804000 | O66: 0 | P66: 0 | Q66: 0 | R66: 0 | S66: 0 | T66: 0 | U66: 0
A67: LFW-G30RS2 | B67: - X - | C67: Depan | D67: LFW | E67: BMW 5 Series 17-24 G30 (2 Sensor / Big /\ O ) | F67: X/MB/RS/List | G67: - | H67: 0 | I67: 0 | J67: 4 | K67: 0 | L67: 0 | M67: 0 | N67: 4202000 | O67: 0 | P67: 0 | Q67: 0 | R67: 0 | S67: 0 | T67: 0 | U67: 0
A68: LFW-F02 | B68: - X - | C68: Depan | D68: LFW | E68: BMW 7 Series 09-15 F01 (1 Sensor / O) | F68: X/MB/RS/List | G68: - | H68: 0 | I68: 0 | J68: 1 | K68: 0 | L68: 0 | M68: 0 | N68: 8005000 | O68: 0 | P68: 0 | Q68: 0 | R68: 0 | S68: 0 | T68: 0 | U68: 0
A69: LFW-E84NONRS | B69: - X - | C69: Depan | D69: LFW | E69: BMW X1 Series 09-14 E84 | F69: X/MB/List | G69: - | H69: 0 | I69: 0 | J69: 1 | K69: 0 | L69: 0 | M69: 0 | N69: 3700000 | O69: 0 | P69: 0 | Q69: 0 | R69: 0 | S69: 0 | T69: 0 | U69: 0
A70: LFW-E84 | B70: F X - | C70: Depan | D70: LFW | E70: BMW X1 Series 09-14 E84 (1 Sensor / [] ) | F70: X/MB/RS | G70: - | H70: 0 | I70: 0 | J70: >10 | K70: 0 | L70: 0 | M70: 0 | N70: 3948000 | O70: 0 | P70: 0 | Q70: 0 | R70: 0 | S70: 0 | T70: 0 | U70: 0
A71: TRW-E84 | B71: F X - | C71: Bagasi | D71: TRW | E71: BMW X1 Series 09-14 E84 | F71: X/Heater | G71: - | H71: 0 | I71: 0 | J71: 2 | K71: 0 | L71: 0 | M71: 0 | N71: 2892000 | O71: 0 | P71: 0 | Q71: 0 | R71: 0 | S71: 0 | T71: 0 | U71: 0
A72: LFW-F48 | B72: F X - | C72: Depan | D72: LFW | E72: BMW X1 Series 15-22 F48 | F72: X/RS | G72: - | H72: 0 | I72: 0 | J72: 9 | K72: 0 | L72: 0 | M72: 0 | N72: 3695000 | O72: 0 | P72: 0 | Q72: 0 | R72: 0 | S72: 0 | T72: 0 | U72: 0
A73: TRW-F48 | B73: - X - | C73: Bagasi | D73: TRW | E73: BMW X1 Series 15-22 F48 (Hitam) | F73: X/Heater/1Hole | G73: - | H73: 0 | I73: 0 | J73: 6 | K73: 0 | L73: 0 | M73: 0 | N73: 3800000 | O73: 0 | P73: 0 | Q73: 0 | R73: 0 | S73: 0 | T73: 0 | U73: 0
A74: LFW-F25 | B74: - X - | C74: Depan | D74: LFW | E74: BMW X3 Series 11-17 F25 | F74: X/RS/List | G74: - | H74: 0 | I74: 0 | J74: 2 | K74: 1 | L74: 0 | M74: 0 | N74: 6159000 | O74: 0 | P74: 0 | Q74: 0 | R74: 0 | S74: 0 | T74: 0 | U74: 0
A75: TRW-F25 | B75: - X - | C75: Bagasi | D75: TRW | E75: BMW X3 Series 11-17 F25 (Hitam) | F75: X/Heater | G75: - | H75: 0 | I75: 0 | J75: 3 | K75: 0 | L75: 0 | M75: 0 | N75: 4200000 | O75: 0 | P75: 0 | Q75: 0 | R75: 0 | S75: 0 | T75: 0 | U75: 0
A76: LFW-E53 | B76: F X - | C76: Depan | D76: LFW | E76: BMW X5 Series 00-06 E53 | F76: X/MB/RS | G76: - | H76: 0 | I76: 0 | J76: 5 | K76: 0 | L76: 0 | M76: 0 | N76: 4202000 | O76: 0 | P76: 0 | Q76: 0 | R76: 0 | S76: 0 | T76: 0 | U76: 0
A77: TRW-E53BLACK | B77: F X - | C77: Bagasi | D77: TRW | E77: BMW X5 Series 00-06 E53 (Hitam) | F77: X/Heater/A/1hole | G77: - | H77: 2 | I77: 0 | J77: 6 | K77: 0 | L77: 0 | M77: 0 | N77: 4282000 | O77: 0 | P77: 0 | Q77: 0 | R77: 0 | S77: 0 | T77: 0 | U77: 0
A78: LFW-E70RS | B78: F X - | C78: Depan | D78: LFW | E78: BMW X5 Series 07-13 E70 (1 Sensor / ꓳ) | F78: X/MB/RS | G78: - | H78: 2 | I78: 0 | J78: 3 | K78: 0 | L78: 0 | M78: 0 | N78: 4535000 | O78: 0 | P78: 0 | Q78: 0 | R78: 0 | S78: 0 | T78: 0 | U78: 0
A79: TRW-E70 | B79: F X - | C79: Bagasi | D79: TRW | E79: BMW X5 Series 07-13 E70 | F79: X/Heater/A/3Hole | G79: - | H79: 0 | I79: 0 | J79: 0 | K79: 0 | L79: 0 | M79: 0 | N79: 3532000 | O79: 0 | P79: 0 | Q79: 0 | R79: 0 | S79: 5 | T79: 0 | U79: 0
A80: RDL-E70 | B80: F - - | C80: Smpg | D80: RD/L | E80: BMW X5 Series 07-13 E70 | F80: 1Hole | G80: - | H80: >10 | I80: 0 | J80: 0 | K80: 0 | L80: 0 | M80: 0 | N80: 966000 | O80: 0 | P80: 0 | Q80: 0 | R80: 0 | S80: 0 | T80: 0 | U80: 0
A81: SWL-E70 | B81: F - - | C81: Smpg | D81: SW/L | E81: BMW X5 Series 07-13 E70 | F81: X | G81: - | H81: >10 | I81: 0 | J81: 0 | K81: 0 | L81: 0 | M81: 0 | N81: 725000 | O81: 0 | P81: 0 | Q81: 0 | R81: 0 | S81: 0 | T81: 0 | U81: 0
A82: LFW-F15 | B82: F X - | C82: Depan | D82: LFW | E82: BMW X5 Series 13-18 F15 | F82: X/RS | G82: - | H82: 1 | I82: 0 | J82: 4 | K82: 0 | L82: 0 | M82: 0 | N82: 4202000 | O82: 0 | P82: 0 | Q82: 0 | R82: 0 | S82: 0 | T82: 0 | U82: 0
A83: TRW-F15 | B83: - X - | C83: Bagasi | D83: TRW | E83: BMW X5 Series 13-18 F15 | F83: X/H/1Hole/List | G83: - | H83: 0 | I83: 0 | J83: 4 | K83: 0 | L83: 0 | M83: 0 | N83: 3532000 | O83: 0 | P83: 0 | Q83: 0 | R83: 0 | S83: 0 | T83: 0 | U83: 0
A84: RDL-F15 | B84: F - - | C84: Smpg | D84: RD/L | E84: BMW X5 Series 13-18 F15 | F84: 1Hole | G84: - | H84: 7 | I84: 0 | J84: 0 | K84: 0 | L84: 0 | M84: 0 | N84: 884000 | O84: 0 | P84: 0 | Q84: 0 | R84: 0 | S84: 0 | T84: 0 | U84: 0
A85: RDR-F15 | B85: F - - | C85: Smpg | D85: RD/R | E85: BMW X5 Series 13-18 F15 | F85: 1Hole | G85: - | H85: 9 | I85: 0 | J85: 0 | K85: 0 | L85: 0 | M85: 0 | N85: 884000 | O85: 0 | P85: 0 | Q85: 0 | R85: 0 | S85: 0 | T85: 0 | U85: 0
A86: LFW-E89 | B86: - X - | C86: Depan | D86: LFW | E86: BMW Z4 09-16 E89 | F86: X/MB/RS | G86: - | H86: 0 | I86: 0 | J86: 0 | K86: 0 | L86: 0 | M86: 0 | N86: 5543000 | O86: 0 | P86: 0 | Q86: 0 | R86: 0 | S86: 0 | T86: 0 | U86: 0
A87: TRW-Z4 | B87: - X - | C87: Bagasi | D87: TRW | E87: BMW Z4 09-16 E89 | F87: X/Heater | G87: - | H87: 0 | I87: 0 | J87: 7 | K87: 0 | L87: 0 | M87: 0 | N87: 7063000 | O87: 0 | P87: 0 | Q87: 0 | R87: 0 | S87: 0 | T87: 0 | U87: 0
A88: BYD | E88: BYD
A89: LFW-ATTO | B89: - X - | C89: Depan | D89: LFW | E89: BYD Atto 3 23- (1 Sensor / Big /\ ) | F89: X/MB/RS/List | G89: New | H89: 0 | I89: 0 | J89: 4 | K89: 2 | L89: 0 | M89: 0 | N89: 2900000 | O89: 0 | P89: 0 | Q89: 0 | R89: 0 | S89: 0 | T89: 0 | U89: 0
A90: LFW-SEAL | B90: - X - | C90: Depan | D90: LFW | E90: BYD Seal 23- (2 Sensor / /\ O ) | F90: X/MB/RS/List | G90: New | H90: 0 | I90: 0 | J90: 7 | K90: 0 | L90: 0 | M90: 0 | N90: 3900000 | O90: 0 | P90: 0 | Q90: 0 | R90: 0 | S90: 0 | T90: 0 | U90: 0
A91: CHERY | E91: CHERY
A92: LFW-OMODARS | B92: - X - | C92: Depan | D92: LFW | E92: Chery Omoda 5 23- (2 Sensor O /\ ) | F92: X/MB/RS | G92: New | H92: 0 | I92: 0 | J92: >10 | K92: 1 | L92: 0 | M92: 0 | N92: 3700000 | O92: 0 | P92: 0 | Q92: 0 | R92: 0 | S92: 0 | T92: 0 | U92: 0
A93: LFW-QQ03 | B93: F X M | C93: Depan | D93: LFW | E93: Chery QQ 03-15 S11 5D / Spark 98-05 | F93: X/MB | G93: - | H93: 0 | I93: 0 | J93: >10 | K93: 0 | L93: 7 | M93: >10 | N93: 1340000 | O93: 0 | P93: 0 | Q93: 0 | R93: 0 | S93: 0 | T93: 0 | U93: 0
A94: TRW-QQ03 | B94: F X - | C94: Bagasi | D94: TRW | E94: Chery QQ 03-15 S11 5D / Spark 98-05 | F94: X/Heater | G94: - | H94: 0 | I94: 0 | J94: 2 | K94: 0 | L94: 0 | M94: 0 | N94: 1563000 | O94: 0 | P94: 0 | Q94: 0 | R94: 0 | S94: 5 | T94: 0 | U94: 0
A95: CHEVROLET | E95: CHEVROLET
A96: LFW-AVEO99 | B96: F X - | C96: Depan | D96: LFW | E96: Chevrolet Aveo 99-08 T200 Hatch. (Panjang) | F96: X/MB | G96: - | H96: 1 | I96: 0 | J96: 2 | K96: 0 | L96: 0 | M96: 0 | N96: 1509000 | O96: 0 | P96: 0 | Q96: 0 | R96: 0 | S96: >10 | T96: 5 | U96: 0
A97: FDL-AVEO99 | B97: F X - | C97: Smpg | D97: FD/L | E97: Chevrolet Aveo 99-11 T200 Hatch. | F97: 2Hole | G97: - | H97: 0 | I97: 0 | J97: 4 | K97: 0 | L97: 0 | M97: 0 | N97: 644000 | O97: 0 | P97: 0 | Q97: 0 | R97: 0 | S97: 0 | T97: 0 | U97: 0
A98: FDR-AVEO99 | B98: F X - | C98: Smpg | D98: FD/R | E98: Chevrolet Aveo 99-11 T200 Hatch. | F98: 2Hole | G98: - | H98: 0 | I98: 0 | J98: 3 | K98: 0 | L98: 0 | M98: 0 | N98: 644000 | O98: 0 | P98: 0 | Q98: 0 | R98: 0 | S98: 0 | T98: 0 | U98: 0
A99: TRW-AVEO99 | B99: F X - | C99: Bagasi | D99: TRW | E99: Chevrolet Aveo 99-11 T200 Hatch. | F99: X/Heater | G99: - | H99: 0 | I99: 0 | J99: 4 | K99: 1 | L99: 0 | M99: 0 | N99: 1771000 | O99: 0 | P99: 0 | Q99: 0 | R99: 0 | S99: 0 | T99: 0 | U99: 0
A100: TRW-KALOS | B100: - X - | C100: Bagasi | D100: TRW | E100: Chevrolet Aveo 99-11 T200 Sedan (Kalos) (Lampu [] ) | F100: X/Heater | G100: - | H100: 0 | I100: 0 | J100: 2 | K100: 2 | L100: 0 | M100: 0 | N100: 1500000 | O100: 0 | P100: 0 | Q100: 0 | R100: 0 | S100: 0 | T100: 0 | U100: 0
A101: LFW-AVEO08 | B101: F X - | C101: Depan | D101: LFW | E101: Chevrolet Aveo 08-11 T250 Hatch. / (Kalos/Lova) (Pendek) | F101: X/MB | G101: - | H101: 0 | I101: 0 | J101: >10 | K101: 0 | L101: 0 | M101: 0 | N101: 1552000 | O101: 0 | P101: 0 | Q101: 0 | R101: 0 | S101: 0 | T101: 0 | U101: 0
A102: TRW-LOVA | B102: - X - | C102: Bagasi | D102: TRW | E102: Chevrolet Aveo 08-11 T250 Sedan (Lova) (Lampu /\ ) | F102: X/Heater | G102: - | H102: 0 | I102: 0 | J102: 2 | K102: 0 | L102: 0 | M102: 0 | N102: 1500000 | O102: 0 | P102: 0 | Q102: 0 | R102: 0 | S102: 0 | T102: 0 | U102: 0
A103: LFW-AVEO11 | B103: F X - | C103: Depan | D103: LFW | E103: Chevrolet Aveo 11- T300 2nd Gen Hatchback | F103: X/MB | G103: - | H103: 0 | I103: 0 | J103: 6 | K103: 0 | L103: 0 | M103: 0 | N103: 1848000 | O103: 0 | P103: 0 | Q103: 0 | R103: 0 | S103: 0 | T103: 0 | U103: 0
...

Sheet Copy of  INV TTD A4 1 PDF
A1: SENTRA AUTOGLASS TANGERANG | J1: Tanggal | L1: 45736
A2: Taman Royal, Ruko Permata Niaga II No. 17, Kota Tangerang, Banten 15119 | J2: Kepada Yth.
J3: P. Aldo
J4: +62 813-9816-4492
J5: Surabaya
D7: NOTA PENJUALAN
A9: INV | B9: C250070 | J9: NO POL
A10: No | B10: Kode | C10: Nama Barang | H10: Qty | J10: Harga Satuan | L10: Jumlah
A11: 1 | B11: TRW-JAZZ07XYG | C11: =IFERROR(VLOOKUP(B11,Stock,3,FALSE),"") -> Honda Jazz 07-13 2nd Gen | H11: 1 | I11: PC | J11: 1087000 | L11: =H11*J11 -> 1087000
C12: =IFERROR(VLOOKUP(B12,Stock,3,FALSE),"") | L12: =H12*J12 -> 0
C13: =IFERROR(VLOOKUP(B13,Stock,3,FALSE),"") | L13: =H13*J13 -> 0
C14: =IFERROR(VLOOKUP(B14,Stock,3,FALSE),"") | L14: =H14*J14 -> 0
C15: =IFERROR(VLOOKUP(B15,Stock,3,FALSE),"") | L15: =H15*J15 -> 0
C16: =IFERROR(VLOOKUP(B16,Stock,3,FALSE),"") | L16: =H16*J16 -> 0
L17: =H17*J17 -> 0
B18: BCA 6041794388 an Alvin Wijaya | L18: =H18*J18 -> 0
K19: TOTAL | L19: =SUM(L11:L18) -> 1087000
D20: Penerima | F20: Kaca yang sudah dipesan/dipasang tidak dapat dibatalkan/dikembalikan. | K20: DISKON
K21: NETTO | L21: =L19-L20 -> 1087000
K23: Ket
A24: Trust the Experts, Drive Safer and Clearer | D24: ....................

Sheet PIKET
A1: Daftar Piket Sentra Autoglass Surabaya
A2: Hari | B2: Penyapu Luar Dalam & Pengelola Sampah | C2: Merapikan Meja-Meja, Trolley, Peralatan Teknisi/ Lap | D2: Penyapu Dalam Ruangan | E2: Pengepel Dalam Ruangan
A3: Senin | B3: Ade | C3: Dimas | D3: Lia | E3: Via
A4: Selasa | B4: Flea | C4: Adin | D4: Via | E4: Lia
A5: Rabu | B5: Dimas | C5: Flea | D5: Lia | E5: Via
A6: Kamis | B6: Adin | C6: Ade | D6: Via | E6: Lia
A7: Jumat | B7: Flea | C7: Dimas | D7: Lia | E7: Via
A12: Piket Mingguan
A13: 1 | B13: Sapu pel luar dalam
A14: 2 | B14: Cuci Mobil & Motor kantor
A15: 3 | B15: Bersihkan Kipas
A16: 4 | B16: Cek kelengkapan toolkit dan inventory
A17: 5 | B17: Membersihkan sudut-sudut yang jarang disentuh (misalnya, ventilasi atau plafon).
A18: 6 | B18: Mengecek dan merapikan seluruh ruangan.
A19: 7 | B19: Mengelap kaca

Sheet SJ POLOS
J1: Tanggal | L1: 10/12/2025
J2: Kepada Yth.
J3: NGM Glory
J4: +62 851-0274-6465
J5: Cv.Titipan Illahi Trans
J6: Jl. Achmad Jais No.66,
J7: RT.009/RW.02, Peneleh
D9: SURAT JALAN
A10: SJ | B10: SJL250030
A11: No | B11: Kode | C11: Nama Barang | L11: QTY
A12: 1 | B12: LFW-KAPSUL02XYG | C12: =IFERROR(VLOOKUP(B12,Stock,3,FALSE),"") -> Toyota Kijang 02-04 Kapsul Lem Efi | L12: 1
A13: 2 | B13: SWR-KAPSUL02LONGASH | C13: Honda BR-V 16-21 (Honda) | L13: 1
C14: =IFERROR(VLOOKUP(B14,Stock,3,FALSE),"")
C15: =IFERROR(VLOOKUP(B15,Stock,3,FALSE),"")
C16: =IFERROR(VLOOKUP(B16,Stock,3,FALSE),"")
E18: Penerima | J18: Kaca yang sudah dipesan tidak dapat dibatalkan/dikembalikan.
J21: KET :
E22: .................... | J22: KIRIM

Sheet KIRIM BKS
B1: QTY | C1: RAK | D1: QTY KIRIM | E1: SO
B2: =sum(B3:B79) -> 163
A3: FDL-MOBILIOASH | B3: 1 | C3: =IFERROR(VLOOKUP(A3,Stock,10,FALSE),"") -> B12T4 | D3: 1
A4: FDR-MOBILIOASH | B4: 1 | C4: =IFERROR(VLOOKUP(A4,Stock,10,FALSE),"") -> B12T4/peti | D4: 1
A5: RDL-MOBILIOASH | B5: 1 | C5: =IFERROR(VLOOKUP(A5,Stock,10,FALSE),"") -> B11T4/peti | D5: 1
A6: RDR-MOBILIOASH | B6: 1 | C6: =IFERROR(VLOOKUP(A6,Stock,10,FALSE),"") -> B11T4 | D6: 1
A7: RDR-HILUX05ASH | B7: 1 | C7: =IFERROR(VLOOKUP(A7,Stock,10,FALSE),"") -> A12T4 | D7: 1
A8: FDL-FORTUNER15ASH | B8: 1 | C8: =IFERROR(VLOOKUP(A8,Stock,10,FALSE),"") -> A12T4 | D8: 1
A9: RVL-FORTUNER15ASH | B9: 1 | C9: =IFERROR(VLOOKUP(A9,Stock,10,FALSE),"") -> B6T4 | D9: 1
A10: RVR-FORTUNER15ASH | B10: 1 | C10: =IFERROR(VLOOKUP(A10,Stock,10,FALSE),"") -> B6T4 | D10: 1
A11: SWR-FORTUNER15ASH | B11: 1 | C11: =IFERROR(VLOOKUP(A11,Stock,10,FALSE),"") -> A12T4 | D11: 1
A12: FDL-FREEDASH | B12: 1 | C12: =IFERROR(VLOOKUP(A12,Stock,10,FALSE),"") -> B12T4 | D12: 1
A13: RDL-RUSH17ASH | B13: 1 | C13: =IFERROR(VLOOKUP(A13,Stock,10,FALSE),"") -> A12T3 | D13: 1
A14: RDR-RUSH17ASH | B14: 2 | C14: =IFERROR(VLOOKUP(A14,Stock,10,FALSE),"") -> A12T3 | D14: 2
... A23: FDL-AVANZA03ASH | B23: 2 | C23: =IFERROR(VLOOKUP(A23,Stock,10,FALSE),"") -> A11T3 | D23: 2
A24: FDR-AVANZA03ASH | B24: 3 | C24: =IFERROR(VLOOKUP(A24,Stock,10,FALSE),"") -> A11T3
A25: RDL-AVANZA03ASH | B25: 3 | C25: =IFERROR(VLOOKUP(A25,Stock,10,FALSE),"") -> A13T4
A26: RDR-AVANZA03ASH | B26: 3 | C26: =IFERROR(VLOOKUP(A26,Stock,10,FALSE),"") -> A13T4
A27: FDL-AVANZA11ASH | B27: 2 | C27: =IFERROR(VLOOKUP(A27,Stock,10,FALSE),"") -> A11T3
A28: FDR-AVANZA11ASH | B28: 2 | C28: =IFERROR(VLOOKUP(A28,Stock,10,FALSE),"") -> A11T3
A29: FDL-AGYA13ASH | B29: 3 | C29: =IFERROR(VLOOKUP(A29,Stock,10,FALSE),"") -> A10T3
A30: FDR-AGYA13ASH | B30: 3 | C30: =IFERROR(VLOOKUP(A30,Stock,10,FALSE),"") -> A10T3
A31: RDL-AGYA13ASH | B31: 3 | C31: =IFERROR(VLOOKUP(A31,Stock,10,FALSE),"") -> A13T4
A32: RDR-AGYA13ASH | B32: 3 | C32: =IFERROR(VLOOKUP(A32,Stock,10,FALSE),"") -> A13T4
A33: FDL-DYNAASH | B33: 3 | C33: =IFERROR(VLOOKUP(A33,Stock,10,FALSE),"") -> A8T3
A34: FDR-DYNAASH | B34: 2 | C34: =IFERROR(VLOOKUP(A34,Stock,10,FALSE),"") -> A7T3
A35: FDL-INNOVA04MSG | B35: 1 | C35: =IFERROR(VLOOKUP(A35,Stock,10,FALSE),"") -> A11T4
... A53: RQR-SIGRA16ASH | B53: 3 | C53: =IFERROR(VLOOKUP(A53,Stock,10,FALSE),"")
A54: SWR-PAJERO16AGC | B54: 1 | C54: =IFERROR(VLOOKUP(A54,Stock,10,FALSE),"") -> B14T4 | E54: CANCEL
A55: RDL-SIGRA16ASH | B55: 3 | C55: =IFERROR(VLOOKUP(A55,Stock,10,FALSE),"") -> B10T4
A56: RDR-SIGRA16ASH | B56: 3 | C56: =IFERROR(VLOOKUP(A56,Stock,10,FALSE),"") -> B10T4
A57: FDL-FE300ASH | B57: 3 | C57: =IFERROR(VLOOKUP(A57,Stock,10,FALSE),"") -> A7T3
A58: FDL-ERTIGA12ASH | B58: 2 | C58: =IFERROR(VLOOKUP(A58,Stock,10,FALSE),"") -> B10T4
A59: SWR-PANTHER91ASH | B59: 2 | C59: =IFERROR(VLOOKUP(A59,Stock,10,FALSE),"") -> B9T4
A60: FDL-CARRYASH | B60: 2 | C60: =IFERROR(VLOOKUP(A60,Stock,10,FALSE),"") -> B10T4
A61: FDL-KUDAASH | B61: 2 | C61: =IFERROR(VLOOKUP(A61,Stock,10,FALSE),"") -> B10T4
A62: FDL-INNOVA15ASH | B62: 3 | C62: =IFERROR(VLOOKUP(A62,Stock,10,FALSE),"") -> A10T4
A63: FDR-INNOVA15ASH | B63: 1 | C63: =IFERROR(VLOOKUP(A63,Stock,10,FALSE),"") -> B10T4
A64: RDR-AVANZA11ASH | B64: 2 | C64: =IFERROR(VLOOKUP(A64,Stock,10,FALSE),"") -> A13T3
A65: RDL-AVANZA11ASH | B65: 3 | C65: =IFERROR(VLOOKUP(A65,Stock,10,FALSE),"") -> A13T3
A66: TRW-GRANMAXPUASH | B66: 3 | C66: =IFERROR(VLOOKUP(A66,Stock,10,FALSE),"") -> B8T4
... A75: LFW-HRV22PIL | B75: 1 | C75: =IFERROR(VLOOKUP(A75,Stock,10,FALSE),"") -> B7T2
A76: LFW-AVANZA21RSASH | B76: 3 | C76: =IFERROR(VLOOKUP(A76,Stock,10,FALSE),"") -> B1T2 | D76: 1
A77: LFW-AVANZA21MU | B77: 3 | C77: =IFERROR(VLOOKUP(A77,Stock,10,FALSE),"") -> B1T2
A78: LFW-BRV22ASH | B78: 2 | C78: =IFERROR(VLOOKUP(A78,Stock,10,FALSE),"") -> B5T1
A79: LFW-CARRYASH | B79: 2 | C79: =IFERROR(VLOOKUP(A79,Stock,10,FALSE),"") -> A13T1
C80: =IFERROR(VLOOKUP(A80,Stock,10,FALSE),"")
A81: Tambahan | C81: =IFERROR(VLOOKUP(A81,Stock,10,FALSE),"")
A82: LFW-FORTUNER05MSG | B82: 5 | C82: =IFERROR(VLOOKUP(A82,Stock,10,FALSE),"") -> B2T2
A83: LFW-ALMAZFY | B83: 3 | C83: =IFERROR(VLOOKUP(A83,Stock,10,FALSE),"") -> A9T1 | D83: 1
C84: =IFERROR(VLOOKUP(A84,Stock,10,FALSE),"")
C85: =IFERROR(VLOOKUP(A85,Stock,10,FALSE),"")
C86: =IFERROR(VLOOKUP(A86,Stock,10,FALSE),"")
C87: =IFERROR(VLOOKUP(A87,Stock,10,FALSE),"")
C88: =IFERROR(VLOOKUP(A88,Stock,10,FALSE),"")
C89: =IFERROR(VLOOKUP(A89,Stock,10,FALSE),"")
C90: =IFERROR(VLOOKUP(A90,Stock,10,FALSE),"")
C91: =IFERROR(VLOOKUP(A91,Stock,10,FALSE),"")
C92: =IFERROR(VLOOKUP(A92,Stock,10,FALSE),"")
C93: =IFERROR(VLOOKUP(A93,Stock,10,FALSE),"")
C94: =IFERROR(VLOOKUP(A94,Stock,10,FALSE),"")
C95: =IFERROR(VLOOKUP(A95,Stock,10,FALSE),"")

Sheet NOTA RETUR
A1: SENTRA AUTOGLASS SURABAYA | J1: Tanggal | L1: 45448
A2: Jalan Simo Jawar No. 108, Simomulyo Baru, Sukomanunggal, Surabaya | J2: Kepada Yth.
A3: (+62) 81288009878 | sentraautoglass.sby@gmail.com | J3: PT. Tirta Jaya Trapac
J4: +62 859-4120-4572
J5: Surabaya
D7: RETUR PENJUALAN
A9: INV : | B9: E240063 | C9: RETUR NO : RTN-F240001 | J9: NO POL
A10: No | B10: Kode | C10: Nama Barang | H10: Qty | J10: Harga Satuan | L10: Jumlah
A11: 1 | B11: TRW-HIACEBLACKXYG | C11: Rear Window Toyota Hi-Ace 04-20 Tempered | H11: 1 | I11: PC | J11: 780600 | L11: =H11*J11 -> 780600
L12: =H12*J12 -> 0
L13: =H13*J13 -> 0
B14: Return to | C14: BCA 4480245542 an Tirtahamidjaja Rahardja | L14: =H14*J14 -> 0
L15: =H15*J15 -> 0
L16: =H16*J16 -> 0
L17: =H17*J17 -> 0
K18: TOTAL | L18: =SUM(L11:L17) -> 780600
D19: Penerima | F19: Kaca yang sudah dipesan/dipasang tidak dapat dibatalkan/dikembalikan. | K19: DISKON | L19: 0
K20: NETTO | L20: =L18-L19 -> 780600
K22: Ket
A23: Trust the Experts, Drive Safer and Clearer | D23: ....................
H30: ,

Sheet Print alamat
A1: PENERIMA :
A2: P. OKTA +62 813-9105-5492

Sheet Petty Cash
A1: Petty Cash Surabaya | I1: Cek | J1: POS KAS
A2: Tanggal | B2: Nama | C2: Ket | D2: Debit | E2: Kredit | F2: Sisa | G2: Input by | H2: Terima uang | J2: Transportasi | K2: Perlengkapan Workshop | L2: Administrasi & Kantor | M2: Konsumsi | N2: Perawatan Fasilitas | O2: Biaya Tak terduga
A3: Juni 2024
A4: 45447 | B4: Uang Masuk | D4: 300000 | F4: =D4-E4 -> 300000 | H4: Via & Lia
A5: 45447 | B5: Lalamove | C5: dari BGI ambil TRW-H1XYG | E5: 84000 | F5: =F4+D5-E5 -> 216000 | G5: Lia | H5: Supir
A6: 45447 | B6: Lalamove | C6: dari Maspion ambil LFW-HRV22PIL | E6: 82000 | F6: =F5+D6-E6 -> 134000 | G6: Lia | H6: Supir
A7: 45447 | B7: parkir lalamove | E7: 5000 | F7: =F6+D7-E7 -> 129000 | G7: Lia | H7: Supir
A8: 45448 | B8: Air minum | C8: Air minum Karyawan Sentra 3 galon | E8: 25500 | F8: =F7+D8-E8 -> 103500 | G8: Lia | H8: Wisman
A9: 45451 | B9: Parkir | C9: parkir granmax kirim expedisi | E9: 5000 | F9: =F8+D9-E9 -> 98500 | G9: Lia | H9: Wisman
A10: 45451 | B10: Kape | C10: Kape @12000/pc | E10: 36000 | F10: =F9+D10-E10 -> 62500 | G10: Lia | H10: Wisman
A11: 45453 | B11: Air minum | C11: Air minum Karyawan Sentra 1 galon | E11: 5000 | F11: =F10+D11-E11 -> 57500 | G11: Lia | H11: Tukang galon
A12: 45453 | B12: Uang Masuk | D12: 300000 | F12: =F11+D12-E12 -> 357500 | G12: Lia | H12: lia
A13: 45453 | B13: Ganti bensin | C13: Ganti bensin lia | E13: 5000 | F13: =F12+D13-E13 -> 352500 | G13: Lia | H13: lia
A14: 45453 | B14: Ganti bensin | C14: Ganti bensin guntur | E14: 20000 | F14: =F13+D14-E14 -> 332500 | G14: Lia | H14: dimas
A15: 45453 | B15: Ganti bensin | C15: Ganti bensin Dimas | E15: 15000 | F15: =F14+D15-E15 -> 317500 | G15: Lia | H15: dimas
A16: 45454 | B16: Bensin granmax | C16: Beli bensin granmax (oprasional) | E16: 300000 | F16: =F15+D16-E16 -> 17500 | G16: Lia | H16: Wisman
A17: 45454 | B17: Uang Masuk | D17: 300000 | F17: =F16+D17-E17 -> 317500 | G17: lia | H17: lia
A18: 45454 | B18: Mata gerenda | C18: Mata gerenda kayu | E18: 50000 | F18: =F17+D18-E18 -> 267500 | G18: via | H18: Dimas
A19: 45455 | B19: Air minum | C19: Air minum Karyawan Sentra 1 galon | E19: 5000 | F19: =F18+D19-E19 -> 262500 | G19: lia | H19: Tukang galon
A20: 45455 | B20: List Ertiga | C20: List karet kaca depan Ertiga | E20: 80000 | F20: =F19+D20-E20 -> 182500 | G20: via | H20: Dimas
A21: 45455 | B21: Parkir | C21: parkir granmax kirim expedisi | E21: 5000 | F21: =F20+D21-E21 -> 177500 | G21: via | H21: Guntur
A22: 45457 | B22: Air minum | C22: Air minum Karyawan Sentra 1 galon | E22: 5000 | F22: =F21+D22-E22 -> 172500 | G22: via | H22: Tukang galon
A23: 45457 | B23: Alat listrik | C23: Alat Listrik (Toko Jaya Abadi) | E23: 5000 | F23: =F22+D23-E23 -> 167500 | G23: via | H23: Wisman
A24: 45457 | B24: Lembur | C24: Lembur pemasangan kaca | E24: 100000 | F24: =F23+D24-E24 -> 67500 | H24: Wisman dan ade
A25: 45461 | B25: Air minum | C25: Air minum Karyawan Sentra 2 galon | E25: 10000 | F25: =F24+D25-E25 -> 57500 | G25: via | H25: Tukang galon
A26: 45461 | B26: Uang Masuk | D26: 300000 | F26: =F25+D26-E26 -> 357500 | G26: LIA | H26: LIA | I26: ok
A27: 45462 | B27: kembalian | C27: Kembalian uang customer | E27: 1000 | F27: =F26+D27-E27 -> 356500 | G27: via | H27: customer
A28: 45465 | B28: Air minum | C28: Air minum Karyawan Sentra 1 galon | E28: 5000 | F28: =F27+D28-E28 -> 351500 | G28: LIA | H28: Dimas
A29: 45465 | B29: Kasbon ADE | C29: Kasbon Ade | E29: 100000 | F29: =F28+D29-E29 -> 251500 | G29: Lia | H29: Ade
A30: 45466 | B30: Lembur | C30: Lembur pemasangan kaca depan | E30: 100000 | F30: =F29+D30-E30 -> 151500 | G30: lia | H30: Wisman dan Dimas
A31: 45466 | B31: Parkir | C31: parkir granmax kirim expedisi | E31: 5000 | F31: =F30+D31-E31 -> 146500 | G31: lia | H31: Guntur
A32: 45466 | B32: Alat listrik | C32: Alat Listrik (Toko Jaya Abadi) | E32: 57000 | F32: =F31+D32-E32 -> 89500 | G32: lia | H32: wisman
A33: 45468 | B33: Uang Masuk | D33: 300000 | F33: =F32+D33-E33 -> 389500 | G33: lia | H33: LIA | I33: ok/reim
A34: 45468 | B34: Alat kebersihan | C34: Pewangi kamar mandi dan sabun cuci | E34: 17800 | F34: =F33+D34-E34 -> 371700 | G34: lia | H34: Dimas
A35: 45468 | B35: Bensin granmax | C35: Beli bensin granmax (oprasional) (NOTA 287.450 DIBULATKAN 287.500) | E35: 287500 | F35: =F34+D35-E35 -> 84200 | G35: lia | H35: wisman
A36: 45469 | B36: Air minum | C36: Air minum Karyawan Sentra 4 galon @8500 | E36: 34000 | F36: =F35+D36-E36 -> 50200 | G36: lia | H36: wisman
A37: 45469 | B37: Alat kebersihan | C37: Super pel (NOTA 17.100 DIBULATKAN 17.000) | E37: 17000 | F37: =F36+D37-E37 -> 33200 | G37: lia | H37: Dimas
A38: 45471 | B38: Parkir | C38: parkir granmax kirim expedisi | E38: 8000 | F38: =F37+D38-E38 -> 25200 | G38: lia | H38: Guntur
A39: Juli 2024
A40: 45476 | B40: Uang Masuk | D40: 500000 | F40: =F38+D40-E40 -> 525200 | G40: via | H40: via | I40: ok/reim
A41: 45476 | B41: Air minum | C41: Air minum Karyawan Sentra 3 galon @8500 | E41: 25500 | F41: =F40+D41-E41 -> 499700 | G41: via | H41: Ade
A42: 45476 | B42: Beli kaca | C42: Kaca belakang new carry pick up | E42: 90000 | F42: =F41+D42-E42 -> 409700 | G42: via | H42: Dimas
A43: 45476 | B43: Parkir | C43: Parkir motor beli kaca | E43: 2000 | F43: =F42+D43-E43 -> 407700 | G43: via | H43: dimas
A44: 45477 | B44: Bensin granmax | C44: Beli bensin granmax (oprasional) | E44: 300000 | F44: =F43+D44-E44 -> 107700 | G44: via | H44: wisman
A45: 45478 | B45: Uang Masuk | D45: 400000 | F45: =F44+D45-E45 -> 507700 | G45: Michelle | H45: - | I45: OK/ reim 10/8/24
A46: 45478 | B46: Uang Masuk | C46: Untuk kasir | D46: 351000 | F46: =F45+D46-E46 -> 858700 | G46: Michelle | I46: OK/reim 10/8/24
A47: 45478 | B47: Kasir | C47: Ganti cash | E47: 351000 | F47: =F46+D47-E47 -> 507700 | G47: Michelle | I47: OK
A48: 45477 | B48: Parkir | C48: parkir granmax kirim expedisi | E48: 5000 | F48: =F47+D48-E48 -> 502700 | G48: via | H48: Guntur
A49: 45481 | B49: Kasbon ADE | C49: Kasbon ADE | E49: 100000 | F49: =F48+D49-E49 -> 402700 | G49: via | H49: Ade
A50: 45482 | B50: Parkir | C50: parkir granmax pasang kaca | E50: 11000 | F50: =F49+D50-E50 -> 391700 | G50: via | H50: Guntur
A51: 45484 | B51: Alat listrik | C51: Alat Listrik (Toko Jaya Abadi) | E51: 12000 | F51: =F50+D51-E51 -> 379700 | G51: via | H51: wisman
A52: 45484 | B52: Parkir | C52: parkir granmax kirim expedisi | E52: 5000 | F52: =F51+D52-E52 -> 374700 | G52: via | H52: Guntur
A53: 45484 | B53: Bensin granmax | C53: Beli bensin granmax (oprasional) | E53: 200000 | F53: =F52+D53-E53 -> 174700 | G53: via | H53: Guntur
A54: 45485 | B54: Uang Masuk | D54: 500000 | F54: =F53+D54-E54 -> 674700 | G54: via | H54: via | I54: OK/reim 12/7/24
A55: 45486 | B55: Ganti uang | C55: Ganti uang dimas | E55: 100000 | F55: =F54+D55-E55 -> 574700 | G55: via | H55: dimas
A56: 45486 | B56: Beli kaca | C56: Beli kaca truk Louhan | E56: 250000 | F56: =F55+D56-E56 -> 324700 | G56: via | H56: Ade
A57: 45486 | B57: Bensin motor | C57: Beli bensin motor Ade | E57: 15000 | F57: =F56+D57-E57 -> 309700 | G57: via | H57: wisman
A58: 45486 | B58: Air minum | C58: Air minum Karyawan Sentra 3 galon @8500 | E58: 25500 | F58: =F57+D58-E58 -> 284200 | G58: via | H58: Ade
A59: 45486 | B59: Uang Masuk | D59: 500000 | F59: =F58+D59-E59 -> 784200 | G59: via | H59: via | I59: OK/ reim 10/8/24
A60: 45486 | B60: Kasbon Wisman | C60: Kasbon Wisman | E60: 300000 | F60: =F59+D60-E60 -> 484200 | G60: via | H60: wisman
A61: 45486 | B61: Kasbon ADE | C61: Kasbon ADE | E61: 100000 | F61: =F60+D61-E61 -> 384200 | G61: via | H61: Ade
A62: 45488 | B62: E-toll | C62: E-toll gran max | E62: 302000 | F62: =F61+D62-E62 -> 82200 | G62: via | H62: Guntur
A63: 45489 | B63: Parkir | C63: parkir granmax beli kaca | E63: 5000 | F63: =F62+D63-E63 -> 77200 | G63: via | H63: Guntur
A64: 45489 | B64: Uang Masuk | D64: 700000 | F64: =F63+D64-E64 -> 777200 | G64: via | H64: via | I64: ok/ dari penjualan/reim 10/8/24
A65: 45490 | B65: Alat kebersihan | C65: Sabun cuci mama lemon | E65: 8800 | F65: =F64+D65-E65 -> 768400 | G65: via | H65: dimas
A66: 45493 | B66: Uang Masuk | D66: 1000000 | F66: =F65+D66-E66 -> 1768400 | G66: via | H66: via | I66: ok/ reim, 10/8/24
A67: 45493 | B67: Kasbon ADE | C67: Kasbon ADE | E67: 100000 | F67: =F66+D67-E67 -> 1668400 | G67: via | H67: Ade
A68: 45493 | B68: Kasbon Dimas | C68: Kasbon Dimas | E68: 200000 | F68: =F67+D68-E68 -> 1468400 | G68: via | H68: dimas
A69: 45493 | B69: Kasbon Guntur | C69: Kasbon Guntur | E69: 100000 | F69: =F68+D69-E69 -> 1368400 | G69: via | H69: Guntur
A70: 45493 | B70: Kasbon Via | C70: Kasbon Via | E70: 100000 | F70: =F69+D70-E70 -> 1268400 | G70: via | H70: Via
A71: 45493 | B71: Kasbon Lia | C71: Kasbon Lia | E71: 200000 | F71: =F70+D71-E71 -> 1068400 | G71: via | H71: Lia
A72: 45493 | B72: Kasbon Wisman | C72: Kasbon Wisman | E72: 300000 | F72: =F71+D72-E72 -> 768400 | G72: via | H72: wisman
A73: 45496 | B73: Bensin granmax | C73: Beli bensin granmax (oprasional) | E73: 300000 | F73: =F72+D73-E73 -> 468400 | G73: via | H73: wisman
A74: 45497 | B74: Air minum | C74: Air minum Karyawan Sentra 3 galon @8500 | E74: 25500 | F74: =F73+D74-E74 -> 442900 | G74: via | H74: Ade
A75: 45498 | B75: Ongkir JNT | C75: Ongkir JNT CARGO | E75: 315000 | F75: =F74+D75-E75 -> 127900 | G75: via | H75: Ade | I75: ok
A76: 45498 | B76: Uang Masuk | D76: 1000000 | F76: =F75+D76-E76 -> 1127900 | G76: via | H76: via | I76: ok/ reim 14/8/24
A77: 45500 | B77: Kasbon ADE | C77: Kasbon ADE | E77: 100000 | F77: =F76+D77-E77 -> 1027900 | G77: via | H77: Ade
A78: 45500 | B78: Kasbon Guntur | C78: Kasbon Guntur | E78: 100000 | F78: =F77+D78-E78 -> 927900 | G78: via | H78: Guntur
A79: 45500 | B79: Kasbon Dimas | C79: Kasbon Dimas | E79: 200000 | F79: =F78+D79-E79 -> 727900 | G79: via | H79: dimas
A80: 45500 | B80: Kasbon Wisman | C80: Kasbon Wisman | E80: 300000 | F80: =F79+D80-E80 -> 427900 | G80: via | H80: wisman
A81: 45500 | B81: Bensin motor | C81: Gantin bensin guntur | E81: 20000 | F81: =F80+D81-E81 -> 407900 | G81: via | H81: Guntur
A82: 45504 | B82: Parkir | C82: parkir granmax kirim expedisi | E82: 5000 | F82: =F81+D82-E82 -> 402900 | G82: via | H82: Guntur
A83: 45504 | B83: Bensin granmax | C83: Beli bensin granmax (oprasional) | E83: 300000 | F83: =F82+D83-E83 -> 102900 | G83: via | H83: wisman
A84: Agustus 2024
A85: 45505 | B85: Uang Masuk | D85: 500000 | F85: =F83+D85-E85 -> 602900 | G85: via | H85: via | I85: ok / reim 14/8/24
A86: 45505 | B86: Kos wisman | C86: Kos wisman | E86: 500000 | F86: =F85+D86-E86 -> 102900 | G86: via | H86: wisman
A87: 45506 | B87: Uang Bensin | C87: Ganti uang bensin motor ade | E87: 20000 | F87: =F86+D87-E87 -> 82900 | G87: via | H87: Ade
A88: 45506 | B88: Uang hilang | C88: MALING | E88: 49000 | F88: =F87+D88-E88 -> 33900 | G88: via | H88: maling
A89: 45512 | B89: Uang Masuk | D89: 300000 | F89: =F88+D89-E89 -> 333900 | I89: OK/ reis 8/8/24
A90: 45512 | B90: Bensin granmax | C90: Beli bensin granmax (oprasional) | E90: 300000 | F90: =F89+D90-E90 -> 33900 | G90: VIA | H90: GUNTUR
A91: 45514 | B91: Uang Masuk | D91: 10600 | F91: =F90+D91-E91 -> 44500
A92: 45514 | B92: Alfamidi | C92: Mama Lemon | E92: 10600 | F92: =F91+D92-E92 -> 33900 | G92: MICHELLE | I92: reim 14/8/24
A93: 45507 | B93: Air minum | C93: Air minum Karyawan Sentra 3 galon @8500 | E93: 25500 | F93: =F92+D93-E93 -> 8400 | G93: via | H93: ade
A94: 45509 | B94: Print dan fc | C94: Print spk dan nota manual | E94: 7000 | F94: =F93+D94-E94 -> 1400 | G94: via | H94: guntur
A95: 45514 | B95: Uang Masuk | C95: Ganti Uang Kasir curian Maling | D95: 148000 | F95: =F94+D95-E95 -> 149400 | G95: MICHELLE | I95: reim 10/8/24
A96: 45514 | B96: Uang keluar | C96: Ganti Uang Kasir curian Maling | E96: 148000 | F96: =F95+D96-E96 -> 1400 | G96: MICHELLE
A97: 45514 | B97: Uang Masuk | D97: 350000 | F97: =F96+D97-E97 -> 351400 | G97: MICHELLE
A98: 45514 | B98: Uang Kasir | E98: 100000 | F98: =F97+D98-E98 -> 251400 | G98: MICHELLE | H98: VIA | I98: reim 10/8/24
A99: 45514 | B99: Uang Masuk | C99: Kasbon | D99: 700000 | F99: =F98+D99-E99 -> 951400 | G99: MICHELLE | I99: reim 14/8/24
A100: 45514 | B100: Kasbon | C100: Kasbon ADE | E100: 100000 | F100: =F99+D100-E100 -> 851400 | G100: via | H100: ade
...

Sheet X
A1: JT FEB 25 | B1: =SUM(H735+H736+H737+H741+H745+H747+H748+H749+H768+H769+H770+H771+H772+H773+H774+H775+H776+H777+H778+H779+H780+H781+H783+H784+H785+H786+H787+H788+H789,H795) -> 52937229 | C1: TOTAL | D1: =SUM(B1:B2) -> 79405478
A2: JT MAR 25 | B2: =SUM(H790:H793)+H796+SUM(H798:H803) -> 26468249
A3: TANGGAL | B3: INV | C3: SUP | D3: KODE | E3: NAMA | F3: PC | G3: Harga | H3: Total Harga | I3: Hutang | J3: Jatuh Tempo | K3: Input By | L3: Check | M3: Bayar? | N3: Tanggal | O3: Kode Sistem
A5: 45348 | B5: SI2024B000252/SKBB033 | C5: MJD | D5: LFW-AVANZA16MU | E5: =IFERROR(VLOOKUP(D5,Stock,3,FALSE),"") -> Toyota Avanza / Xenia 15-21 3rd Gen | F5: 10 | G5: 396825 | H5: =F5*G5 -> 3968250 | O5: PR-00001
A6: 45348 | B6: SI2024B000252/SKBB033 | C6: MJD | D6: LFW-SIGRA16MU | E6: =IFERROR(VLOOKUP(D6,Stock,3,FALSE),"") -> Toyota Calya / Sigra 16- | F6: 10 | G6: 449328 | H6: =F6*G6 -> 4493280 | O6: PR-00001
A7: 45348 | B7: SI2024B000252/SKBB033 | C7: MJD | D7: LFW-AVANZA03MU | E7: =IFERROR(VLOOKUP(D7,Stock,3,FALSE),"") -> Toyota Avanza / Xenia 03-11 1st Gen | F7: 10 | G7: 396825 | H7: =F7*G7 -> 3968250 | O7: PR-00001
A8: 45348 | B8: SI2024B000252/SKBB033 | C8: MJD | D8: LFW-APVMU | E8: =IFERROR(VLOOKUP(D8,Stock,3,FALSE),"") -> Suzuki APV 03- Pickup/ Van (MULIA) | F8: 10 | G8: 483516 | H8: =F8*G8 -> 4835160 | O8: PR-00001
A9: 45348 | B9: SI2024B000252/SKBB033 | C9: MJD | D9: LFW-RUSH17MU | E9: =IFERROR(VLOOKUP(D9,Stock,3,FALSE),"") -> Toyota Rush / Terios 18- | F9: 10 | G9: 493284 | H9: =F9*G9 -> 4932840 | O9: PR-00001
A10: 45348 | B10: SI2024B000252/SKBB033 | C10: MJD | D10: LFW-AVANZA11MU | E10: =IFERROR(VLOOKUP(D10,Stock,3,FALSE),"") -> Toyota Avanza / Xenia 11-15 2nd Gen | F10: 10 | G10: 396825 | H10: =F10*G10 -> 3968250 | I10: 0 | O10: PR-00001
A11: 45348 | B11: SI2024B000252/SKBB033 | C11: MJD | D11: LFW-JAZZ01MU | E11: =IFERROR(VLOOKUP(D11,Stock,3,FALSE),"") -> Honda Jazz 01-07 1st Gen | F11: 10 | G11: 538461 | H11: =F11*G11 -> 5384610 | O11: PR-00001
A12: 45348 | B12: SI2024B000252/SKBB033 | C12: MJD | D12: LFW-FE300MU | E12: =IFERROR(VLOOKUP(D12,Stock,3,FALSE),"") -> Mitsubishi Canter FE300 85- (PS100,120,135 kabin kecil) | F12: 10 | G12: 415140 | H12: =F12*G12 -> 4151400 | O12: PR-00001
A13: 45348 | B13: SI2024B000252/SKBB033 | C13: MJD | D13: LFW-KATANAG84MU | E13: =IFERROR(VLOOKUP(D13,Stock,3,FALSE),"") -> Suzuki Katana 84- | F13: 3 | G13: 273504 | H13: =F13*G13 -> 820512 | O13: PR-00001
A14: 45348 | B14: SI2024B000252/SKBB033 | C14: MJD | D14: LFW-KATANAC84MU | E14: =IFERROR(VLOOKUP(D14,Stock,3,FALSE),"") -> Suzuki Katana 84- | F14: 2 | G14: 273504 | H14: =F14*G14 -> 547008 | O14: PR-00001
A15: 45348 | B15: SI2024B000252/SKBB033 | C15: MJD | D15: LFW-VITARA88MU | E15: =IFERROR(VLOOKUP(D15,Stock,3,FALSE),"") -> Suzuki Vitara 88-97 / Escudo / Sidekick | F15: 5 | G15: 472527 | H15: =F15*G15 -> 2362635 | O15: PR-00001
A16: 45348 | B16: SI2024B000252/SKBB033 | C16: MJD | D16: LFW-RANGER04MU | E16: =IFERROR(VLOOKUP(D16,Stock,3,FALSE),"") -> Ford Everest 04-15 / Ranger 04-11 / Mazda BT-50 | F16: 5 | G16: 463980 | H16: =F16*G16 -> 2319900 | O16: PR-00001
A17: 45348 | B17: SI2024B000252/SKBB033 | C17: MJD | D17: LFW-TARUNAMU | E17: =IFERROR(VLOOKUP(D17,Stock,3,FALSE),"") -> Daihatsu Taruna | F17: 5 | G17: 557997 | H17: =F17*G17 -> 2789985 | O17: PR-00001
A18: 45348 | B18: SI2024B000252/SKBB033 | C18: MJD | D18: LFW-MIRAGEMU | E18: =IFERROR(VLOOKUP(D18,Stock,3,FALSE),"") -> Mitsubishi Mirage 12- | F18: 5 | G18: 570207 | H18: =F18*G18 -> 2851035 | O18: PR-00001
A19: 45348 | B19: SI2024B000252/SKBB033 | C19: MJD | D19: LFW-SPINMU | E19: =IFERROR(VLOOKUP(D19,Stock,3,FALSE),"") -> Chevrolet Spin 12- | F19: 5 | G19: 641025 | H19: =F19*G19 -> 3205125 | O19: PR-00001
A20: 45348 | B20: SI2024B000252/SKBB033 | C20: MJD | D20: LFW-FORTUNER05MU | E20: =IFERROR(VLOOKUP(D20,Stock,3,FALSE),"") -> Toyota Fortuner 05-15 1st Gen | F20: 10 | G20: 493284 | H20: =F20*G20 -> 4932840 | O20: PR-00001
A21: 45348 | B21: SI2024B000252/SKBB033 | C21: MJD | D21: LFW-PAJERO08MU | E21: =IFERROR(VLOOKUP(D21,Stock,3,FALSE),"") -> Mitsubishi Pajero 08-16 | F21: 10 | G21: 456654 | H21: =F21*G21 -> 4566540 | O21: PR-00001
A22: 45348 | B22: SI2024B000252/SKBB033 | C22: MJD | D22: LFW-HILUX15MU | E22: =IFERROR(VLOOKUP(D22,Stock,3,FALSE),"") -> Toyota Hilux Pickup 15- (Revo) | F22: 10 | G22: 523809 | H22: =F22*G22 -> 5238090 | O22: PR-00001
A23: 45353 | B23: RJG03022024 | C23: RJG | D23: LFW-INNOVA04MSG | E23: =IFERROR(VLOOKUP(D23,Stock,3,FALSE),"") -> Toyota Innova 04-15 1st Gen | F23: 1 | G23: 932000 | H23: =F23*G23 -> 932000 | O23: PR-00003
A24: 45355 | B24: SJ000930 | C24: RJG | D24: TRW-ALPHARD08BLACKFR | E24: =IFERROR(VLOOKUP(D24,Stock,3,FALSE),"") -> Toyota Alphard 08-15 ANH20 2nd Gen (Hitam) | F24: 1 | G24: 558763.8 | H24: =F24*G24 -> 558763.8 | M24: TF BCA 33 | N24: 45416 | O24: PR-00004
A25: 45355 | B25: SJ000930 | C25: RJG | D25: FDL-ALPHARD08FR | E25: =IFERROR(VLOOKUP(D25,Stock,3,FALSE),"") -> Toyota Alphard 08-15 ANH20 2nd Gen | F25: 1 | G25: 160477.2 | H25: =F25*G25 -> 160477.2 | M25: TF BCA 33 | N25: 45416 | O25: PR-00004
A26: 45355 | B26: SJ000930 | C26: RJG | D26: FDR-ALPHARD08FR | E26: =IFERROR(VLOOKUP(D26,Stock,3,FALSE),"") -> Toyota Alphard 08-15 ANH20 2nd Gen | F26: 1 | G26: 160477.2 | H26: =F26*G26 -> 160477.2 | M26: TF BCA 33 | N26: 45416 | O26: PR-00004
A27: 45355 | B27: SJ000930 | C27: RJG | D27: LFW-ALPHARD08RSFR | E27: =IFERROR(VLOOKUP(D27,Stock,3,FALSE),"") -> Toyota Alphard 08-15 ANH20 2nd Gen Sensor | F27: 1 | G27: 796320.6 | H27: =F27*G27 -> 796320.6 | M27: TF BCA 33 | N27: 45416 | O27: PR-00004
A28: 45355 | B28: SJ000930 | C28: RJG | D28: TRW-ALPHARD15BLACKFR | E28: =IFERROR(VLOOKUP(D28,Stock,3,FALSE),"") -> Toyota Alphard 15-17 ANH30 3rd Gen (Hitam) | F28: 1 | G28: 570642 | H28: =F28*G28 -> 570642 | M28: TF BCA 33 | N28: 45416 | O28: PR-00004
A29: 45355 | B29: SJ000930 | C29: RJG | D29: RDL-ALPHARD15FR | E29: =IFERROR(VLOOKUP(D29,Stock,3,FALSE),"") -> Toyota Alphard 15- ANH30 3rd Gen | F29: 1 | G29: 173113.2 | H29: =F29*G29 -> 173113.2 | M29: TF BCA 33 | N29: 45416 | O29: PR-00004
A30: 45355 | B30: SJ000930 | C30: RJG | D30: RDR-ALPHARD15FR | E30: =IFERROR(VLOOKUP(D30,Stock,3,FALSE),"") -> Toyota Alphard 15- ANH30 3rd Gen | F30: 1 | G30: 173113.2 | H30: =F30*G30 -> 173113.2 | M30: TF BCA 33 | N30: 45416 | O30: PR-00004
A31: 45355 | B31: SJ000930 | C31: RJG | D31: LFW-ALPHARD15RSFR | E31: =IFERROR(VLOOKUP(D31,Stock,3,FALSE),"") -> Toyota Alphard 15-17 ANH30 3rd Gen (Sensor atas keramik) | F31: 1 | G31: 847370.4 | H31: =F31*G31 -> 847370.4 | M31: TF BCA 33 | N31: 45416 | O31: PR-00004
A32: 45355 | B32: SJ000930 | C32: RJG | D32: TRW-CAPTIVAFR | E32: =IFERROR(VLOOKUP(D32,Stock,3,FALSE),"") -> Chevrolet Captiva 06-18 1st gen C100 | F32: 1 | G32: 324745.2 | H32: =F32*G32 -> 324745.2 | M32: TF BCA 33 | N32: 45416 | O32: PR-00004
A33: 45355 | B33: SJ000930 | C33: RJG | D33: LFW-CAPTIVARSFR | E33: =IFERROR(VLOOKUP(D33,Stock,3,FALSE),"") -> Chevrolet Captiva 06-18 1st gen C100 | F33: 1 | G33: 602989.8 | H33: =F33*G33 -> 602989.8 | M33: TF BCA 33 | N33: 45416 | O33: PR-00004
A34: 45355 | B34: SJ000930 | C34: RJG | D34: LFW-W212RS2FR | E34: =IFERROR(VLOOKUP(D34,Stock,3,FALSE),"") -> Mers-Benz E-Class 09-16 W212 (2 Sensor/ □Δ) Trapes. | F34: 1 | G34: 1513287.6 | H34: =F34*G34 -> 1513287.6 | M34: TF BCA 33 | N34: 45416 | O34: PR-00004
A35: 45355 | B35: SJ000930 | C35: RJG | D35: TRW-FIESTAFR | E35: =IFERROR(VLOOKUP(D35,Stock,3,FALSE),"") -> Ford Fiesta 09-17 | F35: 1 | G35: 324745.2 | H35: =F35*G35 -> 324745.2 | M35: TF BCA 33 | N35: 45416 | O35: PR-00004
... A39: 45355 | B39: SJ000930 | C39: RJG | D39: RDR-HARRIER480NFR | E39: =IFERROR(VLOOKUP(D39,Stock,3,FALSE),"") -> Toyota Harrier - 480N | F39: 1 | G39: 147841.2 | H39: =F39*G39 -> 147841.2 | M39: TF BCA 33 | N39: 45416 | O39: PR-00004
A40: 45355 | B40: SJ000930 | C40: RJG | D40: SRR-HIACEFFR | E40: =IFERROR(VLOOKUP(D40,Stock,3,FALSE),"") -> Toyota Hi-Ace 04-20 Commuter With Frame | G40: RETUR | H40: 0 | M40: TF BCA 33 | N40: 45416 | O40: PR-00004
A41: 45355 | B41: SJ000930 | C41: RJG | D41: RDL-HIACEFBLACKFR | E41: =IFERROR(VLOOKUP(D41,Stock,3,FALSE),"") -> Toyota Hi-Ace 04-20 Commuter With Frame (Hitam) | F41: 1 | G41: 1082905.2 | H41: =F41*G41 -> 1082905.2 | M41: TF BCA 33 | N41: 45416 | O41: PR-00004
A42: 45355 | B42: SJ000930 | C42: RJG | D42: RDL-HIACEFFR | E42: =IFERROR(VLOOKUP(D42,Stock,3,FALSE),"") -> Toyota Hi-Ace 04-20 Commuter With Frame | F42: 1 | G42: 981817.2 | H42: =F42*G42 -> 981817.2 | M42: TF BCA 33 | N42: 45416 | O42: PR-00004
A43: 45355 | B43: SJ000930 | C43: RJG | D43: SRR-HIACEFBLACKFR | E43: =IFERROR(VLOOKUP(D43,Stock,3,FALSE),"") -> Toyota Hi-Ace 04-20 Commuter With Frame (Hitam) | G43: RETUR | H43: 0 | M43: TF BCA 33 | N43: 45416 | O43: PR-00004
A44: 45355 | B44: SJ000930 | C44: RJG | D44: LFW-JUKEFR | E44: =IFERROR(VLOOKUP(D44,Stock,3,FALSE),"") -> Nissan Juke 11- | F44: 1 | G44: 524394 | H44: =F44*G44 -> 524394 | M44: TF BCA 33 | N44: 45416 | O44: PR-00004
A45: 45355 | B45: SJ000930 | C45: RJG | D45: TRW-RX270/350FR | E45: =IFERROR(VLOOKUP(D45,Stock,3,FALSE),"") -> Lexus RX270/350 | F45: 1 | G45: 399045 | H45: =F45*G45 -> 399045 | M45: TF BCA 33 | N45: 45416 | O45: PR-00004
A46: 45355 | B46: SJ000930 | C46: RJG | D46: TRW-VOXY22FR | E46: =IFERROR(VLOOKUP(D46,Stock,3,FALSE),"") -> Toyota Voxy 22- 2nd Gen (Hitam) | F46: 1 | G46: 636601.8 | H46: =F46*G46 -> 636601.8 | M46: TF BCA 33 | N46: 45416 | O46: PR-00004
A47: 45355 | B47: SJ000930 | C47: RJG | D47: LFW-VOXY22RSFR | E47: =IFERROR(VLOOKUP(D47,Stock,3,FALSE),"") -> Toyota Voxy 22- 2nd Gen (1 Sensor / /\ ) | F47: 1 | G47: 558511.2 | H47: =F47*G47 -> 558511.2 | M47: TF BCA 33 | N47: 45416 | O47: PR-00004
A48: 45355 | B48: SJ000930 | C48: RJG | D48: FDL-HIACE19FR | E48: =IFERROR(VLOOKUP(D48,Stock,3,FALSE),"") -> Toyota Hi-Ace 19- Premio | F48: 1 | G48: 185749.2 | H48: =F48*G48 -> 185749.2 | M48: TF BCA 33 | N48: 45416 | O48: PR-00004
A49: 45355 | B49: SJ000930 | C49: RJG | D49: FDR-HIACE19FR | E49: =IFERROR(VLOOKUP(D49,Stock,3,FALSE),"") -> Toyota Hi-Ace 19- Premio | F49: 1 | G49: 185749.2 | H49: =F49*G49 -> 185749.2 | M49: TF BCA 33 | N49: 45416 | O49: PR-00004
A50: 45355 | B50: SJ000930 | C50: RJG | D50: LFW-HIACE19FR | E50: =IFERROR(VLOOKUP(D50,Stock,3,FALSE),"") -> Toyota Hi-Ace 19- Premio | F50: 1 | G50: 661873.8 | H50: =F50*G50 -> 661873.8 | M50: TF BCA 33 | N50: 45416 | O50: PR-00004
A51: 45355 | B51: SJ000930 | C51: RJG | D51: RDR-HIACE19FR | E51: =IFERROR(VLOOKUP(D51,Stock,3,FALSE),"") -> Toyota Hi-Ace 19- Premio | G51: RETUR | H51: 0 | M51: TF BCA 33 | N51: 45416 | O51: PR-00004
A52: 45355 | B52: SJ000930 | C52: RJG | D52: RDL-HIACE19FR | E52: =IFERROR(VLOOKUP(D52,Stock,3,FALSE),"") -> Toyota Hi-Ace 19- Premio | G52: RETUR | H52: 0 | M52: TF BCA 33 | N52: 45416 | O52: PR-00004
A53: 45355 | B53: SJ000930 | C53: RJG | D53: SRL-HIACE19FR | E53: =IFERROR(VLOOKUP(D53,Stock,3,FALSE),"") -> Toyota Hi-Ace 19- Premio | G53: RETUR | H53: 0 | M53: TF BCA 33 | N53: 45416 | O53: PR-00004
A54: 45355 | B54: SJ000930 | C54: RJG | D54: SRR-HIACE19FR | E54: =IFERROR(VLOOKUP(D54,Stock,3,FALSE),"") -> Toyota Hi-Ace 19- Premio | G54: RETUR | H54: 0 | M54: TF BCA 33 | N54: 45416 | O54: PR-00004
A55: 45355 | B55: SJ000930 | C55: RJG | D55: TRW-YARIS05FR | E55: =IFERROR(VLOOKUP(D55,Stock,3,FALSE),"") -> Toyota Yaris 05-13 XP90 1st Gen | F55: 1 | G55: 324745.2 | H55: =F55*G55 -> 324745.2 | M55: TF BCA 33 | N55: 45416 | O55: PR-00004
A56: 45355 | B56: SJ000930 | C56: RJG | D56: TRW-T30FR | E56: =IFERROR(VLOOKUP(D56,Stock,3,FALSE),"") -> Nissan X-Trail 01-07 T30 | F56: 1 | G56: 354060.6 | H56: =F56*G56 -> 354060.6 | M56: TF BCA 33 | N56: 45416 | O56: PR-00004
A57: 45355 | B57: SJ000930 | C57: RJG | D57: LFW-T31FR | E57: =IFERROR(VLOOKUP(D57,Stock,3,FALSE),"") -> Nissan X-Trail 07-13 T31 | F57: 1 | G57: 582267 | H57: =F57*G57 -> 582267 | M57: TF BCA 33 | N57: 45416 | O57: PR-00004
A58: 45356 | B58: SI2024C000112 | C58: MJD | D58: TRW-AVANZA11MU | E58: =IFERROR(VLOOKUP(D58,Stock,3,FALSE),"") -> Toyota Avanza / Xenia 11-15 2nd Gen / 15-21 3rd Gen | F58: 20 | G58: 290598 | H58: =F58*G58 -> 5811960 | O58: PR-00005
A59: 45356 | B59: SI2024C000112 | C59: MJD | D59: TRW-AVANZA03XYG | E59: =IFERROR(VLOOKUP(D59,Stock,3,FALSE),"") -> Toyota Avanza / Xenia 03-11 1st Gen | F59: 20 | G59: 289300 | H59: =F59*G59 -> 5786000 | O59: PR-00005
A60: 45356 | B60: SI2024C000112 | C60: MJD | D60: TRW-APVVANMU | E60: =IFERROR(VLOOKUP(D60,Stock,3,FALSE),"") -> Suzuki APV 03- Van | F60: 5 | G60: 224664 | H60: =F60*G60 -> 1123320 | O60: PR-00005
A61: 45356 | B61: SI2024C000112 | C61: MJD | D61: TRW-GRANMAXVANMU | E61: =IFERROR(VLOOKUP(D61,Stock,3,FALSE),"") -> Daihatsu Gran Max Minibus/Van | F61: 10 | G61: 233211 | H61: =F61*G61 -> 2332110 | O61: PR-00005
A62: 45356 | B62: SI2024C000112 | C62: MJD | D62: SWR-AVANZA03MU | E62: =IFERROR(VLOOKUP(D62,Stock,3,FALSE),"") -> Toyota Avanza / Xenia 03-11 1st Gen | F62: 5 | G62: 63492 | H62: =F62*G62 -> 317460 | O62: PR-00005
A63: 45356 | B63: SI2024C000112 | C63: MJD | D63: SWL-AVANZA03MU | E63: =IFERROR(VLOOKUP(D63,Stock,3,FALSE),"") -> Toyota Avanza / Xenia 03-11 1st Gen | F63: 5 | G63: 63492 | H63: =F63*G63 -> 317460 | O63: PR-00005
A64: 45356 | B64: SI2024C000112 | C64: MJD | D64: SWR-AVANZA11MU | E64: =IFERROR(VLOOKUP(D64,Stock,3,FALSE),"") -> Toyota Avanza / Xenia 11-15 2nd Gen / 15-21 3rd Gen | F64: 5 | G64: 84249 | H64: =F64*G64 -> 421245 | O64: PR-00005
A65: 45356 | B65: SI2024C000112 | C65: MJD | D65: SWL-AVANZA11MU | E65: =IFERROR(VLOOKUP(D65,Stock,3,FALSE),"") -> Toyota Avanza / Xenia 11-15 2nd Gen / 15-21 3rd Gen | F65: 5 | G65: 84249 | H65: =F65*G65 -> 421245 | O65: PR-00005
A66: 45356 | B66: SI2024C000112 | C66: MJD | D66: TRW-LUXIODAIHATSU | E66: =IFERROR(VLOOKUP(D66,Stock,3,FALSE),"") -> Daihatsu Luxio 07- | F66: 5 | G66: 302170 | H66: =F66*G66 -> 1510850 | O66: PR-00005
A67: 45356 | B67: SI2024C000112 | C67: MJD | D67: TRW-RUSH17HMU | E67: =IFERROR(VLOOKUP(D67,Stock,3,FALSE),"") -> Toyota Rush / Terios 18- | F67: 5 | G67: 339438 | H67: =F67*G67 -> 1697190 | O67: PR-00005
A68: 45356 | B68: SI2024C000112 | C68: MJD | D68: SWR-SIGRA16MU | E68: =IFERROR(VLOOKUP(D68,Stock,3,FALSE),"") -> Toyota Calya / Sigra 16- | F68: 5 | G68: 63492 | H68: =F68*G68 -> 317460 | O68: PR-00005
A69: 45356 | B69: SI2024C000112 | C69: MJD | D69: SWL-SIGRA16MU | E69: =IFERROR(VLOOKUP(D69,Stock,3,FALSE),"") -> Toyota Calya / Sigra 16- | F69: 5 | G69: 63492 | H69: =F69*G69 -> 317460 | O69: PR-00005
... A112: 45356 | B112: SI2024C000112 | C112: MJD | D112: LFW-CARRY19MU | E112: =IFERROR(VLOOKUP(D112,Stock,3,FALSE),"") -> Suzuki Carry New 19- | F112: 10 | G112: 493284 | H112: =F112*G112 -> 4932840 | O112: PR-00005
A113: 45357 | B113: M202403014 | C113: BGI | D113: OTH-SEALANTXYG | E113: =IFERROR(VLOOKUP(D113,Stock,3,FALSE),"") -> Sealant Polyurethane XYG Tube | F113: 100 | G113: 33000 | H113: =F113*G113 -> 3300000 | K113: 45357 | M113: TF BCA 33 | N113: 3300000 | O113: PR-00006
A114: 45358 | B114: 2403216 | C114: BGI | D114: LFW-CX5GEN1RSXYG | E114: =IFERROR(VLOOKUP(D114,Stock,3,FALSE),"") -> Mazda CX-5 .12-14 1st Gen KE Pre - (1 Sensor/ □ ) | F114: 1 | G114: 1664300 | H114: =G114 -> 1664300 | I114: =H114 -> 1664300 | J114: 45418 | M114: TF BCA 33 | N114: 45416 | O114: PR-00009
A115: 45358 | B115: 2403216 | C115: BGI | D115: TRW-SIGRA16MU | E115: =IFERROR(VLOOKUP(D115,Stock,3,FALSE),"") -> Toyota Calya / Sigra 16- | F115: 1 | G115: 339900 | H115: =G115 -> 339900 | I115: =H115 -> 339900 | J115: 45418 | M115: TF BCA 33 | N115: 45416 | O115: PR-00009
A116: 45363 | B116: 2403345 | C116: BGI | D116: LFW-CITY96XYG | E116: =IFERROR(VLOOKUP(D116,Stock,3,FALSE),"") -> Honda City 96-02 3rdGen (City Z) | F116: 1 | G116: 654500 | H116: =G116 -> 654500 | I116: =H116 -> 654500 | J116: 45423 | M116: TF BCA 33 | N116: 45422 | O116: PR-00010
A117: 45364 | B117: 2403387 | C117: BGI | D117: TRW-ERTIGA12XYG | E117: =IFERROR(VLOOKUP(D117,Stock,3,FALSE),"") -> Suzuki Ertiga 12-18 1st Gen MPV | F117: 2 | G117: 277000 | H117: =G117*F117 -> 554000 | I117: =H117 -> 554000 | J117: 45424 | M117: TF BCA 33 | N117: 45422 | O117: PR-00011
A118: 45364 | B118: 2403387 | C118: BGI | D118: TRW-AVANZA03HXYG | E118: =IFERROR(VLOOKUP(D118,Stock,3,FALSE),"") -> Toyota Avanza / Xenia 03-11 1st Gen | F118: 1 | G118: 322000 | H118: =G118*F118 -> 322000 | I118: =H118 -> 322000 | J118: 45424 | M118: TF BCA 33 | N118: 45422 | O118: PR-00011
A119: 45364 | B119: 2403387 | C119: BGI | D119: TRW-AVANZA11HXYG | E119: =IFERROR(VLOOKUP(D119,Stock,3,FALSE),"") -> Toyota Avanza / Xenia 11-15 2nd Gen / 15-21 3rd Gen | F119: 1 | G119: 313000 | H119: =G119*F119 -> 313000 | I119: =H119 -> 313000 | J119: 45424 | M119: TF BCA 33 | N119: 45422 | O119: PR-00011
A120: 45364 | B120: 2403387 | C120: BGI | D120: LFW-INNOVA04XYG | E120: =IFERROR(VLOOKUP(D120,Stock,3,FALSE),"") -> Toyota Innova 04-15 1st Gen | F120: 1 | G120: 613800 | H120: =G120*F120 -> 613800 | I120: =H120 -> 613800 | J120: 45424 | M120: TF BCA 33 | N120: 45422 | O120: PR-00011
A121: 45364 | B121: SI2024C000113 | C121: MJD | D121: LFW-TERIOS06MU | E121: =IFERROR(VLOOKUP(D121,Stock,3,FALSE),"") -> Toyota Rush / Terios 06-17 | F121: 10 | G121: 485958 | H121: =F121*G121 -> 4859580 | O121: PR-00012
A122: 45364 | B122: SI2024C000113 | C122: MJD | D122: LFW-PAJERO16MU | E122: =IFERROR(VLOOKUP(D122,Stock,3,FALSE),"") -> Mitsubishi Pajero 16- | F122: 10 | G122: 485958 | H122: =F122*G122 -> 4859580 | O122: PR-00012
A123: 45364 | B123: SI2024C000113 | C123: MJD | D123: LFW-TRITON05MU | E123: =IFERROR(VLOOKUP(D123,Stock,3,FALSE),"") -> Mitsubishi Strada Triton 08-15 | F123: 10 | G123: 456654 | H123: =F123*G123 -> 4566540 | O123: PR-00012
A124: 45364 | B124: SI2024C000113 | C124: MJD | D124: LFW-YARIS05MU | E124: =IFERROR(VLOOKUP(D124,Stock,3,FALSE),"") -> Toyota Yaris 05-13 XP90 1st Gen | F124: 10 | G124: 568986 | H124: =F124*G124 -> 5689860 | O124: PR-00012
A125: 45364 | B125: SI2024C000113 | C125: MJD | D125: LFW-AVANZA21MU | E125: =IFERROR(VLOOKUP(D125,Stock,3,FALSE),"") -> Toyota Avanza / Xenia 21- 4th Gen (Non sensor) | F125: 10 | G125: 604395 | H125: =F125*G125 -> 6043950 | O125: PR-00012
A126: 45364 | B126: SI2024C000113 | C126: MJD | D126: LFW-INNOVA04MU | E126: =IFERROR(VLOOKUP(D126,Stock,3,FALSE),"") -> Toyota Innova 04-15 1st Gen | F126: 10 | G126: 478632 | H126: =F126*G126 -> 4786320 | O126: PR-00012
A127: 45364 | B127: SI2024C000113 | C127: MJD | D127: LFW-XPANDERMU | E127: =IFERROR(VLOOKUP(D127,Stock,3,FALSE),"") -> Mitsubishi Xpander 17- | F127: 10 | G127: 672771 | H127: =F127*G127 -> 6727710 | O127: PR-00012
A128: 45364 | B128: SI2024C000113 | C128: MJD | D128: LFW-JAZZ07MU | E128: =IFERROR(VLOOKUP(D128,Stock,3,FALSE),"") -> Honda Jazz 07-13 2nd Gen | F128: 10 | G128: 628815 | H128: =F128*G128 -> 6288150 | O128: PR-00012
A129: 45364 | B129: SI2024C000113 | C129: MJD | D129: LFW-CARRYFUTURAMU | E129: =IFERROR(VLOOKUP(D129,Stock,3,FALSE),"") -> Suzuki Carry Futura (1300cc) / Mitsubishi Colt T120 | F129: 10 | G129: 329670 | H129: =F129*G129 -> 3296700 | O129: PR-00012
A130: 45364 | B130: SI2024C000113 | C130: MJD | D130: LFW-AGYA13MU | E130: =IFERROR(VLOOKUP(D130,Stock,3,FALSE),"") -> Toyota Agya/Ayla 13-22 1st Gen | F130: 10 | G130: 338217 | H130: =F130*G130 -> 3382170 | O130: PR-00012
A131: 45364 | B131: SI2024C000113 | C131: MJD | D131: LFW-T31MU | E131: =IFERROR(VLOOKUP(D131,Stock,3,FALSE),"") -> Nissan X-Trail 07-13 T31 | F131: 5 | G131: 693528 | H131: =F131*G131 -> 3467640 | O131: PR-00012
A132: 45364 | B132: SI2024C000113 | C132: MJD | D132: LFW-RANGER11MU | E132: =IFERROR(VLOOKUP(D132,Stock,3,FALSE),"") -> Ford Ranger 11- T6 /Mazda BT50 Sing/Doub Cabin | F132: 5 | G132: 660561 | H132: =F132*G132 -> 3302805 | O132: PR-00012
... A134: 45364 | B134: SI2024C000113 | C134: MJD | D134: LFW-CITY02MU | E134: =IFERROR(VLOOKUP(D134,Stock,3,FALSE),"") -> Honda City 02-08 4th Gen Idsi GD8 | F134: 5 | G134: 605616 | H134: =F134*G134 -> 3028080 | O134: PR-00012
A135: 45364 | B135: SI2024C000242 | C135: MJD | D135: SWL-ALPHARD08HITAMXYG | E135: =IFERROR(VLOOKUP(D135,Stock,3,FALSE),"") -> Toyota Alphard 08-15 ANH20 2nd Gen (Hitam) | F135: 1 | G135: 1324500 | H135: =F135*G135 -> 1324500 | M135: TF BCA 33 | N135: 18/4/24 1,068,430 30/5/24 256,070 | O135: PR-00012
A136: 45365 | B136: SJ000942 | C136: RJG | D136: LFW-PICANTO11PIL | E136: =IFERROR(VLOOKUP(D136,Stock,3,FALSE),"") -> Kia Picanto 11-16 2nd Gen | F136: 1 | G136: 960000 | H136: =F136*G136 -> 960000 | M136: TF BCA 33 | N136: 45422 | O136: PR-00013
A137: 45366 | B137: 2403288 | C137: BGI | D137: LFW-HRV14XYG | E137: =IFERROR(VLOOKUP(D137,Stock,3,FALSE),"") -> Honda HR-V 14-21 5D SUV | F137: 1 | G137: 883300 | H137: =F137*G137 -> 883300 | I137: =H137 -> 883300 | J137: 45426 | M137: TF BCA 33 | N137: 45425 | O137: PR-00014
A138: 45366 | B138: 2403288 | C138: BGI | D138: LFW-T30XYG | E138: =IFERROR(VLOOKUP(D138,Stock,3,FALSE),"") -> Nissan X-Trail 01-07 T30 | F138: 1 | G138: 809050 | H138: =F138*G138 -> 809050 | I138: =H138 -> 809050 | J138: 45426 | M138: TF BCA 33 | N138: 45425 | O138: PR-00014
A139: 45369 | B139: 2403517 | C139: BGI | D139: LFW-ELFNMRXYG | E139: =IFERROR(VLOOKUP(D139,Stock,3,FALSE),"") -> Isuzu Elf 17- New NMR NLR | F139: 3 | G139: 502700 | H139: =F139*G139 -> 1508100 | I139: =H139 -> 1508100 | J139: 45429 | M139: TF BCA 33 | N139: 45422 | O139: PR-00015
A140: 45369 | B140: 2403517 | C140: BGI | D140: TRW-BRV16XYG | E140: =IFERROR(VLOOKUP(D140,Stock,3,FALSE),"") -> Honda BR-V 16- | F140: 3 | G140: 546000 | H140: =F140*G140 -> 1638000 | I140: =H140 -> 1638000 | J140: 45429 | M140: TF BCA 33 | N140: 45422 | O140: PR-00015
A141: 45370 | B141: 2403586 | C141: BGI | D141: TRW-VIOS07XYG | E141: =IFERROR(VLOOKUP(D141,Stock,3,FALSE),"") -> Toyota Vios 07-13 XP90 2nd Gen | F141: 2 | G141: 689000 | H141: =F141*G141 -> 1378000 | I141: =H141 -> 1378000 | J141: 45430 | M141: TF BCA 33 | N141: 45428 | O141: PR-00016
A142: 45370 | B142: 2403586 | C142: BGI | D142: LFW-CX5GEN1RSXYG | E142: =IFERROR(VLOOKUP(D142,Stock,3,FALSE),"") -> Mazda CX-5 .12-14 1st Gen KE Pre - (1 Sensor/ □ ) | F142: 2 | G142: 1664300 | H142: =F142*G142 -> 3328600 | I142: =H142 -> 3328600 | J142: 45430 | M142: TF BCA 33 | N142: 45428 | O142: PR-00016
A143: 45374 | B143: SJ000943 | C143: RJG | D143: LFW-INNOVA15PIL | E143: =IFERROR(VLOOKUP(D143,Stock,3,FALSE),"") -> Toyota Innova 15- 2nd Gen | F143: 1 | G143: 975000 | H143: =F143*G143 -> 975000 | M143: TF BCA 33 | N143: 45434 | O143: PR-00017
A144: 45374 | B144: SJ000943 | C144: RJG | D144: LFW-JAZZ13PIL | E144: =IFERROR(VLOOKUP(D144,Stock,3,FALSE),"") -> Honda Jazz 13- 3rd Gen (Honda) | F144: 2 | G144: 1080000 | H144: =F144*G144 -> 2160000 | M144: TF BCA 33 | N144: 45434 | O144: PR-00017
A145: 45374 | B145: SJ000943 | C145: RJG | D145: LFW-HRV14PIL | E145: =IFERROR(VLOOKUP(D145,Stock,3,FALSE),"") -> Honda HR-V 14-21 5D SUV (Honda) | F145: 1 | G145: 1000000 | H145: =F145*G145 -> 1000000 | M145: TF BCA 33 | N145: 45434 | O145: PR-00017
A146: 45377 | B146: SI2024C000126 | C146: MJD | D146: LFW-FIESTAMU | E146: =IFERROR(VLOOKUP(D146,Stock,3,FALSE),"") -> Ford Fiesta 09-17 | F146: 10 | G146: 570207 | H146: =F146*G146 -> 5702070 | O146: PR-00018
A147: 45377 | B147: SI2024C000126 | C147: MJD | D147: LFW-HRV14MU | E147: =IFERROR(VLOOKUP(D147,Stock,3,FALSE),"") -> Honda HR-V 14-21 5D SUV | F147: 10 | G147: 822954 | H147: =F147*G147 -> 8229540 | O147: PR-00018
...

Sheet KAS
A1: Tanggal | B1: Nama | C1: Ket | D1: Debit | E1: Kredit | F1: Sisa | G1: Input by | H1: Terima uang | I1: Cek
A2: Juni 2024
A3: 45478 | B3: Uang Kasir | D3: 250000 | F3: =D3-E3 -> 250000 | G3: Michelle | H3: Via & Lia
A4: 45478 | B4: Tambahan Uang Kasir | D4: 101000 | F4: =F3+D4-E4 -> 351000 | G4: Michelle | H4: Via & Lia
A5: 45506 | B5: Sisa penjualan | C5: Sisa kurang tf penjualan cash | D5: 148000 | F5: =F4+D5-E5 -> 499000
A6: 45506 | B6: Hilang | C6: Uang kasir hilang | E6: 499000 | F6: =F5+D6-E6 -> 0 | H6: Maling
A7: 45514 | B7: Uang Kasir | C7: Masuk | D7: 100000 | F7: =F6+D7-E7 -> 100000 | G7: Michelle
F8: =F7+D8-E8 -> 100000
F9: =F8+D9-E9 -> 100000
F10: =F9+D10-E10 -> 100000
F11: =F10+D11-E11 -> 100000
F12: =F11+D12-E12 -> 100000
F13: =F12+D13-E13 -> 100000
F14: =F13+D14-E14 -> 100000
F15: =F14+D15-E15 -> 100000
F16: =F15+D16-E16 -> 100000
F17: =F16+D17-E17 -> 100000
F18: =F17+D18-E18 -> 100000

Sheet Inventory Dalam
A1: No. | B1: Nama Toolkit | C1: 45456
A2: 1. | B2: Obeng Kancing | C2: 4 PC
A3: 2. | B3: Kape Plastik Doortrim | C3: 3 Set (12 PC)
A4: 3. | B4: Seling | C4: 13 PC
A5: 4. | B5: Lem G / Lem Korea | C5: 12 PC
A6: 5. | B6: Lakban Fragile | C6: 8 PC
A7: 6. | B7: Gel Sensor Besar | C7: 2 PC
A8: 7. | B8: Gel Sensor Kecil | C8: 3 PC
A9: 8. | B9: Lakban Kertas | C9: 5 PC
A10: 9. | B10: Lakban Bening | C10: 4 PC
A11: 10. | B11: Double Tape Foam Kecil | C11: 5 PC
A12: 11. | B12: Double Tape Foam Besar | C12: 1 PC
A13: 12. | B13: Isi Cutter | C13: 4 Pack
... A44: 43. | B44: Kunci T 8mm | C44: 3 PC
A45: 44 | B45: Kanebo | C45: 20 PC
A46: 45 | B46: Cutter | C46: 5 PC
A47: 46 | B47: Solder Tembak | C47: 1 PC
A48: 47 | B48: Klip | C48: 1 Bungkus
A49: 48 | B49: Sealant Boyou B501 | C49: 20 Tube
A50: 49 | B50: Sealant R 68 | C50: 1 Tube
A51: 50 | B51: Seling Boyou | C51: 1 Roll
A52: 51 | B52: No Adhesiv Tape | C52: 1 PC
A53: 52 | B53: Kop Kaca 2 kaki | C53: 1 Set
A54: 53 | B54: Fender Cover Mobil | C54: 2 Set
A55: 54 | B55: Kuas | C55: 1 PC
A56: 55 | B56: Tinta Spidol Permanent | C56: 1 PC
A57: 56 | B57: Tinta Printer Hitam | C57: 1 PC

Sheet Sheet11
A1: No | B1: Nama Toolkit | C1: BOX 1 | D1: BOX 2
A2: 1. | B2: Lakban Merah | C2: 1 PC | D2: 1 PC
A3: 2. | B3: Lakban Bening | C3: 1 PC | D3: 1 PC
A4: 3. | B4: Lakban Kertas | C4: 1 PC
A5: 4. | B5: Lakban Foam Hijau | C5: 1 PC
A6: 5. | B6: Kape Plastik Doortrim | C6: 1 Set (4 PC)
A7: 6. | B7: Seling | C7: 1 Bungkus
A8: 7. | B8: Obeng Kancing
A9: 8. | B9: Asahan
A10: 9. | B10: Kape Dodot
A11: 10. | B11: Obeng +- Pendek
A12: 11. | B12: Set Kunci Bintang
A13: 12. | B13: Dodotan
A14: 13. | B14: Kape tusuk
A15: 14. | B15: Craker
A16: 15. | B16: Lem Epoxy
A17: 16. | B17: Kacamata
A18: 17. | B18: Sarung Tangan
A19: 18. | B19: Dumpkin
... A30: 29. | B30: Kuas

Sheet SPK
A1: SURAT PERINTAH KERJA
A2: PASANG KACA / JASA PASANG / BONGKAR POLA
A3: NO SPK 1 | B3: : | E3: TGL 1 : | J3: (1=admin) (2=teknisi) (3=konsumen)
A4: NAMA KONSUMEN 3 | B4: :
A5: ALAMAT 3 | B5: : | J5: CATATAN:
A6: NO TELP/WA 3 | B6: : | J6: - SPK wajib diisi sebelum dan sesudah pemasangan kaca mobil
A7: EMAIL 3 | B7: : | J7: - SPK diisi dengan kondisi sebenar-benarnya dan disaksikan oleh pihak konsumen
A8: BARANG BERHARGA 3 | B8: : | C8: ADA / TIDAK ADA | J8: - Dokumentasikan bila perlu dan infokan ke kantor
A9: MERK & TYPE MOBIL 1 | B9: : | J9: - SPK ini ditanda-tangani oleh pihak Kaca Mobil dan Konsumen agar menjadi
A10: NO POLISI 2 | B10: : | J10: bukti sah dari segala kondisi yang ada pada mobil
A11: PART, MERK, JENIS KACA 1 | B11: : | J11: - contoh kondisi = baik / patah / retak / regas / baret / tidak ada / dll
A12: SEALANT 1 | B12: :
A13: LIST KARET 2 | B13: : | C13: GANTI / TIDAK
A14: NAMA TEKSINI 2 | B14: : | D14: &
A15: KETERANGAN | C15: SEBELUM | F15: SESUDAH | J15: KETERANGAN | K15: SEBELUM | N15: SESUDAH
A16: DEPAN/BELAKANG | C16: KONDISI | D16: TECH | E16: CUST | F16: KONDISI | G16: TECH | H16: CUST | J16: KACA SAMPING | K16: KONDISI | L16: TECH | M16: CUST | N16: KONDISI | O16: TECH | P16: CUST
A17: KACA YG AKAN DIPASANG | J17: KACA YG AKAN DIPASANG
A18: SPION DALAM | J18: BAUT BAUT
A19: TUTUP TULANG KI/KA | J19: POWER WINDOW
A20: AKSESORIS LAIN | J20: REGULATOR
A21: WIPER KANAN/KIRI | J21: DUDUKAN KACA
A22: TUTUP WIPER KA/KI | J22: KARET RUN CHANNEL
A23: TALANG/PANGGANGAN | J23: TEST TURUN NAIK PW
A24: LIST/KARET | J24: TURUN NAIK KACA
A25: BODY ATAS & SAMPING | J25: BODY DISEKITAR
A26: KAP MOBIL | J26: LAIN LAIN/KM
A27: LIST SAMPING | J27: JAM PENGERJAAN
A28: SENSOR KACA | J28: Keterangan kondisi lain : | L28: ADMIN | N28: TEKNISI | O28: CUSTOMER
A29: LAIN-LAIN/KM
A30: JAM PENGERJAAN
A32: SURAT PERINTAH KERJA
A33: PASANG KACA / JASA PASANG / BONGKAR POLA
A34: NO SPK 1 | B34: : | E34: TGL 1 : | J34: (1=admin) (2=teknisi) (3=konsumen)
A35: NAMA KONSUMEN 3 | B35: :
A36: ALAMAT 3 | B36: : | J36: CATATAN:
A37: NO TELP/WA 3 | B37: : | J37: - SPK wajib diisi sebelum dan sesudah pemasangan kaca mobil
A38: EMAIL 3 | B38: : | J38: - SPK diisi dengan kondisi sebenar-benarnya dan disaksikan oleh pihak konsumen
A39: BARANG BERHARGA 3 | B39: : | C39: ADA / TIDAK ADA | J39: - Dokumentasikan bila perlu dan infokan ke kantor
A40: MERK & TYPE MOBIL 1 | B40: : | J40: - SPK ini ditanda-tangani oleh pihak Kaca Mobil dan Konsumen agar menjadi
A41: NO POLISI 2 | B41: : | J41: bukti sah dari segala kondisi yang ada pada mobil
A42: PART, MERK, JENIS KACA 1 | B42: :
A43: SEALANT 1 | B43: :
A44: LIST KARET 2 | B44: : | C44: GANTI / TIDAK | J44: contoh kondisi = baik / patah / retak / regas / baret / tidak ada / dll
A45: NAMA TEKSINI 2 | B45: : | D45: &
A46: KETERANGAN | C46: SEBELUM | F46: SESUDAH | J46: KETERANGAN | K46: SEBELUM | N46: SESUDAH
A47: DEPAN/BELAKANG | C47: KONDISI | D47: TECH | E47: CUST | F47: KONDISI | G47: TECH | H47: CUST | J47: KACA SAMPING | K47: KONDISI | L47: TECH | M47: CUST | N47: KONDISI | O47: TECH | P47: CUST
A48: KACA YG AKAN DIPASANG | J48: KACA YG AKAN DIPASANG
A49: SPION DALAM | J49: BAUT BAUT
A50: TUTUP TULANG KI/KA | J50: POWER WINDOW
A51: AKSESORIS LAIN | J51: REGULATOR
A52: WIPER KANAN/KIRI | J52: DUDUKAN KACA
A53: TUTUP WIPER KA/KI | J53: KARET RUN CHANNEL
A54: TALANG/PANGGANGAN | J54: TEST TURUN NAIK PW
A55: LIST/KARET | J55: TURUN NAIK KACA
A56: BODY ATAS & SAMPING | J56: BODY DISEKITAR
A57: KAP MOBIL | J57: LAIN LAIN/KM
A58: LIST SAMPING | J58: JAM PENGERJAAN
A59: SENSOR KACA | J59: Keterangan kondisi lain : | L59: ADMIN | N59: TEKNISI | O59: CUSTOMER
A60: LAIN-LAIN/KM
A61: JAM PENGERJAAN

Sheet MEMO
B1: PT Karunia Jaya Distribusindo | D1: Jalan Simo Jawar No. 108, Simomulyo Baru, Sukomanunggal, Surabaya
D2: (+62) 81288009878
C4: MEMO PENGAMBILAN BARANG
J6: Tanggal | L6: 46094
J7: Kepada Yth.
J8: PD Jaya Baru
J9: Di- Tempat
B11: Salam Hormat,
B13: Melalui memo ini mohon untuk diberikan :
B14: - 3TR04M-AFDRTA1 5pc
B15: - 3SR32M-3FDLTT1 5pc
B16: - 3DGM7M-3FDLTA1 5pc
B17: - 3DGM7M-3FDRTA1 5pc
B18: - 3TR04M-AFDRTA1 5pc
B19: - 3SR32M-3RDRTT1 5pc
B20: - 3TR18M-3FDLTA0 5pc
B22: Kepada tim kami atas nama Dimas
B24: Mohon untuk memberikan Nota dalam amplop kepada tim kami.
B25: Terima kasih atas perhatian dan kerjasamanya.
J27: Hormat Kami | X27: d
J31: ....................

Sheet peti jangan balik
A1: JANGAN DIBALIK - PETI HADAP ATAS | J1: JANGAN DIBALIK - PETI HADAP ATAS
A14: BARANG PECAH BELAH !! | J14: BARANG PECAH BELAH !!
A16: JANGAN BANTING | J16: JANGAN BANTING
A19: JANGAN DIBALIK - PETI HADAP ATAS | J19: JANGAN DIBALIK - PETI HADAP ATAS
A32: BARANG PECAH BELAH !! | J32: BARANG PECAH BELAH !!
A34: JANGAN BANTING | J34: JANGAN BANTING

Sheet Barang MJD
A1: KODE | B1: PCS | C1: SISA QTY KJD | D1: KIRIM | E1: QTY KIRIM | F1: Lia | G1: Cici | I1: 369153862 | J1: =I1-sum(I2:I131) -> 270660587 | K1: =sum(I2:I131) -> 98493275
A2: LFW-AVANZA16MU | B2: 10 | C2: =IFERROR(VLOOKUP(A2,stockKJD,9,FALSE)," ") -> 3 | D2: KEEP | F2: KF 1PC | I2: =E2*H2 -> 0
A3: LFW-SIGRA16MU | B3: 10 | C3: =IFERROR(VLOOKUP(A3,stockKJD,9,FALSE)," ") -> 1 | D3: KEEP | F3: KF 2PC | I3: =E3*H3 -> 0
A4: LFW-AVANZA03MU | B4: 10 | C4: =IFERROR(VLOOKUP(A4,stockKJD,9,FALSE)," ") -> 3 | D4: KEEP | F4: KF 1PC | I4: =E4*H4 -> 0
