Workbook
Name Stock: 'Current Stock'!$A:$N
Name kirim: #REF!
Name Tugas: #REF!
Name stockKJD: 'Current Stock'!$A$2:$J$2156
Name StockAll: 'Current Stock'!$A$1:$N$2165
Name BGI: #REF!
Name Penjualan: PENJUALAN!$A$4:$I$10719
Name hpp: #REF!
Name NamedRange1: 'Current Stock'!$1:$2934

Sheet Current Stock
A1: Kode | B1: Kode Mobil | C1: Tipe Mobil | D1: Part | E1: Merk | F1: Aksesoris | G1: SO | H1: Masuk | I1: Keluar | J1: Stok Akhir | K1: Rak | L1: SO | M1: Alert | N1: Lain - Lain
A2: =CONCATENATE(B2,E2) -> OTH-SEALANTXYG | B2: OTH-SEALANT | C2: Sealant Polyurethane XYG Tube | D2: OTH | E2: XYG | H2: =SUMIFS(X!$F$3:$F$5978,X!$D$3:$D$5978,'Current Stock'!A2) -> 0 | I2: =SUMIFS(PENJUALAN!$E$4:$E$3651,PENJUALAN!$C$4:$C$3651,'Current Stock'!A2) -> 0 | J2: =H2-I2 -> 0 | M2: 10
A3: =CONCATENATE(B3,E3) -> OTH-PETIKAYU | B3: OTH-PETI | C3: Peti Kayu | D3: OTH | E3: KAYU | G3: 45988 | H3: =SUMIFS(X!$F$3:$F$5978,X!$D$3:$D$5978,'Current Stock'!A3) -> 1 | I3: =SUMIFS(PENJUALAN!$E$4:$E$3651,PENJUALAN!$C$4:$C$3651,'Current Stock'!A3) -> 27 | J3: =H3-I3 -> -26 | M3: 10
A4: =CONCATENATE(B4,E4) -> OTH-SERTR | B4: OTH-SER | C4: 9092 Sealant Application | D4: OTH | E4: TR | H4: =SUMIFS(X!$F$3:$F$5978,X!$D$3:$D$5978,'Current Stock'!A4) -> 0 | I4: =SUMIFS(PENJUALAN!$E$4:$E$3651,PENJUALAN!$C$4:$C$3651,'Current Stock'!A4) -> 0 | J4: =H4-I4 -> 0
A5: =CONCATENATE(B5,E5) -> OTH-SERBY | B5: OTH-SER | C5: 501 Sealant Application | D5: OTH | E5: BY | G5: 45988 | H5: =SUMIFS(X!$F$3:$F$5978,X!$D$3:$D$5978,'Current Stock'!A5) -> 1540 | I5: =SUMIFS(PENJUALAN!$E$4:$E$3651,PENJUALAN!$C$4:$C$3651,'Current Stock'!A5) -> 270 | J5: =H5-I5 -> 1270
A6: =CONCATENATE(B6,E6) -> OTH-SERSK | B6: OTH-SER | C6: 255 Ultra + Actv-100 Application | D6: OTH | E6: SK | G6: 45988 | H6: =SUMIFS(X!$F$3:$F$5978,X!$D$3:$D$5978,'Current Stock'!A6) -> 90 | I6: =SUMIFS(PENJUALAN!$E$4:$E$3651,PENJUALAN!$C$4:$C$3651,'Current Stock'!A6) -> 84 | J6: =H6-I6 -> 6
A7: =CONCATENATE(B7,E7) -> OTH-SEROTO | B7: OTH-SER | C7: Otoseal Sealant Application | D7: OTH | E7: OTO | H7: =SUMIFS(X!$F$3:$F$5978,X!$D$3:$D$5978,'Current Stock'!A7) -> 5 | I7: =SUMIFS(PENJUALAN!$E$4:$E$3651,PENJUALAN!$C$4:$C$3651,'Current Stock'!A7) -> 0 | J7: =H7-I7 -> 5
A8: =CONCATENATE(B8,E8) -> OTH-SERTRANSPORT | B8: OTH-SER | C8: Transport | D8: OTH | E8: TRANSPORT | G8: 45988 | H8: =SUMIFS(X!$F$3:$F$5978,X!$D$3:$D$5978,'Current Stock'!A8) -> 1 | I8: =SUMIFS(PENJUALAN!$E$4:$E$3651,PENJUALAN!$C$4:$C$3651,'Current Stock'!A8) -> 479 | J8: =H8-I8 -> -478
A9: =CONCATENATE(B9,E9) -> OTH-LIST04TOYDAI | B9: OTH-LIST04 | C9: List Kaca Depan Code 04 | D9: OTH | E9: TOYDAI | G9: 45988 | H9: =SUMIFS(X!$F$3:$F$5978,X!$D$3:$D$5978,'Current Stock'!A9) -> 57 | I9: =SUMIFS(PENJUALAN!$E$4:$E$3651,PENJUALAN!$C$4:$C$3651,'Current Stock'!A9) -> 31 | J9: =H9-I9 -> 26 | M9: 2
A10: =CONCATENATE(B10,E10) -> OTH-LIST11TOYDAI | B10: OTH-LIST11 | C10: List Kaca Depan Code 11 | D10: OTH | E10: TOYDAI | G10: 45988 | H10: =SUMIFS(X!$F$3:$F$5978,X!$D$3:$D$5978,'Current Stock'!A10) -> 35 | I10: =SUMIFS(PENJUALAN!$E$4:$E$3651,PENJUALAN!$C$4:$C$3651,'Current Stock'!A10) -> 22 | J10: =H10-I10 -> 13 | M10: 2
A11: =CONCATENATE(B11,E11) -> OTH-LISTINVTOY | B11: OTH-LISTINV | C11: List Kaca Depan INV | D11: OTH | E11: TOY | G11: 45988 | H11: =SUMIFS(X!$F$3:$F$5978,X!$D$3:$D$5978,'Current Stock'!A11) -> 25 | I11: =SUMIFS(PENJUALAN!$E$4:$E$3651,PENJUALAN!$C$4:$C$3651,'Current Stock'!A11) -> 19 | J11: =H11-I11 -> 6 | M11: 2
A12: =CONCATENATE(B12,E12) -> OTH-LISTWSERT12SGP | B12: OTH-LISTWSERT12 | C12: List Kaca Depan Ertiga 2012-2018 SGP | D12: OTH | E12: SGP | H12: =SUMIFS(X!$F$3:$F$5978,X!$D$3:$D$5978,'Current Stock'!A12) -> 0 | I12: =SUMIFS(PENJUALAN!$E$4:$E$3651,PENJUALAN!$C$4:$C$3651,'Current Stock'!A12) -> 0 | J12: =H12-I12 -> 0
A13: =CONCATENATE(B13,E13) -> MLDG-LFWHRV14UPHON | B13: MLDG-LFWHRV14UP | C13: Moulding List Honda HR-V 14-21 5D SUV (Upper) | D13: MLDG | E13: HON | G13: 45988 | H13: =SUMIFS(X!$F$3:$F$5978,X!$D$3:$D$5978,'Current Stock'!A13) -> 2 | I13: =SUMIFS(PENJUALAN!$E$4:$E$3651,PENJUALAN!$C$4:$C$3651,'Current Stock'!A13) -> 1 | J13: =H13-I13 -> 1
A14: =CONCATENATE(B14,E14) -> MLDG-LFWHRV14SIDEHON | B14: MLDG-LFWHRV14SIDE | C14: Moulding List Honda HR-V 14-21 5D SUV (Side) | D14: MLDG | E14: HON | G14: 45988 | H14: =SUMIFS(X!$F$3:$F$5978,X!$D$3:$D$5978,'Current Stock'!A14) -> 4 | I14: =SUMIFS(PENJUALAN!$E$4:$E$3651,PENJUALAN!$C$4:$C$3651,'Current Stock'!A14) -> 2 | J14: =H14-I14 -> 2
A15: =CONCATENATE(B15,E15) -> MLDG-ANH20AGH30UPTOY | B15: MLDG-ANH20AGH30UP | C15: Moulding List Alphard ANH20 AGH30 (Upper) | D15: MLDG | E15: TOY | H15: =SUMIFS(X!$F$3:$F$5978,X!$D$3:$D$5978,'Current Stock'!A15) -> 1 | I15: =SUMIFS(PENJUALAN!$E$4:$E$3651,PENJUALAN!$C$4:$C$3651,'Current Stock'!A15) -> 1 | J15: =H15-I15 -> 0
A16: =CONCATENATE(B16,E16) -> MLDG-LFWFE700MIT | B16: MLDG-LFWFE700 | C16: Moulding List Mitsubishi Canter FE700 01- (PS110,125) (Windshield) | D16: MLDG | E16: MIT | H16: =SUMIFS(X!$F$3:$F$5978,X!$D$3:$D$5978,'Current Stock'!A16) -> 1 | I16: =SUMIFS(PENJUALAN!$E$4:$E$3651,PENJUALAN!$C$4:$C$3651,'Current Stock'!A16) -> 1 | J16: =H16-I16 -> 0
A17: =CONCATENATE(B17,E17) -> MLDG-LFWFORTUNER05TOY | B17: MLDG-LFWFORTUNER05 | C17: Moulding List Toyota Fortuner 05-15 1st Gen (Windshield) | D17: MLDG | E17: TOY | H17: =SUMIFS(X!$F$3:$F$5978,X!$D$3:$D$5978,'Current Stock'!A17) -> 0 | I17: =SUMIFS(PENJUALAN!$E$4:$E$3651,PENJUALAN!$C$4:$C$3651,'Current Stock'!A17) -> 1 | J17: =H17-I17 -> -1
A18: =CONCATENATE(B18,E18) -> MLDG-LFWCROSSTREK23SUB | B18: MLDG-LFWCROSSTREK23 | C18: Moulding List Subaru Crosstrek 23- (Windshield) | D18: MLDG | E18: SUB | H18: =SUMIFS(X!$F$3:$F$5978,X!$D$3:$D$5978,'Current Stock'!A18) -> 0 | I18: =SUMIFS(PENJUALAN!$E$4:$E$3651,PENJUALAN!$C$4:$C$3651,'Current Stock'!A18) -> 0 | J18: =H18-I18 -> 0
A19: =CONCATENATE(B19,E19) -> OTH-RPLXLFW | B19: OTH-RPLX | C19: Bongkar Pasang Kaca Mobil Depan | D19: OTH | E19: LFW | G19: 45988 | H19: =SUMIFS(X!$F$3:$F$5978,X!$D$3:$D$5978,'Current Stock'!A19) -> 0 | I19: =SUMIFS(PENJUALAN!$E$4:$E$3651,PENJUALAN!$C$4:$C$3651,'Current Stock'!A19) -> 52 | J19: =H19-I19 -> -52 | M19: 100
A20: =CONCATENATE(B20,E20) -> OTH-RPLXTRW | B20: OTH-RPLX | C20: Bongkar Pasang Kaca Mobil Belakang | D20: OTH | E20: TRW | G20: 45988 | H20: =SUMIFS(X!$F$3:$F$5978,X!$D$3:$D$5978,'Current Stock'!A20) -> 0 | I20: =SUMIFS(PENJUALAN!$E$4:$E$3651,PENJUALAN!$C$4:$C$3651,'Current Stock'!A20) -> 12 | J20: =H20-I20 -> -12 | M20: 100
A21: =CONCATENATE(B21,E21) -> OTH-RPLXSIDE | B21: OTH-RPLX | C21: Bongkar Pasang Kaca Mobil Samping | D21: OTH | E21: SIDE | G21: 45988 | H21: =SUMIFS(X!$F$3:$F$5978,X!$D$3:$D$5978,'Current Stock'!A21) -> 0 | I21: =SUMIFS(PENJUALAN!$E$4:$E$3651,PENJUALAN!$C$4:$C$3651,'Current Stock'!A21) -> 12 | J21: =H21-I21 -> -12 | M21: 100
A22: =CONCATENATE(B22,E22) -> OTH-SERLMB | B22: OTH-SER | C22: Lembur | D22: OTH | E22: LMB | G22: 45988 | H22: =SUMIFS(X!$F$3:$F$5978,X!$D$3:$D$5978,'Current Stock'!A22) -> 15 | I22: =SUMIFS(PENJUALAN!$E$4:$E$3651,PENJUALAN!$C$4:$C$3651,'Current Stock'!A22) -> 77 | J22: =H22-I22 -> -62
A23: =CONCATENATE(B23,E23) -> OTH-CKC | B23: OTH-C | C23: Biaya Pengecekan | D23: OTH | E23: KC | G23: 45988 | H23: =SUMIFS(X!$F$3:$F$5978,X!$D$3:$D$5978,'Current Stock'!A23) -> 0 | I23: =SUMIFS(PENJUALAN!$E$4:$E$3651,PENJUALAN!$C$4:$C$3651,'Current Stock'!A23) -> 15 | J23: =H23-I23 -> -15
A24: =CONCATENATE(B24,E24) -> FILM-40STD | B24: FILM-40 | C24: Automotive Film Standard - Black 40% | D24: FILM | E24: STD | H24: =SUMIFS(X!$F$3:$F$5978,X!$D$3:$D$5978,'Current Stock'!A24) -> 0 | I24: =SUMIFS(PENJUALAN!$E$4:$E$3651,PENJUALAN!$C$4:$C$3651,'Current Stock'!A24) -> 41 | J24: =H24-I24 -> -41
A25: =CONCATENATE(B25,E25) -> FILM-60STD | B25: FILM-60 | C25: Automotive Film Standard - Black 40% | D25: FILM | E25: STD | G25: 45988 | H25: =SUMIFS(X!$F$3:$F$5978,X!$D$3:$D$5978,'Current Stock'!A25) -> 33 | I25: =SUMIFS(PENJUALAN!$E$4:$E$3651,PENJUALAN!$C$4:$C$3651,'Current Stock'!A25) -> 48 | J25: =H25-I25 -> -15
A26: =CONCATENATE(B26,E26) -> FILM-80STD | B26: FILM-80 | C26: Automotive Film Standard - Black 80% | D26: FILM | E26: STD | H26: =SUMIFS(X!$F$3:$F$5978,X!$D$3:$D$5978,'Current Stock'!A26) -> 1 | I26: =SUMIFS(PENJUALAN!$E$4:$E$3651,PENJUALAN!$C$4:$C$3651,'Current Stock'!A26) -> 13 | J26: =H26-I26 -> -12
A27: =CONCATENATE(B27,E27) -> FILM-BPSG | B27: FILM-BP | C27: Black Phantom Solar Gard | D27: FILM | E27: SG | G27: 45988 | H27: =SUMIFS(X!$F$3:$F$5978,X!$D$3:$D$5978,'Current Stock'!A27) -> 15 | I27: =SUMIFS(PENJUALAN!$E$4:$E$3651,PENJUALAN!$C$4:$C$3651,'Current Stock'!A27) -> 19 | J27: =H27-I27 -> -4
A28: =CONCATENATE(B28,E28) -> TRW-AVANZA03HAUTO | B28: TRW-AVANZA03H | C28: Toyota Avanza / Xenia 03-11 1st Gen | D28: TRW | E28: AUTO | F28: X/H | H28: =SUMIFS(X!$F$3:$F$5978,X!$D$3:$D$5978,'Current Stock'!A28) -> 0 | I28: =SUMIFS(PENJUALAN!$E$4:$E$3651,PENJUALAN!$C$4:$C$3651,'Current Stock'!A28) -> 0 | J28: =H28-I28 -> 0
A29: =CONCATENATE(B29,E29) -> RDR-CRV12SG | B29: RDR-CRV12 | C29: Honda CR-V 12-16 4th Gen | D29: RDR | E29: SG | H29: =SUMIFS(X!$F$3:$F$5978,X!$D$3:$D$5978,'Current Stock'!A29) -> 0 | I29: =SUMIFS(PENJUALAN!$E$4:$E$3651,PENJUALAN!$C$4:$C$3651,'Current Stock'!A29) -> 0 | J29: =H29-I29 -> 0
A30: =CONCATENATE(B30,E30) -> LFW-ALPHARD08RSPIL | B30: LFW-ALPHARD08RS | C30: Toyota Alphard 08-15 ANH20 2nd Gen | D30: LFW | E30: PIL | F30: X/MB/RS | H30: =SUMIFS(X!$F$3:$F$5978,X!$D$3:$D$5978,'Current Stock'!A30) -> 2 | I30: =SUMIFS(PENJUALAN!$E$4:$E$3651,PENJUALAN!$C$4:$C$3651,'Current Stock'!A30) -> 2 | J30: =H30-I30 -> 0
A31: =CONCATENATE(B31,E31) -> RDL-AVANZA03ASH | B31: RDL-AVANZA03 | C31: Toyota Avanza / Xenia 03-11 1st Gen | D31: RDL | E31: ASH | H31: =SUMIFS(X!$F$3:$F$5978,X!$D$3:$D$5978,'Current Stock'!A31) -> 1 | I31: =SUMIFS(PENJUALAN!$E$4:$E$3651,PENJUALAN!$C$4:$C$3651,'Current Stock'!A31) -> 0 | J31: =H31-I31 -> 1
A32: =CONCATENATE(B32,E32) -> RDR-AVANZA11ASH | B32: RDR-AVANZA11 | C32: Toyota Avanza / Xenia 11-15 2nd Gen/3rd Gen | D32: RDR | E32: ASH | G32: 45988 | H32: =SUMIFS(X!$F$3:$F$5978,X!$D$3:$D$5978,'Current Stock'!A32) -> 4 | I32: =SUMIFS(PENJUALAN!$E$4:$E$3651,PENJUALAN!$C$4:$C$3651,'Current Stock'!A32) -> 4 | J32: =H32-I32 -> 0 | K32: D1T3
A33: =CONCATENATE(B33,E33) -> RDL-AVANZA11ASH | B33: RDL-AVANZA11 | C33: Toyota Avanza / Xenia 11-15 2nd Gen/3rd Gen | D33: RDL | E33: ASH | H33: =SUMIFS(X!$F$3:$F$5978,X!$D$3:$D$5978,'Current Stock'!A33) -> 0 | I33: =SUMIFS(PENJUALAN!$E$4:$E$3651,PENJUALAN!$C$4:$C$3651,'Current Stock'!A33) -> 0 | J33: =H33-I33 -> 0
A34: =CONCATENATE(B34,E34) -> TRW-AVANZA11ORI | B34: TRW-AVANZA11 | C34: Toyota Avanza / Xenia 11-15 2nd Gen/3rd Gen | D34: TRW | E34: ORI | F34: X/Logo | H34: =SUMIFS(X!$F$3:$F$5978,X!$D$3:$D$5978,'Current Stock'!A34) -> 0 | I34: =SUMIFS(PENJUALAN!$E$4:$E$3651,PENJUALAN!$C$4:$C$3651,'Current Stock'!A34) -> 0 | J34: =H34-I34 -> 0
A35: =CONCATENATE(B35,E35) -> RDL-AVANZA11AGC | B35: RDL-AVANZA11 | C35: Toyota Avanza / Xenia 11-15 2nd Gen/3rd Gen | D35: RDL | E35: AGC | H35: =SUMIFS(X!$F$3:$F$5978,X!$D$3:$D$5978,'Current Stock'!A35) -> 0 | I35: =SUMIFS(PENJUALAN!$E$4:$E$3651,PENJUALAN!$C$4:$C$3651,'Current Stock'!A35) -> 0 | J35: =H35-I35 -> 0
A36: =CONCATENATE(B36,E36) -> RDR-AVANZA11ACG | B36: RDR-AVANZA11 | C36: Toyota Avanza / Xenia 11-15 2nd Gen/3rd Gen | D36: RDR | E36: ACG | H36: =SUMIFS(X!$F$3:$F$5978,X!$D$3:$D$5978,'Current Stock'!A36) -> 0 | I36: =SUMIFS(PENJUALAN!$E$4:$E$3651,PENJUALAN!$C$4:$C$3651,'Current Stock'!A36) -> 0 | J36: =H36-I36 -> 0
A37: =CONCATENATE(B37,E37) -> FDL-AVANZA11ACG | B37: FDL-AVANZA11 | C37: Toyota Avanza / Xenia 11-15 2nd Gen/3rd Gen | D37: FDL | E37: ACG | H37: =SUMIFS(X!$F$3:$F$5978,X!$D$3:$D$5978,'Current Stock'!A37) -> 0 | I37: =SUMIFS(PENJUALAN!$E$4:$E$3651,PENJUALAN!$C$4:$C$3651,'Current Stock'!A37) -> 0 | J37: =H37-I37 -> 0
A38: =CONCATENATE(B38,E38) -> FDR-AVANZA11ACG | B38: FDR-AVANZA11 | C38: Toyota Avanza / Xenia 11-15 2nd Gen/3rd Gen | D38: FDR | E38: ACG | H38: =SUMIFS(X!$F$3:$F$5978,X!$D$3:$D$5978,'Current Stock'!A38) -> 0 | I38: =SUMIFS(PENJUALAN!$E$4:$E$3651,PENJUALAN!$C$4:$C$3651,'Current Stock'!A38) -> 0 | J38: =H38-I38 -> 0
A39: =CONCATENATE(B39,E39) -> LFW-ETIOSASH | B39: LFW-ETIOS | C39: Toyota Etios 10- 1st Gen Sedan | D39: LFW | E39: ASH | F39: X | H39: =SUMIFS(X!$F$3:$F$5978,X!$D$3:$D$5978,'Current Stock'!A39) -> 0 | I39: =SUMIFS(PENJUALAN!$E$4:$E$3651,PENJUALAN!$C$4:$C$3651,'Current Stock'!A39) -> 0 | J39: =H39-I39 -> 0 | M39: 1
A40: =CONCATENATE(B40,E40) -> TRW-LUXIODAIHATSU | B40: TRW-LUXIO | C40: Daihatsu Luxio 07- | D40: TRW | E40: DAIHATSU | F40: X/Logo | G40: 45988 | H40: =SUMIFS(X!$F$3:$F$5978,X!$D$3:$D$5978,'Current Stock'!A40) -> 29 | I40: =SUMIFS(PENJUALAN!$E$4:$E$3651,PENJUALAN!$C$4:$C$3651,'Current Stock'!A40) -> 20 | J40: =H40-I40 -> 9 | K40: A3T3 | M40: 1
A41: =CONCATENATE(B41,E41) -> SWR-RAIZEORI | B41: SWR-RAIZE | C41: Toyota Raize / Daihatsu Rocky 20- | D41: SWR | E41: ORI | F41: X | H41: =SUMIFS(X!$F$3:$F$5978,X!$D$3:$D$5978,'Current Stock'!A41) -> 0 | I41: =SUMIFS(PENJUALAN!$E$4:$E$3651,PENJUALAN!$C$4:$C$3651,'Current Stock'!A41) -> 0 | J41: =H41-I41 -> 0 | M41: 1
A42: =CONCATENATE(B42,E42) -> TRW-BRV16AGC | B42: TRW-BRV16 | C42: Honda BR-V 16-21 (Honda) | D42: TRW | E42: AGC | F42: X/H/Logo | H42: =SUMIFS(X!$F$3:$F$5978,X!$D$3:$D$5978,'Current Stock'!A42) -> 2 | I42: =SUMIFS(PENJUALAN!$E$4:$E$3651,PENJUALAN!$C$4:$C$3651,'Current Stock'!A42) -> 0 | J42: =H42-I42 -> 2 | K42: B5T3 | M42: 1
A43: =CONCATENATE(B43,E43) -> LFW-AUDIB8FY | B43: LFW-AUDIB8 | C43: Audi A4 08-15 B8 | D43: LFW | E43: FY | F43: X/RS/List | H43: =SUMIFS(X!$F$3:$F$5978,X!$D$3:$D$5978,'Current Stock'!A43) -> 0 | I43: =SUMIFS(PENJUALAN!$E$4:$E$3651,PENJUALAN!$C$4:$C$3651,'Current Stock'!A43) -> 0 | J43: =H43-I43 -> 0
A44: =CONCATENATE(B44,E44) -> TRW-AUDIB8FY | B44: TRW-AUDIB8 | C44: TRW-AUDIB8 | D44: TRW | E44: FY | F44: X/H/A | H44: =SUMIFS(X!$F$3:$F$5978,X!$D$3:$D$5978,'Current Stock'!A44) -> 0 | I44: =SUMIFS(PENJUALAN!$E$4:$E$3651,PENJUALAN!$C$4:$C$3651,'Current Stock'!A44) -> 0 | J44: =H44-I44 -> 0
A45: =CONCATENATE(B45,E45) -> LFW-AUDIC7FY | B45: LFW-AUDIC7 | C45: Audi A6 11-18 C7 | D45: LFW | E45: FY | F45: X/RS/List | H45: =SUMIFS(X!$F$3:$F$5978,X!$D$3:$D$5978,'Current Stock'!A45) -> 0 | I45: =SUMIFS(PENJUALAN!$E$4:$E$3651,PENJUALAN!$C$4:$C$3651,'Current Stock'!A45) -> 0 | J45: =H45-I45 -> 0
A46: =CONCATENATE(B46,E46) -> TRW-AUDIC7FY | B46: TRW-AUDIC7 | C46: Audi A6 11-18 C7 | D46: TRW | E46: FY | F46: X/H/List | H46: =SUMIFS(X!$F$3:$F$5978,X!$D$3:$D$5978,'Current Stock'!A46) -> 0 | I46: =SUMIFS(PENJUALAN!$E$4:$E$3651,PENJUALAN!$C$4:$C$3651,'Current Stock'!A46) -> 0 | J46: =H46-I46 -> 0
A47: =CONCATENATE(B47,E47) -> LFW-E30FY | B47: LFW-E30 | C47: BMW 3 Series 82-94 E30 | D47: LFW | E47: FY | H47: =SUMIFS(X!$F$3:$F$5978,X!$D$3:$D$5978,'Current Stock'!A47) -> 0 | I47: =SUMIFS(PENJUALAN!$E$4:$E$3651,PENJUALAN!$C$4:$C$3651,'Current Stock'!A47) -> 0 | J47: =H47-I47 -> 0
A48: =CONCATENATE(B48,E48) -> TRW-E30FY | B48: TRW-E30 | C48: BMW 3 Series 82-94 E30 | D48: TRW | E48: FY | F48: H | H48: =SUMIFS(X!$F$3:$F$5978,X!$D$3:$D$5978,'Current Stock'!A48) -> 0 | I48: =SUMIFS(PENJUALAN!$E$4:$E$3651,PENJUALAN!$C$4:$C$3651,'Current Stock'!A48) -> 0 | J48: =H48-I48 -> 0
A49: =CONCATENATE(B49,E49) -> LFW-E36FY | B49: LFW-E36 | C49: BMW 3 Series 90-99 E36 | D49: LFW | E49: FY | F49: X/MB | H49: =SUMIFS(X!$F$3:$F$5978,X!$D$3:$D$5978,'Current Stock'!A49) -> 0 | I49: =SUMIFS(PENJUALAN!$E$4:$E$3651,PENJUALAN!$C$4:$C$3651,'Current Stock'!A49) -> 0 | J49: =H49-I49 -> 0
A50: =CONCATENATE(B50,E50) -> TRW-E36FY | B50: TRW-E36 | C50: BMW 3 Series 90-99 E36 | D50: TRW | E50: FY | F50: X/H | H50: =SUMIFS(X!$F$3:$F$5978,X!$D$3:$D$5978,'Current Stock'!A50) -> 0 | I50: =SUMIFS(PENJUALAN!$E$4:$E$3651,PENJUALAN!$C$4:$C$3651,'Current Stock'!A50) -> 0 | J50: =H50-I50 -> 0
A51: =CONCATENATE(B51,E51) -> FDL-E36FY | B51: FDL-E36 | C51: BMW 3 Series 90-99 E36 | D51: FD/L | E51: FY | H51: =SUMIFS(X!$F$3:$F$5978,X!$D$3:$D$5978,'Current Stock'!A51) -> 0 | I51: =SUMIFS(PENJUALAN!$E$4:$E$3651,PENJUALAN!$C$4:$C$3651,'Current Stock'!A51) -> 0 | J51: =H51-I51 -> 0
A52: =CONCATENATE(B52,E52) -> FDR-E36FY | B52: FDR-E36 | C52: BMW 3 Series 90-99 E36 | D52: FD/R | E52: FY | H52: =SUMIFS(X!$F$3:$F$5978,X!$D$3:$D$5978,'Current Stock'!A52) -> 0 | I52: =SUMIFS(PENJUALAN!$E$4:$E$3651,PENJUALAN!$C$4:$C$3651,'Current Stock'!A52) -> 0 | J52: =H52-I52 -> 0
A53: =CONCATENATE(B53,E53) -> RDL-E36FY | B53: RDL-E36 | C53: BMW 3 Series 90-99 E36 | D53: RD/L | E53: FY | H53: =SUMIFS(X!$F$3:$F$5978,X!$D$3:$D$5978,'Current Stock'!A53) -> 0 | I53: =SUMIFS(PENJUALAN!$E$4:$E$3651,PENJUALAN!$C$4:$C$3651,'Current Stock'!A53) -> 0 | J53: =H53-I53 -> 0
A54: =CONCATENATE(B54,E54) -> RDR-E36FY | B54: RDR-E36 | C54: BMW 3 Series 90-99 E36 | D54: RD/R | E54: FY | H54: =SUMIFS(X!$F$3:$F$5978,X!$D$3:$D$5978,'Current Stock'!A54) -> 0 | I54: =SUMIFS(PENJUALAN!$E$4:$E$3651,PENJUALAN!$C$4:$C$3651,'Current Stock'!A54) -> 0 | J54: =H54-I54 -> 0
A55: =CONCATENATE(B55,E55) -> LFW-E46RSFY | B55: LFW-E46RS | C55: BMW 3 Series 98-06 E46 | D55: LFW | E55: FY | F55: X/MB/RS | H55: =SUMIFS(X!$F$3:$F$5978,X!$D$3:$D$5978,'Current Stock'!A55) -> 0 | I55: =SUMIFS(PENJUALAN!$E$4:$E$3651,PENJUALAN!$C$4:$C$3651,'Current Stock'!A55) -> 0 | J55: =H55-I55 -> 0
A56: =CONCATENATE(B56,E56) -> LFW-E46FY | B56: LFW-E46 | C56: BMW 3 Series 98-06 E46 | D56: LFW | E56: FY | F56: X/MB | H56: =SUMIFS(X!$F$3:$F$5978,X!$D$3:$D$5978,'Current Stock'!A56) -> 0 | I56: =SUMIFS(PENJUALAN!$E$4:$E$3651,PENJUALAN!$C$4:$C$3651,'Current Stock'!A56) -> 0 | J56: =H56-I56 -> 0
A57: =CONCATENATE(B57,E57) -> TRW-E46FY | B57: TRW-E46 | C57: BMW 3 Series 98-06 E46 | D57: TRW | E57: FY | F57: X/H | H57: =SUMIFS(X!$F$3:$F$5978,X!$D$3:$D$5978,'Current Stock'!A57) -> 1 | I57: =SUMIFS(PENJUALAN!$E$4:$E$3651,PENJUALAN!$C$4:$C$3651,'Current Stock'!A57) -> 0 | J57: =H57-I57 -> 1
A58: =CONCATENATE(B58,E58) -> FDL-E46FY | B58: FDL-E46 | C58: BMW 3 Series 98-06 E46 | D58: FD/L | E58: FY | F58: 2Hole | H58: =SUMIFS(X!$F$3:$F$5978,X!$D$3:$D$5978,'Current Stock'!A58) -> 0 | I58: =SUMIFS(PENJUALAN!$E$4:$E$3651,PENJUALAN!$C$4:$C$3651,'Current Stock'!A58) -> 0 | J58: =H58-I58 -> 0
A59: =CONCATENATE(B59,E59) -> FDR-E46FY | B59: FDR-E46 | C59: BMW 3 Series 98-06 E46 | D59: FD/R | E59: FY | F59: 2Hole | H59: =SUMIFS(X!$F$3:$F$5978,X!$D$3:$D$5978,'Current Stock'!A59) -> 1 | I59: =SUMIFS(PENJUALAN!$E$4:$E$3651,PENJUALAN!$C$4:$C$3651,'Current Stock'!A59) -> 1 | J59: =H59-I59 -> 0
A60: =CONCATENATE(B60,E60) -> RDL-E46FY | B60: RDL-E46 | C60: BMW 3 Series 98-06 E46 | D60: RD/L | E60: FY | F60: 1Hole | H60: =SUMIFS(X!$F$3:$F$5978,X!$D$3:$D$5978,'Current Stock'!A60) -> 0 | I60: =SUMIFS(PENJUALAN!$E$4:$E$3651,PENJUALAN!$C$4:$C$3651,'Current Stock'!A60) -> 0 | J60: =H60-I60 -> 0
A61: =CONCATENATE(B61,E61) -> RDR-E46FY | B61: RDR-E46 | C61: BMW 3 Series 98-06 E46 | D61: RD/R | E61: FY | F61: 1Hole | H61: =SUMIFS(X!$F$3:$F$5978,X!$D$3:$D$5978,'Current Stock'!A61) -> 0 | I61: =SUMIFS(PENJUALAN!$E$4:$E$3651,PENJUALAN!$C$4:$C$3651,'Current Stock'!A61) -> 0 | J61: =H61-I61 -> 0
A62: =CONCATENATE(B62,E62) -> LFW-E46RS2DOORFY | B62: LFW-E46RS2DOOR | C62: BMW 3 Series 98-06 E46 (2-Door Coupe) | D62: LFW | E62: FY | F62: X/MB | H62: =SUMIFS(X!$F$3:$F$5978,X!$D$3:$D$5978,'Current Stock'!A62) -> 0 | I62: =SUMIFS(PENJUALAN!$E$4:$E$3651,PENJUALAN!$C$4:$C$3651,'Current Stock'!A62) -> 0 | J62: =H62-I62 -> 0
A63: =CONCATENATE(B63,E63) -> LFW-E90RSFY | B63: LFW-E90RS | C63: BMW 3 Series 05-12 E90 | D63: LFW | E63: FY | F63: X/MB/RS | H63: =SUMIFS(X!$F$3:$F$5978,X!$D$3:$D$5978,'Current Stock'!A63) -> 1 | I63: =SUMIFS(PENJUALAN!$E$4:$E$3651,PENJUALAN!$C$4:$C$3651,'Current Stock'!A63) -> 1 | J63: =H63-I63 -> 0
A64: =CONCATENATE(B64,E64) -> LFW-E90FY | B64: LFW-E90 | C64: BMW 3 Series 05-12 E90 | D64: LFW | E64: FY | F64: X/MB | H64: =SUMIFS(X!$F$3:$F$5978,X!$D$3:$D$5978,'Current Stock'!A64) -> 0 | I64: =SUMIFS(PENJUALAN!$E$4:$E$3651,PENJUALAN!$C$4:$C$3651,'Current Stock'!A64) -> 0 | J64: =H64-I64 -> 0
A65: =CONCATENATE(B65,E65) -> TRW-E90FY | B65: TRW-E90 | C65: BMW 3 Series 05-12 E90 | D65: TRW | E65: FY | F65: X/H | H65: =SUMIFS(X!$F$3:$F$5978,X!$D$3:$D$5978,'Current Stock'!A65) -> 0 | I65: =SUMIFS(PENJUALAN!$E$4:$E$3651,PENJUALAN!$C$4:$C$3651,'Current Stock'!A65) -> 0 | J65: =H65-I65 -> 0
A66: =CONCATENATE(B66,E66) -> FDL-E90FY | B66: FDL-E90 | C66: BMW 3 Series 05-12 E90 | D66: FD/L | E66: FY | F66: 2Hole | H66: =SUMIFS(X!$F$3:$F$5978,X!$D$3:$D$5978,'Current Stock'!A66) -> 0 | I66: =SUMIFS(PENJUALAN!$E$4:$E$3651,PENJUALAN!$C$4:$C$3651,'Current Stock'!A66) -> 0 | J66: =H66-I66 -> 0
... A69: =CONCATENATE(B69,E69) -> RDR-E90FY | B69: RDR-E90 | C69: BMW 3 Series 05-12 E90 | D69: RD/R | E69: FY | F69: 1Hole | H69: =SUMIFS(X!$F$3:$F$5978,X!$D$3:$D$5978,'Current Stock'!A69) -> 0 | I69: =SUMIFS(PENJUALAN!$E$4:$E$3651,PENJUALAN!$C$4:$C$3651,'Current Stock'!A69) -> 0 | J69: =H69-I69 -> 0
A70: =CONCATENATE(B70,E70) -> LFW-F30FY | B70: LFW-F30 | C70: BMW 3 Series 12-18 F30/F35 | D70: LFW | E70: FY | F70: X/RS/List | G70: 45988 | H70: =SUMIFS(X!$F$3:$F$5978,X!$D$3:$D$5978,'Current Stock'!A70) -> 3 | I70: =SUMIFS(PENJUALAN!$E$4:$E$3651,PENJUALAN!$C$4:$C$3651,'Current Stock'!A70) -> 3 | J70: =H70-I70 -> 0
A71: =CONCATENATE(B71,E71) -> TRW-F30FY | B71: TRW-F30 | C71: BMW 3 Series 12-18 F30/F35 | D71: TRW | E71: FY | F71: X/H | H71: =SUMIFS(X!$F$3:$F$5978,X!$D$3:$D$5978,'Current Stock'!A71) -> 0 | I71: =SUMIFS(PENJUALAN!$E$4:$E$3651,PENJUALAN!$C$4:$C$3651,'Current Stock'!A71) -> 0 | J71: =H71-I71 -> 0
A72: =CONCATENATE(B72,E72) -> FDL-F30FY | B72: FDL-F30 | C72: BMW 3 Series 12-18 F30/F35 | D72: FD/L | E72: FY | F72: 2Hole | H72: =SUMIFS(X!$F$3:$F$5978,X!$D$3:$D$5978,'Current Stock'!A72) -> 0 | I72: =SUMIFS(PENJUALAN!$E$4:$E$3651,PENJUALAN!$C$4:$C$3651,'Current Stock'!A72) -> 0 | J72: =H72-I72 -> 0
A73: =CONCATENATE(B73,E73) -> FDR-F30FY | B73: FDR-F30 | C73: BMW 3 Series 12-18 F30/F35 | D73: FD/R | E73: FY | F73: 2Hole | H73: =SUMIFS(X!$F$3:$F$5978,X!$D$3:$D$5978,'Current Stock'!A73) -> 0 | I73: =SUMIFS(PENJUALAN!$E$4:$E$3651,PENJUALAN!$C$4:$C$3651,'Current Stock'!A73) -> 0 | J73: =H73-I73 -> 0
A74: =CONCATENATE(B74,E74) -> RDL-F30FY | B74: RDL-F30 | C74: BMW 3 Series 12-18 F30/F35 | D74: RD/L | E74: FY | F74: 1Hole | H74: =SUMIFS(X!$F$3:$F$5978,X!$D$3:$D$5978,'Current Stock'!A74) -> 0 | I74: =SUMIFS(PENJUALAN!$E$4:$E$3651,PENJUALAN!$C$4:$C$3651,'Current Stock'!A74) -> 0 | J74: =H74-I74 -> 0
A75: =CONCATENATE(B75,E75) -> RDR-F30FY | B75: RDR-F30 | C75: BMW 3 Series 12-18 F30/F35 | D75: RD/R | E75: FY | F75: 1Hole | H75: =SUMIFS(X!$F$3:$F$5978,X!$D$3:$D$5978,'Current Stock'!A75) -> 1 | I75: =SUMIFS(PENJUALAN!$E$4:$E$3651,PENJUALAN!$C$4:$C$3651,'Current Stock'!A75) -> 1 | J75: =H75-I75 -> 0
A76: =CONCATENATE(B76,E76) -> LFW-E60RSKFY | B76: LFW-E60RSK | C76: BMW 5 Series 03-10 E60 (1 Sensor / [] ) | D76: LFW | E76: FY | F76: X/MB/RS | H76: =SUMIFS(X!$F$3:$F$5978,X!$D$3:$D$5978,'Current Stock'!A76) -> 0 | I76: =SUMIFS(PENJUALAN!$E$4:$E$3651,PENJUALAN!$C$4:$C$3651,'Current Stock'!A76) -> 0 | J76: =H76-I76 -> 0
A77: =CONCATENATE(B77,E77) -> LFW-E60RSOFY | B77: LFW-E60RSO | C77: BMW 5 Series 03-10 E60 (1 Sensor / O) | D77: LFW | E77: FY | F77: X/MB/RS | H77: =SUMIFS(X!$F$3:$F$5978,X!$D$3:$D$5978,'Current Stock'!A77) -> 0 | I77: =SUMIFS(PENJUALAN!$E$4:$E$3651,PENJUALAN!$C$4:$C$3651,'Current Stock'!A77) -> 0 | J77: =H77-I77 -> 0
A78: =CONCATENATE(B78,E78) -> TRW-E60FY | B78: TRW-E60 | C78: BMW 5 Series 03-10 E60 | D78: TRW | E78: FY | F78: X/H | H78: =SUMIFS(X!$F$3:$F$5978,X!$D$3:$D$5978,'Current Stock'!A78) -> 0 | I78: =SUMIFS(PENJUALAN!$E$4:$E$3651,PENJUALAN!$C$4:$C$3651,'Current Stock'!A78) -> 0 | J78: =H78-I78 -> 0
A79: =CONCATENATE(B79,E79) -> FDL-E60FY | B79: FDL-E60 | C79: BMW 5 Series 03-10 E60 | D79: FD/L | E79: FY | H79: =SUMIFS(X!$F$3:$F$5978,X!$D$3:$D$5978,'Current Stock'!A79) -> 0 | I79: =SUMIFS(PENJUALAN!$E$4:$E$3651,PENJUALAN!$C$4:$C$3651,'Current Stock'!A79) -> 0 | J79: =H79-I79 -> 0
A80: =CONCATENATE(B80,E80) -> FDR-E60FY | B80: FDR-E60 | C80: BMW 5 Series 03-10 E60 | D80: FD/R | E80: FY | H80: =SUMIFS(X!$F$3:$F$5978,X!$D$3:$D$5978,'Current Stock'!A80) -> 0 | I80: =SUMIFS(PENJUALAN!$E$4:$E$3651,PENJUALAN!$C$4:$C$3651,'Current Stock'!A80) -> 0 | J80: =H80-I80 -> 0
A81: =CONCATENATE(B81,E81) -> RDL-E60FY | B81: RDL-E60 | C81: BMW 5 Series 03-10 E60 | D81: RD/L | E81: FY | F81: 1Hole | H81: =SUMIFS(X!$F$3:$F$5978,X!$D$3:$D$5978,'Current Stock'!A81) -> 0 | I81: =SUMIFS(PENJUALAN!$E$4:$E$3651,PENJUALAN!$C$4:$C$3651,'Current Stock'!A81) -> 0 | J81: =H81-I81 -> 0
A82: =CONCATENATE(B82,E82) -> RDR-E60FY | B82: RDR-E60 | C82: BMW 5 Series 03-10 E60 | D82: RD/R | E82: FY | F82: 1Hole | H82: =SUMIFS(X!$F$3:$F$5978,X!$D$3:$D$5978,'Current Stock'!A82) -> 0 | I82: =SUMIFS(PENJUALAN!$E$4:$E$3651,PENJUALAN!$C$4:$C$3651,'Current Stock'!A82) -> 0 | J82: =H82-I82 -> 0
A83: =CONCATENATE(B83,E83) -> LFW-F10FY | B83: LFW-F10 | C83: BMW 5 Series 10-16 F10 (1 Sensor / ꓳ Tengah) | D83: LFW | E83: FY | F83: X/MB/RS | H83: =SUMIFS(X!$F$3:$F$5978,X!$D$3:$D$5978,'Current Stock'!A83) -> 0 | I83: =SUMIFS(PENJUALAN!$E$4:$E$3651,PENJUALAN!$C$4:$C$3651,'Current Stock'!A83) -> 0 | J83: =H83-I83 -> 0
A84: =CONCATENATE(B84,E84) -> FDL-F10FY | B84: FDL-F10 | C84: BMW 5 Series 10-16 F10 | D84: FD/L | E84: FY | F84: 2Hole | H84: =SUMIFS(X!$F$3:$F$5978,X!$D$3:$D$5978,'Current Stock'!A84) -> 0 | I84: =SUMIFS(PENJUALAN!$E$4:$E$3651,PENJUALAN!$C$4:$C$3651,'Current Stock'!A84) -> 0 | J84: =H84-I84 -> 0
A85: =CONCATENATE(B85,E85) -> FDL-F10FY | B85: FDL-F10 | C85: BMW 5 Series 10-16 F10 | D85: FD/R | E85: FY | F85: 2Hole | H85: =SUMIFS(X!$F$3:$F$5978,X!$D$3:$D$5978,'Current Stock'!A85) -> 0 | I85: =SUMIFS(PENJUALAN!$E$4:$E$3651,PENJUALAN!$C$4:$C$3651,'Current Stock'!A85) -> 0 | J85: =H85-I85 -> 0
A86: =CONCATENATE(B86,E86) -> RDL-F10FY | B86: RDL-F10 | C86: BMW 5 Series 10-16 F10 | D86: RD/L | E86: FY | F86: 1Hole | H86: =SUMIFS(X!$F$3:$F$5978,X!$D$3:$D$5978,'Current Stock'!A86) -> 0 | I86: =SUMIFS(PENJUALAN!$E$4:$E$3651,PENJUALAN!$C$4:$C$3651,'Current Stock'!A86) -> 0 | J86: =H86-I86 -> 0
A87: =CONCATENATE(B87,E87) -> RDR-F10FY | B87: RDR-F10 | C87: BMW 5 Series 10-16 F10 | D87: RD/R | E87: FY | F87: 1Hole | H87: =SUMIFS(X!$F$3:$F$5978,X!$D$3:$D$5978,'Current Stock'!A87) -> 0 | I87: =SUMIFS(PENJUALAN!$E$4:$E$3651,PENJUALAN!$C$4:$C$3651,'Current Stock'!A87) -> 0 | J87: =H87-I87 -> 0
A88: =CONCATENATE(B88,E88) -> LFW-E84FY | B88: LFW-E84 | C88: BMW X1 Series 09-14 E84 (1 Sensor / [] ) | D88: LFW | E88: FY | F88: X/MB/RS | H88: =SUMIFS(X!$F$3:$F$5978,X!$D$3:$D$5978,'Current Stock'!A88) -> 0 | I88: =SUMIFS(PENJUALAN!$E$4:$E$3651,PENJUALAN!$C$4:$C$3651,'Current Stock'!A88) -> 0 | J88: =H88-I88 -> 0
A89: =CONCATENATE(B89,E89) -> TRW-E84FY | B89: TRW-E84 | C89: BMW X1 Series 09-14 E84 | D89: TRW | E89: FY | F89: X/H | H89: =SUMIFS(X!$F$3:$F$5978,X!$D$3:$D$5978,'Current Stock'!A89) -> 1 | I89: =SUMIFS(PENJUALAN!$E$4:$E$3651,PENJUALAN!$C$4:$C$3651,'Current Stock'!A89) -> 1 | J89: =H89-I89 -> 0
A90: =CONCATENATE(B90,E90) -> LFW-F48FY | B90: LFW-F48 | C90: BMW X1 Series 15- F48 | D90: LFW | E90: FY | F90: X/RS | H90: =SUMIFS(X!$F$3:$F$5978,X!$D$3:$D$5978,'Current Stock'!A90) -> 0 | I90: =SUMIFS(PENJUALAN!$E$4:$E$3651,PENJUALAN!$C$4:$C$3651,'Current Stock'!A90) -> 0 | J90: =H90-I90 -> 0
A91: =CONCATENATE(B91,E91) -> LFW-E53FY | B91: LFW-E53 | C91: BMW X5 Series 00-06 E53 | D91: LFW | E91: FY | F91: X/MB/RS | H91: =SUMIFS(X!$F$3:$F$5978,X!$D$3:$D$5978,'Current Stock'!A91) -> 0 | I91: =SUMIFS(PENJUALAN!$E$4:$E$3651,PENJUALAN!$C$4:$C$3651,'Current Stock'!A91) -> 0 | J91: =H91-I91 -> 0
A92: =CONCATENATE(B92,E92) -> TRW-E53BLACKFY | B92: TRW-E53BLACK | C92: BMW X5 Series 00-06 E53 (Hitam) | D92: TRW | E92: FY | F92: X/H/A/1hole | H92: =SUMIFS(X!$F$3:$F$5978,X!$D$3:$D$5978,'Current Stock'!A92) -> 0 | I92: =SUMIFS(PENJUALAN!$E$4:$E$3651,PENJUALAN!$C$4:$C$3651,'Current Stock'!A92) -> 0 | J92: =H92-I92 -> 0
... A122: =CONCATENATE(B122,E122) -> LFW-ORLANDOFY | B122: LFW-ORLANDO | C122: Chevrolet Orlando 12- 1st Gen | D122: LFW | E122: FY | F122: X/MB | H122: =SUMIFS(X!$F$3:$F$5978,X!$D$3:$D$5978,'Current Stock'!A122) -> 0 | I122: =SUMIFS(PENJUALAN!$E$4:$E$3651,PENJUALAN!$C$4:$C$3651,'Current Stock'!A122) -> 0 | J122: =H122-I122 -> 0
A123: =CONCATENATE(B123,E123) -> FDR-ORLANDOFY | B123: FDR-ORLANDO | C123: Chevrolet Orlando 12- 1st Gen | D123: FD/R | E123: FY | H123: =SUMIFS(X!$F$3:$F$5978,X!$D$3:$D$5978,'Current Stock'!A123) -> 0 | I123: =SUMIFS(PENJUALAN!$E$4:$E$3651,PENJUALAN!$C$4:$C$3651,'Current Stock'!A123) -> 0 | J123: =H123-I123 -> 0
A124: =CONCATENATE(B124,E124) -> RDL-ORLANDOFY | B124: RDL-ORLANDO | C124: Chevrolet Orlando 12- 1st Gen | D124: RD/L | E124: FY | H124: =SUMIFS(X!$F$3:$F$5978,X!$D$3:$D$5978,'Current Stock'!A124) -> 0 | I124: =SUMIFS(PENJUALAN!$E$4:$E$3651,PENJUALAN!$C$4:$C$3651,'Current Stock'!A124) -> 0 | J124: =H124-I124 -> 0
A125: =CONCATENATE(B125,E125) -> LFW-SPARK98FY | B125: LFW-SPARK98 | C125: Chevrolet Spark 98-05 M100 1stGen (800cc) | D125: LFW | E125: FY | F125: X/MB | H125: =SUMIFS(X!$F$3:$F$5978,X!$D$3:$D$5978,'Current Stock'!A125) -> 0 | I125: =SUMIFS(PENJUALAN!$E$4:$E$3651,PENJUALAN!$C$4:$C$3651,'Current Stock'!A125) -> 0 | J125: =H125-I125 -> 0
A126: =CONCATENATE(B126,E126) -> TRW-SPARK98FY | B126: TRW-SPARK98 | C126: Chevrolet Spark 98-05 M100 1stGen (800cc) | D126: TRW | E126: FY | F126: X/H | H126: =SUMIFS(X!$F$3:$F$5978,X!$D$3:$D$5978,'Current Stock'!A126) -> 0 | I126: =SUMIFS(PENJUALAN!$E$4:$E$3651,PENJUALAN!$C$4:$C$3651,'Current Stock'!A126) -> 0 | J126: =H126-I126 -> 0
A127: =CONCATENATE(B127,E127) -> LFW-SPARK05FY | B127: LFW-SPARK05 | C127: Chevrolet Spark 05-09 M200 2nd Gen (1000cc) | D127: LFW | E127: FY | F127: X/MB | H127: =SUMIFS(X!$F$3:$F$5978,X!$D$3:$D$5978,'Current Stock'!A127) -> 0 | I127: =SUMIFS(PENJUALAN!$E$4:$E$3651,PENJUALAN!$C$4:$C$3651,'Current Stock'!A127) -> 0 | J127: =H127-I127 -> 0
A128: =CONCATENATE(B128,E128) -> TRW-SPARK05FY | B128: TRW-SPARK05 | C128: Chevrolet Spark 05-09 M200 2nd Gen (1000cc) | D128: TRW | E128: FY | F128: X/H | H128: =SUMIFS(X!$F$3:$F$5978,X!$D$3:$D$5978,'Current Stock'!A128) -> 0 | I128: =SUMIFS(PENJUALAN!$E$4:$E$3651,PENJUALAN!$C$4:$C$3651,'Current Stock'!A128) -> 0 | J128: =H128-I128 -> 0
A129: =CONCATENATE(B129,E129) -> FDL-SPARK05FY | B129: FDL-SPARK05 | C129: Chevrolet Spark 05-09 M200 2nd Gen (1000cc) | D129: FD/L | E129: FY | F129: 2Hole | H129: =SUMIFS(X!$F$3:$F$5978,X!$D$3:$D$5978,'Current Stock'!A129) -> 0 | I129: =SUMIFS(PENJUALAN!$E$4:$E$3651,PENJUALAN!$C$4:$C$3651,'Current Stock'!A129) -> 0 | J129: =H129-I129 -> 0
A130: =CONCATENATE(B130,E130) -> FDR-SPARK05FY | B130: FDR-SPARK05 | C130: Chevrolet Spark 05-09 M200 2nd Gen (1000cc) | D130: FD/R | E130: FY | F130: 2Hole | H130: =SUMIFS(X!$F$3:$F$5978,X!$D$3:$D$5978,'Current Stock'!A130) -> 0 | I130: =SUMIFS(PENJUALAN!$E$4:$E$3651,PENJUALAN!$C$4:$C$3651,'Current Stock'!A130) -> 0 | J130: =H130-I130 -> 0
A131: =CONCATENATE(B131,E131) -> RDR-SPARK05FY | B131: RDR-SPARK05 | C131: Chevrolet Spark 05-09 M200 2nd Gen (1000cc) | D131: RD/R | E131: FY | H131: =SUMIFS(X!$F$3:$F$5978,X!$D$3:$D$5978,'Current Stock'!A131) -> 0 | I131: =SUMIFS(PENJUALAN!$E$4:$E$3651,PENJUALAN!$C$4:$C$3651,'Current Stock'!A131) -> 0 | J131: =H131-I131 -> 0
...

Sheet PENJUALAN
A2: TANGGAL | B2: INV | C2: PRODUK | E2: PC | F2: Penjualan | K2: Konsumen | P2: Sales via | Q2: Pembayaran | X2: Input By | Y2: RIAN | Z2: Check
C3: KODE | D3: NAMA | F3: Satuan | G3: Jumlah | H3: Diskon | I3: Nett | J3: Jumlah | K3: Nama | L3: No Telp | M3: Email | N3: No Pol | O3: Alamat | Q3: TUNAI | R3: DP TUNAI | S3: DP TF | T3: TRANSFER | U3: TOKPED | V3: POTONG | W3: Kembali
A4: 45719 | B4: C250001 | C4: LFW-ALMAZRSXYG | D4: =IFERROR(VLOOKUP(C4,Stock,3,FALSE),"") -> Wuling Almaz (Sensor) | E4: 1 | F4: 3150000 | G4: =E4*F4 -> 3150000 | H4: 150000 | I4: =G4-H4 -> 3000000 | J4: =I4 -> 3000000 | K4: Rudi | L4: +62 818-213-689 | N4: B 869 RS | O4: BSD | P4: GOOGLE | T4: 3000000 | X4: CM | Z4: TF 388
A5: 45721 | B5: C250002 | C5: LFW-TIMORMU | D5: =IFERROR(VLOOKUP(C5,Stock,3,FALSE),"") -> Kia Timor 95-98 / Sephia 94-05 | E5: 1 | F5: 1480000 | G5: =E5*F5 -> 1480000 | I5: =G5-H5 -> 1480000 | J5: =I5 -> 1480000 | K5: Icshan | L5: +62 812-8854-6009 | O5: Pondok Aren | P5: GOOGLE | T5: 130000 | Z5: DP 130K TF
A6: 45721 | B6: C250002 | C6: OTH-SERTRANSPORT | D6: =IFERROR(VLOOKUP(C6,Stock,3,FALSE),"") -> Transport | E6: 1 | F6: 150000 | G6: =E6*F6 -> 150000 | I6: =G6-H6 -> 150000 | J6: =I6 -> 150000 | K6: Icshan | L6: +62 812-8854-6009 | O6: Pondok Aren | P6: GOOGLE
A7: 45721 | B7: C250003 | C7: TRW-IGNISXYG | D7: =IFERROR(VLOOKUP(C7,Stock,3,FALSE),"") -> Suzuki Ignis 17- | E7: 1 | F7: 1149000 | G7: =E7*F7 -> 1149000 | I7: =G7-H7 -> 1149000 | J7: =I7 -> 1149000 | K7: Rudy Widyanto | L7: +62 816-531-320 | N7: B 2003 BYB | O7: Meruya | P7: GOOGLE
A8: 45722 | B8: C250004 | C8: OTH-RPLXLFW | D8: =IFERROR(VLOOKUP(C8,Stock,3,FALSE),"") -> Bongkar Pasang Kaca Mobil Depan | E8: 1 | F8: 450000 | G8: =E8*F8 -> 450000 | I8: =G8-H8 -> 450000 | J8: =I8 -> 450000 | K8: Gloss Patrol | L8: +62 813-8800-0093 | O8: BSD | P8: GOOGLE | T8: 100000 | Z8: TF 388 100K DENNY KRISANDI
A9: 45722 | B9: C250004 | C9: OTH-RPLXSIDE | D9: =IFERROR(VLOOKUP(C9,Stock,3,FALSE),"") -> Bongkar Pasang Kaca Mobil Samping | E9: 2 | F9: 200000 | G9: =E9*F9 -> 400000 | I9: =G9-H9 -> 400000 | J9: =I9 -> 400000 | K9: Gloss Patrol | L9: +62 813-8800-0093 | O9: BSD | P9: GOOGLE | Z9: TF 388 850K DENNY KRISANDI
A10: 45722 | B10: C250004 | C10: OTH-SERTRANSPORT | D10: =IFERROR(VLOOKUP(C10,Stock,3,FALSE),"") -> Transport | E10: 1 | F10: 100000 | G10: =E10*F10 -> 100000 | I10: =G10-H10 -> 100000 | J10: =I10 -> 100000 | K10: Gloss Patrol | L10: +62 813-8800-0093 | O10: BSD | P10: GOOGLE | Z10: TF 388
A11: 45722 | B11: C250005 | C11: SWL-PAJERO08XYG | D11: =IFERROR(VLOOKUP(C11,Stock,3,FALSE),"") -> Mitsubishi Pajero 08-16 | E11: 1 | F11: 839000 | G11: =E11*F11 -> 839000 | I11: =G11-H11 -> 839000 | J11: =I11 -> 839000 | K11: Togap Parlindungan Simanjuntak | L11: +62 813-8288-8277 | N11: B 1439 NCY | O11: Karang Tengah | P11: GOOGLE | T11: 100000 | Z11: TF 388 100K TOGAP PARLINDUNGAN /
A12: 45722 | B12: C250005 | C12: OTH-SERTRANSPORT | D12: =IFERROR(VLOOKUP(C12,Stock,3,FALSE),"") -> Transport | E12: 1 | F12: 80000 | G12: =E12*F12 -> 80000 | I12: =G12-H12 -> 80000 | J12: =I12 -> 80000 | K12: Togap Parlindungan Simanjuntak | L12: +62 813-8288-8277 | N12: B 1439 NCY | O12: Karang Tengah | P12: GOOGLE
A13: 45722 | B13: C250006 | C13: TRW-SIGRA16MU | D13: =IFERROR(VLOOKUP(C13,Stock,3,FALSE),"") -> Toyota Calya / Sigra 16- | E13: 1 | F13: 850000 | G13: =E13*F13 -> 850000 | I13: =G13-H13 -> 850000 | J13: =I13 -> 850000 | K13: Riki | L13: +62 811-239-870 | O13: Ruko | P13: GOOGLE
A14: 45722 | B14: C250007 | C14: FDR-SIGRA16MU | D14: =IFERROR(VLOOKUP(C14,Stock,3,FALSE),"") -> Toyota Calya / Sigra 16- | E14: 1 | F14: 450000 | G14: =E14*F14 -> 450000 | I14: =G14-H14 -> 450000 | J14: =I14 -> 450000 | K14: Edison | L14: 081288843107 | N14: B 1038 VOF | O14: Tigaraksa | P14: GOOGLE
A15: 45723 | B15: C250008 | C15: LFW-AUDIB811XYG | D15: =IFERROR(VLOOKUP(C15,Stock,3,FALSE),"") -> Audi A4 08-15 B8 [11-15] (1 Sensor / O Sempurna) | E15: 1 | F15: 5081000 | G15: =E15*F15 -> 5081000 | I15: =G15-H15 -> 5081000 | J15: =I15 -> 5081000 | K15: Hamzah Purnama | L15: +62 815-6500-874 | N15: H 1904 T2 | O15: Jakarta Selatan | P15: GOOGLE | T15: 5081000 | X15: lia
A16: 45723 | B16: C250008 | C16: OTH-SERTRANSPORT | D16: =IFERROR(VLOOKUP(C16,Stock,3,FALSE),"") -> Transport | E16: 1 | F16: 250000 | G16: =E16*F16 -> 250000 | I16: =G16-H16 -> 250000 | J16: =I16 -> 250000 | K16: Hamzah Purnama | L16: +62 815-6500-874 | N16: H 1904 T2 | O16: Jakarta Selatan | P16: GOOGLE | T16: 250000 | X16: lia
A17: 45723 | B17: C250009 | C17: TRW-RUSH17HXYG | D17: =IFERROR(VLOOKUP(C17,Stock,3,FALSE),"") -> Toyota Rush / Terios 18- | E17: 1 | F17: 1052000 | G17: =E17*F17 -> 1052000 | I17: =G17-H17 -> 1052000 | J17: =I17 -> 1052000 | K17: Pak Hartono. | L17: +62 817-0705-500 | O17: Tangerang | P17: GOOGLE | T17: 100000 | X17: lia
A18: 45723 | B18: C250009 | C18: OTH-SERTRANSPORT | D18: =IFERROR(VLOOKUP(C18,Stock,3,FALSE),"") -> Transport | E18: 1 | F18: 120000 | G18: =E18*F18 -> 120000 | I18: =G18-H18 -> 120000 | J18: =I18 -> 120000 | K18: Pak Hartono. | L18: +62 817-0705-500 | N18: B 1148 VOQ | O18: Tangerang | P18: GOOGLE | X18: lia
A19: 45724 | B19: C250010 | C19: LFW-VIOS02MU | D19: =IFERROR(VLOOKUP(C19,Stock,3,FALSE),"") -> Toyota Vios 02-07 XP40 1st Gen | E19: 1 | F19: 1455000 | G19: =E19*F19 -> 1455000 | I19: =G19-H19 -> 1455000 | J19: =I19 -> 1455000 | K19: Rika | L19: +62 855-8685-624 | M19: rika26aditya@gmail.com | N19: A 1054 VN | O19: Batuceper | P19: GOOGLE | Q19: 1455000
A20: 45724 | B20: C250011 | C20: LFW-CRV95XYG | D20: =IFERROR(VLOOKUP(C20,Stock,3,FALSE),"") -> Honda CR-V 95-01 1st Gen | E20: 1 | F20: 1600000 | G20: =E20*F20 -> 1600000 | I20: =G20-H20 -> 1600000 | J20: =I20 -> 1600000 | K20: Among | L20: +62 817-6488-584 | M20: aqlylsno@gmail.com | N20: B 8136 T | O20: Kembangan | P20: GOOGLE
A21: 45724 | B21: C250012 | C21: VOID | D21: =IFERROR(VLOOKUP(C21,Stock,3,FALSE),"")
A22: 45724 | B22: C250013 | C22: TRW-AVANZA21HASH | D22: =IFERROR(VLOOKUP(C22,Stock,3,FALSE),"") -> Toyota Avanza / Xenia 21- 4th Gen | E22: 1 | F22: 975000 | G22: =E22*F22 -> 975000 | I22: =G22-H22 -> 975000 | J22: =I22 -> 975000 | K22: Nurjanah Efendy | L22: +62 813-4199-1001 | O22: Tangerang | P22: GOOGLE | Q22: 975000 | Z22: TF 388
A23: 45724 | B23: C250013 | C23: OTH-PETIKAYU | D23: =IFERROR(VLOOKUP(C23,Stock,3,FALSE),"") -> Peti Kayu | E23: 1 | F23: 200000 | G23: =E23*F23 -> 200000 | I23: =G23-H23 -> 200000 | J23: =I23 -> 200000 | K23: Nurjanah Efendy | L23: +62 813-4199-1001 | O23: Tangerang | P23: GOOGLE | Q23: 200000 | Z23: TF 388
A24: 45724 | B24: C250013 | C24: OTH-SERTRANSPORT | D24: =IFERROR(VLOOKUP(C24,Stock,3,FALSE),"") -> Transport | E24: 1 | F24: 150000 | G24: =E24*F24 -> 150000 | I24: =G24-H24 -> 150000 | J24: =I24 -> 150000 | K24: Nurjanah Efendy | L24: +62 813-4199-1001 | O24: Tangerang | P24: GOOGLE | Q24: 150000 | Z24: TF 388
A25: 45726 | B25: C250014 | C25: LFW-CROSSXYG | D25: =IFERROR(VLOOKUP(C25,Stock,3,FALSE),"") -> Toyota Corolla Cross 21- | E25: 1 | F25: 3750000 | G25: =E25*F25 -> 3750000 | I25: =G25-H25 -> 3750000 | J25: =I25 -> 3750000 | K25: P. Brian Wahyu | L25: +62 818-780-808 | O25: Tangerang | P25: GOOGLE | T25: 810000 | X25: lia | Z25: TF 388
A26: 45726 | B26: C250014 | C26: OTH-PETIKAYU | D26: =IFERROR(VLOOKUP(C26,Stock,3,FALSE),"") -> Peti Kayu | E26: 1 | F26: 200000 | G26: =E26*F26 -> 200000 | I26: =G26-H26 -> 200000 | J26: =I26 -> 200000 | K26: P. Brian Wahyu | L26: +62 818-780-808 | O26: Tangerang | P26: GOOGLE | X26: lia | Z26: TF 388
A27: 45726 | B27: C250014 | C27: OTH-SERTRANSPORT | D27: =IFERROR(VLOOKUP(C27,Stock,3,FALSE),"") -> Transport | E27: 1 | F27: 100000 | G27: =E27*F27 -> 100000 | I27: =G27-H27 -> 100000 | J27: =I27 -> 100000 | K27: P. Brian Wahyu | L27: +62 818-780-808 | O27: Tangerang | P27: GOOGLE | X27: lia | Z27: TF 388
A28: 45726 | B28: C250014 | C28: OTH-SERTRANSPORT | D28: =IFERROR(VLOOKUP(C28,Stock,3,FALSE),"") -> Transport | E28: 1 | F28: 388000 | G28: =E28*F28 -> 388000 | I28: =G28-H28 -> 388000 | J28: =I28 -> 388000 | K28: P. Brian Wahyu | L28: +62 818-780-808 | O28: Tangerang | P28: GOOGLE
A29: 45726 | B29: C250015 | C29: LFW-HIACEXYG | D29: =IFERROR(VLOOKUP(C29,Stock,3,FALSE),"") -> Toyota Hi-Ace 04-20 Commuter | E29: 1 | F29: 1759000 | G29: =E29*F29 -> 1759000 | I29: =G29-H29 -> 1759000 | J29: =I29 -> 1759000 | K29: Nirwana reborn | L29: +6287877218668 | O29: Tangerang | P29: GOOGLE | X29: lia
A30: 45726 | B30: C250016 | C30: OTH-RPLXLFW | D30: =IFERROR(VLOOKUP(C30,Stock,3,FALSE),"") -> Bongkar Pasang Kaca Mobil Depan | E30: 1 | F30: 550000 | G30: =E30*F30 -> 550000 | I30: =G30-H30 -> 550000 | J30: =I30 -> 550000 | K30: Fauzan | L30: +62 812-9940-9142 | O30: Tangerang | P30: GOOGLE
A31: 45726 | B31: C250016 | C31: OTH-SERTRANSPORT | D31: =IFERROR(VLOOKUP(C31,Stock,3,FALSE),"") -> Transport | E31: 1 | F31: 80000 | G31: =E31*F31 -> 80000 | I31: =G31-H31 -> 80000 | J31: =I31 -> 80000 | K31: Fauzan | L31: +62 812-9940-9142 | O31: Tangerang | P31: GOOGLE
A32: 45726 | B32: C250017 | C32: TRW-BRIONOLBGXYG | D32: =IFERROR(VLOOKUP(C32,Stock,3,FALSE),"") -> Honda Brio 10-17 [Tanpa Lubang] | E32: 1 | F32: 955000 | G32: =E32*F32 -> 955000 | I32: =G32-H32 -> 955000 | J32: =I32 -> 955000 | K32: Muhammad Haidar | L32: 6282143097683 | O32: Pondok Aren | P32: GOOGLE
A33: 45726 | B33: C250018 | C33: LFW-BIANTEXYG | D33: =IFERROR(VLOOKUP(C33,Stock,3,FALSE),"") -> Mazda Biante 08- | E33: 1 | F33: 3661000 | G33: =E33*F33 -> 3661000 | I33: =G33-H33 -> 3661000 | J33: =I33 -> 3661000 | K33: Fadhan Osti | L33: 08132809993 | M33: fadhan.osti@gmail.com | O33: Tangerang | P33: GOOGLE
A34: 45726 | B34: C250019 | C34: LFW-COROLLA91XYG | D34: =IFERROR(VLOOKUP(C34,Stock,3,FALSE),"") -> Toyota Corolla Great E100 91-96 7th Gen | E34: 1 | F34: 1488000 | G34: =E34*F34 -> 1488000 | I34: =G34-H34 -> 1488000 | J34: =I34 -> 1488000 | O34: Tangerang | P34: Tokped BKS
A35: 45726 | B35: C250020 | C35: TRW-BALENO15XYG | D35: =IFERROR(VLOOKUP(C35,Stock,3,FALSE),"") -> Suzuki Baleno 15-21 | E35: 1 | F35: 1164000 | G35: =E35*F35 -> 1164000 | I35: =G35-H35 -> 1164000 | J35: =I35 -> 1164000 | K35: Chuko Tanah Abang | L35: +62 813-4335-0809 | O35: Jakarta pusat | P35: GOOGLE | T35: 1164000 | X35: lia
A36: 45726 | B36: C250020 | C36: OTH-PETIKAYU | D36: =IFERROR(VLOOKUP(C36,Stock,3,FALSE),"") -> Peti Kayu | E36: 1 | F36: 200000 | G36: =E36*F36 -> 200000 | I36: =G36-H36 -> 200000 | J36: =I36 -> 200000 | K36: Chuko Tanah Abang | L36: +62 813-4335-0809 | O36: Jakarta pusat | P36: GOOGLE | T36: 200000 | X36: lia
A37: 45726 | B37: C250021 | C37: LFW-FORTUNER15MU | D37: =IFERROR(VLOOKUP(C37,Stock,3,FALSE),"") -> Toyota Fortuner 15- 2nd Gen | E37: 1 | F37: 1737000 | G37: =E37*F37 -> 1737000 | I37: =G37-H37 -> 1737000 | J37: =I37 -> 1737000 | K37: Johanes | L37: +62 813-5190-4272 | O37: Tangerang | P37: GOOGLE | T37: 100000
A38: 45726 | B38: C250021 | C38: OTH-SERTRANSPORT | D38: =IFERROR(VLOOKUP(C38,Stock,3,FALSE),"") -> Transport | E38: 1 | F38: 20000 | G38: =E38*F38 -> 20000 | I38: =G38-H38 -> 20000 | J38: =I38 -> 20000 | K38: Johanes | L38: +62 813-5190-4272 | O38: Tangerang | P38: GOOGLE
A39: 45728 | B39: C250022 | C39: LFW-GRANMAXMU | D39: =IFERROR(VLOOKUP(C39,Stock,3,FALSE),"") -> Daihatsu Gran Max / Luxio 07- | E39: 1 | F39: 985000 | G39: =E39*F39 -> 985000 | I39: =G39-H39 -> 985000 | J39: =I39 -> 985000 | K39: Dedy Candra | L39: +6281385045210 | O39: Kamal | P39: GOOGLE | T39: 50000
A40: 45728 | B40: C250022 | C40: OTH-SERTRANSPORT | D40: =IFERROR(VLOOKUP(C40,Stock,3,FALSE),"") -> Transport | E40: 1 | F40: 70000 | G40: =E40*F40 -> 70000 | I40: =G40-H40 -> 70000 | J40: =I40 -> 70000 | K40: Dedy Candra | L40: +6281385045210 | O40: Kamal | P40: GOOGLE
A41: 45728 | B41: C250023 | C41: TRW-SIGRA16MU | D41: =IFERROR(VLOOKUP(C41,Stock,3,FALSE),"") -> Toyota Calya / Sigra 16- | E41: 1 | F41: 850000 | G41: =E41*F41 -> 850000 | I41: =G41-H41 -> 850000 | J41: =I41 -> 850000 | K41: P.Syahril | L41: +6282177528028 | O41: Tangerang | P41: GOOGLE | T41: 100000
A42: 45728 | B42: C250024 | C42: LFW-DYNAMU | D42: =IFERROR(VLOOKUP(C42,Stock,3,FALSE),"") -> Toyota Dyna/Hino Dutro 00- | E42: 1 | F42: 1150000 | G42: =E42*F42 -> 1150000 | I42: =G42-H42 -> 1150000 | J42: =I42 -> 1150000 | K42: PT. Prima Makmur Indonesia | O42: Cipondoh - Pergudangan Era Prima | P42: GOOGLE
A43: 45728 | B43: C250025 | C43: LFW-OUTLANDERXYG | D43: =IFERROR(VLOOKUP(C43,Stock,3,FALSE),"") -> Mitsubishi Outlander 10-21 GA3 | E43: 1 | F43: 2138000 | G43: =E43*F43 -> 2138000 | H43: 38000 | I43: =G43-H43 -> 2100000 | J43: =I43 -> 2100000 | K43: Johanes | L43: +62 821-3089-8903 | O43: Jalan Kopi- Jakarta Barat | P43: GOOGLE
A44: 45728 | B44: C250025 | C44: OTH-SERTRANSPORT | D44: =IFERROR(VLOOKUP(C44,Stock,3,FALSE),"") -> Transport | E44: 1 | F44: 200000 | G44: =E44*F44 -> 200000 | I44: =G44-H44 -> 200000 | J44: =I44 -> 200000 | K44: Gloss Patrol | L44: +62 813-8800-0093 | O44: BSD | P44: GOOGLE
A45: 45730 | B45: C250026 | C45: OTH-RPLXLFW | D45: =IFERROR(VLOOKUP(C45,Stock,3,FALSE),"") -> Bongkar Pasang Kaca Mobil Depan | E45: 1 | F45: 650000 | G45: =E45*F45 -> 650000 | I45: =G45-H45 -> 650000 | J45: =I45 -> 650000 | K45: Gloss Patrol | L45: +62 813-8800-0093 | O45: BSD | P45: GOOGLE
A46: 45730 | B46: C250026 | C46: OTH-RPLXTRW | D46: =IFERROR(VLOOKUP(C46,Stock,3,FALSE),"") -> Bongkar Pasang Kaca Mobil Belakang | E46: 1 | F46: 450000 | G46: =E46*F46 -> 450000 | I46: =G46-H46 -> 450000 | J46: =I46 -> 450000 | K46: Gloss Patrol | L46: +62 813-8800-0093 | O46: BSD | P46: GOOGLE
A47: 45730 | B47: C250026 | C47: OTH-RPLXSIDE | D47: =IFERROR(VLOOKUP(C47,Stock,3,FALSE),"") -> Bongkar Pasang Kaca Mobil Samping | E47: 2 | F47: 350000 | G47: =E47*F47 -> 700000 | I47: =G47-H47 -> 700000 | J47: =I47 -> 700000 | K47: Gloss Patrol | L47: +62 813-8800-0093 | O47: BSD | P47: GOOGLE
A48: 45731 | B48: C250027 | C48: OTH-RPLXLFW | D48: =IFERROR(VLOOKUP(C48,Stock,3,FALSE),"") -> Bongkar Pasang Kaca Mobil Depan | E48: 1 | F48: 600000 | G48: =E48*F48 -> 600000 | I48: =G48-H48 -> 600000 | J48: =I48 -> 600000 | K48: P. Dimas | L48: +62 812-3320-696 | N48: B 1018 TMN | O48: Jaksel | P48: GOOGLE | X48: via
A49: 45731 | B49: C250027 | C49: OTH-SERTRANSPORT | D49: =IFERROR(VLOOKUP(C49,Stock,3,FALSE),"") -> Transport | E49: 1 | F49: 150000 | G49: =E49*F49 -> 150000 | I49: =G49-H49 -> 150000 | J49: =I49 -> 150000 | K49: P. Dimas | L49: +62 812-3320-696 | N49: B 1018 TMN | O49: Jaksel | P49: GOOGLE | X49: via
A50: 45731 | B50: C250028 | C50: LFW-TARUNAMU | D50: =IFERROR(VLOOKUP(C50,Stock,3,FALSE),"") -> Daihatsu Taruna | E50: 1 | F50: 1500000 | G50: =E50*F50 -> 1500000 | I50: =G50-H50 -> 1500000 | J50: =I50 -> 1500000 | K50: P. Ananta | L50: +62 822-9728-3361 | O50: Tangerang | P50: GOOGLE
A51: 45733 | B51: C250029 | C51: TRW-AVANZA11HAGC | D51: =IFERROR(VLOOKUP(C51,Stock,3,FALSE),"") -> Toyota Avanza / Xenia 11-15 2nd Gen/3rd Gen (Toyota/Daihatsu) | E51: 1 | F51: 1522000 | G51: =E51*F51 -> 1522000 | I51: =G51-H51 -> 1522000 | J51: =I51 -> 1522000 | K51: Damana Pradito | L51: +62 818-0555-7547 | O51: Tangerang | P51: GOOGLE | T51: 480000 | X51: lia
A52: 45733 | B52: C250029 | C52: OTH-SERTRANSPORT | D52: =IFERROR(VLOOKUP(C52,Stock,3,FALSE),"") -> Transport | E52: 1 | F52: 75000 | G52: =E52*F52 -> 75000 | I52: =G52-H52 -> 75000 | J52: =I52 -> 75000 | K52: Damana Pradito | L52: +62 818-0555-7547 | O52: Tangerang | P52: GOOGLE | X52: lia
A53: 45733 | B53: C250030 | C53: LFW-CRV12MU | D53: =IFERROR(VLOOKUP(C53,Stock,3,FALSE),"") -> Honda CR-V 12-16 4th Gen | E53: 1 | F53: 1949000 | G53: =E53*F53 -> 1949000 | I53: =G53-H53 -> 1949000 | J53: =I53 -> 1949000 | K53: Ali | L53: +62 853-7270-1893 | N53: BH 1470 MZ | O53: PIK | P53: GOOGLE
A54: 45733 | B54: C250031 | C54: LFW-ODYSSEY13XYG | D54: =IFERROR(VLOOKUP(C54,Stock,3,FALSE),"") -> Honda Odyssey 13- 5th Gen RC1/RC2 | E54: 1 | F54: 3823000 | G54: =E54*F54 -> 3823000 | I54: =G54-H54 -> 3823000 | J54: =I54 -> 3823000 | K54: Ralfie Sekenauto | L54: +62 812‑8898‑6668 | N54: B 1525 TYN | O54: Tangerang | P54: GOOGLE
A55: 45734 | B55: C250032 | C55: OTH-RPLXLFW | D55: =IFERROR(VLOOKUP(C55,Stock,3,FALSE),"") -> Bongkar Pasang Kaca Mobil Depan | E55: 1 | F55: 550000 | G55: =E55*F55 -> 550000 | I55: =G55-H55 -> 550000 | J55: =I55 -> 550000 | K55: Frans | L55: +6282122255591 | O55: Tangerang | P55: GOOGLE | T55: 550000 | X55: LIA
A56: 45734 | B56: C250032 | C56: OTH-SERTRANSPORT | D56: =IFERROR(VLOOKUP(C56,Stock,3,FALSE),"") -> Transport | E56: 1 | F56: 100000 | G56: =E56*F56 -> 100000 | I56: =G56-H56 -> 100000 | J56: =I56 -> 100000 | K56: Frans | L56: +6282122255591 | O56: Tangerang | P56: GOOGLE | T56: 100000 | X56: LIA
A57: 45735 | B57: C250033 | C57: TRW-ALPHARD08BLACKXYG | D57: =IFERROR(VLOOKUP(C57,Stock,3,FALSE),"") -> Toyota Alphard 08-15 ANH20 2nd Gen (Hitam) | E57: 1 | F57: 2944000 | G57: =E57*F57 -> 2944000 | I57: =G57-H57 -> 2944000 | J57: =I57 -> 2944000 | K57: Angeline | L57: +62 813-1622-0729 | O57: Tangerang | P57: GOOGLE | T57: 2944000 | X57: LIA
A58: 45735 | B58: C250033 | C58: OTH-SERTRANSPORT | D58: =IFERROR(VLOOKUP(C58,Stock,3,FALSE),"") -> Transport | E58: 1 | F58: 50000 | G58: =E58*F58 -> 50000 | I58: =G58-H58 -> 50000 | J58: =I58 -> 50000 | K58: Angeline | L58: +62 813-1622-0729 | O58: Tangerang | P58: GOOGLE | T58: 50000 | X58: LIA
A59: 45735 | B59: C250034 | C59: TRW-SIGRA16MU | D59: =IFERROR(VLOOKUP(C59,Stock,3,FALSE),"") -> Toyota Calya / Sigra 16- | E59: 1 | F59: 850000 | G59: =E59*F59 -> 850000 | I59: =G59-H59 -> 850000 | J59: =I59 -> 850000 | K59: P. Sarno nugroho | L59: +62 857-1442-8194 | O59: Jakarta barat | P59: GOOGLE | T59: 850000 | X59: LIA
A60: 45735 | B60: C250035 | C60: LFW-ERTIGA12MU | D60: =IFERROR(VLOOKUP(C60,Stock,3,FALSE),"") -> Suzuki Ertiga 12-18 1st Gen MPV | E60: 1 | F60: 1300000 | G60: =E60*F60 -> 1300000 | I60: =G60-H60 -> 1300000 | J60: =I60 -> 1300000 | K60: P. Waliyo | L60: +6285934228131 | O60: Tangerang | P60: GOOGLE | Q60: 1300000 | X60: LIA
A61: 45735 | B61: C250035 | C61: OTH-SERTRANSPORT | D61: =IFERROR(VLOOKUP(C61,Stock,3,FALSE),"") -> Transport | E61: 1 | F61: 100000 | G61: =E61*F61 -> 100000 | I61: =G61-H61 -> 100000 | J61: =I61 -> 100000 | K61: P. Waliyo | L61: +6285934228131 | O61: Tangerang | P61: GOOGLE | T61: 100000 | X61: LIA
A62: 45736 | B62: C250036 | C62: LFW-W213XYG | D62: =IFERROR(VLOOKUP(C62,Stock,3,FALSE),"") -> Mers-Benz E-Class 17- W213 (1 Sensor/ □ ) | E62: 1 | F62: 8090000 | G62: =E62*F62 -> 8090000 | I62: =G62-H62 -> 8090000 | J62: =I62 -> 8090000 | K62: P. Steven | L62: +62 813-8433-4614 | O62: Tangerang | P62: GOOGLE | T62: 900000 | X62: LIA
A63: 45736 | B63: C250036 | C63: OTH-SERTRANSPORT | D63: =IFERROR(VLOOKUP(C63,Stock,3,FALSE),"") -> Transport | E63: 1 | F63: 150000 | G63: =E63*F63 -> 150000 | I63: =G63-H63 -> 150000 | J63: =I63 -> 150000 | K63: P. Steven | L63: +62 813-8433-4614 | O63: Tangerang | P63: GOOGLE | X63: LIA
A64: 45737 | B64: C250037 | C64: TRW-XPANDERXYG | D64: =IFERROR(VLOOKUP(C64,Stock,3,FALSE),"") -> Mitsubishi Xpander 17-21 | E64: 1 | F64: 620000 | G64: =E64*F64 -> 620000 | I64: =G64-H64 -> 620000 | J64: =I64 -> 620000 | K64: Fidel | L64: +6281283385638 | O64: Ciputat | P64: Tokped BKS | U64: =J64+J65 -> 1412000 | X64: Leni
A65: 45737 | B65: C250037 | C65: SWR-XPANDERCHASH | D65: =IFERROR(VLOOKUP(C65,Stock,3,FALSE),"") -> Mitsubishi Xpander 17- / Livina 19- 2nd Gen (Chrome) | E65: 1 | F65: 792000 | G65: =E65*F65 -> 792000 | I65: =G65-H65 -> 792000 | J65: =I65 -> 792000 | K65: Fidel | L65: +6281283385638 | O65: Ciputat | P65: Tokped BKS
A66: 45737 | B66: C250037 | C66: OTH-SERTRANSPORT | D66: =IFERROR(VLOOKUP(C66,Stock,3,FALSE),"") -> Transport | E66: 1 | F66: 100000 | G66: =E66*F66 -> 100000 | I66: =G66-H66 -> 100000 | J66: =I66 -> 100000 | K66: Fidel | L66: +6281283385638 | O66: Ciputat | P66: Tokped BKS
A67: 45737 | B67: C250038 | C67: TRW-CRV17XYG | D67: =IFERROR(VLOOKUP(C67,Stock,3,FALSE),"") -> Honda CR-V 17- 5th Gen | E67: 1 | F67: 1546000 | G67: =E67*F67 -> 1546000 | I67: =G67-H67 -> 1546000 | J67: =I67 -> 1546000 | K67: Irma | L67: +62 817-823-992 | O67: Serpong | P67: GOOGLE
A68: 45737 | B68: C250039 | C68: LFW-INNOVA04MU | D68: =IFERROR(VLOOKUP(C68,Stock,3,FALSE),"") -> Toyota Innova 04-15 1st Gen | E68: 1 | F68: 1250000 | G68: =E68*F68 -> 1250000 | I68: =G68-H68 -> 1250000 | J68: =I68 -> 1250000 | K68: P. Carlos Gultom | L68: +62 856-9722-2748 | O68: Tangerang | P68: GOOGLE | T68: 100000 | X68: lia
A69: 45737 | B69: C250039 | C69: OTH-SERTRANSPORT | D69: =IFERROR(VLOOKUP(C69,Stock,3,FALSE),"") -> Transport | E69: 1 | F69: 100000 | G69: =E69*F69 -> 100000 | I69: =G69-H69 -> 100000 | J69: =I69 -> 100000 | K69: P. Carlos Gultom | L69: +62 856-9722-2748 | O69: Tangerang | P69: GOOGLE | X69: lia
A70: 45738 | B70: C250040 | C70: LFW-MARCHMU | D70: =IFERROR(VLOOKUP(C70,Stock,3,FALSE),"") -> Nissan March 10- K13 | E70: 1 | F70: 1528000 | G70: =E70*F70 -> 1528000 | I70: =G70-H70 -> 1528000 | J70: =I70 -> 1528000 | K70: Kak Qais | L70: +62 813-8836-8774 | O70: Tangerang | P70: GOOGLE | X70: lia
A71: 45738 | B71: C250041 | C71: LFW-AVANZA16MU | D71: =IFERROR(VLOOKUP(C71,Stock,3,FALSE),"") | E71: 1 | F71: 1020000 | G71: =E71*F71 -> 1020000 | I71: =G71-H71 -> 1020000 | J71: =I71 -> 1020000 | K71: P. Adi | L71: +62 878-8882-1775 | O71: Tangerang | P71: GOOGLE | T71: 1020000 | X71: lia
A72: 45738 | B72: C250042 | C72: TRW-AVANZA21ASH | D72: =IFERROR(VLOOKUP(C72,Stock,3,FALSE),"") -> Toyota Avanza / Xenia 21- 4th Gen | E72: 1 | F72: 950000 | G72: =E72*F72 -> 950000 | I72: =G72-H72 -> 950000 | J72: =I72 -> 950000 | K72: P Denny Christian Susanto | L72: +62 822-5555-8262 | N72: B 1595 HOA | O72: Tangerang | P72: GOOGLE | T72: 950000 | X72: via
A73: 45738 | B73: C250043 | C73: OTH-RPLXLFW | D73: =IFERROR(VLOOKUP(C73,Stock,3,FALSE),"") -> Bongkar Pasang Kaca Mobil Depan | E73: 1 | F73: 600000 | G73: =E73*F73 -> 600000 | I73: =G73-H73 -> 600000 | J73: =I73 -> 600000 | K73: P. Dimas | L73: +62 813-1457-8229 | O73: Tangerang | P73: GOOGLE
A74: 45738 | B74: C250043 | C74: OTH-SERLMB | D74: =IFERROR(VLOOKUP(C74,Stock,3,FALSE),"") -> Lembur | E74: 1 | F74: 100000 | G74: =E74*F74 -> 100000 | I74: =G74-H74 -> 100000 | J74: =I74 -> 100000 | K74: P. Dimas | L74: +62 813-1457-8229 | O74: Tangerang | P74: GOOGLE
A75: 45739 | B75: C250044 | C75: RDL-FORTUNER15AGC | D75: =IFERROR(VLOOKUP(C75,Stock,3,FALSE),"") -> Toyota Fortuner 15- 2nd Gen (Toyota) | E75: 1 | F75: 1232000 | G75: =E75*F75 -> 1232000 | I75: =G75-H75 -> 1232000 | J75: =I75 -> 1232000 | K75: Marsela Agustia | L75: +62 852-1628-2248 | O75: Tangerang | P75: GOOGLE | T75: 246400
A76: 45741 | B76: C250045 | C76: TRW-RUSH17HMU | D76: =IFERROR(VLOOKUP(C76,Stock,3,FALSE),"") -> Toyota Rush / Terios 18- | E76: 1 | F76: 1038000 | G76: =E76*F76 -> 1038000 | I76: =G76-H76 -> 1038000 | J76: =I76 -> 1038000 | K76: Galih Sugiharto | L76: +62823-2215-0999 | N76: B 2810 TIC | O76: Tangerang | P76: GOOGLE
A77: 45740 | B77: C250046 | C77: LFW-CARRY19MU | D77: =IFERROR(VLOOKUP(C77,Stock,3,FALSE),"") -> Suzuki Carry New 19- | E77: 1 | F77: 1200000 | G77: =E77*F77 -> 1200000 | I77: =G77-H77 -> 1200000 | J77: =I77 -> 1200000 | K77: P. Syarip | L77: +62 858-8230-7698 | O77: Serpong | P77: GOOGLE | T77: 1200000 | X77: cici
A78: 45740 | B78: C250046 | C78: OTH-SERTRANSPORT | D78: =IFERROR(VLOOKUP(C78,Stock,3,FALSE),"") -> Transport | E78: 1 | F78: 100000 | G78: =E78*F78 -> 100000 | I78: =G78-H78 -> 100000 | J78: =I78 -> 100000 | K78: P. Syarip | L78: +62 858-8230-7698 | O78: Serpong | P78: GOOGLE | T78: 100000 | X78: cici
A79: 45736 | B79: C250047 | C79: LFW-QQ03MU | D79: =IFERROR(VLOOKUP(C79,Stock,3,FALSE),"") -> Chery QQ 03-15 S11 5D / Spark 98-05 | E79: 1 | F79: 1690000 | G79: =E79*F79 -> 1690000 | I79: =G79-H79 -> 1690000 | J79: =I79 -> 1690000 | K79: Budi | L79: +62 812-8222-2514 | N79: B 7050 KI | O79: Slipi | P79: GOOGLE | T79: 1690000
A80: 45741 | B80: C250048 | C80: OTH-RPLXLFW | D80: =IFERROR(VLOOKUP(C80,Stock,3,FALSE),"") -> Bongkar Pasang Kaca Mobil Depan | E80: 1 | F80: 500000 | G80: =E80*F80 -> 500000 | I80: =G80-H80 -> 500000 | J80: =I80 -> 500000 | K80: Dudi D | L80: 0816968161 | N80: N 1266 GN | O80: Bintaro | P80: GOOGLE | Q80: 500000 | X80: cici
A81: 45741 | B81: C250048 | C81: OTH-SERTRANSPORT | D81: =IFERROR(VLOOKUP(C81,Stock,3,FALSE),"") -> Transport | E81: 1 | F81: 250000 | G81: =E81*F81 -> 250000 | I81: =G81-H81 -> 250000 | J81: =I81 -> 250000 | K81: Dudi D | L81: 0816968161 | N81: N 1266 GN | O81: Bintaro | P81: GOOGLE | Q81: 250000 | X81: cici
A82: 45731 | B82: C250049 | C82: VOID | D82: =IFERROR(VLOOKUP(C82,Stock,3,FALSE),"") | G82: =E82*F82 -> 0 | I82: =G82-H82 -> 0 | J82: =I82 -> 0 | P82: GOOGLE
A83: 45742 | B83: C250050 | C83: LFW-SIRION18XYG | D83: =IFERROR(VLOOKUP(C83,Stock,3,FALSE),"") -> Daihatsu Sirion 18- 3rd Gen | E83: 1 | F83: 1750000 | G83: =E83*F83 -> 1750000 | I83: =G83-H83 -> 1750000 | J83: =I83 -> 1750000 | K83: Avril | L83: 081315058684 | N83: KT 1864 YB | O83: Bintaro | P83: GOOGLE
A84: 45742 | B84: C250051 | C84: LFW-CRV02XYG | D84: =IFERROR(VLOOKUP(C84,Stock,3,FALSE),"") -> Honda CR-V 02-04 2nd Gen (Spion Jepit) | E84: 1 | F84: 1832000 | G84: =E84*F84 -> 1832000 | I84: =G84-H84 -> 1832000 | J84: =I84 -> 1832000 | K84: Edward | L84: 081212226862 | N84: KB 1376 QN | O84: Alam Sutra | P84: GOOGLE | T84: 1832000
A85: 45742 | B85: C250051 | C85: OTH-SERTRANSPORT | D85: =IFERROR(VLOOKUP(C85,Stock,3,FALSE),"") -> Transport | E85: 1 | F85: 50000 | G85: =E85*F85 -> 50000 | I85: =G85-H85 -> 50000 | J85: =I85 -> 50000 | K85: Edward | L85: 081212226862 | N85: KB 1376 QN | O85: Alam Sutra | P85: GOOGLE | T85: 50000
A86: 45743 | B86: C250052 | C86: LFW-DYNAMU | D86: =IFERROR(VLOOKUP(C86,Stock,3,FALSE),"") -> Toyota Dyna/Hino Dutro 00- | E86: 1 | F86: 1250000 | G86: =E86*F86 -> 1250000 | I86: =G86-H86 -> 1250000 | J86: =I86 -> 1250000 | K86: Ervan Wijaya | L86: +62 822-6038-3843 | O86: Duri | P86: GOOGLE
A87: 45743 | B87: C250052 | C87: OTH-SERTRANSPORT | D87: =IFERROR(VLOOKUP(C87,Stock,3,FALSE),"") -> Transport | E87: 1 | F87: 200000 | G87: =E87*F87 -> 200000 | I87: =G87-H87 -> 200000 | J87: =I87 -> 200000 | K87: Ervan Wijaya | L87: +62 822-6038-3843 | O87: Duri | P87: GOOGLE
A88: 45743 | B88: C250053 | C88: LFW-AVANZA16MU | D88: =IFERROR(VLOOKUP(C88,Stock,3,FALSE),"") | E88: 1 | F88: 1050000 | G88: =E88*F88 -> 1050000 | I88: =G88-H88 -> 1050000 | J88: =I88 -> 1050000 | K88: Bp RW Adang | L88: +62 858-8127-4993 | O88: Depok | P88: GOOGLE | T88: 100000 | X88: lia
A89: 45743 | B89: C250053 | C89: OTH-SERTRANSPORT | D89: =IFERROR(VLOOKUP(C89,Stock,3,FALSE),"") -> Transport | E89: 1 | F89: 150000 | G89: =E89*F89 -> 150000 | I89: =G89-H89 -> 150000 | J89: =I89 -> 150000 | K89: Bp RW Adang | L89: +62 858-8127-4993 | O89: Depok | P89: GOOGLE | X89: lia
A90: 45744 | B90: C250054 | C90: TRW-MOBILIOXYG | D90: =IFERROR(VLOOKUP(C90,Stock,3,FALSE),"") -> Honda Mobilio 14- | E90: 1 | F90: 1151000 | G90: =E90*F90 -> 1151000 | I90: =G90-H90 -> 1151000 | J90: =I90 -> 1151000 | K90: Een Yulia | L90: +62 818‑698‑181‬ | O90: Ruko | P90: GOOGLE | T90: 1151000 | X90: cici
A91: 45754 | B91: D250001 | C91: LFW-FREEDAGC | D91: =IFERROR(VLOOKUP(C91,Stock,3,FALSE),"") -> Honda Freed 08-16 1st Gen (Honda) | E91: 1 | F91: 3422000 | G91: =E91*F91 -> 3422000 | I91: =G91-H91 -> 3422000 | J91: =I91 -> 3422000 | K91: Deni Purbaya | L91: +62 852-6533-2039 | O91: Tangerang | P91: GOOGLE | T91: 1071600 | X91: lia
A92: 45754 | B92: D250001 | C92: OTH-SERTRANSPORT | D92: =IFERROR(VLOOKUP(C92,Stock,3,FALSE),"") -> Transport | E92: 1 | F92: 150000 | G92: =E92*F92 -> 150000 | I92: =G92-H92 -> 150000 | J92: =I92 -> 150000 | K92: Deni Purbaya | L92: +62 852-6533-2039 | O92: Tangerang | P92: GOOGLE | X92: lia
A93: 45755 | B93: D250002 | C93: TRW-T30XYG | D93: =IFERROR(VLOOKUP(C93,Stock,3,FALSE),"") -> Nissan X-Trail 01-07 T30 | E93: 1 | F93: 1950000 | G93: =E93*F93 -> 1950000 | I93: =G93-H93 -> 1950000 | J93: =I93 -> 1950000 | K93: P. Aby | L93: +62 895-4117-48269 | O93: Tangerang | P93: GOOGLE | T93: 1950000 | X93: lia
A94: 45756 | B94: D250003 | C94: TRW-FREEDXYG | D94: =IFERROR(VLOOKUP(C94,Stock,3,FALSE),"") -> Honda Freed 08-16 1st gen | E94: 1 | F94: 1496000 | G94: =E94*F94 -> 1496000 | I94: =G94-H94 -> 1496000 | J94: =I94 -> 1496000 | K94: Kak Desy | L94: +62 818-953-621 | O94: Tangerang | P94: GOOGLE | T94: 1496000 | X94: lia
A95: 45756 | B95: D250004 | C95: RDR-INNOVA15ASH | D95: =IFERROR(VLOOKUP(C95,Stock,3,FALSE),"") -> Toyota Innova 15- 2nd Gen | E95: 1 | F95: 650000 | G95: =E95*F95 -> 650000 | I95: =G95-H95 -> 650000 | J95: =I95 -> 650000 | K95: P. Anton | L95: +62 812-9310-506 | O95: Tangerang | P95: GOOGLE | T95: 650000 | X95: via
A96: 45757 | B96: D250005 | C96: LFW-FE700MU | D96: =IFERROR(VLOOKUP(C96,Stock,3,FALSE),"") -> Mitsubishi Canter FE700 01- (PS110,125) | E96: 1 | F96: 1194000 | G96: =E96*F96 -> 1194000 | I96: =G96-H96 -> 1194000 | J96: =I96 -> 1194000 | K96: P. Han | L96: +62 813-8696-5008 | N96: B 9403 BDC | O96: Jakarta Barat | P96: GOOGLE | T96: 1194000 | X96: via
A97: 45757 | B97: D250005 | C97: OTH-SERTRANSPORT | D97: =IFERROR(VLOOKUP(C97,Stock,3,FALSE),"") -> Transport | E97: 1 | F97: 200000 | G97: =E97*F97 -> 200000 | I97: =G97-H97 -> 200000 | J97: =I97 -> 200000 | K97: P. Han | L97: +62 813-8696-5008 | N97: B 9403 BDC | O97: Jakarta Barat | P97: GOOGLE | T97: 200000 | X97: via
A98: 45757 | B98: D250006 | C98: SRR-HIACEFXYG | D98: =IFERROR(VLOOKUP(C98,Stock,3,FALSE),"") -> Toyota Hi-Ace 04-20 Commuter With Frame | E98: 1 | F98: 2695000 | G98: =E98*F98 -> 2695000 | I98: =G98-H98 -> 2695000 | J98: =I98 -> 2695000 | K98: Robani | L98: +62 813‑8304‑5660‬‬ | O98: Tangerang | P98: GOOGLE | T98: 539000
A99: 45758 | B99: D250007 | C99: LFW-AGYA13MU | D99: =IFERROR(VLOOKUP(C99,Stock,3,FALSE),"") -> Toyota Agya/Ayla 13-22 1st Gen | E99: 1 | F99: 1050000 | G99: =E99*F99 -> 1050000 | I99: =G99-H99 -> 1050000 | J99: =I99 -> 1050000 | K99: P. Yanto | L99: +62 812-9757-6252 | N99: B 2526 UFU | O99: Tangerang | P99: GOOGLE | T99: 1050000 | X99: LIA
A100: 45758 | B100: D250008 | C100: LFW-CRV17XYG | D100: =IFERROR(VLOOKUP(C100,Stock,3,FALSE),"") -> Honda CR-V 17- 5th Gen | E100: 1 | F100: 2050000 | G100: =E100*F100 -> 2050000 | I100: =G100-H100 -> 2050000 | J100: =I100 -> 2050000 | K100: P. Dekri | L100: +62 831‑4596‑1281‬‬ | N100: BE 1047 DY | O100: Tangerang | P100: GOOGLE | T100: 2050000
A101: 45759 | B101: D250009 | C101: OTH-CKC | D101: =IFERROR(VLOOKUP(C101,Stock,3,FALSE),"") -> Biaya Pengecekan | E101: 1 | F101: 300000 | G101: =E101*F101 -> 300000 | I101: =G101-H101 -> 300000 | J101: =I101 -> 300000 | K101: P. Daniel | L101: +62 811-9714-853 | O101: Tangerang | P101: GOOGLE | T101: 300000 | X101: via
...

Sheet Copy of Copy of INV VIRTUAL AME
A1: SENTRA AUTOGLASS TANGERANG | J1: Tanggal | L1: 46132
A2: Ruko Permata Niaga II No. 17, Taman Royal I, Tanah Tinggi, Kota Tangerang 15119 | J2: Kepada Yth.
A3: (+62) 81288009878 | (+62) 81281161200
J4: +62 858-1000-8154
J5: Tangerang
D8: NOTA PENJUALAN
A10: INV | B10: D260129 | J10: NO POL
A11: No | B11: Kode | C11: Nama Barang | H11: Qty | J11: Harga Satuan | L11: Jumlah
A12: 1 | B12: LFW-VOXY17XYG | C12: =IFERROR(VLOOKUP(B12,Stock,3,FALSE),"") -> Toyota Voxy 17- | H12: 1 | I12: PC | J12: 3326000 | L12: =H12*J12 -> 3326000
A13: 2 | B13: FDL-VOXY17AGC | C13: =IFERROR(VLOOKUP(B13,Stock,3,FALSE),"") | H13: 1 | I13: x | J13: 2004000 | L13: =H13*J13 -> 2004000
A14: 3 | C14: =IFERROR(VLOOKUP(B14,Stock,3,FALSE),"") | L14: =H14*J14 -> 0
A15: 4 | C15: =IFERROR(VLOOKUP(B15,Stock,3,FALSE),"") | L15: =H15*J15 -> 0
A16: 5 | C16: =IFERROR(VLOOKUP(B16,Stock,3,FALSE),"") | L16: =H16*J16 -> 0
A17: 6 | C17: =IFERROR(VLOOKUP(B17,Stock,3,FALSE),"") | L17: =H17*J17 -> 0
A18: BCA 5781177611 an Adrian Kurniawan | K18: TOTAL | L18: =SUM(L12:L17) -> 5330000
K19: DP | L19: 0
E20: Kaca yang sudah dipesan/dipasang tidak dapat dibatalkan/dikembalikan. Tidak ada garansi kaca. | K20: DISKON | L20: 0
K21: NETTO | L21: =L18-L19-L20 -> 5330000
K23: Ket
A24: Trust the Experts, Drive Safer and Clearer

Sheet Copy of INV VIRTUAL AMEL 2 1
A1: SENTRA AUTOGLASS TANGERANG | J1: Tanggal | L1: 46132
A2: Ruko Permata Niaga II No. 17, Taman Royal I, Tanah Tinggi, Kota Tangerang 15119 | J2: Kepada Yth.
A3: (+62) 81288009878 | (+62) 81281161200
J4: +62 858-1000-8154
J5: Tangerang
D8: NOTA PENJUALAN
A10: INV | B10: D260129 | J10: NO POL
A11: No | B11: Kode | C11: Nama Barang | H11: Qty | J11: Harga Satuan | L11: Jumlah
A12: 1 | B12: LFW-VOXY17XYG | C12: =IFERROR(VLOOKUP(B12,Stock,3,FALSE),"") -> Toyota Voxy 17- | H12: 1 | I12: PC | J12: 3326000 | L12: =H12*J12 -> 3326000
A13: 2 | B13: FDL-VOXY17AGC | C13: =IFERROR(VLOOKUP(B13,Stock,3,FALSE),"") | H13: 1 | I13: x | J13: 2004000 | L13: =H13*J13 -> 2004000
A14: 3 | C14: =IFERROR(VLOOKUP(B14,Stock,3,FALSE),"") | L14: =H14*J14 -> 0
A15: 4 | C15: =IFERROR(VLOOKUP(B15,Stock,3,FALSE),"") | L15: =H15*J15 -> 0
A16: 5 | C16: =IFERROR(VLOOKUP(B16,Stock,3,FALSE),"") | L16: =H16*J16 -> 0
A17: 6 | C17: =IFERROR(VLOOKUP(B17,Stock,3,FALSE),"") | L17: =H17*J17 -> 0
A18: BCA 5781177611 an Adrian Kurniawan | K18: TOTAL | L18: =SUM(L12:L17) -> 5330000
K19: DP | L19: 0
E20: Kaca yang sudah dipesan/dipasang tidak dapat dibatalkan/dikembalikan. Tidak ada garansi kaca. | K20: DISKON | L20: 0
K21: NETTO | L21: =L18-L19-L20 -> 5330000
K23: Ket
A24: Trust the Experts, Drive Safer and Clearer

Sheet tanda terima dp
A1: Tanda Terima Pembayaran
A4: NO | B4: PENJUALAN | C4: NOMINAL
A5: 1 | B5: Tanda Jadi D260113 TRW-VIOS02XYG | C5: 100000
B9: TOTAL | C9: =SUM(C5:C8) -> 100000
B11: Tangerang, 18 April 2026
A13: Trust the Experts, Drive Safer and Clearer

Sheet Copy of INV VIRTUAL AMEL 2
A1: SENTRA AUTOGLASS TANGERANG | J1: Tanggal | L1: 46130
A2: Ruko Permata Niaga II No. 17, Taman Royal I, Tanah Tinggi, Kota Tangerang 15119 | J2: Kepada Yth.
A3: (+62) 81288009878 | (+62) 81281161200 | J3: Iko/Reza
J4: +62 822-2937-5656
J5: Tangerang
D8: NOTA PENJUALAN
A10: INV | B10: D260115 | J10: NO POL
A11: No | B11: Kode | C11: Nama Barang | H11: Qty | J11: Harga Satuan | L11: Jumlah
A12: 1 | B12: LFW-QUESTERXYG | C12: =IFERROR(VLOOKUP(B12,Stock,3,FALSE),"") -> Nissan Quester / Cw445 Quon 05- | H12: 2 | I12: PC | J12: 2469000 | L12: =H12*J12 -> 4938000
A13: 2 | B13: LFW-AXORXYG | C13: =IFERROR(VLOOKUP(B13,Stock,3,FALSE),"") -> Mers-Benz Axor 98- Truck | H13: 1 | I13: PC | J13: 2199000 | L13: =H13*J13 -> 2199000
A14: 3 | B14: OTH-SERTRANSPORT | C14: =IFERROR(VLOOKUP(B14,Stock,3,FALSE),"") -> Transport | H14: 1 | I14: x | J14: 1100000 | L14: =H14*J14 -> 1100000
A15: 4 | C15: =IFERROR(VLOOKUP(B15,Stock,3,FALSE),"") | L15: =H15*J15 -> 0
A16: 5 | C16: =IFERROR(VLOOKUP(B16,Stock,3,FALSE),"") | L16: =H16*J16 -> 0
A17: 6 | C17: =IFERROR(VLOOKUP(B17,Stock,3,FALSE),"") | L17: =H17*J17 -> 0
A18: BCA 5781177611 an Adrian Kurniawan | K18: TOTAL | L18: =SUM(L12:L17) -> 8237000
K19: DP | L19: 3000000
E20: Kaca yang sudah dipesan/dipasang tidak dapat dibatalkan/dikembalikan. Tidak ada garansi kaca. | K20: DISKON | L20: 0
K21: NETTO | L21: =L18-L19-L20 -> 5237000
K23: Ket
A24: Trust the Experts, Drive Safer and Clearer

Sheet INV SALSA
A1: SENTRA AUTOGLASS TANGERANG | J1: Tanggal | L1: 46139
A2: Ruko Permata Niaga II No. 17, Taman Royal I, Tanah Tinggi, Kota Tangerang 15119 | J2: Kepada Yth.
A3: (+62) 81288009878 | (+62) 81281161200 | J3: Melissa
J4: +62 813-8605-9107
D8: NOTA PENJUALAN
A10: INV | B10: D260167 | J10: NO POL
A11: No | B11: Kode | C11: Nama Barang | H11: Qty | J11: Harga Satuan | L11: Jumlah
A12: 1 | B12: TRW-INNOVA15XYG | C12: =IFERROR(VLOOKUP(B12,Stock,3,FALSE),"") -> Toyota Innova 15- 2nd Gen | H12: 1 | I12: PC | J12: 1199000 | L12: =H12*J12 -> 1199000
A13: 2 | B13: OTH-SERTRANSPORT | C13: =IFERROR(VLOOKUP(B13,Stock,3,FALSE),"") -> Transport | H13: 1 | I13: X | J13: 100000 | L13: =H13*J13 -> 100000
A14: 3 | C14: =IFERROR(VLOOKUP(B14,Stock,3,FALSE),"") | L14: =H14*J14 -> 0
A15: 4 | C15: =IFERROR(VLOOKUP(B15,Stock,3,FALSE),"") | L15: =H15*J15 -> 0
A16: 5 | C16: =IFERROR(VLOOKUP(B16,Stock,3,FALSE),"") | L16: =H16*J16 -> 0
A17: 6 | C17: =IFERROR(VLOOKUP(B17,Stock,3,FALSE),"") | L17: =H17*J17 -> 0
A18: BCA 5781177611 an Adrian Kurniawan | K18: TOTAL | L18: =SUM(L12:L17) -> 1299000
K19: DP | L19: 100000
E20: Kaca yang sudah dipesan/dipasang tidak dapat dibatalkan/dikembalikan. Tidak ada garansi kaca. | K20: DISKON | L20: 0
K21: NETTO | L21: =L18-L19-L20 -> 1199000
K23: Ket
A24: Trust the Experts, Drive Safer and Clearer

Sheet Copy of INV SALSA
A1: SENTRA AUTOGLASS TANGERANG | J1: Tanggal | L1: 46137
A2: Ruko Permata Niaga II No. 17, Taman Royal I, Tanah Tinggi, Kota Tangerang 15119 | J2: Kepada Yth.
A3: (+62) 81288009878 | (+62) 81281161200 | J3: Satria Dwi Kusuma
J4: 62 812-8771-8773
D8: NOTA PENJUALAN
A10: INV | B10: D260164 | J10: NO POL | L10: B 1189 JFW
A11: No | B11: Kode | C11: Nama Barang | H11: Qty | J11: Harga Satuan | L11: Jumlah
A12: 1 | B12: RDL-BRV22ASH | C12: Honda BR-V 22- 2nd Gen | H12: 1 | I12: PC | J12: 650000 | L12: =H12*J12 -> 650000
A13: 2 | B13: FILM-60STD | C13: Automotive Film Standard - Black 60% | H13: 1 | I13: PC | J13: 200000 | L13: =H13*J13 -> 200000
A14: 3 | B14: OTH-SERTRANSPORT | C14: =IFERROR(VLOOKUP(B14,Stock,3,FALSE),"") -> Transport | H14: 1 | I14: X | J14: 75000 | L14: =H14*J14 -> 75000
A15: 4 | C15: =IFERROR(VLOOKUP(B15,Stock,3,FALSE),"") | L15: =H15*J15 -> 0
A16: 5 | C16: =IFERROR(VLOOKUP(B16,Stock,3,FALSE),"") | L16: =H16*J16 -> 0
A17: 6 | C17: =IFERROR(VLOOKUP(B17,Stock,3,FALSE),"") | L17: =H17*J17 -> 0
A18: BCA 5781177611 an Adrian Kurniawan | K18: TOTAL | L18: =SUM(L12:L17) -> 925000
K19: DP | L19: 100000
E20: Kaca yang sudah dipesan/dipasang tidak dapat dibatalkan/dikembalikan. Tidak ada garansi kaca. | K20: DISKON | L20: 0
K21: NETTO | L21: =L18-L19-L20 -> 825000
K23: Ket
A24: Trust the Experts, Drive Safer and Clearer

Sheet INV VIRTUAL VISCA
A1: SENTRA AUTOGLASS TANGERANG | J1: Tanggal | L1: 46118
A2: Ruko Permata Niaga II No. 17, Taman Royal I, Tanah Tinggi, Kota Tangerang 15119 | J2: Kepada Yth.
A3: (+62) 81288009878 | (+62) 81281161200
D8: NOTA PENJUALAN
A10: INV | B10: D260116 | J10: NO POL
A11: No | B11: Kode | C11: Nama Barang | H11: Qty | J11: Harga Satuan | L11: Jumlah
A12: 1 | C12: =IFERROR(VLOOKUP(B12,Stock,3,FALSE),"") | H12: 1 | I12: PC | L12: =H12*J12 -> 0
A13: 2 | C13: =IFERROR(VLOOKUP(B13,Stock,3,FALSE),"") | L13: =H13*J13 -> 0
A14: 3 | C14: =IFERROR(VLOOKUP(B14,Stock,3,FALSE),"") | L14: =H14*J14 -> 0
A15: 4 | C15: =IFERROR(VLOOKUP(B15,Stock,3,FALSE),"") | L15: =H15*J15 -> 0
A16: 5 | L16: =H16*J16 -> 0
A17: 6
A18: BCA 5781177611 an Adrian Kurniawan | K18: TOTAL | L18: =SUM(L12:L17) -> 0
A19: Hormat Kami, | K19: DP | L19: 0 | P19: ='Current Stock'!O1414
E20: Kaca yang sudah dipesan/dipasang tidak dapat dibatalkan/dikembalikan. Tidak ada garansi kaca. | K20: DISKON | L20: 0
K21: NETTO | L21: =L18-L19-L20 -> 0
K23: Ket
B26: Visca

Sheet Copy of INV VIRTUAL VISCA
A1: SENTRA AUTOGLASS TANGERANG | J1: Tanggal | L1: 46137
A2: Ruko Permata Niaga II No. 17, Taman Royal I, Tanah Tinggi, Kota Tangerang 15119 | J2: Kepada Yth.
A3: (+62) 81288009878 | (+62) 81281161200 | J3: Mulya
J4: +62 858-1004-5727
D8: NOTA PENJUALAN
A10: INV | B10: D260159 | J10: NO POL
A11: No | B11: Kode | C11: Nama Barang | H11: Qty | J11: Harga Satuan | L11: Jumlah
A12: 1 | B12: RDL-SIENTAAGC | C12: Toyota Sienta 15- | H12: 1 | I12: PC | J12: 985000 | L12: =H12*J12 -> 985000
A13: 2 | C13: =IFERROR(VLOOKUP(B13,Stock,3,FALSE),"") | L13: =H13*J13 -> 0
A14: 3 | C14: =IFERROR(VLOOKUP(B14,Stock,3,FALSE),"") | L14: =H14*J14 -> 0
A15: 4 | L15: =H15*J15 -> 0
A16: 5 | L16: =H16*J16 -> 0
A17: 6 | L17: 0
A18: BCA 5781177611 an Adrian Kurniawan | K18: TOTAL | L18: =SUM(L12:L17) -> 985000
K19: DP | L19: 492500
E20: Kaca yang sudah dipesan/dipasang tidak dapat dibatalkan/dikembalikan. Tidak ada garansi kaca. | K20: DISKON | L20: 0
K21: NETTO | L21: =L18-L19-L20 -> 492500
K23: Ket
A24: Trust the Experts, Drive Safer and Clearer | K24: DP 50%

Sheet Copy of Copy of INV VIRTUAL VIS
A1: SENTRA AUTOGLASS TANGERANG | J1: Tanggal | L1: 46134
A2: Ruko Permata Niaga II No. 17, Taman Royal I, Tanah Tinggi, Kota Tangerang 15119 | J2: Kepada Yth.
A3: (+62) 81288009878 | (+62) 81281161200 | J3: Pak Arief
J4: +62 812-8278-6940
D8: NOTA PENJUALAN
A10: INV | B10: D260149 | J10: NO POL | L10: B 2181 VVO
A11: No | B11: Kode | C11: Nama Barang | H11: Qty | J11: Harga Satuan | L11: Jumlah
A12: 1 | B12: FILM-BPSG | C12: =IFERROR(VLOOKUP(B12,Stock,3,FALSE),"") -> Black Phantom Solar Gard | H12: 1 | I12: PC | J12: 1375000 | L12: =H12*J12 -> 1375000
A13: 2 | C13: =IFERROR(VLOOKUP(B13,Stock,3,FALSE),"") | L13: =H13*J13 -> 0
A14: 3 | C14: =IFERROR(VLOOKUP(B14,Stock,3,FALSE),"") | L14: =H14*J14 -> 0
A15: 4 | L15: =H15*J15 -> 0
A16: 5 | L16: =H16*J16 -> 0
A17: 6 | L17: 0
A18: BCA 5781177611 an Adrian Kurniawan | K18: TOTAL | L18: =SUM(L12:L17) -> 1375000
K19: DP | L19: 100000
E20: Kaca yang sudah dipesan/dipasang tidak dapat dibatalkan/dikembalikan. Tidak ada garansi kaca. | K20: DISKON | L20: 0
K21: NETTO | L21: =L18-L19-L20 -> 1275000
K23: Ket
A24: Trust the Experts, Drive Safer and Clearer

Sheet INV VIRTUAL VISCA 2
A1: SENTRA AUTOGLASS TANGERANG | J1: Tanggal | L1: 46133
A2: Ruko Permata Niaga II No. 17, Taman Royal I, Tanah Tinggi, Kota Tangerang 15119 | J2: Kepada Yth.
A3: (+62) 81288009878 | (+62) 81281161200 | J3: yoga
J4: +62 857-1536-2263
D8: NOTA PENJUALAN
A10: INV | B10: D260148 | J10: NO POL | L10: B 2127 TJB
A11: No | B11: Kode | C11: Nama Barang | H11: Qty | J11: Harga Satuan | L11: Jumlah
A12: 1 | B12: LFW-SANTAFE21RS2XYG | C12: Hyundai santa Fe 18-23 (thn 21-23) (2 Sensor / /\ O) | H12: 1 | I12: PC | J12: 3800000 | L12: =H12*J12 -> 3800000
A13: 2 | B13: FILM-40STD | C13: =IFERROR(VLOOKUP(B13,Stock,3,FALSE),"") -> Automotive Film Standard - Black 40% | H13: 1 | I13: PC | J13: 450000 | L13: =H13*J13 -> 450000
A14: 3 | C14: =IFERROR(VLOOKUP(B14,Stock,3,FALSE),"") | L14: =H14*J14 -> 0
A15: 4 | L15: =H15*J15 -> 0
A16: 5 | L16: =H16*J16 -> 0
A17: 6 | L17: =H17*J17 -> 0
A18: BCA 5781177611 an Adrian Kurniawan | K18: TOTAL | L18: =SUM(L12:L17) -> 4250000
K19: DP | L19: 100000
E20: Kaca yang sudah dipesan/dipasang tidak dapat dibatalkan/dikembalikan. Tidak ada garansi kaca. | K20: DISKON | L20: 0
K21: NETTO | L21: =L18-L19-L20 -> 4150000
K23: Ket
A24: Trust the Experts, Drive Safer and Clearer

Sheet Copy of INV VIRTUAL 5
J1: Tanggal | L1: 46078
A2: Ruko Permata Niaga II No. 17, Taman Royal I, Tanah Tinggi, Kota Tangerang 15119 | J2: Kepada Yth.
A3: (+62) 81288009878 | (+62) 81281161200 | J3: dikki
J4: +62 819-3813-788;
D7: INVOICE PENJUALAN
A9: INV | B9: B260136 | J9: NO POL | L9: B 1544 BOS
A10: No | B10: Kode | C10: Nama Barang | H10: Qty | J10: Harga Satuan | L10: Jumlah
A11: 1 | B11: TRW-ALPHARD15BLACKXYG | C11: =IFERROR(VLOOKUP(B11,Stock,3,FALSE),"") -> Toyota Alphard 15-17 ANH30 3rd Gen (Hitam) | H11: 1 | I11: PC | J11: 2820000 | L11: =H11*J11 -> 2820000
A12: 2 | B12: OTH-SERTRANSPORT | C12: =IFERROR(VLOOKUP(B12,Stock,3,FALSE),"") -> Transport | H12: 1 | I12: X | J12: 150000 | L12: =H12*J12 -> 150000
A13: 3 | C13: =IFERROR(VLOOKUP(B13,Stock,3,FALSE),"") | L13: =H13*J13 -> 0
A14: 4 | C14: =IFERROR(VLOOKUP(B14,Stock,3,FALSE),"") | L14: =H14*J14 -> 0
A15: 5 | C15: =IFERROR(VLOOKUP(B15,Stock,3,FALSE),"") | L15: =H15*J15 -> 0
A16: 6 | C16: =IFERROR(VLOOKUP(B16,Stock,3,FALSE),"") | L16: =H16*J16 -> 0
A17: BCA 5781177611 an Adrian Kurniawan | K17: TOTAL | L17: =SUM(L11:L16) -> 2970000
E18: Kaca yang sudah dipesan/dipasang tidak dapat dibatalkan/dikembalikan. | K18: DISKON | L18: =SUM(L12:L17) -> 3120000
K19: DP | L19: 100000
K20: DISKON | L20: 0
K21: SISA | L21: =L17-L19-L20 -> 2870000
A23: Trust the Experts, Drive Safer and Clearer | K23: Ket

Sheet INV-Asep Saipul Milah
A1: SENTRA AUTOGLASS TANGERANG | J1: Tanggal | L1: 46085
A2: Ruko Permata Niaga II No. 17, Taman Royal I, Tanah Tinggi, Kota Tangerang 15119 | J2: Kepada Yth.
A3: (+62) 81288009878 | (+62) 81281161200 | J3: Asep Saipul Milah
J4: +62 857-2121-1537
J5: Tangerang
D8: NOTA PENJUALAN
A10: INV | B10: C260017 | J10: NO POL | L10: B 2028 VVI
A11: No | B11: Kode | C11: Nama Barang | H11: Qty | J11: Harga Satuan | L11: Jumlah
A12: 1 | B12: LFW-AVANZA16XYG | C12: =IFERROR(VLOOKUP(B12,Stock,3,FALSE),"") -> Toyota Avanza / Xenia 15-21 3rd Gen | H12: 1 | I12: PC | J12: 999000 | L12: =H12*J12 -> 999000
A13: 2 | B13: FILM-40STD | C13: =IFERROR(VLOOKUP(B13,Stock,3,FALSE),"") -> Automotive Film Standard - Black 40% | H13: 1 | I13: PC | J13: 350000 | L13: =H13*J13 -> 350000
C14: =IFERROR(VLOOKUP(B14,Stock,3,FALSE),"") | L14: =H14*J14 -> 0
C15: =IFERROR(VLOOKUP(B15,Stock,3,FALSE),"") | L15: =H15*J15 -> 0
L16: =H16*J16 -> 0
A18: BCA 5781177611 an Adrian Kurniawan | K18: TOTAL | L18: =SUM(L12:L17) -> 1349000
K19: DP | L19: 0
K20: DISKON | L20: 0
K21: NETTO | L21: =L18-L19-L20 -> 1349000
K23: Ket
A24: Trust the Experts, Drive Safer and Clearer

Sheet Copy of PROFORMA INVOICE
A1: SENTRA AUTOGLASS TANGERANG | J1: Tanggal | L1: 46080
A2: Ruko Permata Niaga II No. 17, Taman Royal I, Tanah Tinggi, Kota Tangerang 15119 | J2: Kepada Yth.
A3: (+62) 81288009878 | (+62) 81281161200 | J3: Plaza Subaru Kebon Jeruk
J4: (Plaza Auto Cipta)
J5: Jakarta
D8: PROFORMA INVOICE
A10: PI | B10: TGRB01888 | J10: NO POL | L10: -
A11: No | B11: Kode | C11: Nama Barang | H11: Qty | J11: Harga Satuan | L11: Jumlah
A12: 1 | B12: LFW-FORESTER22RS3AGC | C12: =IFERROR(VLOOKUP(B12,Stock,3,FALSE),"") -> Subaru Forester 22- (3 Sensor / /\ [] /\ ) (Subaru) | H12: 1 | I12: PC | J12: 32500000 | L12: =H12*J12 -> 32500000
B13: Windshield / Kaca Depan Subaru Forester 2.0i-S EyeSight AWD CVT 2024 JF1SK7KL5RG212291 | L13: =H13*J13 -> 0
L14: =H14*J14 -> 0
L15: =H15*J15 -> 0
L16: =H16*J16 -> 0
L17: 0
A18: Pembayaran : BCA 5781177611 an Adrian Kurniawan | K18: TOTAL | L18: 32500000
K19: DISKON | L19: 550000
A20: Keterangan | K20: NETTO | L20: =L18-L19 -> 31950000
A21: - Produk yang ditawarkan merupakan Genuine / Original Automotive Glass berlogo resmi, disesuaikan berdasarkan VIN kendaraan untuk memastikan kesesuaian part. - Validitas penawaran berlaku selama 7 (tujuh) hari sejak tanggal surat ini diterbitkan. - Metode Pembayaran : Tunai
J25: Trust the Experts, Drive Safer and Clearer

Sheet JADWAL
A1: Periode 1–7 Maret
A2: Nama | B2: Fokus Mingguan | C2: Tanggung Jawab Utama | D2: 1 | E2: 2 | F2: 3 | G2: 4 | H2: 5 | I2: 6 | J2: 7
A3: Putri | B3: 🟢 Finance & Reporting | C3: Cash, petty cash, laporan
A4: Visca | B4: 🔵 Marketing & Customer | C4: Konten, follow up, review
A5: Amel | B5: 🟡 Operasional & Inventory | C5: Toolbox, stok, koordinasi teknisi
A7: Periode 8–14 Maret
A8: Nama | B8: Fokus Mingguan | C8: Tanggung Jawab Utama | D8: 8 | E8: 9 | F8: 10 | G8: 11 | H8: 12 | I8: 13 | J8: 14
A9: Putri | B9: 🟡 Operasional & Inventory | C9: Toolbox, stok, koordinasi teknisi
A10: Visca | B10: 🟢 Finance & Reporting | C10: Cash, petty cash, laporan
A11: Amel | B11: 🔵 Marketing & Customer | C11: Konten, follow up, review
A13: Periode 15–21 Maret
A14: Nama | B14: Fokus Mingguan | C14: Tanggung Jawab Utama | D14: 15 | E14: 16 | F14: 17 | G14: 18 | H14: 19 | I14: 20 | J14: 21
A15: Putri | B15: 🔵 Marketing & Customer | C15: Konten, follow up, review
A16: Visca | B16: 🟡 Operasional & Inventory | C16: Toolbox, stok, koordinasi teknisi
A17: Amel | B17: 🟢 Finance & Reporting | C17: Cash, petty cash, laporan
A19: Periode 25-31 Maret
A20: Nama | B20: Fokus Mingguan | C20: Tanggung Jawab Utama | D20: 1 | E20: 2 | F20: 3 | G20: 4 | H20: 5 | I20: 6 | J20: 7
A21: Putri | B21: 🟢 Finance & Reporting | C21: Cash, petty cash, laporan
A22: Visca | B22: 🔵 Marketing & Customer | C22: Konten, follow up, review
A23: Amel | B23: 🟡 Operasional & Inventory | C23: Toolbox, stok, koordinasi teknisi
A27: Job Desc Tiap Role | B27: Tanggung Jawab | C27: Laporan | D27: Kontrol
A28: 🟢 Finance | B28: 💰 Cash & Keuangan - Terima uang cash dari customer - Input petty cash - Cocokkan total nota vs uang masuk - Simpan uang di dompet kas dengan rapi | C28: - Buat laporan penjualan harian - Buat laporan pembelian barang - Kirim laporan ke atasan sebelum tutup - Setor uang kasir | D28: - Pastikan tidak ada nota yang belum masuk sistem - Pastikan selisih kas = 0
A29: 🟡 Operasional & Inventory | B29: 📦 Inventory - Cek toolbox dengan teknisi setiap pagi/sore - Catat pengambilan inventory - Pastikan stok fast moving aman - Laporkan jika ada stok menipis - Selalu paling update posisi tim dan kondisi tim - Membuat SJ dan input barang datang/keluar - Pengecekan barang masuk/keluar - Pastikan barang pembelian sesuai fisik - Cek dokumentasi pemasangan (before-after) - Pengecekan SPK | C29: 🔧 Koordinasi Teknis - Update kebutuhan teknisi - Update tugas teknisi
A30: 🔵 Marketing & Customer | B30: 📱 Konten & Sosial Media - Upload story WA status setiap hari - Upload story Instagram setiap hari - Posting kegiatan cabang 💬 Customer - Follow up customer pending - Balas DM dan chat (PIC Utama) - Ingatkan customer untuk kasih review | C30: ⭐ Review Target Rekap review harian Pastikan tidak ada hari kosong tanpa review

Sheet Petty Cash
A1: 1 | K1: POS KAS
A2: NO | B2: Tanggal | C2: Nama | D2: Ket | E2: Debit | F2: Kredit | G2: Sisa | H2: Input by | I2: Terima uang | J2: Cek | K2: Transportasi | L2: Perlengkapan Workshop | M2: Administrasi & Kantor , Inventory | N2: Konsumsi | O2: Perawatan Fasilitas | P2: Biaya Tak terduga
A3: 1 | B3: 45913 | C3: Uang Masuk | E3: 500000 | G3: =E3-F3 -> 500000 | H3: CICI | I3: THARINA | J3: CICI
A4: 2 | B4: 45913 | C4: Perlengkapan Workshop - TB SURYA | D4: Paku 3kg | F4: 48000 | G4: =G3+E4-F4 -> 452000 | H4: Tharina | I4: ko Rian | L4: 48000
A5: 3 | B5: 45918 | C5: Perlengkapan Workshop - Lucky Seven | D5: Galon atas | F5: 6000 | G5: =G4+E5-F5 -> 446000 | H5: Tharina | I5: Guntur | N5: 6000
A6: 4 | B6: 45918 | C6: Perlengkapan Workshop - Yupiter | D6: Galon bawah | F6: 20000 | G6: =G5+E6-F6 -> 426000 | H6: Tharina | I6: Guntur | N6: 20000
A7: 5 | B7: 45923 | C7: Parkir saat home service | D7: 2 lokasi (Rp 5.000 dan Rp 4.000) | F7: 9000 | G7: =G6+E7-F7 -> 417000 | H7: Tharina | I7: Pavel | K7: 9000
A8: 6 | B8: 45923 | C8: Perlengkapan workshop - Indomaret | D8: Shampoo | F8: 17900 | G8: =G7+E8-F8 -> 399100 | H8: Tharina | I8: Pavel | O8: 17900
A9: 7 | B9: 45923 | C9: Perlengkapan workshop - Indomaret | D9: Sabun | F9: 19000 | G9: =G8+E9-F9 -> 380100 | H9: Tharina | I9: Pavel | O9: 19000
A10: 8 | B10: 45924 | C10: Perlengkapan workshop - Mobil | D10: Bensin | F10: 300000 | G10: =G9+E10-F10 -> 80100 | H10: Tharina | I10: Guntur | K10: 300000
A11: 9 | B11: 45924 | C11: Uang masuk | E11: 500000 | G11: =G10+E11-F11 -> 580100 | H11: Tharina | I11: Tharina
A12: 10 | B12: 45924 | C12: Gojek send | D12: LMB ke TGR | F12: 30000 | G12: =G11+E12-F12 -> 550100 | H12: Tharina | I12: Gojek | K12: 30000
A13: 11 | B13: 45924 | C13: Gocar send | D13: BGI ke TGR | F13: 32000 | G13: =G12+E13-F13 -> 518100 | H13: Tharina | I13: Gocar | K13: 32000
A14: 12 | B14: 45924 | C14: Perlengkapan workshop - Talago | D14: HVS 1 rim | F14: 52000 | G14: =G13+E14-F14 -> 466100 | H14: Tharina | I14: Yansyah | M14: 52000
A15: 13 | B15: 45925 | C15: Perlengkapan workshop - Motor | D15: Bensin | F15: 70000 | G15: =G14+E15-F15 -> 396100 | H15: Tharina | I15: Yansyah | K15: 70000
A16: 14 | B16: 45925 | C16: Perlengkapan Workshop - Lucky Seven | D16: Galon bawah | F16: 6000 | G16: =G15+E16-F16 -> 390100 | H16: Tharina | I16: Guntur | N16: 6000
A17: 15 | B17: 45925 | C17: Perlengkapan workshop - Mobil | D17: LMB ke TGR | F17: 51000 | G17: =G16+E17-F17 -> 339100 | H17: Tharina | I17: Gocar | K17: 51000
A18: 16 | B18: 45926 | C18: Perlengkapan workshop - Motor | D18: Benerin rante | F18: 10000 | G18: =G17+E18-F18 -> 329100 | H18: Tharina | I18: Agung | P18: 10000
A19: 17 | B19: 45926 | C19: Gocar send | D19: BGI ke TGR | F19: 35000 | G19: =G18+E19-F19 -> 294100 | H19: Tharina | I19: Gocar | K19: 35000
A20: 18 | B20: 45927 | C20: Perlengkapan workshop - Mobil | D20: Bensin | F20: 290000 | G20: =G19+E20-F20 -> 4100 | H20: Tharina | I20: Gocar | K20: 290000
A21: 19 | B21: 45929 | C21: Uang masuk | E21: 500000 | G21: =G20+E21-F21 -> 504100 | H21: Tharina | I21: Tharina
A22: 20 | B22: 45929 | C22: Perlengkapan Workshop - Indomaret | D22: Prostek | F22: 19400 | G22: =G21+E22-F22 -> 484700 | H22: Tharina | I22: Pavel | O22: 19400
A23: 21 | B23: 45931 | C23: Gojek send | D23: MOS ke TGR | F23: 68000 | G23: =G22+E23-F23 -> 416700 | H23: Tharina | I23: ko Rian | K23: 68000
A24: 22 | B24: 45931 | C24: Gojek send | D24: LMB ke TGR | F24: 32500 | G24: =G23+E24-F24 -> 384200 | H24: Tharina | I24: Gojek | K24: 32500
A25: 23 | B25: 45931 | C25: Gocar send | D25: LMB ke TGR | F25: 52000 | G25: =G24+E25-F25 -> 332200 | H25: Tharina | I25: Gocar | K25: 52000
A26: 24 | B26: 45932 | C26: Perlengkapan workshop - Indomaret | D26: Galon | F26: 42000 | G26: =G25+E26-F26 -> 290200 | H26: Tharina | I26: ko Rian | N26: 42000
A27: 25 | B27: 45933 | C27: Gojek send | D27: TGR ke BKS | F27: 120000 | G27: =G26+E27-F27 -> 170200 | H27: Tharina | I27: Ko Rian | K27: 120000
A28: 26 | B28: 45933 | C28: Perlengkapan workshop - Motor | D28: Bensin | F28: 100000 | G28: =G27+E28-F28 -> 70200 | H28: Tharina | I28: Ko Rian | K28: 100000
A29: 27 | B29: 45933 | C29: Gojek send | D29: LMB ke TGR | F29: 33000 | G29: =G28+E29-F29 -> 37200 | H29: Tharina | I29: Ko Rian | K29: 33000
A30: 28 | B30: 45934 | C30: Uang masuk | E30: 800000 | G30: =G29+E30-F30 -> 837200 | H30: Tharina | I30: Tharina | J30: CICI
A31: 29 | B31: 45934 | C31: Perlengkapan workshop - Epoxy | D31: TB Surya | F31: 20000 | G31: =G30+E31-F31 -> 817200 | H31: Tharina | I31: Agung | L31: 20000
A32: 30 | B32: 45934 | C32: Perlengkapan workshop - Mobil | D32: Bensin | F32: 300000 | G32: =G31+E32-F32 -> 517200 | H32: Tharina | I32: Ko Rian | K32: 300000
A33: 31 | B33: 45934 | C33: Perlengkapan Workshop - Lucky Seven | D33: Galon bawah | F33: 7000 | G33: =G32+E33-F33 -> 510200 | H33: Tharina | I33: Guntur | N33: 7000
A34: 32 | B34: 45936 | C34: Perlengkapan workshop - Mobil | D34: Bensin | F34: 300000 | G34: =G33+E34-F34 -> 210200 | H34: Ko Rian | I34: Guntur | K34: 300000
A35: 33 | B35: 45936 | C35: Lalamove Van Kaca Evalia | D35: MOS ke TGR | F35: 125000 | G35: =G34+E35-F35 -> 85200 | H35: Ko Rian | I35: Guntur | K35: 125000
A36: 34 | B36: 45939 | C36: Uang Masuk | E36: 500000 | G36: =G35+E36-F36 -> 585200 | H36: Cici | I36: Ko Rian
A37: 35 | B37: 45939 | C37: Perlengkapan workshop - Mobil | D37: E-toll | F37: 200000 | G37: =G36+E37-F37 -> 385200 | H37: Ko Rian | I37: Ko Rian | K37: 300000
A38: 36 | B38: 45939 | C38: Perlengkapan workshop - Mobil | D38: Bensin | F38: 300000 | G38: =G37+E38-F38 -> 85200 | H38: Ko Rian | I38: Ko Rian | K38: 200000
A39: 37 | B39: 45940 | C39: Perlengkapan Workshop - Lucky Seven | D39: Galon atas | F39: 20000 | G39: =G38+E39-F39 -> 65200 | H39: Ko Rian | I39: Guntur | N39: 20000
A40: 38 | B40: 45941 | C40: Uang Masuk | E40: 1000000 | G40: =G39+E40-F40 -> 1065200 | H40: Ko rian | I40: ko rian
A41: 39 | B41: 45941 | C41: Perlengkapan workshop - Mobil | D41: E-toll | F41: 200000 | G41: =G40+E41-F41 -> 865200 | H41: Ko rian | I41: ko rian | K41: 200000
A42: 40 | B42: 45943 | C42: Perlengkapan workshop - Motor | D42: Bensin | F42: 100000 | G42: =G41+E42-F42 -> 765200 | H42: Ko rian | I42: Agung | K42: 100000
A43: 41 | B43: 45943 | C43: Perlengkapan workshop - Motor | D43: Gojek | F43: 65000 | G43: =G42+E43-F43 -> 700200 | H43: Tharina | I43: Gojek | K43: 65000
A44: 42 | B44: 45943 | C44: Lembur | D44: Teknisi hari minggu | F44: 275000 | G44: =G43+E44-F44 -> 425200 | H44: Tharina | I44: Teknisi
A45: 43 | B45: 45943 | C45: Perlengkapan Workshop - Lucky Seven | D45: Galon | F45: 6000 | G45: =G44+E45-F45 -> 419200 | H45: Tharina | I45: Guntur | N45: 6000
A46: 44 | B46: 45944 | C46: Perlengkapan workshop - kebersihan | D46: Super Pel | F46: 7900 | G46: =G45+E46-F46 -> 411300 | H46: Ko rian | I46: Yansyah | O46: 7900
A47: 45 | B47: 45944 | C47: Perlengkapan Workshop - Wellpack Tangerang | D47: Bubble wrap | F47: 91000 | G47: =G46+E47-F47 -> 320300 | H47: Ko rian | I47: Yansyah | L47: 91000
A48: 46 | B48: 45945 | C48: Perlengkapan workshop - Mobil | D48: E-toll | F48: 200000 | G48: =G47+E48-F48 -> 120300 | H48: Ko rian | I48: ko rian | K48: 200000
A49: 47 | B49: 45945 | C49: Uang Tips Teknisi | D49: Yansyah | F49: 45000 | G49: =G48+E49-F49 -> 75300 | H49: Ko rian | I49: Yansyah | P49: Cs Kasih Uang Tips Ke teknisi
A50: 48 | B50: 45946 | C50: Refund uang customer | D50: RDR-ALTIS | F50: 50000 | G50: =G49+E50-F50 -> 25300 | H50: Ko rian | I50: Tarina | P50: Refund
A51: 50 | B51: 45947 | C51: Gojek send | D51: MOS KE TGR | F51: 9500 | G51: =G50+E51-F51 -> 15800 | H51: Ko rian | I51: ko rian | K51: 9500
A52: 51 | B52: 45950 | C52: Uang masuk | E52: 500000 | G52: =G51+E52-F52 -> 515800 | H52: mery | I52: ko rian
A53: 52 | B53: 45950 | C53: Ganti uang kasir | D53: Terpakai untuk gojek | F53: 100000 | G53: =G52+E53-F53 -> 415800 | H53: mery | I53: ko rian | P53: 100000
A54: 53 | B54: 45950 | C54: Perlengkapan Workshop - Lucky Seven | D54: Galon atas | F54: 40000 | G54: =G53+E54-F54 -> 375800 | H54: mery | I54: Guntur | N54: 40000
A55: 54 | B55: 45950 | C55: Perlengkapan Workshop - Biru | D55: Galon bawah | F55: 9000 | G55: =G54+E55-F55 -> 366800 | H55: mery | I55: Guntur | N55: 9000
A56: 55 | B56: 45952 | C56: Perlengkapan workshop - Mobil | D56: Bensin | F56: 300000 | G56: =G55+E56-F56 -> 66800 | H56: Ko rian | I56: yayan | K56: 300000
A57: 56 | B57: 45953 | C57: Gojek send | D57: Lmb-tgr | F57: 56500 | G57: =G56+E57-F57 -> 10300 | H57: Ko rian | I57: Ko rian | K57: 56500
A58: 57 | B58: 45954 | C58: Uang masuk | E58: 1000000 | G58: =G57+E58-F58 -> 1010300 | H58: Ko rian | I58: Ko rian
A59: 58 | B59: 45954 | C59: Ganti Ban Motor | D59: Ban motor 2pcs, depan dan belakang | F59: 1007000 | G59: =G58+E59-F59 -> 3300 | H59: Ko rian | I59: Agung | P59: 1007000
A60: 59 | B60: 45957 | C60: Perlengkapan Workshop - Biru | D60: Galon bawah | F60: 6000 | G60: =G59+E60-F60 -> -2700 | H60: mery | I60: Yansyah | N60: 6000
A61: 60 | B61: 45957 | C61: Perlengkapan workshop - Mobil | D61: Bensin | F61: 300000 | G61: =G60+E61-F61 -> -302700 | H61: mery | I61: Guntur | K61: 300000
A62: 61 | B62: 45960 | C62: Uang masuk | E62: 500000 | G62: =G61+E62-F62 -> 197300 | H62: Tharina | I62: Tharina
A63: 62 | B63: 45960 | C63: Perlengkapan workshop - Mobil | D63: Gosend | F63: 40000 | G63: =G62+E63-F63 -> 157300 | H63: Tharina | I63: Gocar | K63: 40000
A64: 63 | B64: 45961 | C64: Perlengkapan workshop - Mobil | D64: Bensin | F64: 300000 | G64: =G63+E64-F64 -> -142700 | H64: Tharina | I64: Pavel | K64: 300000
A65: 64 | B65: 45962 | C65: Uang masuk | E65: 500000 | G65: =G64+E65-F65 -> 357300 | H65: Tharina | I65: Tharina
A66: 65 | B66: 45962 | C66: Lembur | D66: Jankrik alphard agung sm dimas | F66: 150000 | G66: =G65+E66-F66 -> 207300 | H66: Tharina | I66: Agung | P66: 150000
A67: 66 | B67: 45962 | C67: Perlengkapan Workshop - Lucky Seven | D67: Galon atas, 2 | F67: 40000 | G67: =G66+E67-F67 -> 167300 | H67: Tharina | I67: Guntur | N67: 40000
A68: 67 | B68: 45962 | C68: Perlengkapan workshop - Motor | D68: bensin motor thar | F68: 35000 | G68: =G67+E68-F68 -> 132300 | H68: Tharina | I68: Tharina | K68: 35000
A69: 68 | B69: 45962 | C69: Perlengkapan workshop - Motor | D69: bensin motor bekasi | F69: 28000 | G69: =G68+E69-F69 -> 104300 | H69: Tharina | I69: Tharina | K69: 28000
A70: 69 | B70: 45964 | C70: Perlengkapan workshop - Mobil | D70: E-toll | F70: 100000 | G70: =G69+E70-F70 -> 4300 | H70: Tharina | I70: Guntur | K70: 100000
A71: 70 | B71: 45965 | C71: Uang masuk : ini uang dari tgl 30/10. dimasukin 300k spya gk minus nnti. tapi uang yg ada sesuai | E71: 300000 | G71: =G70+E71-F71 -> 304300
A72: 71 | B72: 45965 | C72: Gocar send | D72: gosend mobil | F72: 255000 | G72: =G71+E72-F72 -> 49300 | H72: Tharina | I72: Ko rian | K72: 225000
A73: 72 | B73: 45965 | C73: Gocar send | D73: gosend mobil | F73: 40000 | G73: =G72+E73-F73 -> 9300 | H73: Tharina | I73: Ko rian | K73: 40000
A74: 73 | B74: 45966 | C74: Uang masuk | E74: 1000000 | G74: =G73+E74-F74 -> 1009300 | H74: Tharina | I74: Ko rian
A75: 74 | B75: 45966 | C75: Perlengkapan workshop - Mobil | D75: gosend mobil | F75: 37500 | G75: =G74+E75-F75 -> 971800 | H75: Tharina | I75: pavel
A76: 75 | B76: 45966 | C76: Perlengkapan workshop - Mobil | D76: e-toll | F76: 300000 | G76: =G75+E76-F76 -> 671800 | H76: Tharina | I76: Ko rian | K76: 300000
A77: 76 | B77: 45967 | C77: Perlengkapan workshop - Mobil | D77: Bensin Mobil | F77: 250000 | G77: =G76+E77-F77 -> 421800 | H77: Tharina | I77: Ko rian
A78: 77 | B78: 45967 | C78: Ganti cash uang di bank ko rian | F78: 244000 | G78: =G77+E78-F78 -> 177800 | H78: Tharina | I78: Ko rian
A79: 78 | B79: 45967 | C79: Perlengkapan Workshop - Biru | D79: Galon bawah | F79: 9000 | G79: =G78+E79-F79 -> 168800 | H79: Tharina | I79: guntur | N79: 10000
A80: 79 | B80: 45969 | C80: Perlengkapan workshop - Mobil | D80: Bensin Mobil | F80: 150000 | G80: =G79+E80-F80 -> 18800 | H80: Tharina | I80: guntur | K80: 150000
A81: 80 | B81: 45969 | C81: Perlengkapan workshop - Mobil | D81: Sunligt untuk cuci mobil | F81: 9500 | G81: =G80+E81-F81 -> 9300 | H81: Ko rian | I81: Guntur | O81: 9500
A82: 81 | B82: 45971 | C82: Perlengkapan workshop - Motor | D82: Bensin Motor | F82: 100000 | G82: =G81+E82-F82 -> -90700 | H82: Ko rian | I82: Guntur | K82: 100000
A83: 82 | B83: 45971 | C83: Uang masuk | E83: 500000 | G83: =G82+E83-F83 -> 409300 | H83: Tharina | I83: Tharina
A84: 83 | B84: 45972 | C84: Perlengkapan workshop - Mobil | D84: Bensin Mobil | F84: 300000 | G84: =G83+E84-F84 -> 109300 | H84: Tharina | I84: Guntur | K84: 300000
A85: 84 | B85: 45972 | C85: Perlengkapan workshop - Mobil | D85: gosend mobil | F85: 71000 | G85: =G84+E85-F85 -> 38300 | H85: Tharina | I85: Gocar | K85: 71000
A86: 85 | B86: 45973 | C86: Uang masuk | E86: 500000 | G86: =G85+E86-F86 -> 538300 | H86: Tharina | I86: Tharina
A87: 86 | B87: 45973 | C87: Perlengkapan workshop - Mobil | D87: Bensin Mobil | F87: 300000 | G87: =G86+E87-F87 -> 238300 | H87: Tharina | I87: Ko rian
A88: 87 | B88: 45975 | C88: Perlengkapan workshop - Mobil | D88: etoll | F88: 200000 | G88: =G87+E88-F88 -> 38300 | H88: Ko rian | I88: Ko rian | K88: 200000
A89: 88 | B89: 45975 | C89: Uang masuk | E89: 500000 | G89: =G88+E89-F89 -> 538300 | H89: Tharina | I89: Tharina
A90: 89 | B90: 45975 | C90: Perlengkapan workshop | D90: jas ujan | F90: 10000 | G90: =G89+E90-F90 -> 528300 | H90: Tharina | I90: dimas | P90: 10000
A91: 90 | B91: 45973 | C91: Perlengkapan workshop - Mobil | D91: etoll | F91: 200000 | G91: =G90+E91-F91 -> 328300 | H91: Ko rian | I91: Ko rian | K91: 200000
A92: 91 | B92: 45975 | C92: Jankrik | D92: Jangkrik | F92: 150000 | G92: =G91+E92-F92 -> 178300 | H92: Ko rian | I92: Pavel | P92: 150000
A93: 92 | B93: 45976 | C93: Uang Masuk | E93: 500000 | G93: =G92+E93-F93 -> 678300 | H93: Ko rian | I93: Ko rian
A94: 93 | B94: 45976 | C94: toll | D94: toll gocar kirim nano | F94: 19500 | G94: =G93+E94-F94 -> 658800 | H94: Tharina | I94: Guntur | K94: 19500
A95: 94 | B95: 45977 | C95: Perlengkapan Workshop - Motor | D95: Bensin Motor | F95: 50000 | G95: =G94+E95-F95 -> 608800 | H95: Ko rian | I95: Agung | K95: 50000
A96: 95 | B96: 45978 | C96: Perlengkapan Workshop-Mobil | D96: Etoll | F96: 200000 | G96: =G95+E96-F96 -> 408800 | H96: Ko Rian | I96: Ko Rian | K96: 200000
A97: 96 | B97: 45978 | C97: Perlengkapan Workshop - Biru | D97: Galon bawah | F97: 9000 | G97: =G96+E97-F97 -> 399800 | H97: Tharina | I97: Guntur | N97: 9000
A98: 97 | B98: 45978 | C98: Perlengkapan Workshop - Motor | D98: Bensin Motor thari | F98: 40000 | G98: =G97+E98-F98 -> 359800 | H98: Tharina | I98: tharina
A99: 98 | B99: 45979 | C99: Kembalikan uang kasir | F99: 18000 | G99: =G98+E99-F99 -> 341800 | H99: Tharina | I99: tharina
A100: 99 | B100: 45979 | C100: Gojek kirim kaca | D100: mose ke tgr | F100: 65000 | G100: =G99+E100-F100 -> 276800 | H100: Tharina | I100: gojek | K100: 65000
...

Sheet Laporan Setor
A1: LAPORAN KAS TUNAI CABANG TANGERANG
A2: Tanggal | B2: Saldo Awal | C2: Cash Masuk | D2: Cash Keluar | E2: Setoran | F2: Saldo Akhir | G2: Selisih | H2: Setor ke | I2: Input By | J2: Diterima oleh | K2: Done setor bank
A3: 46079 | B3: 125000 | C3: 1150000 | E3: 1150000 | F3: =B3+C3-D3-E3 -> 125000 | H3: rian | I3: putri | J3: RIAN | K3: sudah trf
A4: 46079 | B4: =F3 -> 125000 | C4: 2831000 | E4: 2831000 | F4: =B4+C4-D4-E4 -> 125000 | H4: rian | I4: rian | J4: rian | K4: sudah trf
A5: 46081 | B5: =F4 -> 125000 | C5: 400000 | E5: 400000 | F5: =B5+C5-D5-E5 -> 125000 | H5: rian | I5: putri | J5: rian | K5: sudah trf
A6: 46081 | B6: =F5 -> 125000 | C6: 1050000 | E6: 1050000 | F6: =B6+C6-D6-E6 -> 125000 | H6: rian | I6: putri | J6: rian | K6: sudah trf
A7: 46081 | B7: =F6 -> 125000 | C7: 1000000 | E7: 1000000 | F7: =B7+C7-D7-E7 -> 125000 | H7: rian | I7: rian | J7: rian | K7: sudah trf
A8: 46081 | B8: =F7 -> 125000 | C8: 500000 | E8: 500000 | F8: =B8+C8-D8-E8 -> 125000 | H8: rian | I8: rian | J8: rian | K8: sudah trf
A9: 46056 | B9: =F8 -> 125000 | C9: 1500000 | E9: 1500000 | F9: =B9+C9-D9-E9 -> 125000 | H9: rian | I9: putri | J9: rian | K9: sudah trf
A10: 46056 | B10: =F9 -> 125000 | C10: 525000 | E10: 525000 | F10: =B10+C10-D10-E10 -> 125000 | H10: rian | I10: putri | J10: rian | K10: sudah trf
A11: 46084 | B11: =F10 -> 125000 | C11: 818000 | E11: 818000 | F11: =B11+C11-D11-E11 -> 125000 | H11: rian | I11: putri | J11: RIAN | K11: sudah trf
A12: 46086 | B12: =F11 -> 125000 | C12: 2492000 | E12: 2492000 | F12: =B12+C12-D12-E12 -> 125000 | H12: cici | I12: putri | J12: rian | K12: sudah trf
A13: 46086 | B13: =F12 -> 125000 | C13: 1510000 | E13: 1510000 | F13: =B13+C13-D13-E13 -> 125000 | H13: rian | I13: putri | J13: rian | K13: sudah trf
A14: 46086 | B14: =F13 -> 125000 | C14: 1800000 | E14: 1800000 | F14: =B14+C14-D14-E14 -> 125000 | H14: rian | I14: putri | J14: rian | K14: sudah trf
A15: 46087 | B15: =F14 -> 125000 | C15: 350000 | E15: 350000 | F15: =B15+C15-D15-E15 -> 125000 | H15: cici | I15: putri | J15: cici | K15: sudah trf
... A47: 46108 | B47: =F46 -> 201000 | C47: 2870000 | E47: 2900000 | F47: =B47+C47-D47-E47 -> 171000 | H47: Rian | I47: putri | J47: putri | K47: setor
A48: 46109 | B48: =F47 -> 171000 | C48: 100000 | F48: =B48+C48-D48-E48 -> 271000 | H48: Rian | I48: putri | J48: putri | K48: setor
A49: 46109 | B49: =F48 -> 271000 | C49: 1550000 | E49: 1550000 | F49: =B49+C49-D49-E49 -> 271000 | H49: cici | I49: putri | J49: Rian | K49: Sudah TRF
A50: 46111 | B50: =F49 -> 271000 | C50: 1190000 | E50: 1336000 | F50: =B50+C50-D50-E50 -> 125000 | H50: Rian | I50: visca | J50: Rian | K50: Sudah TRF
A51: 46112 | B51: =F50 -> 125000 | C51: 350000 | E51: 350000 | F51: =B51+C51-D51-E51 -> 125000 | H51: Rian | I51: visca | J51: Rian | K51: Sudah TRF
A52: 46113 | B52: =F51 -> 125000 | C52: 1000000 | E52: 1000000 | F52: =B52+C52-D52-E52 -> 125000 | H52: Rian | I52: visca | J52: Rian | K52: Sudah TRF
A53: 46114 | B53: =F52 -> 125000 | C53: 2700000 | E53: 2700000 | F53: =B53+C53-D53-E53 -> 125000 | H53: Rian | I53: visca | J53: Rian | K53: Sudah TRF
A54: 46115 | B54: =F53 -> 125000 | C54: 950000 | E54: 950000 | F54: =B54+C54-D54-E54 -> 125000 | H54: Rian | I54: visca | J54: Rian | K54: Sudah TRF
A55: 46115 | B55: =F54 -> 125000 | C55: 1150000 | E55: 1150000 | F55: =B55+C55-D55-E55 -> 125000 | H55: Rian | I55: visca | J55: Rian | K55: Sudah TRF
A56: 46118 | B56: =F55 -> 125000 | C56: 1446000 | E56: 1446000 | F56: =B56+C56-D56-E56 -> 125000 | H56: Rian | I56: visca | J56: Rian | K56: Sudah TRF
A57: 46118 | B57: =F56 -> 125000 | C57: 1200000 | E57: 1200000 | F57: =B57+C57-D57-E57 -> 125000 | H57: Rian | I57: visca | J57: Rian | K57: Sudah TRF
A58: 46120 | B58: =F57 -> 125000 | C58: 1100000 | E58: 1100000 | F58: =B58+C58-D58-E58 -> 125000 | H58: Rian | I58: visca | J58: Rian | K58: Petty Cash
A59: 46122 | B59: =F58 -> 125000 | C59: 900000 | E59: 900000 | F59: =B59+C59-D59-E59 -> 125000 | I59: visca | J59: Rian | K59: Sudah TRF
A60: 46123 | B60: =F59 -> 125000 | C60: 1000000 | E60: 1000000 | F60: =B60+C60-D60-E60 -> 125000 | J60: Rian | K60: Sudah TRF
A61: 46130 | B61: =F60 -> 125000 | C61: 1722000 | E61: 1722000 | F61: =B61+C61-D61-E61 -> 125000 | I61: visca | J61: Rian | K61: Sudah TRF
A62: 46132 | B62: =F61 -> 125000 | C62: 1200000 | E62: 1200000 | F62: =B62+C62-D62-E62 -> 125000 | H62: rian | I62: rian | J62: Rian | K62: Sudah TRF
A63: 46134 | B63: =F62 -> 125000 | C63: 1823000 | E63: 1823000 | F63: =B63+C63-D63-E63 -> 125000 | I63: visca | J63: Rian | K63: Sudah TRF
A64: 46135 | B64: =F63 -> 125000 | C64: 1650000 | E64: 1650000 | F64: =B64+C64-D64-E64 -> 125000 | I64: visca | J64: Rian | K64: Sudah TRF
A65: 46136 | B65: =F64 -> 125000 | C65: 1000000 | E65: 1000000 | F65: =B65+C65-D65-E65 -> 125000 | I65: visca | J65: Rian | K65: Sudah TRF
B66: =F65 -> 125000 | F66: =B66+C66-D66-E66 -> 125000
B67: =F66 -> 125000 | F67: =B67+C67-D67-E67 -> 125000
B68: =F67 -> 125000 | F68: =B68+C68-D68-E68 -> 125000
B69: =F68 -> 125000 | F69: =B69+C69-D69-E69 -> 125000
B70: =F69 -> 125000 | F70: =B70+C70-D70-E70 -> 125000
B71: =F70 -> 125000 | F71: =B71+C71-D71-E71 -> 125000
B72: =F71 -> 125000 | F72: =B72+C72-D72-E72 -> 125000
B73: =F72 -> 125000 | F73: =B73+C73-D73-E73 -> 125000
B74: =F73 -> 125000 | F74: =B74+C74-D74-E74 -> 125000
B75: =F74 -> 125000 | F75: =B75+C75-D75-E75 -> 125000
B76: =F75 -> 125000 | F76: =B76+C76-D76-E76 -> 125000
B77: =F76 -> 125000 | F77: =B77+C77-D77-E77 -> 125000
... B80: =F79 -> 125000 | F80: =B80+C80-D80-E80 -> 125000
F81: =B81+C81-D81-E81 -> 0
F82: =B82+C82-D82-E82 -> 0
F83: =B83+C83-D83-E83 -> 0
F84: =B84+C84-D84-E84 -> 0
F85: =B85+C85-D85-E85 -> 0
F86: =B86+C86-D86-E86 -> 0
F87: =B87+C87-D87-E87 -> 0
F88: =B88+C88-D88-E88 -> 0
F89: =B89+C89-D89-E89 -> 0
F90: =B90+C90-D90-E90 -> 0
F91: =B91+C91-D91-E91 -> 0
F92: =B92+C92-D92-E92 -> 0
... F101: =B101+C101-D101-E101 -> 0

Sheet X
B1: INV | C1: SUP | D1: KODE | E1: NAMA | F1: PC | G1: Harga | H1: Total Harga | I1: Hutang | J1: Jatuh Tempo | K1: Input By | L1: Check | M1: Bayar? | N1: Tanggal | O1: Kode Sistem
A3: 45719 | B3: 2503056 | C3: BGI | D3: LFW-ALMAZRSXYG | E3: =IFERROR(VLOOKUP(D3,Stock,3,FALSE),"") -> Wuling Almaz (Sensor) | F3: 1 | G3: 1890000 | H3: =F3*G3 -> 1890000 | J3: 45778 | K3: CICI | L3: OK | M3: TF 388 | N3: 45773
A4: 45721 | B4: 2503138 | C4: BGI | D4: LFW-TIMORMU | E4: =IFERROR(VLOOKUP(D4,Stock,3,FALSE),"") -> Kia Timor 95-98 / Sephia 94-05 | F4: 1 | G4: 805000 | H4: =G4*F4 -> 805000 | I4: =H4 -> 805000 | L4: OK | M4: TF 388 | N4: 45773
A5: 45721 | B5: 2503138 | C5: BGI | D5: TRW-IGNISXYG | E5: =IFERROR(VLOOKUP(D5,Stock,3,FALSE),"") -> Suzuki Ignis 17- | F5: 1 | G5: 594300 | H5: =G5*F5 -> 594300 | I5: =H5 -> 594300 | L5: OK | M5: TF 388 | N5: 45773
A6: 45722 | B6: 2503194 | C6: BGI | D6: SWL-PAJERO08XYG | E6: =IFERROR(VLOOKUP(D6,Stock,3,FALSE),"") -> Mitsubishi Pajero 08-16 | F6: 1 | G6: 412300 | H6: =G6*F6 -> 412300 | I6: =H6 -> 412300 | L6: OK | M6: TF 388 | N6: 45773
A7: 45722 | B7: BCP2025C000019 | C7: MJD | D7: TRW-SIGRA16MU | E7: =IFERROR(VLOOKUP(D7,Stock,3,FALSE),"") -> Toyota Calya / Sigra 16- | F7: 1 | G7: 417150 | H7: =G7*F7 -> 417150 | M7: TF 388 | N7: 45724
A8: 45722 | B8: BCP2025C000019 | C8: MJD | D8: FDR-SIGRA16MU | E8: =IFERROR(VLOOKUP(D8,Stock,3,FALSE),"") -> Toyota Calya / Sigra 16- | F8: 1 | G8: 195000 | H8: =G8*F8 -> 195000 | M8: TF 388 | N8: 45724
A9: 45722 | B9: BCP2025C000019 | C9: MJD | D9: FDR-INNOVA15ASH | E9: =IFERROR(VLOOKUP(D9,Stock,3,FALSE),"") -> Toyota Innova 15- 2nd Gen | F9: 1 | G9: 440000 | H9: =G9*F9 -> 440000 | M9: TF 388 | N9: 45724
A10: 45723 | B10: 2503215 | C10: BGI | D10: LFW-AUDIB811XYG | E10: =IFERROR(VLOOKUP(D10,Stock,3,FALSE),"") -> Audi A4 08-15 B8 [11-15] (1 Sensor / O Sempurna) | F10: 1 | G10: 3276700 | H10: =G10*F10 -> 3276700 | I10: =H10 -> 3276700 | L10: OK | M10: TF 388 | N10: 45773
A11: 45723 | B11: 2503215 | C11: BGI | D11: LFW-VIOS02MU | E11: =IFERROR(VLOOKUP(D11,Stock,3,FALSE),"") -> Toyota Vios 02-07 XP40 1st Gen | F11: 1 | G11: 773500 | H11: =G11*F11 -> 773500 | I11: =H11 -> 773500 | L11: OK | M11: TF 388 | N11: 45773
A12: 45723 | B12: 2503241 | C12: BGI | D12: TRW-RUSH17HXYG | E12: =IFERROR(VLOOKUP(D12,Stock,3,FALSE),"") -> Toyota Rush / Terios 18- | F12: 1 | G12: 526400 | H12: =G12*F12 -> 526400 | I12: =H12 -> 526400 | L12: OK | M12: TF 388 | N12: 45773
A13: 45724 | B13: BCP2025C000026 | C13: MJD | D13: LFW-CRV95XYG | E13: =IFERROR(VLOOKUP(D13,Stock,3,FALSE),"") -> Honda CR-V 95-01 1st Gen | F13: 1 | G13: 984150 | H13: =G13*F13 -> 984150 | M13: TF 388 | N13: 45724
A14: 45724 | B14: BCP2025C000027 | C14: MJD | D14: OTH-LIST04TOYDAI | E14: =IFERROR(VLOOKUP(D14,Stock,3,FALSE),"") -> List Kaca Depan Code 04 | F14: 5 | G14: 65000 | H14: =G14*F14 -> 325000 | M14: TF 388 | N14: 45724
A15: 45724 | B15: BCP2025C000027 | C15: MJD | D15: OTH-LIST11TOYDAI | E15: =IFERROR(VLOOKUP(D15,Stock,3,FALSE),"") -> List Kaca Depan Code 11 | F15: 5 | G15: 65000 | H15: =G15*F15 -> 325000 | M15: TF 388 | N15: 45724
A16: 45726 | B16: BCP2025C000031 | C16: MJD | D16: LFW-HIACEXYG | E16: =IFERROR(VLOOKUP(D16,Stock,3,FALSE),"") -> Toyota Hi-Ace 04-20 Commuter | F16: 1 | G16: 951075 | H16: =G16*F16 -> 951075 | M16: TF 388 | N16: 45730
A17: 45728 | B17: BCP2025C000034 | C17: MJD | D17: TRW-SIGRA16MU | E17: =IFERROR(VLOOKUP(D17,Stock,3,FALSE),"") -> Toyota Calya / Sigra 16- | F17: 1 | G17: 417150 | H17: =G17*F17 -> 417150 | M17: TF 388 | N17: 45728
A18: 45724 | B18: AG-R2503000072 | C18: AG | D18: TRW-AVANZA21HASH | E18: =IFERROR(VLOOKUP(D18,Stock,3,FALSE),"") -> Toyota Avanza / Xenia 21- 4th Gen | F18: 1 | G18: 650000 | H18: =G18*F18 -> 650000 | M18: TF 388 | N18: 45735
A19: 45729 | B19: SI2025C000114 | C19: MJD | D19: LFW-CROSSXYG | E19: =IFERROR(VLOOKUP(D19,Stock,3,FALSE),"") -> Toyota Corolla Cross 21- | F19: 1 | G19: 2058750 | H19: =G19*F19 -> 2058750 | M19: TF 388 | N19: 45735
A20: 45726 | B20: 2503267 | C20: BGI | D20: TRW-BRIONOLBGXYG | E20: =IFERROR(VLOOKUP(D20,Stock,3,FALSE),"") -> Honda Brio 10-17 [Tanpa Lubang] | F20: 1 | G20: 668500 | H20: =G20*F20 -> 668500 | L20: OK | M20: TF 388 | N20: 45784
A21: 45726 | B21: 2503267 | C21: BGI | D21: LFW-BIANTEXYG | E21: =IFERROR(VLOOKUP(D21,Stock,3,FALSE),"") -> Mazda Biante 08- | F21: 1 | G21: 2317700 | H21: =G21*F21 -> 2317700 | L21: OK | M21: TF 388 | N21: 45784
A22: 45726 | B22: 2503300 | C22: BGI | D22: LFW-COROLLA91XYG | E22: =IFERROR(VLOOKUP(D22,Stock,3,FALSE),"") -> Toyota Corolla Great E100 91-96 7th Gen | F22: 1 | G22: 986300 | H22: =G22*F22 -> 986300 | L22: OK | M22: TF 388 | N22: 45773
A23: 45727 | B23: 2503323 | C23: BGI | D23: TRW-BALENO15XYG | E23: =IFERROR(VLOOKUP(D23,Stock,3,FALSE),"") -> Suzuki Baleno 15-21 | F23: 1 | G23: 744800 | H23: =G23*F23 -> 744800 | L23: OK | M23: TF 388 | N23: 45784
A24: 45727 | B24: 2503323 | C24: BGI | D24: OTH-PETIKAYU | E24: =IFERROR(VLOOKUP(D24,Stock,3,FALSE),"") -> Peti Kayu | F24: 1 | G24: 150000 | H24: =G24*F24 -> 150000 | L24: OK | M24: TF 388 | N24: 45784
A25: 45727 | B25: 2503328 | C25: BGI | D25: LFW-FORTUNER15MU | E25: =IFERROR(VLOOKUP(D25,Stock,3,FALSE),"") -> Toyota Fortuner 15- 2nd Gen | F25: 1 | G25: 1015000 | H25: =G25*F25 -> 1015000 | L25: OK | M25: TF 388 | N25: 45784
C26: BKS | D26: LFW-GRANMAXMU | E26: =IFERROR(VLOOKUP(D26,Stock,3,FALSE),"") -> Daihatsu Gran Max / Luxio 07- | F26: 1 | H26: =G26*F26 -> 0
A27: 45728 | B27: 2503372 | C27: BGI | D27: LFW-OUTLANDERXYG | E27: =IFERROR(VLOOKUP(D27,Stock,3,FALSE),"") -> Mitsubishi Outlander 10-21 GA3 | F27: 1 | G27: 1251600 | H27: =G27*F27 -> 1251600 | L27: OK | M27: TF 388 | N27: 45784
A28: 45731 | B28: BCP2025C000047 | C28: MJD | D28: LFW-TARUNAMU | E28: =IFERROR(VLOOKUP(D28,Stock,3,FALSE),"") -> Daihatsu Taruna | F28: 1 | G28: 742500 | H28: =G28*F28 -> 742500 | M28: TF 388 | N28: 45735
A29: 45733 | B29: BCP2025C000054 | C29: MJD | D29: LFW-CRV12MU | E29: =IFERROR(VLOOKUP(D29,Stock,3,FALSE),"") -> Honda CR-V 12-16 4th Gen | F29: 1 | G29: 1079325 | H29: =G29*F29 -> 1079325 | M29: TF 388 | N29: 45735
A30: 45733 | B30: BCP2025C000054 | C30: MJD | D30: LFW-ODYSSEY13XYG | E30: =IFERROR(VLOOKUP(D30,Stock,3,FALSE),"") -> Honda Odyssey 13- 5th Gen RC1/RC2 | F30: 1 | G30: 2344275 | H30: =G30*F30 -> 2344275 | M30: TF 388 | N30: 45735
A31: 45734 | B31: 2503567 | C31: BGI | D31: TRW-ALPHARD08BLACKXYG | E31: =IFERROR(VLOOKUP(D31,Stock,3,FALSE),"") -> Toyota Alphard 08-15 ANH20 2nd Gen (Hitam) | F31: 1 | G31: 1780800 | H31: =G31*F31 -> 1780800 | L31: OK | M31: TF 388 | N31: 45792
A32: 45734 | B32: DA250301510 | C32: OCS | D32: TRW-AVANZA11HAGC | E32: =IFERROR(VLOOKUP(D32,Stock,3,FALSE),"") -> Toyota Avanza / Xenia 11-15 2nd Gen/3rd Gen (Toyota/Daihatsu) | F32: 1 | G32: 995000 | H32: =G32*F32 -> 995000 | I32: 995000 | M32: TF 388 | N32: 45741
A33: 45735 | B33: BCP2025C000065 | C33: MJD | D33: TRW-SIGRA16MU | E33: =IFERROR(VLOOKUP(D33,Stock,3,FALSE),"") -> Toyota Calya / Sigra 16- | F33: 1 | G33: 417150 | H33: =G33*F33 -> 417150 | M33: TF 388 | N33: 45735
A34: 45735 | C34: ALG | D34: LFW-ERTIGA12MU | E34: =IFERROR(VLOOKUP(D34,Stock,3,FALSE),"") -> Suzuki Ertiga 12-18 1st Gen MPV | F34: 1 | H34: =G34*F34 -> 0
A35: 45735 | C35: ALG | D35: LFW-DYNAMU | E35: =IFERROR(VLOOKUP(D35,Stock,3,FALSE),"") -> Toyota Dyna/Hino Dutro 00- | F35: 2 | H35: =G35*F35 -> 0
A36: 45735 | C36: ALG | D36: LFW-FE700MU | E36: =IFERROR(VLOOKUP(D36,Stock,3,FALSE),"") -> Mitsubishi Canter FE700 01- (PS110,125) | F36: 2 | H36: =G36*F36 -> 0
A37: 45735 | C37: ALG | D37: LFW-INNOVA04MU | E37: =IFERROR(VLOOKUP(D37,Stock,3,FALSE),"") -> Toyota Innova 04-15 1st Gen | F37: 1 | H37: =G37*F37 -> 0
A38: 45736 | B38: 2503658 | C38: BGI | D38: LFW-QQ03MU | E38: =IFERROR(VLOOKUP(D38,Stock,3,FALSE),"") -> Chery QQ 03-15 S11 5D / Spark 98-05 | F38: 1 | G38: 938000 | H38: =G38*F38 -> 938000 | L38: OK | M38: TF 388 | N38: 45792
A39: 45736 | B39: MOS-200325 | C39: MOS | D39: SWR-XPANDERCHASH | E39: =IFERROR(VLOOKUP(D39,Stock,3,FALSE),"") -> Mitsubishi Xpander 17- / Livina 19- 2nd Gen (Chrome) | F39: 1 | G39: 775000 | M39: TF 388 | N39: 45741
A40: 45737 | B40: BCP2025C000072 | C40: MJD | D40: TRW-CRV17XYG | E40: =IFERROR(VLOOKUP(D40,Stock,3,FALSE),"") -> Honda CR-V 17- 5th Gen | F40: 1 | G40: 699975 | H40: =G40*F40 -> 699975 | L40: OK | M40: TF 388 | N40: 45756
A41: 45737 | B41: 2503684 | C41: BGI | D41: LFW-W213XYG | E41: =IFERROR(VLOOKUP(D41,Stock,3,FALSE),"") -> Mers-Benz E-Class 17- W213 (1 Sensor/ □ ) | F41: 1 | G41: 5173000 | H41: =G41*F41 -> 5173000 | L41: OK | M41: TF 388 | N41: 45797
A42: 45737 | B42: 2503684 | C42: BGI | D42: TRW-XPANDERXYG | E42: =IFERROR(VLOOKUP(D42,Stock,3,FALSE),"") -> Mitsubishi Xpander 17-21 | F42: 1 | G42: 371700 | H42: =G42*F42 -> 371700 | L42: OK | M42: TF 388 | N42: 45797
A43: 45738 | B43: BCP2025C000077 | C43: MJD | D43: LFW-MARCHMU | E43: =IFERROR(VLOOKUP(D43,Stock,3,FALSE),"") -> Nissan March 10- K13 | F43: 1 | G43: 771525 | H43: =G43*F43 -> 771525 | M43: TF 388 | N43: 45741
A44: 45738 | B44: MOS-220325 | C44: MOS | D44: TRW-AVANZA21ASH | E44: =IFERROR(VLOOKUP(D44,Stock,3,FALSE),"") -> Toyota Avanza / Xenia 21- 4th Gen | F44: 1 | G44: 350000 | H44: =G44*F44 -> 350000 | M44: TF 388 | N44: 45741
A45: 45738 | B45: MOS-220325 | C45: MOS | D45: RDR-CONFEROASH | E45: =IFERROR(VLOOKUP(D45,Stock,3,FALSE),"") -> Wuling Confero / Formo | F45: 1 | G45: 330000 | H45: =G45*F45 -> 330000 | M45: TF 388 | N45: 45741
A46: 45740 | B46: BCP2025C000094 | C46: MJD | D46: LFW-CARRY19MU | E46: =IFERROR(VLOOKUP(D46,Stock,3,FALSE),"") -> Suzuki Carry New 19- | F46: 1 | G46: 567000 | H46: =G46*F46 -> 567000 | L46: OK | M46: TF 388 | N46: 45741
A47: 45740 | B47: BCP2025C000094 | C47: MJD | D47: TRW-RUSH17HMU | E47: =IFERROR(VLOOKUP(D47,Stock,3,FALSE),"") -> Toyota Rush / Terios 18- | F47: 1 | G47: 507600 | H47: =G47*F47 -> 507600 | L47: OK | M47: TF 388 | N47: 45741
A48: 45740 | B48: BY-240325 | C48: BY | D48: OTH-SERBY | E48: =IFERROR(VLOOKUP(D48,Stock,3,FALSE),"") -> 501 Sealant Application | F48: 400 | G48: 37000 | H48: =G48*F48 -> 14800000 | J48: 45769 | L48: OK | M48: TF 388 | N48: 45771
A49: 45740 | B49: BY-240325 | C49: BY | D49: LAKBAN KUNING | E49: =IFERROR(VLOOKUP(D49,Stock,3,FALSE),"") | F49: 12 | G49: 28000 | H49: =G49*F49 -> 336000 | J49: 45769 | L49: OK | M49: TF 388 | N49: 45771
A50: 45740 | B50: BY-240325 | C50: BY | D50: PEGANGAN SLING | E50: =IFERROR(VLOOKUP(D50,Stock,3,FALSE),"") | F50: 3 | G50: 95000 | H50: =G50*F50 -> 285000 | J50: 45769 | L50: OK | M50: TF 388 | N50: 45771
A51: 45740 | B51: BY-240325 | C51: BY | D51: TUSUKAN SLING | E51: =IFERROR(VLOOKUP(D51,Stock,3,FALSE),"") | F51: 3 | G51: 75000 | H51: =G51*F51 -> 225000 | J51: 45769 | L51: OK | M51: TF 388 | N51: 45771
A52: 45740 | B52: BY-240325 | C52: BY | D52: SLING BY | E52: =IFERROR(VLOOKUP(D52,Stock,3,FALSE),"") | F52: 3 | G52: 135000 | H52: =G52*F52 -> 405000 | J52: 45769 | L52: OK | M52: TF 388 | N52: 45771
A53: 45740 | B53: BY-240325 | C53: BY | D53: MEJA KACA | E53: =IFERROR(VLOOKUP(D53,Stock,3,FALSE),"") | F53: 1 | G53: 650000 | H53: =G53*F53 -> 650000 | J53: 45769 | L53: OK | M53: TF 388 | N53: 45771
A54: 45740 | B54: 2503727 | C54: BGI | D54: LFW-SIRION18XYG | E54: =IFERROR(VLOOKUP(D54,Stock,3,FALSE),"") -> Daihatsu Sirion 18- 3rd Gen | F54: 1 | G54: 1015000 | H54: =G54*F54 -> 1015000 | L54: OK | M54: TF 388 | N54: 45797
A55: 45740 | B55: 2503727 | C55: BGI | D55: TRW-T30XYG | E55: =IFERROR(VLOOKUP(D55,Stock,3,FALSE),"") -> Nissan X-Trail 01-07 T30 | F55: 1 | G55: 1180200 | H55: =G55*F55 -> 1180200 | L55: OK | M55: TF 388 | N55: 45797
A56: 45743 | B56: DA250302182 | C56: OCS | D56: RDL-FORTUNER15AGC | E56: =IFERROR(VLOOKUP(D56,Stock,3,FALSE),"") -> Toyota Fortuner 15- 2nd Gen (Toyota) | F56: 1 | G56: 285000 | H56: =G56*F56 -> 285000 | L56: OK | M56: TF 388 | N56: 45756
A57: 45756 | B57: BCP2025D000023 | C57: MJD | D57: RDR-INNOVA15ASH | E57: =IFERROR(VLOOKUP(D57,Stock,3,FALSE),"") -> Toyota Innova 15- 2nd Gen | F57: 1 | G57: 285000 | H57: =G57*F57 -> 285000 | L57: OK | M57: TF 388 | N57: 45757
A58: 45758 | B58: BCP2025D000028 | C58: MJD | D58: LFW-CITY19XYG | E58: =IFERROR(VLOOKUP(D58,Stock,3,FALSE),"") -> Honda City 19- GN | F58: 1 | G58: 1567350 | H58: =G58*F58 -> 1567350 | L58: OK | M58: TF 388 | N58: 45762
A59: 45758 | B59: BCP2025D000028 | C59: MJD | D59: LFW-CRV17XYG | E59: =IFERROR(VLOOKUP(D59,Stock,3,FALSE),"") -> Honda CR-V 17- 5th Gen | F59: 1 | G59: 1047600 | H59: =G59*F59 -> 1047600 | L59: OK | M59: TF 388 | N59: 45762
A60: 45719 | B60: BY-030325 | C60: BY | D60: OTH-SERBY | E60: =IFERROR(VLOOKUP(D60,Stock,3,FALSE),"") -> 501 Sealant Application | F60: 200 | G60: 38000 | H60: =G60*F60 -> 7600000 | L60: OK | M60: TF 388 | N60: 45755
A61: 45719 | B61: BY-030325 | C61: BY | D61: MEJA KACA | E61: =IFERROR(VLOOKUP(D61,Stock,3,FALSE),"") | F61: 1 | G61: 650000 | H61: =G61*F61 -> 650000 | L61: OK | M61: TF 388 | N61: 45755
A62: 45719 | B62: BY-030325 | C62: BY | D62: PRIMER 10ML | E62: =IFERROR(VLOOKUP(D62,Stock,3,FALSE),"") | F62: 30 | G62: 30000 | H62: =G62*F62 -> 900000 | L62: OK | M62: TF 388 | N62: 45755
A63: 45719 | B63: BY-030325 | C63: BY | D63: PEGANGAN SLING | E63: =IFERROR(VLOOKUP(D63,Stock,3,FALSE),"") | F63: 2 | G63: 95000 | H63: =G63*F63 -> 190000 | L63: OK | M63: TF 388 | N63: 45755
A64: 45719 | B64: BY-030325 | C64: BY | D64: REFILL KAPE BY | E64: =IFERROR(VLOOKUP(D64,Stock,3,FALSE),"") | F64: 4 | G64: 50000 | H64: =G64*F64 -> 200000 | L64: OK | M64: TF 388 | N64: 45755
A65: 45719 | B65: BY-030325 | C65: BY | D65: KAPE KAYU | E65: =IFERROR(VLOOKUP(D65,Stock,3,FALSE),"") | F65: 1 | G65: 100000 | H65: =G65*F65 -> 100000 | L65: OK | M65: TF 388 | N65: 45755
A66: 45761 | B66: BCP2025D000038 | C66: MJD | D66: RDR-INNOVA04ASH | E66: =IFERROR(VLOOKUP(D66,Stock,3,FALSE),"") -> Toyota Innova 04-15 1st Gen | F66: 1 | G66: 285000 | H66: =G66*F66 -> 285000 | L66: OK | M66: TF 388 | N66: 45762
A67: 45762 | B67: BCP2025D000041 | C67: MJD | D67: TRW-SIGRA16MU | E67: =IFERROR(VLOOKUP(D67,Stock,3,FALSE),"") -> Toyota Calya / Sigra 16- | F67: 1 | G67: 417150 | H67: =G67*F67 -> 417150 | L67: OK | M67: TF 388 | N67: 45762
A68: 45742 | B68: BCP2025C000110 | C68: MJD | D68: LFW-CRV02XYG | E68: =IFERROR(VLOOKUP(D68,Stock,3,FALSE),"") -> Honda CR-V 02-04 2nd Gen (Spion Jepit) | F68: 1 | G68: 1000350 | H68: =G68*F68 -> 1000350 | L68: OK | M68: TF 388 | N68: 45756
A69: 45743 | C69: ALG | D69: LFW-AVANZA16MU | E69: =IFERROR(VLOOKUP(D69,Stock,3,FALSE),"") | F69: 1 | H69: =G69*F69 -> 0
A70: 45755 | B70: 2504075 | C70: BGI | D70: TRW-FREEDXYG | E70: =IFERROR(VLOOKUP(D70,Stock,3,FALSE),"") -> Honda Freed 08-16 1st gen | F70: 1 | G70: 837200 | H70: =G70*F70 -> 837200 | L70: OK | M70: TF 388 | N70: 45811
A71: 45755 | B71: 2504075 | C71: BGI | D71: SRR-HIACEFXYG | E71: =IFERROR(VLOOKUP(D71,Stock,3,FALSE),"") -> Toyota Hi-Ace 04-20 Commuter With Frame | F71: 1 | G71: 1816500 | H71: =G71*F71 -> 1816500 | L71: OK | M71: TF 388 | N71: 45811
A72: 45762 | B72: 2504260 | C72: BGI | D72: TRW-ERTIGA12XYG | E72: =IFERROR(VLOOKUP(D72,Stock,3,FALSE),"") -> Suzuki Ertiga 12-18 1st Gen MPV | F72: 1 | G72: 371700 | H72: =G72*F72 -> 371700 | L72: OK | M72: TF 388 | N72: 45811
D73: LFW-AGYA13MU | E73: =IFERROR(VLOOKUP(D73,Stock,3,FALSE),"") -> Toyota Agya/Ayla 13-22 1st Gen | F73: 1 | H73: =G73*F73 -> 0
A74: 45765 | C74: ALG | D74: LFW-GRANMAXMU | E74: =IFERROR(VLOOKUP(D74,Stock,3,FALSE),"") -> Daihatsu Gran Max / Luxio 07- | F74: 1
A75: 45766 | B75: BCP2025D000057 | C75: MJD | D75: TRW-INNOVA15XYG | E75: =IFERROR(VLOOKUP(D75,Stock,3,FALSE),"") -> Toyota Innova 15- 2nd Gen | F75: 1 | G75: 654075 | H75: =G75*F75 -> 654075 | L75: OK | M75: TF 388 | N75: 45769
A76: 45768 | B76: 2504379 | C76: BGI | D76: LFW-F15XYG | E76: =IFERROR(VLOOKUP(D76,Stock,3,FALSE),"") -> BMW X5 Series 13-18 F15 (1 Sensor / O ) | F76: 1 | G76: 2941400 | H76: =G76*F76 -> 2941400 | L76: OK | M76: TF 388 | N76: 45811
A77: 45769 | B77: BCP2025D000085 | C77: MJD | D77: TRW-FE700ASH | E77: =IFERROR(VLOOKUP(D77,Stock,3,FALSE),"") -> Mitsubishi Canter FE700 01- (PS110,125) | F77: 1 | G77: 185000 | H77: =G77*F77 -> 185000 | L77: OK | M77: TF 388 | N77: 45769
A78: 45764 | B78: MOS-170425 | C78: MOS | D78: LFW-TRAGAASH | E78: =IFERROR(VLOOKUP(D78,Stock,3,FALSE),"") -> Isuzu Traga | F78: 1 | G78: 740000 | H78: =G78*F78 -> 740000 | L78: OK | M78: TF 388 | N78: 45769
A79: 45766 | B79: MOS-190425 | C79: MOS | D79: LFW-TRAGAASH | E79: =IFERROR(VLOOKUP(D79,Stock,3,FALSE),"") -> Isuzu Traga | F79: 1 | G79: 740000 | H79: =G79*F79 -> 740000 | L79: OK | M79: TF 388 | N79: 45769
A80: 45769 | B80: 2504451 | C80: BGI | D80: FVL-ALPHARD08XYG | E80: =IFERROR(VLOOKUP(D80,Stock,3,FALSE),"") -> Toyota Alphard 08-15 ANH20 2nd Gen | F80: 1 | G80: 326200 | H80: =G80*F80 -> 326200 | L80: OK | M80: TF 388 | N80: 45813
A81: 45770 | C81: ALG | D81: LFW-RUSH17MU | E81: =IFERROR(VLOOKUP(D81,Stock,3,FALSE),"") -> Toyota Rush / Terios 18- | F81: 1 | H81: =G81*F81 -> 0
A82: 45770 | C82: ALG | D82: LFW-AGYA13MU | E82: =IFERROR(VLOOKUP(D82,Stock,3,FALSE),"") -> Toyota Agya/Ayla 13-22 1st Gen | F82: 1 | H82: =G82*F82 -> 0
A83: 45771 | B83: BCP2025D000073 | C83: MJD | D83: FDL-TAFTGTASH | E83: =IFERROR(VLOOKUP(D83,Stock,3,FALSE),"") -> Taft GT Rocky / / Hiline / Feroza (Daihatsu) | F83: 1 | G83: 220000 | H83: =G83*F83 -> 220000 | L83: OK | M83: TF 388 | N83: 45773
A84: 45771 | B84: BCP2025D000073 | C84: MJD | D84: FDR-TAFTGTASH | E84: =IFERROR(VLOOKUP(D84,Stock,3,FALSE),"") -> Taft GT Rocky / / Hiline / Feroza (Daihatsu) | F84: 1 | G84: 220000 | H84: =G84*F84 -> 220000 | L84: OK | M84: TF 388 | N84: 45773
A85: 45772 | B85: BCP2025D000080 | C85: MJD | D85: FVR-JAZZ01ASH | E85: =IFERROR(VLOOKUP(D85,Stock,3,FALSE),"") -> Honda Jazz 01-07 1st Gen | F85: 1 | G85: 235000 | H85: =G85*F85 -> 235000 | L85: OK | M85: TF 388 | N85: 45773
A86: 45772 | B86: 2504570 | C86: BGI | D86: LFW-ERTIGA12MU | E86: =IFERROR(VLOOKUP(D86,Stock,3,FALSE),"") -> Suzuki Ertiga 12-18 1st Gen MPV | F86: 1 | G86: 672000 | H86: =G86*F86 -> 672000 | L86: OK | M86: TF 388 | N86: 45829
A87: 45772 | B87: 2504570 | C87: BGI | D87: LFW-PAJERO16MU | E87: =IFERROR(VLOOKUP(D87,Stock,3,FALSE),"") -> Mitsubishi Pajero 16- | F87: 1 | G87: 826000 | H87: =G87*F87 -> 826000 | L87: OK | M87: TF 388 | N87: 45829
A88: 45772 | B88: 2504570 | C88: BGI | D88: LFW-W205RS3FY | E88: =IFERROR(VLOOKUP(D88,Stock,3,FALSE),"") -> Mers-Benz C-Class 14 - W205 (3 Sensor/ Δ□Δ) | F88: 1 | G88: 2705500 | H88: =G88*F88 -> 2705500 | L88: OK | M88: TF 388 | N88: 45829
A89: 45772 | B89: 2504591 | C89: BGI | D89: LFW-CARRY19XYG | E89: =IFERROR(VLOOKUP(D89,Stock,3,FALSE),"") -> Suzuki Carry New 19- | F89: 1 | G89: 588000 | H89: =G89*F89 -> 588000 | L89: OK | M89: TF 388 | N89: 45829
A90: 45772 | B90: 2504560 | C90: BGI | D90: LFW-KAPSUL02XYG | E90: =IFERROR(VLOOKUP(D90,Stock,3,FALSE),"") -> Toyota Kijang 02-04 Kapsul Lem Efi | F90: 1 | G90: 754600 | H90: =G90*F90 -> 754600 | L90: OK | M90: TF 388 | N90: 45829
A91: 45772 | B91: 2504560 | C91: BGI | D91: LFW-CAMRY06RSXYG | E91: =IFERROR(VLOOKUP(D91,Stock,3,FALSE),"") -> Toyota Camry 06-11 XV40 4th Gen | F91: 1 | G91: 1976100 | H91: =G91*F91 -> 1976100 | L91: OK | M91: TF 388 | N91: 45829
A92: 45773 | B92: BCP2025D000089 | C92: MJD | D92: TRW-INNOVA04HXYG | E92: =IFERROR(VLOOKUP(D92,Stock,3,FALSE),"") -> Toyota Innova 04-15 1st Gen | F92: 1 | G92: 737100 | H92: =G92*F92 -> 737100 | L92: OK | M92: TF 388 | N92: 45780
A93: 45773 | B93: BCP2025D000089 | C93: MJD | D93: LFW-CAMRY02XYG | E93: =IFERROR(VLOOKUP(D93,Stock,3,FALSE),"") -> Toyota Camry 02-06 ACV30 3rd Gen | F93: 1 | G93: 1497150 | H93: =G93*F93 -> 1497150 | L93: OK | M93: TF 388 | N93: 45780
A94: 45775 | B94: 2504656 | C94: BGI | D94: LFW-XPANDERMU | E94: =IFERROR(VLOOKUP(D94,Stock,3,FALSE),"") -> Mitsubishi Xpander 17- | F94: 1 | G94: 940800 | H94: =G94*F94 -> 940800 | L94: OK | M94: TF 388 | N94: 45829
A95: 45775 | B95: 2504656 | C95: BGI | D95: LFW-CARRY19XYG | E95: =IFERROR(VLOOKUP(D95,Stock,3,FALSE),"") -> Suzuki Carry New 19- | F95: 1 | G95: 588000 | H95: =G95*F95 -> 588000 | L95: OK | M95: TF 388 | N95: 45829
A96: 45775 | B96: 2504656 | C96: BGI | D96: TRW-FORTUNER05BLACKXYG | E96: =IFERROR(VLOOKUP(D96,Stock,3,FALSE),"") -> Toyota Fortuner 05-15 1st Gen (Hitam) | F96: 1 | G96: 1365000 | H96: =G96*F96 -> 1365000 | L96: OK | M96: TF 388 | N96: 45829
A97: 45777 | B97: BCP2025D000112 | C97: MJD | D97: FDL-FORTUNER05ASH | E97: =IFERROR(VLOOKUP(D97,Stock,3,FALSE),"") -> Toyota Fortuner 05-15 1st Gen / Hilux Pickup 05-15 | F97: 1 | G97: 455000 | H97: =G97*F97 -> 455000 | L97: OK | M97: TF 388 | N97: 45780
A98: 45779 | B98: 2505027 | C98: BGI | D98: LFW-AVANZA16MU | E98: =IFERROR(VLOOKUP(D98,Stock,3,FALSE),"") | F98: 1 | G98: 454800 | H98: =G98*F98 -> 454800 | L98: OK | M98: TF 388 | N98: 45833
A99: 45779 | B99: 2505027 | C99: BGI | D99: TRW-FREEDXYG | E99: =IFERROR(VLOOKUP(D99,Stock,3,FALSE),"") -> Honda Freed 08-16 1st gen | F99: 1 | G99: 717600 | H99: =G99*F99 -> 717600 | L99: OK | M99: TF 388 | N99: 45833
A100: 45779 | B100: 2505037 | C100: BGI | D100: LFW-MAZDA209XYG | E100: =IFERROR(VLOOKUP(D100,Stock,3,FALSE),"") -> Mazda 2 09-14 3rd Gen | F100: 1 | G100: 959400 | H100: =G100*F100 -> 959400 | L100: OK | M100: TF 388 | N100: 45833
A101: 45779 | B101: 2505070 | C101: BGI | D101: LFW-KAPSUL97XYG | E101: =IFERROR(VLOOKUP(D101,Stock,3,FALSE),"") -> Toyota Kijang 98- Kapsul Karet | F101: 1 | G101: 646800 | H101: =G101*F101 -> 646800 | L101: OK | M101: TF 388 | N101: 45833
...

Sheet SURAT JALAN
A1: SENTRA AUTOGLASS TANGERANG | I1: Tanggal | L1: 46135
A2: Taman Royal, Ruko Permata Niaga 2. 17, Jl. Permata Raya Perumahan No.1 | I2: Kepada Yth.
A3: (+62) 812-8116-1200 | sentraautomotif@gmail.com | I3: Sentra Bekasi
D7: SURAT JALAN
A9: NO | B9: SJTGRC260018
A10: No | B10: Kode | C10: Nama Barang | H10: Keterangan | L10: QTY
A11: 1 | B11: LFW-GRANMAXMU | C11: =IFERROR(VLOOKUP(B11,Stock,3,FALSE),"") -> Daihatsu Gran Max / Luxio 07- | L11: 2
A12: 2 | B12: LFW-E36XYG | C12: =IFERROR(VLOOKUP(B12,Stock,3,FALSE),"") -> BMW 3 Series 90-99 E36 | L12: 2
A13: 3 | B13: LFW-CITY02XYG | C13: =IFERROR(VLOOKUP(B13,Stock,3,FALSE),"") -> Honda City 02-08 4th Gen Idsi GD8 | L13: 2
A14: 4 | B14: LFW-AVANZA21MU | C14: =IFERROR(VLOOKUP(B14,Stock,3,FALSE),"") -> Toyota Avanza / Xenia 21- 4th Gen (Non sensor) | L14: 2
A15: 5 | B15: LFW-AVANZA11XYG | C15: =IFERROR(VLOOKUP(B15,Stock,3,FALSE),"") -> Toyota Avanza / Xenia 11-15 2nd Gen | L15: 2
A16: 6 | B16: LFW-AVANZA11MU | C16: =IFERROR(VLOOKUP(B16,Stock,3,FALSE),"") -> Toyota Avanza / Xenia 11-15 2nd Gen | L16: 2
A17: 7 | B17: LFW-AVANZA16XYG | C17: =IFERROR(VLOOKUP(B17,Stock,3,FALSE),"") -> Toyota Avanza / Xenia 15-21 3rd Gen | L17: 3
A18: 8 | B18: LFW-DYNAXYG | C18: =IFERROR(VLOOKUP(B18,Stock,3,FALSE),"") -> Toyota Dyna/Hino Dutro 00- | L18: 5
A19: 9 | C19: =IFERROR(VLOOKUP(B19,Stock,3,FALSE),"")
A20: 10 | C20: =IFERROR(VLOOKUP(B20,Stock,3,FALSE),"")
A21: 11 | C21: =IFERROR(VLOOKUP(B21,Stock,3,FALSE),"")
A22: 12 | C22: =IFERROR(VLOOKUP(B22,Stock,3,FALSE),"")
A23: 13 | C23: =IFERROR(VLOOKUP(B23,Stock,3,FALSE),"")
K24: Total | L24: =SUM(L11:L23) -> 20
E25: Penerima
B29: Trust the Experts, Drive Safer and Clearer | E29: ....................

Sheet Copy of SURAT JALAN
A1: SENTRA AUTOGLASS TANGERANG | I1: Tanggal | L1: 46121
A2: Taman Royal, Ruko Permata Niaga 2. 17, Jl. Permata Raya Perumahan No.1 | I2: Kepada Yth.
A3: (+62) 812-8116-1200 | sentraautomotif@gmail.com | I3: Sentra Bekasi
D7: SURAT JALAN
A9: NO | B9: SJTGRC260016
A10: No | B10: Kode | C10: Nama Barang | H10: Keterangan | L10: QTY
A11: 1 | B11: RDL-FORTUNER15AGC | C11: =IFERROR(VLOOKUP(B11,Stock,3,FALSE),"") -> Toyota Fortuner 15- 2nd Gen (Toyota) | L11: 1
A12: 2 | C12: =IFERROR(VLOOKUP(B12,Stock,3,FALSE),"")
A13: 3 | C13: =IFERROR(VLOOKUP(B13,Stock,3,FALSE),"")
A14: 4 | C14: =IFERROR(VLOOKUP(B15,Stock,3,FALSE),"")
A15: 5 | C15: =IFERROR(VLOOKUP(#REF!,Stock,3,FALSE),"")
A16: 6 | C16: =IFERROR(VLOOKUP(B16,Stock,3,FALSE),"")
A17: 7 | C17: =IFERROR(VLOOKUP(B17,Stock,3,FALSE),"")
K18: Total | L18: =SUM(L11:L17) -> 1
E19: Penerima
B23: Trust the Experts, Drive Safer and Clearer | E23: ....................

Sheet  INV POLOS
J1: Tanggal | L1: 46128
J2: Kepada Yth.
J3: Andrean Ganie Hendranata
J4: +62 896-8899-8928
J5: Kantor Pusat
J6: Tangerang
D8: NOTA PENJUALAN
A10: INV | B10: D260105 | J10: NO POL | L10: B 1928 VO
A11: No | B11: Kode | C11: Nama Barang | H11: Qty | J11: Harga Satuan | L11: Jumlah
A12: 1 | B12: FDR-ERTIGA18MU | C12: =IFERROR(VLOOKUP(B12,Stock,3,FALSE),"") -> Suzuki Ertiga 18- 2nd Gen (ORI MULIA) / XL7 | H12: 1 | I12: PC | J12: 2800000 | L12: =H12*J12 -> 2800000
A13: 2 | B13: FILM-60STD | C13: =IFERROR(VLOOKUP(B13,Stock,3,FALSE),"") -> Automotive Film Standard - Black 40% | H13: 1 | I13: PC | J13: 375000 | L13: =H13*J13 -> 375000
A14: 3 | B14: OTH-SERTRANSPORT | C14: =IFERROR(VLOOKUP(B14,Stock,3,FALSE),"") -> Transport | H14: 1 | I14: X | J14: 175000 | L14: =H14*J14 -> 175000
C15: =IFERROR(VLOOKUP(B15,Stock,3,FALSE),"") | L15: =H15*J15 -> 0
C16: =IFERROR(VLOOKUP(B16,Stock,3,FALSE),"") | L16: =H16*J16 -> 0
K18: TOTAL | L18: =SUM(L12:L17) -> 3350000
E19: Kaca yang sudah dipesan/dipasang tidak dapat dibatalkan/dikembalikan. Tidak ada garansi kaca. | K19: DP | L19: 0
K20: SISA | L20: =L18-L19 -> 3350000
K22: Ket

Sheet Uang Setoran
A1: Tanggal | B1: Nomor Inovice | C1: Total Cash | D1: Total Cash di Setor | E1: Sisa Uang Setor | F1: Total Semua Uang Setoran | G1: Keterangan | H1: SETOR by RIAN | I1: SETOR by MICEL | J1: Kembalian kasir
A2: 45955 | B2: J250101 / Rp 100,000 | C2: 100000 | D2: 1300000 | E2: - | F2: 1300000 | G2: Rp 15,000 dari uang kasir untuk kembalian belum kembali | H2: Sudah | J2: Sudah
A3: 45958 | B3: J250117 / Rp 1,185,000 | C3: 1185000 | H3: Sudah | J3: Sudah
A4: 45965 | B4: K250015 / Rp 2,650,000 | C4: 2650000 | D4: 3150000 | E4: - | F4: 1350000 | G4: Rp 15,000 diambil untuk balikin uang kasir | H4: Sudah | J4: Sudah
A5: 45965 | B5: K250019 / Rp 515,000 | C5: 515000 | H5: Sudah | J5: Sudah
A6: 45967 | B6: K250029 / Rp 1,070,000 | C6: 1100000 | D6: 3250000 | E6: - | F6: 3230000 | G6: Rp 20,000 diambil untuk balikin uang Guntur (dipakai untuk kembalian) | H6: Sudah | J6: Sudah
A7: 45968 | B7: K250032 / Rp 2,129,000 | C7: 2150000 | G7: Rp 30,000 belum balik dari kembalian | H7: Sudah | J7: Sudah
A8: 45971 | B8: K250047 / Rp 1,000,000 | C8: 1000000 | D8: 2300000 | E8: - | F8: 2250000 | G8: Rp 25,000 diambil untuk balikin uang Guntur (dipakai untuk kembalian) | H8: Sudah | J8: Sudah
A9: 45971 | B9: K250048 / Rp 1,275,000 | C9: 1300000 | G9: Rp 25,000 balikin uang kasir (-Rp 5,000 uang kasir) | H9: Sudah | J9: Sudah
A10: 45973 | B10: K250055 / Rp 1,000,000 | C10: 1000000 | D10: 1000000 | E10: - | F10: 1000000 | G10: Rp 5,000 uang kasir belum balik | H10: Sudah | J10: Sudah
A11: 45974 | B11: K250063 / Rp 2,697,000 | C11: 2700000 | D11: 2200000 | E11: 500000 | F11: 2200000 | G11: Rp 3,000 uang kasir belum balik Rp 500,000 utk petty cash, gak bisa masuk ko rian jadikan Perry cash | H11: Sudah | J11: Sudah
A12: 45975 | B12: K250070 / TF | C12: kelebihan TF Rp 10,000 | G12: Rp 10,000 diambil dari kasir untuk kembalian (kelebihan tf) | H12: Sudah | J12: Sudah
A13: 45976 | B13: K250076 / Rp 1,000,000 | C13: 1000000 | D13: 1000000 | E13: - | F13: 1000000 | G13: Total uang kasir belum balik Rp 18,000 | H13: Sudah | J13: Sudah
A14: 45978 | B14: K250085 / Rp 1,327,000 | C14: 1327000 | D14: 1327000 | E14: 497000 | G14: Rp 18,000 sudah balik dari petty cash | H14: Sudah | J14: Sudah
A15: 45979 | B15: K250087 / Rp 1950,000 | C15: 1950000 | D15: 1950000 | G15: Rp.497,000 gak bisa ke setor | H15: Sudah | J15: Sudah
A16: 45979 | B16: K250088 / Rp 620,000 | C16: 620000 | D16: 620000
A17: 45980 | B17: K250093 / Rp 1,400,000 | C17: 1400000 | D17: 1400000 | E17: - | F17: 2400000 | G17: sudah ke setor semua | H17: Sudah
A18: 45980 | B18: K250095 / Rp 1,000,000 | C18: 1000000 | D18: 1000000 | E18: -
A19: 45981 | B19: K250097 / Rp 575,000 | C19: 600000 | D19: 100000 | E19: 500000 | F19: 1950000 | G19: Rp 500,000 untuk petty cash Rp 25,000 pakai uang kasir kembalian | H19: Sudah | J19: Sudah
A20: 45981 | B20: K250101 / Rp 839,000 | C20: 850000 | D20: 850000 | E20: - | G20: Rp 11,000 pakai uang kasir kembalian | J20: Sudah
A21: 45981 | B21: K250102 / Rp 995,000 | C21: 1000000 | D21: 1000000 | E21: - | G21: Rp 5,000 pakai uang kasir kembalian | J21: Sudah
A22: 45982 | B22: K250107/ Rp.1.244.000 | C22: 1244000 | D22: 744000 | E22: 500000 | F22: 1204000 | G22: Rp 500.000 Untuk Petty Cash | H22: Sudah | J22: Tidak pakai kembali
A23: 45985 | B23: K250112 / Rp 1,260,000 | C23: 1260000 | D23: 1260000 | E23: 800000 | G23: Rp 800.000 Untuk Petty Cash | H23: Sudah | J23: Tidak pakai kembali
A24: 45990 | B24: K250139 / Rp 1.705.000 | C24: 1710000 | D24: 1705000 | E24: - | F24: 2205000 | G24: Rp 500.000 Untuk Petty Cash | H24: Sudah | J24: Tidak pakai kembali
A25: 45990 | B25: K250141 / Rp 900.000 | C25: 900000 | D25: 400000 | E25: 500000 | J25: Tidak pakai kembali
A26: 45992 | B26: L2500007 / Rp 100.000 | C26: 100000 | D26: 100000 | E26: - | J26: Tidak pakai kembali
A27: 45993 | B27: L2500015 / Rp 450,000 | C27: 450000 | D27: 450000 | E27: - | F27: 3700000 | G27: Rp 500.000 Untuk Petty Cash | H27: Sudah | J27: Tidak pakai kembali
A28: 45994 | B28: L2500019 / Rp 3,750,000 | C28: 3750000 | D28: 3750000 | E28: 500000 | H28: Sudah | J28: Tidak pakai kembali
A29: 45996 | B29: L2500027 / Rp 1,000,000 | C29: 1000000 | D29: 1000000 | E29: 800000 | F29: =D29-E29 -> 200000 | G29: Rp 800,000 masuk ke pettycash | H29: Sudah | J29: Sudah
A30: 45996 | B30: L2500029 / Rp 470,000 | C30: 500000 | D30: 500000 | E30: - | F30: 500000 | G30: Rp 30,000 pakai uang kasir | H30: Sudah | J30: Sudah
A31: 45999 | B31: L250045 / Rp 500,000 | C31: 500000 | D31: 500000 | E31: - | F31: =D31+D32 -> 1800000 | H31: Sudah | J31: Tidak pakai kembali
A32: 45999 | B32: L250048 / 1,289,000 | C32: 1300000 | D32: 1300000 | E32: - | G32: Rp 11,000 pakai uang kasir | H32: Sudah | J32: Sudah
A33: 46002 | B33: L250061 / 100,000 | C33: 100000 | D33: 100000 | E33: - | F33: 100000 | H33: Belum | J33: Tidak pakai kembali
A34: 46004 | B34: L250071 / Rp 1,300,000 | C34: 1300000 | D34: 800000 | E34: 500000 | F34: 800000 | G34: Rp 500,000 utk petty cash | I34: Sudah | J34: Tidak pakai kembali
A35: 46006 | B35: L250082 / Rp 1,4080,000 | C35: 1408000 | D35: 1408000 | E35: - | F35: 1408000 | G35: Udah di alvin uangnya | I35: Sudah | J35: Tidak pakai kembali
A36: 46006 | B36: L250084 / Rp 330,000 | C36: 330000 | D36: 30000 | E36: 300000 | F36: 30000 | G36: cash utk di misel, Rp 300,000 utk petty cash | I36: Sudah | J36: Tidak pakai kembali
A37: 46011 | B37: L250107 /Rp 4,802,000 | C37: 4802000 | D37: 4802000 | E37: 4802000 | F37: 4802000 | G37: Udah di alvin uangnya / 20 des | I37: Sudah | J37: Tidak pakai kembali
A38: 46015 | B38: L250126 / 1,800,000 | C38: 1800000 | D38: 1300000 | E38: 500000 | F38: 1300000 | G38: 500rb utk petty cash | I38: Sudah
A39: 46017 | B39: L250139 / Rp 750,000 | C39: 750000 | D39: 750000 | E39: - | F39: 750000 | G39: udah di alvin / 26 des | I39: Sudah
A40: 46022 | B40: K250094 / Rp 5.000.000 | C40: 5000000 | D40: 5000000 | F40: 5000000 | G40: udah di misel | I40: Sudah

Sheet Copy of SURAT PO toyota PJM
A1: SENTRA AUTOGLASS | I1: Tanggal | K1: 46137
A2: Cabang : Tangerang - Bekasi- Surabaya | I2: Kepada Yth.
A3: (+62) 81288009878 | (+62) 81281161200 | I3: Putra Jaya Motor
I4: 081299380016
D7: PURCHASE ORDER
A9: PO | B9: PJMTGRD00004
A10: No | B10: Kode | C10: Nama Barang | F10: Qty | H10: Satuan | I10: Disc (%) | J10: Harga | K10: Jumlah
A11: 1 | B11: 56101VT070 | C11: kaca depan innova 2023 | F11: 1 | G11: PC | H11: 880000 | I11: 8 | J11: =H11-(H11*I11/100) -> 809600 | K11: =F11*J11 -> 809600
A12: 2 | B12: 56101-VT914 | C12: kaca depan innova 2023 | F12: 1 | G12: PC | H12: 1240000 | I12: 8 | J12: =H12-(H12*I12/100) -> 1140800 | K12: =F12*J12 -> 1140800
A13: 3 | B13: 68103-BZ411 | C13: kaca pintu tengah kanan toyota rush 2019 | F13: 1 | G13: PC | H13: 349600 | J13: =H13-(H13*I13/100) -> 349600 | K13: =F13*J13 -> 349600
A14: 4 | B14: 68104-BZ411 | C14: kaca pintu tengah kiri toyota rush 2019 | F14: 1 | G14: PC | H14: 349600 | J14: =H14-(H14*I14/100) -> 349600 | K14: =F14*J14 -> 349600
A15: 5 | B15: 68114-0D341 | C15: kaca pintu tengah kiri toyota sienta | F15: 1 | G15: PC | H15: 205000 | I15: 8 | J15: =H15-(H15*I15/100) -> 188600 | K15: =F15*J15 -> 188600
A16: 6 | B16: 68113-0D341 | C16: kaca pintu tengah kanan toyota sienta | F16: 1 | G16: PC | H16: 205000 | I16: 8 | J16: =H16-(H16*I16/100) -> 188600 | K16: =F16*J16 -> 188600
A17: Note : Kirim Tangerang | J17: SUB TOTAL | K17: =SUM(K11:K16) -> 3026800
J18: DISKON | K18: 0
J19: TOTAL | K19: =K17-K18 -> 3026800
J22: Ket
A23: Trust the Experts, Drive Safer and Clearer | J23: Tempo 30 hari

Sheet SURAT PO BKS Honda
A1: SENTRA AUTOGLASS | I1: Tanggal | K1: 46129
A2: Cabang : Tangerang - Bekasi- Surabaya | I2: Kepada Yth.
A3: (+62) 81288009878 | (+62) 81281161200 | I3: Panen Autopart
I4: 081374748818
D7: PURCHASE ORDER
A9: PO | B9: BKSD00001
A10: No | B10: Kode | C10: Nama Barang | F10: Qty | H10: Satuan | I10: Disc (%) | J10: Harga | K10: Jumlah
A11: 1 | B11: 73111-TVL T31 | C11: Kaca depan accord | F11: 1 | G11: PC | H11: 7632000 | I11: 12 | J11: =H11-(H11*I11/100) -> 6716160 | K11: =F11*J11 -> 6716160
A12: 2 | J12: =H12-(H12*I12/100) -> 0 | K12: =F12*J12 -> 0
A13: 3 | J13: =H13-(H13*I13/100) -> 0 | K13: =F13*J13 -> 0
A14: 4 | J14: =H14-(H14*I14/100) -> 0 | K14: =F14*J14 -> 0
A15: 5 | J15: =H15-(H15*I15/100) -> 0 | K15: =F15*J15 -> 0
A16: 6
A17: 7 | J17: =H17-(H17*I17/100) -> 0 | K17: =F17*J17 -> 0
A18: 8 | J18: =H18-(H18*I18/100) -> 0 | K18: =F18*J18 -> 0
A19: Note : Kaca di ambil langsung | J19: SUB TOTAL | K19: =SUM(K11:K18) -> 6716160
J20: DISKON | K20: 0
J21: TOTAL | K21: =K19-K20 -> 6716160
J24: Ket
A25: Trust the Experts, Drive Safer and Clearer | J25: Tempo 60 hari

Sheet SURAT PO BKS toyota
A1: SENTRA AUTOGLASS | I1: Tanggal | K1: 46025
A2: Cabang : Tangerang - Bekasi- Surabaya | I2: Kepada Yth.
A3: (+62) 81288009878 | (+62) 81281161200 | I3: Panen Autopart
I4: 081374748818
D7: PURCHASE ORDER
A9: PO | B9: BKSA00002
A10: No | B10: Kode | C10: Nama Barang | F10: Qty | H10: Satuan | I10: Disc (%) | J10: Harga | K10: Jumlah
A11: 1 | B11: 561010K090 | C11: Kaca depan innova 2004 | F11: 2 | G11: PC | H11: 1711199 | J11: =H11-(H11*I11/100) -> 1711199 | K11: =F11*J11 -> 3422398
A12: 2 | J12: =H12-(H12*I12/100) -> 0 | K12: =F12*J12 -> 0
A13: 3
A14: 4 | J14: =H14-(H14*I14/100) -> 0 | K14: =F14*J14 -> 0
A15: 5 | J15: =H15-(H15*I15/100) -> 0 | K15: =F15*J15 -> 0
A16: 6 | J16: =H16-(H16*I16/100) -> 0 | K16: =F16*J16 -> 0
A17: 7 | J17: =H17-(H17*I17/100) -> 0 | K17: =F17*J17 -> 0
A18: 8 | J18: =H18-(H18*I18/100) -> 0 | K18: =F18*J18 -> 0
A19: 9 | J19: =H19-(H19*I19/100) -> 0 | K19: =F19*J19 -> 0
A20: 10 | J20: =H20-(H20*I20/100) -> 0 | K20: =F20*J20 -> 0
A21: Note : Kirim BEKASI | J21: SUB TOTAL | K21: =SUM(K11:K20) -> 3422398
J22: DISKON | K22: 0
J23: TOTAL | K23: =K21-K22 -> 3422398
J26: Ket
A27: Trust the Experts, Drive Safer and Clearer | J27: Tempo 60 hari

Sheet SURAT PO BKS Mitsubisi
A1: SENTRA AUTOGLASS | I1: Tanggal | K1: 46120
A2: Cabang : Tangerang - Bekasi- Surabaya | I2: Kepada Yth.
A3: (+62) 81288009878 | (+62) 81281161200 | I3: Oto Citra Lestari
D7: PURCHASE ORDER
A9: PO | B9: OCSTGRD00002
A10: No | B10: Kode | C10: Nama Barang | F10: Qty | H10: Satuan | I10: Disc (%) | J10: Harga | K10: Jumlah
A11: 1 | B11: 72700A140P | C11: Kaca depan triton 2024 | F11: 1 | G11: PC | H11: 6000000 | J11: =H11-(H11*I11/100) -> 6000000 | K11: =F11*J11 -> 6000000
A12: 2 | J12: =H12-(H12*I12/100) -> 0 | K12: =F12*J12 -> 0
A13: 3 | J13: =H13-(H13*I13/100) -> 0 | K13: =F13*J13 -> 0
A14: 4 | J14: =H14-(H14*I14/100) -> 0 | K14: =F14*J14 -> 0
A15: 5 | J15: =H15-(H15*I15/100) -> 0 | K15: =F15*J15 -> 0
A16: 6 | J16: =H16-(H16*I16/100) -> 0 | K16: =F16*J16 -> 0
A17: 7 | J17: =H17-(H17*I17/100) -> 0 | K17: =F17*J17 -> 0
A18: 8 | J18: =H18-(H18*I18/100) -> 0 | K18: =F18*J18 -> 0
A19: 9 | J19: =H19-(H19*I19/100) -> 0 | K19: =F19*J19 -> 0
A20: 6 | J20: =H20-(H20*I20/100) -> 0 | K20: =F20*J20 -> 0
A21: Note : Kaca di ambil sendiri | J21: SUB TOTAL | K21: =SUM(K11:K20) -> 6000000
J22: DISKON | K22: 0
J23: TOTAL | K23: =K21-K22 -> 6000000
J26: Ket
A27: Trust the Experts, Drive Safer and Clearer

Sheet FORM ambil barang
A1: SENTRA AUTOGLASS TANGERANG | H1: Periode Bulan
A2: Ruko Permata Niaga II No. 17, Taman Royal I, Tanah Tinggi, Kota Tangerang 15119 | H2: 46113
A3: (+62) 81288009878 | (+62) 81281161200
A7: Form Pengambilan Barang
A10: No | B10: Untuk | C10: Nama Barang | D10: Tanggal Pengambilan | E10: Jam Pengambilan | F10: Qty | G10: Parah (Diberikan) | I10: Paraf (Diambil)
A11: 1 | B11: Home service / Ruko | C11: =IFERROR(VLOOKUP(B11,Stock,3,FALSE),"")
A12: 2 | B12: Home service / Ruko
A13: 3 | B13: Home service / Ruko
A14: 4 | B14: Home service / Ruko
A15: 5 | B15: Home service / Ruko
A16: 6 | B16: Home service / Ruko
A17: 7 | B17: Home service / Ruko
A18: 8 | B18: Home service / Ruko
A19: 9 | B19: Home service / Ruko
A20: 10 | B20: Home service / Ruko
A21: 11 | B21: Home service / Ruko
A22: 12 | B22: Home service / Ruko
A23: 13 | B23: Home service / Ruko
... A53: 43 | B53: Home service / Ruko

Sheet SURAT PO TGR toyota
A1: SENTRA AUTOGLASS | I1: Tanggal | K1: 46030
A2: Cabang : Tangerang - Bekasi- Surabaya | I2: Kepada Yth.
A3: (+62) 81288009878 | (+62) 81281161200 | I3: Panen Autopart
I4: 081374748818
D7: PURCHASE ORDER
A9: PO | B9: TGRA00006
A10: No | B10: Kode | C10: Nama Barang | F10: Qty | H10: Satuan | I10: Disc (%) | J10: Harga | K10: Jumlah
A11: 1 | B11: 68103-VT010 | C11: KACA PINTU TENGAH KIRI INNOVA 2023 | F11: 1 | G11: PC | H11: 142500 | J11: =H11-(H11*I11/100) -> 142500 | K11: =F11*J11 -> 142500
A12: 2 | B12: 68103-BZ460 | C12: KACA PINTU TENGAH KIRI AVANZA 2022 | F12: 1 | G12: PC | H12: 303600 | J12: =H12-(H12*I12/100) -> 303600 | K12: =F12*J12 -> 303600
A13: 3 | J13: =H13-(H13*I13/100) -> 0 | K13: =F13*J13 -> 0
A14: 4 | J14: =H14-(H14*I14/100) -> 0 | K14: =F14*J14 -> 0
A15: 5 | J15: =H15-(H15*I15/100) -> 0 | K15: =F15*J15 -> 0
A16: 6 | J16: =H16-(H16*I16/100) -> 0 | K16: =F16*J16 -> 0
A17: 7 | J17: =H17-(H17*I17/100) -> 0 | K17: =F17*J17 -> 0
A18: 8 | J18: =H18-(H18*I18/100) -> 0 | K18: =F18*J18 -> 0
A19: 9 | J19: =H19-(H19*I19/100) -> 0 | K19: =F19*J19 -> 0
A20: 10 | J20: =H20-(H20*I20/100) -> 0 | K20: =F20*J20 -> 0
A21: Note : Kirim TANGERANG | J21: SUB TOTAL | K21: =SUM(K11:K20) -> 446100
J22: DISKON | K22: 0
J23: TOTAL | K23: =K21-K22 -> 446100
J26: Ket
A27: Trust the Experts, Drive Safer and Clearer | J27: Tempo 60 hari

Sheet SURAT PO TGR honda
A1: SENTRA AUTOGLASS | I1: Tanggal | K1: 46137
A2: Cabang : Tangerang - Bekasi- Surabaya | I2: Kepada Yth.
A3: (+62) 81288009878 | (+62) 81281161200 | I3: Panen Autopart
I4: 081374748818
D7: PURCHASE ORDER
A9: PO | B9: TGRD00004
A10: No | B10: Kode | C10: Nama Barang | F10: Qty | H10: Satuan | I10: Disc (%) | J10: Harga | K10: Jumlah
A11: 1 | B11: 73111-T0N-T01 | C11: LFW-CRV12AGC | F11: 1 | G11: PC | H11: 2378508 | J11: =H11-(H11*I11/100) -> 2378508 | K11: =F11*J11 -> 2378508
A12: 2 | B12: 73450-SZY-T10 | C12: RDL-FREEDAGC | F12: 1 | G12: PC | H12: 477300 | I12: 12 | J12: =H12-(H12*I12/100) -> 420024 | K12: =F12*J12 -> 420024
A13: 3 | B13: 73111-SWK-T20 | C13: LFW-CRV07AGC | F13: 1 | G13: PC | H13: 2744808 | J13: =H13-(H13*I13/100) -> 2744808 | K13: =F13*J13 -> 2744808
A14: 4 | B14: 73450-TG4-T01 | C14: RDL-BRIO18AGC | F14: 1 | G14: PC | H14: 146520 | I14: 12 | J14: =H14-(H14*I14/100) -> 128937.6 | K14: =F14*J14 -> 128937.6
A15: 5 | J15: =H15-(H15*I15/100) -> 0 | K15: =F15*J15 -> 0
A16: 6 | J16: =H16-(H16*I16/100) -> 0 | K16: =F16*J16 -> 0
A17: 7 | J17: =H17-(H17*I17/100) -> 0 | K17: =F17*J17 -> 0
A18: Note : Kirim TANGERANG | J18: SUB TOTAL | K18: =SUM(K11:K17) -> 5672277.6
J19: DISKON | K19: 0
J20: TOTAL | K20: =K18-K19 -> 5672277.6
J23: Ket
A24: Trust the Experts, Drive Safer and Clearer | J24: Tempo 60 hari

Sheet STOK KOSONG
B1: KODE | G1: IN | H1: OUT | I1: SISA | K1: ORDER | L1: ket | M1: URGENSI | P1: PL 30% | Q1: SUB TOTAL
A2: TRW-LUXIO | B2: TRW-LUXIODAIHATSU | C2: Daihatsu Luxio 07- | D2: TRW | E2: DAIHATSU | F2: X/Logo | G2: 5 | H2: 5 | I2: 0 | J2: B8T3 | O2: =IFERROR(VLOOKUP(A2,BGI,14,FALSE),"") | Q2: =P2*K2 -> 0
A3: LFW-CRV02 | B3: LFW-CRV02FY | C3: Honda CR-V 02-04 2nd Gen (Spion Jepit) | D3: LFW | E3: FY | F3: X/MB | G3: 2 | H3: 2 | I3: 0 | J3: B5T2 | K3: 1 | M3: 3 | O3: =IFERROR(VLOOKUP(A3,BGI,14,FALSE),"") | P3: =O3*70% -> 0 | Q3: =P3*K3 -> 0
A4: LFW-CX5GEN1RS3 | B4: LFW-CX5GEN1RS3XYG | C4: Mazda CX-5 .14-17 1st Gen KE Facelift - (3 Sensor/ /\8 ) | D4: LFW | E4: XYG | F4: X/MB/RS/List | G4: 1 | H4: 1 | I4: 0 | O4: =IFERROR(VLOOKUP(A4,BGI,14,FALSE),"") | P4: =O4*70% -> 0 | Q4: =P4*K4 -> 0
A5: TRW-HIU | B5: TRW-HIUFY | C5: Mitsubishi Galant 96-03 YC/EA2A 8th Gen (Hiu) | D5: TRW | E5: FY | F5: X/H | G5: 1 | H5: 1 | I5: 0 | O5: =IFERROR(VLOOKUP(A5,BGI,14,FALSE),"") | P5: =O5*70% -> 0 | Q5: =P5*K5 -> 0
A6: LFW-ALPHARD02 | B6: LFW-ALPHARD02PIL | C6: Toyota Alphard 02-08 ANH10 1st Gen | D6: LFW | E6: PIL | F6: X/MB | G6: 2 | H6: 2 | I6: 0 | J6: A1T1 | O6: =IFERROR(VLOOKUP(A6,BGI,14,FALSE),"") | P6: =O6*70% -> 0 | Q6: =P6*K6 -> 0
A7: LFW-AUDIQ508 | B7: LFW-AUDIQ508XYG | C7: Audi Q5 08-17 | D7: LFW | E7: XYG | F7: X/RS/List | G7: 1 | H7: 1 | I7: 0 | O7: =IFERROR(VLOOKUP(A7,BGI,14,FALSE),"") | P7: =O7*70% -> 0 | Q7: =P7*K7 -> 0
A8: LFW-E84 | B8: LFW-E84XYG | C8: BMW X1 Series 09-14 E84 (1 Sensor / [] ) | D8: LFW | E8: XYG | F8: X/MB/RS | G8: 1 | H8: 1 | I8: 0 | O8: =IFERROR(VLOOKUP(A8,BGI,14,FALSE),"") | P8: =O8*70% -> 0 | Q8: =P8*K8 -> 0
A9: LFW-OPTRA | B9: LFW-OPTRAXYG | C9: Chevrolet Optra 03- | D9: LFW | E9: XYG | F9: X/MB | G9: 1 | H9: 1 | I9: 0 | O9: =IFERROR(VLOOKUP(A9,BGI,14,FALSE),"") | P9: =O9*70% -> 0 | Q9: =P9*K9 -> 0
A10: TRW-SIRION1 | B10: TRW-SIRION1XYG | C10: Daihatsu Sirion 04-10 1st Gen | D10: TRW | E10: XYG | F10: X/H | G10: 2 | H10: 2 | I10: 0 | J10: B7T3 | K10: 1 | M10: 3 | O10: =IFERROR(VLOOKUP(A10,BGI,14,FALSE),"") | P10: =O10*70% -> 0 | Q10: =P10*K10 -> 0
A11: LFW-PANDA | B11: LFW-PANDAXYG | C11: Geely Panda 09- LC Hatchback | D11: LFW | E11: XYG | F11: X/MB | G11: 1 | H11: 1 | I11: 0 | O11: =IFERROR(VLOOKUP(A11,BGI,14,FALSE),"") | P11: =O11*70% -> 0 | Q11: =P11*K11 -> 0
A12: LFW-BRV16 | B12: LFW-BRV16XYG | C12: Honda BR-V 16- | D12: LFW | E12: XYG | F12: X | G12: 1 | H12: 1 | I12: 0 | O12: =IFERROR(VLOOKUP(A12,BGI,14,FALSE),"") | P12: =O12*70% -> 0 | Q12: =P12*K12 -> 0
A13: TRW-BRIONOLBG | B13: TRW-BRIONOLBGXYG | C13: Honda Brio 10-17 [Tanpa Lubang] | D13: TRW | E13: XYG | F13: X | G13: 2 | H13: 2 | I13: 0 | J13: A4T3 | K13: 1 | M13: 1 | O13: =IFERROR(VLOOKUP(A13,BGI,14,FALSE),"") | P13: =O13*70% -> 0 | Q13: =P13*K13 -> 0
A14: TRW-BRIO | B14: TRW-BRIOXYG | C14: Honda Brio 10-17 [Lubang Wiper] | D14: TRW | E14: XYG | F14: X/9Hole | G14: 2 | H14: 2 | I14: 0 | J14: A4T3 | K14: 1 | M14: 1 | O14: =IFERROR(VLOOKUP(A14,BGI,14,FALSE),"") | P14: =O14*70% -> 0 | Q14: =P14*K14 -> 0
A15: TRW-CIVIC96 | B15: TRW-CIVIC96XYG | C15: Honda Civic 96-00 SO4/SO6 (Ferio) | D15: TRW | E15: XYG | F15: X/H | G15: 1 | H15: 1 | I15: 0 | J15: A5T3 | O15: =IFERROR(VLOOKUP(A15,BGI,14,FALSE),"") | P15: =O15*70% -> 0 | Q15: =P15*K15 -> 0
A16: TRW-FREED | B16: TRW-FREEDXYG | C16: Honda Freed 08-16 1st gen | D16: TRW | E16: XYG | F16: X/H | G16: 5 | H16: 5 | I16: 0 | J16: B6T3 | K16: 1 | M16: 1 | O16: =IFERROR(VLOOKUP(A16,BGI,14,FALSE),"") | P16: =O16*70% -> 0 | Q16: =P16*K16 -> 0
A17: LFW-HRV14 | B17: LFW-HRV14XYG | C17: Honda HR-V 14-21 5D SUV | D17: LFW | E17: XYG | F17: X/MB | G17: 1 | H17: 1 | I17: 0 | K17: 1 | M17: 2 | O17: =IFERROR(VLOOKUP(A17,BGI,14,FALSE),"") | P17: =O17*70% -> 0 | Q17: =P17*K17 -> 0
A18: TRW-JAZZ01 | B18: TRW-JAZZ01XYG | C18: Honda Jazz 01-07 1st Gen | D18: TRW | E18: XYG | F18: X/H/1Hole | G18: 2 | H18: 2 | I18: 0 | J18: B7T3 | K18: 1 | M18: 1 | O18: =IFERROR(VLOOKUP(A18,BGI,14,FALSE),"") | P18: =O18*70% -> 0 | Q18: =P18*K18 -> 0
A19: TRW-JAZZ13 | B19: TRW-JAZZ13XYG | C19: Honda Jazz 13- 3rd Gen | D19: TRW | E19: XYG | F19: X/H | G19: 2 | H19: 2 | I19: 0 | J19: B7T3 | K19: 1 | M19: 3 | O19: =IFERROR(VLOOKUP(A19,BGI,14,FALSE),"") | P19: =O19*70% -> 0 | Q19: =P19*K19 -> 0
A20: TRW-STREAM00 | B20: TRW-STREAM00XYG | C20: Honda Stream 00-06 S7A/RN1 | D20: TRW | E20: XYG | F20: X/H/1Hole | G20: 1 | H20: 1 | I20: 0 | O20: =IFERROR(VLOOKUP(A20,BGI,14,FALSE),"") | P20: =O20*70% -> 0 | Q20: =P20*K20 -> 0
A21: TRW-AVEGA99 | B21: TRW-AVEGA99XYG | C21: Hyundai Avega 06-12 Sedan | D21: TRW | E21: XYG | F21: X/H | G21: 1 | H21: 1 | I21: 0 | O21: =IFERROR(VLOOKUP(A21,BGI,14,FALSE),"") | P21: =O21*70% -> 0 | Q21: =P21*K21 -> 0
A22: TRW-H1 | B22: TRW-H1XYG | C22: Hyundai H1 08- / Mover (Lubang) | D22: TRW | E22: XYG | F22: X/H/1Hole | G22: 1 | H22: 1 | I22: 0 | O22: =IFERROR(VLOOKUP(A22,BGI,14,FALSE),"") | P22: =O22*70% -> 0 | Q22: =P22*K22 -> 0
A23: LFW-SANTAFE12 | B23: LFW-SANTAFE12XYG | C23: Hyundai Santa Fe 12-18 | D23: LFW | E23: XYG | F23: X/MB | G23: 1 | H23: 1 | I23: 0 | O23: =IFERROR(VLOOKUP(A23,BGI,14,FALSE),"") | P23: =O23*70% -> 0 | Q23: =P23*K23 -> 0
A24: LFW-RUBICON18 | B24: LFW-RUBICON18XYG | C24: Jeep Wrangler Rubicon 18- JL | D24: LFW | E24: XYG | F24: X | G24: 1 | H24: 1 | I24: 0 | J24: B9T4 | O24: =IFERROR(VLOOKUP(A24,BGI,14,FALSE),"") | P24: =O24*70% -> 0 | Q24: =P24*K24 -> 0
A25: LFW-RIO11 | B25: LFW-RIO11XYG | C25: Kia Rio 11-17 UB Hatchback | D25: LFW | E25: XYG | F25: X/MB | G25: 1 | H25: 1 | I25: 0 | O25: =IFERROR(VLOOKUP(A25,BGI,14,FALSE),"") | P25: =O25*70% -> 0 | Q25: =P25*K25 -> 0
A26: LFW-SONET | B26: LFW-SONETXYG | C26: Kia Sonet 21- | D26: LFW | E26: XYG | F26: X/MB | G26: 1 | H26: 1 | I26: 0 | J26: A6T1 | K26: 1 | M26: 1 | O26: =IFERROR(VLOOKUP(A26,BGI,14,FALSE),"") | P26: =O26*70% -> 0 | Q26: =P26*K26 -> 0
A27: LFW-SORENTO | B27: LFW-SORENTOXYG | C27: Kia Sorento 09-14 2nd Gen | D27: LFW | E27: XYG | F27: X/MB | G27: 1 | H27: 1 | I27: 0 | O27: =IFERROR(VLOOKUP(A27,BGI,14,FALSE),"") | P27: =O27*70% -> 0 | Q27: =P27*K27 -> 0
A28: TRW-SPORTAGE10S | B28: TRW-SPORTAGE10SXYG | C28: Kia Sportage 10-15 SL [Tipe ada Spoiler] | D28: TRW | E28: XYG | F28: X/H/1Hole | G28: 1 | H28: 1 | I28: 0 | O28: =IFERROR(VLOOKUP(A28,BGI,14,FALSE),"") | P28: =O28*70% -> 0 | Q28: =P28*K28 -> 0
A29: LFW-XU30 | B29: LFW-XU30XYG | C29: Lexus RX (Harrier) 03-08 XU30 | D29: LFW | E29: XYG | F29: X/MB | G29: 1 | H29: 1 | I29: 0 | O29: =IFERROR(VLOOKUP(A29,BGI,14,FALSE),"") | P29: =O29*70% -> 0 | Q29: =P29*K29 -> 0
A30: TRW-MAZDA209 | B30: TRW-MAZDA209XYG | C30: Mazda 2 09-14 3rd Gen Hatchback | D30: TRW | E30: XYG | F30: X/H | G30: 2 | H30: 2 | I30: 0 | J30: A4T3 | O30: =IFERROR(VLOOKUP(A30,BGI,14,FALSE),"") | P30: =O30*70% -> 0 | Q30: =P30*K30 -> 0
A31: TRW-BIANTEBLACK | B31: TRW-BIANTEBLACKXYG | C31: Mazda Biante 08- (Hitam) | D31: TRW | E31: XYG | F31: X/H/1hole | G31: 2 | H31: 2 | I31: 0 | J31: B9T3 | O31: =IFERROR(VLOOKUP(A31,BGI,14,FALSE),"") | P31: =O31*70% -> 0 | Q31: =P31*K31 -> 0
A32: LFW-CX5GEN1RS | B32: LFW-CX5GEN1RSFY | C32: Mazda CX-5 .14-17 1st Gen KE Facelift - (3 Sensor/ /\8 ) | D32: LFW | E32: FY | F32: X/MB/A/RS/List | G32: 1 | H32: 1 | I32: 0 | O32: =IFERROR(VLOOKUP(A32,BGI,14,FALSE),"") | P32: =O32*70% -> 0 | Q32: =P32*K32 -> 0
A33: LFW-CX9GEN1 | B33: LFW-CX9GEN1XYG | C33: Mazda CX-9 07-15 1st Gen | D33: LFW | E33: XYG | F33: X/RS | G33: 1 | H33: 1 | I33: 0 | O33: =IFERROR(VLOOKUP(A33,BGI,14,FALSE),"") | P33: =O33*70% -> 0 | Q33: =P33*K33 -> 0
A34: LFW-W169 | B34: LFW-W169XYG | C34: Mers-Benz A150/170/A200 05-12 W169/ B-Class 05-11 W245 | D34: LFW | E34: XYG | F34: X/List | G34: 1 | H34: 1 | I34: 0 | O34: =IFERROR(VLOOKUP(A34,BGI,14,FALSE),"") | P34: =O34*70% -> 0 | Q34: =P34*K34 -> 0
A35: LFW-W176 | B35: LFW-W176XYG | C35: Mers-Benz A180/200/250 13-18 W176 / GLA 13-19 W156 | D35: LFW | E35: XYG | F35: X/MB/RS/List | G35: 1 | H35: 1 | I35: 0 | O35: =IFERROR(VLOOKUP(A35,BGI,14,FALSE),"") | P35: =O35*70% -> 0 | Q35: =P35*K35 -> 0
A36: LFW-W211 | B36: LFW-W211XYG | C36: Mers-Benz E-Class 02-09 W211 | D36: LFW | E36: XYG | F36: X/RS | G36: 1 | H36: 1 | I36: 0 | O36: =IFERROR(VLOOKUP(A36,BGI,14,FALSE),"") | P36: =O36*70% -> 0 | Q36: =P36*K36 -> 0
A37: LFW-W222 | B37: LFW-W222XYG | C37: Mers-Benz S-Class 13-20 W222 4D | D37: LFW | E37: XYG | F37: X/H/A/3S/List | G37: 1 | H37: 1 | I37: 0 | O37: =IFERROR(VLOOKUP(A37,BGI,14,FALSE),"") | P37: =O37*70% -> 0 | Q37: =P37*K37 -> 0
A38: LFW-L200DOUBLE | B38: LFW-L200DOUBLEXYG | C38: Mitsubishi L200 02-07 Double Cabin | D38: LFW | E38: XYG | F38: X/MB | G38: 1 | H38: 1 | I38: 0 | O38: =IFERROR(VLOOKUP(A38,BGI,14,FALSE),"") | P38: =O38*70% -> 0 | Q38: =P38*K38 -> 0
A39: TRW-PAJERO16 | B39: TRW-PAJERO16XYG | C39: Mitsubishi Pajero 16- | D39: TRW | E39: XYG | F39: X/H/1Hole | G39: 2 | H39: 2 | I39: 0 | J39: B14T3 | K39: 1 | M39: 1 | O39: =IFERROR(VLOOKUP(A39,BGI,14,FALSE),"") | P39: =O39*70% -> 0 | Q39: =P39*K39 -> 0
A40: TRW-LIVINA13 | B40: TRW-LIVINA13XYG | C40: Nissan Livina 13-18 L11 (Lubang) | D40: TRW | E40: XYG | F40: X/H | G40: 2 | H40: 2 | I40: 0 | J40: B10T3 | K40: 2 | M40: 1 | O40: =IFERROR(VLOOKUP(A40,BGI,14,FALSE),"") | P40: =O40*70% -> 0 | Q40: =P40*K40 -> 0
A41: TRW-C24 | B41: TRW-C24XYG | C41: Nissan Serena 99-10 MKII C24 | D41: TRW | E41: XYG | F41: X/H | G41: 1 | H41: 1 | I41: 0 | O41: =IFERROR(VLOOKUP(A41,BGI,14,FALSE),"") | P41: =O41*70% -> 0 | Q41: =P41*K41 -> 0
A42: LFW-TEANA | B42: LFW-TEANAXYG | C42: Nissan Teana 08-12 J32 | D42: LFW | E42: XYG | G42: 1 | H42: 1 | I42: 0 | O42: =IFERROR(VLOOKUP(A42,BGI,14,FALSE),"") | P42: =O42*70% -> 0 | Q42: =P42*K42 -> 0
A43: LFW-T30 | B43: LFW-T30XYG | C43: Nissan X-Trail 01-07 T30 | D43: LFW | E43: XYG | F43: X | G43: 1 | H43: 1 | I43: 0 | K43: 1 | M43: 3 | O43: =IFERROR(VLOOKUP(A43,BGI,14,FALSE),"") | P43: =O43*70% -> 0 | Q43: =P43*K43 -> 0
A44: TRW-BALENO96 | B44: TRW-BALENO96XYG | C44: Suzuki Baleno 96-01 | D44: TRW | E44: XYG | F44: X/H | G44: 1 | H44: 1 | I44: 0 | O44: =IFERROR(VLOOKUP(A44,BGI,14,FALSE),"") | P44: =O44*70% -> 0 | Q44: =P44*K44 -> 0
A45: LFW-SWIFT04 | B45: LFW-SWIFT04XYG | C45: Suzuki Swift 04-11 1st Gen | D45: LFW | E45: XYG | F45: X | G45: 4 | H45: 4 | I45: 0 | J45: B11T2 | K45: 1 | M45: 3 | O45: =IFERROR(VLOOKUP(A45,BGI,14,FALSE),"") | P45: =O45*70% -> 0 | Q45: =P45*K45 -> 0
A46: TRW-WAGON13 | B46: TRW-WAGON13XYG | C46: Suzuki Wagon R 12- | D46: TRW | E46: XYG | F46: X/H | G46: 2 | H46: 2 | I46: 0 | J46: B10T3 | O46: =IFERROR(VLOOKUP(A46,BGI,14,FALSE),"") | P46: =O46*70% -> 0 | Q46: =P46*K46 -> 0
A47: SWL-ALPHARD08HITAM | B47: SWL-ALPHARD08HITAMXYG | C47: Toyota Alphard 08-15 ANH20 2nd Gen (Hitam) | D47: SW/L | E47: XYG | F47: X/A | G47: 1 | H47: 1 | I47: 0 | O47: =IFERROR(VLOOKUP(A47,BGI,14,FALSE),"") | P47: =O47*70% -> 0 | Q47: =P47*K47 -> 0
A48: TRW-ALTIS06 | B48: TRW-ALTIS06XYG | C48: Toyota Altis 06-13 E140 10th Gen | D48: TRW | E48: XYG | F48: X/H/A/List | G48: 1 | H48: 1 | I48: 0 | O48: =IFERROR(VLOOKUP(A48,BGI,14,FALSE),"") | P48: =O48*70% -> 0 | Q48: =P48*K48 -> 0
A49: TRW-AVANZA03 | B49: TRW-AVANZA03XYG | C49: Toyota Avanza / Xenia 03-11 1st Gen | D49: TRW | E49: XYG | F49: X | G49: 20 | H49: 20 | I49: 0 | J49: B4T3 | K49: 3 | M49: 1 | O49: =IFERROR(VLOOKUP(A49,BGI,14,FALSE),"") | P49: =O49*70% -> 0 | Q49: =P49*K49 -> 0
A50: LFW-CAMRY06 | B50: LFW-CAMRY06XYG | C50: Toyota Camry 06-11 XV40 4th Gen | D50: LFW | E50: XYG | F50: X/MB | G50: 2 | H50: 2 | I50: 0 | J50: A1T2 | K50: 1 | M50: 3 | O50: =IFERROR(VLOOKUP(A50,BGI,14,FALSE),"") | P50: =O50*70% -> 0 | Q50: =P50*K50 -> 0
A51: LFW-COROLLA95 | B51: LFW-COROLLA95XYG | C51: Toyota Corolla All New AE111 95-02 8th Gen | D51: LFW | E51: XYG | F51: X | G51: 1 | H51: 1 | I51: 0 | O51: =IFERROR(VLOOKUP(A51,BGI,14,FALSE),"") | P51: =O51*70% -> 0 | Q51: =P51*K51 -> 0
A52: TRW-FORTUNER05BLACK | B52: TRW-FORTUNER05BLACKXYG | C52: Toyota Fortuner 05-15 1st Gen (Hitam) | D52: TRW | E52: XYG | F52: X/H | G52: 6 | H52: 6 | I52: 0 | J52: B9T3 | K52: 1 | M52: 1 | O52: =IFERROR(VLOOKUP(A52,BGI,14,FALSE),"") | P52: =O52*70% -> 0 | Q52: =P52*K52 -> 0
A53: TRW-FORTUNER15 | B53: TRW-FORTUNER15XYG | C53: Toyota Fortuner 15- 2nd Gen | D53: TRW | E53: XYG | F53: X/H/1Hole | G53: 1 | H53: 1 | I53: 0 | J53: B2T3 | K53: 1 | M53: 1 | O53: =IFERROR(VLOOKUP(A53,BGI,14,FALSE),"") | P53: =O53*70% -> 0 | Q53: =P53*K53 -> 0
A54: TRW-HIACE19 | B54: TRW-HIACE19XYG | C54: Toyota Hi-Ace 19- Premio (Hitam) (Tinggi 56.7cm) | D54: TRW | E54: XYG | F54: X/H/1Hole | G54: 2 | H54: 2 | I54: 0 | J54: A1T3 | K54: 1 | M54: 1 | O54: =IFERROR(VLOOKUP(A54,BGI,14,FALSE),"") | P54: =O54*70% -> 0 | Q54: =P54*K54 -> 0
A55: RVL-HILUX15 | B55: RVL-HILUX15XYG | C55: Toyota Hilux Pickup 15- (Revo) | D55: RV/L | E55: XYG | G55: 1 | H55: 1 | I55: 0 | O55: =IFERROR(VLOOKUP(A55,BGI,14,FALSE),"") | P55: =O55*70% -> 0 | Q55: =P55*K55 -> 0
A56: LFW-INNOVA04 | B56: LFW-INNOVA04XYG | C56: Toyota Innova 04-15 1st Gen | D56: LFW | E56: XYG | F56: X/MB | G56: 1 | H56: 1 | I56: 0 | J56: A2T1 | O56: =IFERROR(VLOOKUP(A56,BGI,14,FALSE),"") | P56: =O56*70% -> 0 | Q56: =P56*K56 -> 0
A57: TRW-INNOVA15H | B57: TRW-INNOVA15HXYG | C57: Toyota Innova 15- 2nd Gen | D57: TRW | E57: XYG | F57: X/H/1Hole | G57: 2 | H57: 2 | I57: 0 | J57: A3T3 | O57: =IFERROR(VLOOKUP(A57,BGI,14,FALSE),"") | P57: =O57*70% -> 0 | Q57: =P57*K57 -> 0
A58: LFW-FJ150 | B58: LFW-FJ150XYG | C58: Toyota LandCruiser Prado FJ150W 09- | D58: LFW | E58: XYG | F58: X/MB/RS/List | G58: 1 | H58: 1 | I58: 0 | O58: =IFERROR(VLOOKUP(A58,BGI,14,FALSE),"") | P58: =O58*70% -> 0 | Q58: =P58*K58 -> 0
A59: LFW-NAV07 | B59: LFW-NAV07XYG | C59: Toyota NAV1/Noah 07-17 | D59: LFW | E59: XYG | F59: X/MB | G59: 2 | H59: 2 | I59: 0 | J59: A1T2 | O59: =IFERROR(VLOOKUP(A59,BGI,14,FALSE),"") | P59: =O59*70% -> 0 | Q59: =P59*K59 -> 0
A60: TRW-NAV07 | B60: TRW-NAV07XYG | C60: Toyota NAV1/Noah 07-17 | D60: TRW | E60: XYG | F60: X/H | G60: 1 | H60: 1 | I60: 0 | O60: =IFERROR(VLOOKUP(A60,BGI,14,FALSE),"") | P60: =O60*70% -> 0 | Q60: =P60*K60 -> 0
A61: TRW-VIOS02 | B61: TRW-VIOS02XYG | C61: Toyota Vios 02-07 XP40 1st Gen | D61: TRW | E61: XYG | F61: X/H | G61: 1 | H61: 1 | I61: 0 | O61: =IFERROR(VLOOKUP(A61,BGI,14,FALSE),"") | P61: =O61*70% -> 0 | Q61: =P61*K61 -> 0
A62: TRW-VOXY | B62: TRW-VOXYXYG | C62: Toyota Voxy 17- (Hitam) | D62: TRW | E62: XYG | F62: X/H/1Hole | G62: 1 | H62: 1 | I62: 0 | O62: =IFERROR(VLOOKUP(A62,BGI,14,FALSE),"") | P62: =O62*70% -> 0 | Q62: =P62*K62 -> 0
A63: TRW-YARIS13 | B63: TRW-YARIS13XYG | C63: Toyota Yaris 13- 2nd Gen (Lampu C) XP150 | D63: TRW | E63: XYG | F63: X/H | G63: 2 | H63: 2 | I63: 0 | J63: B6T3 | O63: =IFERROR(VLOOKUP(A63,BGI,14,FALSE),"") | P63: =O63*70% -> 0 | Q63: =P63*K63 -> 0
A64: TRW-YARIS17 | B64: TRW-YARIS17XYG | C64: Toyota Yaris 18- 3rd Gen (Lampu -) XP151 | D64: TRW | E64: XYG | F64: X/H | G64: 2 | H64: 2 | I64: 0 | J64: B6T3 | O64: =IFERROR(VLOOKUP(A64,BGI,14,FALSE),"") | P64: =O64*70% -> 0 | Q64: =P64*K64 -> 0
A65: LFW-ALMAZRS | B65: LFW-ALMAZRSXYG | C65: Wuling Almaz (Sensor) | D65: LFW | E65: XYG | F65: X/MB/RS Cat | G65: 1 | H65: 1 | I65: 0 | O65: =IFERROR(VLOOKUP(A65,BGI,14,FALSE),"") | P65: =O65*70% -> 0 | Q65: =P65*K65 -> 0
A66: TRW-ALMAZ | B66: TRW-ALMAZXYG | C66: Wuling Almaz | D66: TRW | E66: XYG | F66: X | G66: 2 | H66: 2 | I66: 0 | J66: B13T3 | O66: =IFERROR(VLOOKUP(A66,BGI,14,FALSE),"") | P66: =O66*70% -> 0 | Q66: =P66*K66 -> 0
A67: LFW-FK40 | B67: LFW-FK40XYG | C67: Mitsubishi Fuso Fighter FK40 82-(PS190,220) | D67: LFW | E67: XYG | G67: 3 | H67: 3 | I67: 0 | J67: PETI | O67: =IFERROR(VLOOKUP(A67,BGI,14,FALSE),"") | P67: =O67*70% -> 0 | Q67: =P67*K67 -> 0
A68: LFW-E36 | B68: LFW-E36MU | C68: BMW 3 Series 90-99 E36 | D68: LFW | E68: MU | F68: X/MB | G68: 10 | H68: 10 | I68: 0 | J68: A6T2 | O68: =IFERROR(VLOOKUP(A68,BGI,14,FALSE),"") | P68: =O68*70% -> 0 | Q68: =P68*K68 -> 0
A69: LFW-E46NORS | B69: LFW-E46NORSMU | C69: BMW 3 Series 98-06 E46 | D69: LFW | E69: MU | F69: X/MB/Green | G69: 5 | H69: 5 | I69: 0 | J69: A6T2 | O69: =IFERROR(VLOOKUP(A69,BGI,14,FALSE),"") | P69: =O69*70% -> 0 | Q69: =P69*K69 -> 0
A70: LFW-QQ03 | B70: LFW-QQ03MU | C70: Chery QQ 03-15 S11 5D / Spark 98-05 | D70: LFW | E70: MU | F70: X/MB | G70: 1 | H70: 1 | I70: 0 | O70: =IFERROR(VLOOKUP(A70,BGI,14,FALSE),"") | P70: =O70*70% -> 0 | Q70: =P70*K70 -> 0
A71: LFW-AVEO08 | B71: LFW-AVEO08MU | C71: Chevrolet Aveo 08-11 T250 Hatch. (Kalos/Lova) (Pendek) Barina | D71: LFW | E71: MU | F71: X | G71: 5 | H71: 5 | I71: 0 | J71: A9T2 | O71: =IFERROR(VLOOKUP(A71,BGI,14,FALSE),"") | P71: =O71*70% -> 0 | Q71: =P71*K71 -> 0
A72: LFW-SPIN | B72: LFW-SPINMU | C72: Chevrolet Spin 12- | D72: LFW | E72: MU | F72: X/MB | G72: 5 | H72: 5 | I72: 0 | J72: A9T2 | O72: =IFERROR(VLOOKUP(A72,BGI,14,FALSE),"") | P72: =O72*70% -> 0 | Q72: =P72*K72 -> 0
A73: LFW-GRANMAX | B73: LFW-GRANMAXMU | C73: Daihatsu Gran Max / Luxio 07- | D73: LFW | E73: MU | F73: X | G73: 48 | H73: 48 | I73: 0 | J73: B8T1 | O73: =IFERROR(VLOOKUP(A73,BGI,14,FALSE),"") | P73: =O73*70% -> 0 | Q73: =P73*K73 -> 0
A74: LFW-SIRION1 | B74: LFW-SIRION1MU | C74: Daihatsu Sirion 04-10 1st Gen | D74: LFW | E74: MU | F74: X/MB | G74: 1 | H74: 1 | I74: 0 | O74: =IFERROR(VLOOKUP(A74,BGI,14,FALSE),"") | P74: =O74*70% -> 0 | Q74: =P74*K74 -> 0
A75: LFW-SIRION2 | B75: LFW-SIRION2MU | C75: Daihatsu Sirion 11-18 2nd Gen | D75: LFW | E75: MU | F75: X/MB | G75: 5 | H75: 5 | I75: 0 | J75: B8T2 | O75: =IFERROR(VLOOKUP(A75,BGI,14,FALSE),"") | P75: =O75*70% -> 0 | Q75: =P75*K75 -> 0
A76: LFW-TARUNA | B76: LFW-TARUNAMU | C76: Daihatsu Taruna | D76: LFW | E76: MU | F76: X | G76: 5 | H76: 5 | I76: 0 | J76: B8T2 | O76: =IFERROR(VLOOKUP(A76,BGI,14,FALSE),"") | P76: =O76*70% -> 0 | Q76: =P76*K76 -> 0
A77: LFW-FIESTA | B77: LFW-FIESTAMU | C77: Ford Fiesta 09-17 | D77: LFW | E77: MU | F77: X/MB | G77: 10 | H77: 10 | I77: 0 | J77: A3T1 | O77: =IFERROR(VLOOKUP(A77,BGI,14,FALSE),"") | P77: =O77*70% -> 0 | Q77: =P77*K77 -> 0
A78: LFW-RANGER11 | B78: LFW-RANGER11MU | C78: Ford Ranger 11- T6 /Mazda BT50 Sing/Doub Cabin | D78: LFW | E78: MU | F78: X/MB | G78: 5 | H78: 5 | I78: 0 | J78: A3T2 | O78: =IFERROR(VLOOKUP(A78,BGI,14,FALSE),"") | P78: =O78*70% -> 0 | Q78: =P78*K78 -> 0
A79: LFW-BRV16 | B79: LFW-BRV16MU | C79: Honda BR-V 16- | D79: LFW | E79: MU | G79: 10 | H79: 10 | I79: 0 | J79: B3T1 | N79: * 1pc *8 , 1pc KF | O79: =IFERROR(VLOOKUP(A79,BGI,14,FALSE),"") | P79: =O79*70% -> 0 | Q79: =P79*K79 -> 0
A80: LFW-CIVIC96 | B80: LFW-CIVIC96MU | C80: Honda Civic 96-00 SO4/SO6 (Ferio) | D80: LFW | E80: MU | F80: X/Green | G80: 5 | H80: 5 | I80: 0 | J80: B7T2 | O80: =IFERROR(VLOOKUP(A80,BGI,14,FALSE),"") | P80: =O80*70% -> 0 | Q80: =P80*K80 -> 0
A81: LFW-HRV14 | B81: LFW-HRV14MU | C81: Honda HR-V 14-21 5D SUV | D81: LFW | E81: MU | F81: X/MB/Blue | G81: 10 | H81: 10 | I81: 0 | J81: B6T2 | N81: 1pc pecah | O81: =IFERROR(VLOOKUP(A81,BGI,14,FALSE),"") | P81: =O81*70% -> 0 | Q81: =P81*K81 -> 0
A82: LFW-JAZZ01 | B82: LFW-JAZZ01MU | C82: Honda Jazz 01-07 1st Gen | D82: LFW | E82: MU | F82: X | G82: 10 | H82: 10 | I82: 0 | J82: B4T1 | K82: 1 | M82: 1 | N82: *2pcs baret tengah bawah, +- 20cm, terlihat | O82: =IFERROR(VLOOKUP(A82,BGI,14,FALSE),"") | P82: =O82*70% -> 0 | Q82: =P82*K82 -> 0
A83: LFW-JAZZ13 | B83: LFW-JAZZ13MU | C83: Honda Jazz 13- 3rd Gen | D83: LFW | E83: MU | F83: X/MB | G83: 10 | H83: 10 | I83: 0 | J83: B6T1 | K83: 1 | M83: 1 | O83: =IFERROR(VLOOKUP(A83,BGI,14,FALSE),"") | P83: =O83*70% -> 0 | Q83: =P83*K83 -> 0
A84: LFW-EXCEL94 | B84: LFW-EXCEL94MU | C84: Hyundai Accent/Excel/Cakra 94-01 Sedan | D84: LFW | E84: MU | F84: X | G84: 1 | H84: 1 | I84: 0 | J84: A10T2 | O84: =IFERROR(VLOOKUP(A84,BGI,14,FALSE),"") | P84: =O84*70% -> 0 | Q84: =P84*K84 -> 0
A85: LFW-ATOZ | B85: LFW-ATOZMU | C85: Hyundai Atoz | D85: LFW | E85: MU | F85: X | G85: 1 | H85: 1 | I85: 0 | O85: =IFERROR(VLOOKUP(A85,BGI,14,FALSE),"") | P85: =O85*70% -> 0 | Q85: =P85*K85 -> 0
A86: LFW-CHEROKEE | B86: LFW-CHEROKEEMU | C86: Jeep Cherooke 94-99 XJ | D86: LFW | E86: MU | F86: X/Blue | G86: 5 | H86: 5 | I86: 0 | J86: A7T2 | O86: =IFERROR(VLOOKUP(A86,BGI,14,FALSE),"") | P86: =O86*70% -> 0 | Q86: =P86*K86 -> 0
A87: LFW-GCHEROKEE | B87: LFW-GCHEROKEEMU | C87: Jeep Grand Cherooke 96-99 ZJ | D87: LFW | E87: MU | G87: 5 | H87: 5 | I87: 0 | J87: A7T2 | N87: * 5pc tdk ada MB *7 | O87: =IFERROR(VLOOKUP(A87,BGI,14,FALSE),"") | P87: =O87*70% -> 0 | Q87: =P87*K87 -> 0
A88: LFW-CAREN99 | B88: LFW-CAREN99MU | C88: Kia Caren 1 99-04 / Caren 2 04-12 | D88: LFW | E88: MU | F88: X/MB/Blue | G88: 5 | H88: 5 | I88: 0 | J88: A7T1 | O88: =IFERROR(VLOOKUP(A88,BGI,14,FALSE),"") | P88: =O88*70% -> 0 | Q88: =P88*K88 -> 0
A89: LFW-PREGIO | B89: LFW-PREGIOMU | C89: Kia Pregio Van 95- | D89: LFW | E89: MU | F89: X/MB/Logo | G89: 5 | H89: 5 | I89: 0 | J89: A7T1 | N89: 1pc ☆3 | O89: =IFERROR(VLOOKUP(A89,BGI,14,FALSE),"") | P89: =O89*70% -> 0 | Q89: =P89*K89 -> 0
A90: LFW-RIO00 | B90: LFW-RIO00MU | C90: Kia Rio 00-05 DC Sedan/Hatchback | D90: LFW | E90: MU | F90: X/MB | G90: 3 | H90: 3 | I90: 0 | J90: A7T1 | O90: =IFERROR(VLOOKUP(A90,BGI,14,FALSE),"") | P90: =O90*70% -> 0 | Q90: =P90*K90 -> 0
A91: LFW-SPORTAGE04 | B91: LFW-SPORTAGE04MU | C91: Kia Sportage 04-10 JE/KM | D91: LFW | E91: MU | F91: X/MB/Blue | G91: 3 | H91: 3 | I91: 0 | J91: A7T1 | O91: =IFERROR(VLOOKUP(A91,BGI,14,FALSE),"") | P91: =O91*70% -> 0 | Q91: =P91*K91 -> 0
A92: LFW-MAZDA209 | B92: LFW-MAZDA209MU | C92: Mazda 2 09-14 3rd Gen | D92: LFW | E92: MU | F92: X/MB | G92: 5 | H92: 5 | I92: 0 | J92: A4T1 | O92: =IFERROR(VLOOKUP(A92,BGI,14,FALSE),"") | P92: =O92*70% -> 0 | Q92: =P92*K92 -> 0
A93: LFW-INTERPLAY | B93: LFW-INTERPLAYMU | C93: Mazda INTERPLAY 1992-97 FHG | D93: LFW | E93: MU | G93: 5 | H93: 5 | I93: 0 | J93: A4T2 | N93: * 1pc kurang ceramic *8 | O93: =IFERROR(VLOOKUP(A93,BGI,14,FALSE),"") | P93: =O93*70% -> 0 | Q93: =P93*K93 -> 0
A94: LFW-LANTIS | B94: LFW-LANTISMU | C94: Ford Lynx/Liata Mazda Lantis/Familia | D94: LFW | E94: MU | F94: Green | G94: 3 | H94: 3 | I94: 0 | J94: A4T2 | O94: =IFERROR(VLOOKUP(A94,BGI,14,FALSE),"") | P94: =O94*70% -> 0 | Q94: =P94*K94 -> 0
A95: LFW-KUDA | B95: LFW-KUDAMU | C95: Mitsubishi Kuda 99-06 | D95: LFW | E95: MU | F95: Blue | G95: 5 | H95: 5 | I95: 0 | J95: B13T2 | O95: =IFERROR(VLOOKUP(A95,BGI,14,FALSE),"") | P95: =O95*70% -> 0 | Q95: =P95*K95 -> 0
A96: LFW-EVO3 | B96: LFW-EVO3MU | C96: Mitsubishi Lancer 91-96 LE41 CB4/5 (Evo3) | D96: LFW | E96: MU | F96: X/Green | G96: 3 | H96: 3 | I96: 0 | J96: B13T2 | O96: =IFERROR(VLOOKUP(A96,BGI,14,FALSE),"") | P96: =O96*70% -> 0 | Q96: =P96*K96 -> 0
A97: LFW-MIRAGE | B97: LFW-MIRAGEMU | C97: Mitsubishi Mirage 12- | D97: LFW | E97: MU | F97: X | G97: 5 | H97: 5 | I97: 0 | J97: B13T2 | O97: =IFERROR(VLOOKUP(A97,BGI,14,FALSE),"") | P97: =O97*70% -> 0 | Q97: =P97*K97 -> 0
A98: LFW-TRITON05 | B98: LFW-TRITON05MU | C98: Mitsubishi Strada Triton 08-15 | D98: LFW | E98: MU | F98: X/MB | G98: 10 | H98: 10 | I98: 0 | J98: B14T1 | O98: =IFERROR(VLOOKUP(A98,BGI,14,FALSE),"") | P98: =O98*70% -> 0 | Q98: =P98*K98 -> 0
A99: LFW-TRITON14 | B99: LFW-TRITON14MU | C99: Mitsubishi Strada Triton 16- | D99: LFW | E99: MU | F99: X/MB | G99: 10 | H99: 10 | I99: 0 | J99: B12T1 | O99: =IFERROR(VLOOKUP(A99,BGI,14,FALSE),"") | P99: =O99*70% -> 0 | Q99: =P99*K99 -> 0
A100: LFW-NAVARA97 | B100: LFW-NAVARA97MU | C100: Nissan Frontier Navara 97-04 D22 1st Gen | D100: LFW | E100: MU | G100: 2 | H100: 2 | I100: 0 | O100: =IFERROR(VLOOKUP(A100,BGI,14,FALSE),"") | P100: =O100*70% -> 0 | Q100: =P100*K100 -> 0
...

Sheet INV TTD A4
A1: SENTRA AUTOGLASS TANGERANG | J1: Tanggal | L1: 45895
A2: Ruko Permata Niaga II No. 17, Taman Royal I, Tanah Tinggi, Kota Tangerang 15119 | J2: Kepada Yth.
A3: (+62) 81288009878 | (+62) 81281161200 | J3: Tharina
J4: +62 857-1705-0327
D7: NOTA PENJUALAN
A9: INV | B9: H250120 | J9: NO POL | L9: -
A10: No | B10: Kode | C10: Nama Barang | H10: Qty | J10: Harga Satuan | L10: Jumlah
A11: 1 | B11: LFW-BRIOAGC | C11: =IFERROR(VLOOKUP(B11,Stock,3,FALSE),"") -> Honda Brio 10- / Mobilio 11- (Honda) | H11: 3 | I11: PC | J11: 1633333.3 | L11: =H11*J11 -> 4900000
C12: =IFERROR(VLOOKUP(B12,Stock,3,FALSE),"") | L12: =H12*J12 -> 0
C13: =IFERROR(VLOOKUP(B13,Stock,3,FALSE),"") | L13: =H13*J13 -> 0
C14: =IFERROR(VLOOKUP(B14,Stock,3,FALSE),"") | L14: =H14*J14 -> 0
C15: =IFERROR(VLOOKUP(B15,Stock,3,FALSE),"") | L15: =H15*J15 -> 0
C16: =IFERROR(VLOOKUP(B16,Stock,3,FALSE),"") | L16: =H16*J16 -> 0
C17: =IFERROR(VLOOKUP(B17,Stock,3,FALSE),"") | L17: =H17*J17 -> 0
B18: BCA 6041794388 an Alvin Wijaya | L18: =H18*J18 -> 0
K19: TOTAL | L19: =SUM(L11:L18) -> 4900000
D20: Penerima | F20: Kaca yang sudah dipesan/dipasang tidak dapat dibatalkan/dikembalikan. | K20: DEPOSIT | L20: 0
K21: NETTO | L21: =L19-L20 -> 4900000
K23: Ket
A24: Trust the Experts, Drive Safer and Clearer | D24: .................... | K24: LUNAS
A30: =A1 -> SENTRA AUTOGLASS TANGERANG | J30: Tanggal | L30: =L1 -> 45895
A31: =A2 -> Ruko Permata Niaga II No. 17, Taman Royal I, Tanah Tinggi, Kota Tangerang 15119 | J31: Kepada Yth.
A32: =A3 -> (+62) 81288009878 | (+62) 81281161200 | J32: =J3 -> Tharina
J33: =J4 -> +62 857-1705-0327
J34: =J5
J35: =J6
D36: NOTA PENJUALAN
A38: INV | B38: =B9 -> H250120 | J38: NO POL | L38: =L9 -> -
A39: No | B39: Kode | C39: Nama Barang | H39: Qty | J39: Harga Satuan | L39: Jumlah
A40: 1 | B40: =B11 -> LFW-BRIOAGC | C40: =IFERROR(VLOOKUP(B40,Stock,3,FALSE),"") -> Honda Brio 10- / Mobilio 11- (Honda) | H40: =H11 -> 3 | I40: PC | J40: =J11 -> 1633333.3 | L40: =H40*J40 -> 4900000
A41: =A12 | B41: =B12 | C41: =IFERROR(VLOOKUP(B41,Stock,3,FALSE),"") | H41: =H12 | I41: =I12 | J41: =J12 | L41: =H41*J41 -> 0
A42: =A13 | B42: =B13 | C42: =IFERROR(VLOOKUP(B42,Stock,3,FALSE),"") | H42: =H13 | I42: =I13 | J42: =J13 | L42: =H42*J42 -> 0
A43: =A14 | B43: =B14 | C43: =IFERROR(VLOOKUP(B43,Stock,3,FALSE),"") | H43: =H14 | I43: =I14 | J43: =J14 | L43: =H43*J43 -> 0
A44: =A15 | C44: =IFERROR(VLOOKUP(B44,Stock,3,FALSE),"") | H44: =H15 | I44: =I15 | J44: =J15 | L44: =H44*J44 -> 0
A45: =A16 | B45: =B16 | C45: =IFERROR(VLOOKUP(B45,Stock,3,FALSE),"") | H45: =H16 | I45: =I16 | J45: =J16 | L45: =H45*J45 -> 0
L46: =H46*J46 -> 0
A47: =A18 | B47: =B18 -> BCA 6041794388 an Alvin Wijaya | I47: =I18 | J47: =J18 | L47: =L18 -> 0
K48: TOTAL | L48: =L19 -> 4900000
D49: Penerima | F49: Kaca yang sudah dipesan/dipasang tidak dapat dibatalkan/dikembalikan. | K49: =K20 -> DEPOSIT | L49: =L20 -> 0
K50: NETTO | L50: =L21 -> 4900000
K52: Ket
A53: Trust the Experts, Drive Safer and Clearer | D53: .................... | K53: =K24 -> LUNAS
K54: =K25

Sheet INV TTD A4 KF
A1: SENTRA AUTOGLASS SURABAYA | J1: Tanggal | L1: 45661
A2: Jalan Simo Jawar No. 108, Simomulyo Baru, Sukomanunggal, Surabaya | J2: Kepada Yth.
A3: (+62) 81288009878 | sentraautoglass.sby@gmail.com | J3: P. Yazid
J4: +62 823-3491-8186
J5: Madura
D7: NOTA PENJUALAN
A9: INV | B9: A250013 | J9: NO POL | L9: W 1310 CL
A10: No | B10: Kode | C10: Nama Barang | H10: Qty | J10: Harga Satuan | L10: Jumlah
A11: 1 | B11: LFW-ERTIGA12MU | C11: =IFERROR(VLOOKUP(B11,Stock,3,FALSE),"") -> Suzuki Ertiga 12-18 1st Gen MPV | H11: 1 | I11: PC | J11: 1360000 | L11: =H11*J11 -> 1360000
A12: 2 | B12: FILM-40STD | C12: =IFERROR(VLOOKUP(B12,Stock,3,FALSE),"") -> Automotive Film Standard - Black 40% | H12: 1 | I12: X | J12: 350000 | L12: =H12*J12 -> 350000
C13: =IFERROR(VLOOKUP(B13,Stock,3,FALSE),"") | L13: =H13*J13 -> 0
C14: =IFERROR(VLOOKUP(B14,Stock,3,FALSE),"") | L14: =H14*J14 -> 0
C15: =IFERROR(VLOOKUP(B15,Stock,3,FALSE),"") | L15: =H15*J15 -> 0
L16: =H16*J16 -> 0
B17: BCA 6041794388 an Alvin Wijaya | L17: =H17*J17 -> 0
K18: TOTAL | L18: =SUM(L11:L17) -> 1710000
D19: Penerima | F19: Kaca yang sudah dipesan/dipasang tidak dapat dibatalkan/dikembalikan. | K19: DISKON
K20: NETTO | L20: =L18-L19 -> 1710000
K22: Ket
A23: Trust the Experts, Drive Safer and Clearer | D23: ....................
A31: SENTRA AUTOGLASS SURABAYA | J31: Tanggal | L31: =L1 -> 45661
A32: Jalan Simo Jawar No. 108, Simomulyo Baru, Sukomanunggal, Surabaya | J32: Kepada Yth.
A33: (+62) 81288009878 | sentraautoglass.sby@gmail.com | J33: =J3 -> P. Yazid
J34: =J4 -> +62 823-3491-8186
J35: =J5 -> Madura
D37: NOTA PENJUALAN
A39: INV | B39: =B9 -> A250013 | J39: NO POL | L39: =L9 -> W 1310 CL
A40: No | B40: Kode | C40: Nama Barang | H40: Qty | J40: Harga Satuan | L40: Jumlah
A41: 1 | B41: =B11 -> LFW-ERTIGA12MU | C41: =C11 -> Suzuki Ertiga 12-18 1st Gen MPV | H41: =H11 -> 1 | I41: =I11 -> PC | J41: =J11 -> 1360000 | L41: =H41*J41 -> 1360000
A42: =A12 -> 2 | B42: =B12 -> FILM-40STD | C42: =IFERROR(VLOOKUP(B42,Stock,3,FALSE),"") -> Automotive Film Standard - Black 40% | H42: =H12 -> 1 | I42: =I12 -> X | J42: =J12 -> 350000 | L42: =L12 -> 350000
A43: =A13 | B43: =B13 | C43: =IFERROR(VLOOKUP(B43,Stock,3,FALSE),"") | H43: =H13 | I43: =I13 | J43: =J13 | L43: =L13 -> 0
A44: =A14 | B44: =B14 | C44: =IFERROR(VLOOKUP(B44,Stock,3,FALSE),"") | H44: =H14 | I44: =I14 | J44: =J14 | L44: =L14 -> 0
A45: =A15 | B45: =B15 | C45: =IFERROR(VLOOKUP(B45,Stock,3,FALSE),"") | H45: =H15 | I45: =I15 | J45: =J15 | L45: =L15 -> 0
A46: =A16 | B46: =B16 | C46: =IFERROR(VLOOKUP(B46,Stock,3,FALSE),"") | H46: =H16 | I46: =I16 | J46: =J16 | L46: =L16 -> 0
A47: =A17 | B47: =B17 -> BCA 6041794388 an Alvin Wijaya | H47: =H17 | I47: =I17 | J47: =J17 | L47: =L17 -> 0
K48: TOTAL | L48: =L18 -> 1710000
D49: Penerima | F49: Kaca yang sudah dipesan/dipasang tidak dapat dibatalkan/dikembalikan. | K49: DISKON | L49: =L19
K50: NETTO | L50: =L20 -> 1710000
K52: Ket
A53: Trust the Experts, Drive Safer and Clearer | D53: .................... | K53: =K23

Sheet SURAT JALAN PRINT
A1: SENTRA AUTOGLASS TANGERANG | I1: Tanggal | L1: 46008
A2: Taman Royal, Ruko Permata Niaga 2. 17, Jl. Permata Raya Perumahan No.1 | I2: Kepada Yth.
A3: (+62) 812-8116-1200 | sentraautomotif@gmail.com | I3: SENTRA
I4: +62 812-8800-9878
I5: Bekasi
D7: SURAT JALAN
A9: NO | B9: SJTGRL250010
A10: No | B10: Kode | C10: Nama Barang | H10: Keterangan | L10: QTY
A11: 1 | B11: SWL-SIGRA16MU | C11: =IFERROR(VLOOKUP(B11,Stock,3,FALSE),"") -> Toyota Calya / Sigra 16- | L11: 5
A12: 2 | B12: SWR-SIGRA16MU | C12: =IFERROR(VLOOKUP(B12,Stock,3,FALSE),"") -> Toyota Calya / Sigra 16- | L12: 5
A13: 3 | B13: SWL-AVANZA11MU | C13: =IFERROR(VLOOKUP(B13,Stock,3,FALSE),"") -> Toyota Avanza / Xenia 11-15 2nd Gen / 15-21 3rd Gen | L13: 5
A14: 4 | B14: SWR-AVANZA11MU | C14: =IFERROR(VLOOKUP(B14,Stock,3,FALSE),"") -> Toyota Avanza / Xenia 11-15 2nd Gen / 15-21 3rd Gen | L14: 5
C15: =IFERROR(VLOOKUP(B15,Stock,3,FALSE),"")
C16: =IFERROR(VLOOKUP(B16,Stock,3,FALSE),"")
K17: Total | L17: =SUM(L10:L16) -> 20
E18: Penerima
B22: Trust the Experts, Drive Safer and Clearer | E22: ....................
A30: SENTRA AUTOGLASS TANGERANG | I30: Tanggal | L30: =L1 -> 46008
A31: Taman Royal, Ruko Permata Niaga 2. 17, Jl. Permata Raya Perumahan No.1 | I31: Kepada Yth.
A32: (+62) 812-8116-1200 | sentraautomotif@gmail.com | I32: =I3 -> SENTRA
I33: =I4 -> +62 812-8800-9878
I34: =I5 -> Bekasi
D36: SURAT JALAN
A38: NO | B38: =B9 -> SJTGRL250010
A39: No | B39: Kode | C39: Nama Barang | H39: Keterangan | L39: QTY
A40: =A11 -> 1 | B40: =B11 -> SWL-SIGRA16MU | C40: =IFERROR(VLOOKUP(B40,Stock,3,FALSE),"") -> Toyota Calya / Sigra 16- | L40: =L11 -> 5
A41: =A12 -> 2 | B41: =B12 -> SWR-SIGRA16MU | C41: =IFERROR(VLOOKUP(B41,Stock,3,FALSE),"") -> Toyota Calya / Sigra 16- | L41: =L12 -> 5
A42: =A13 -> 3 | B42: =B13 -> SWL-AVANZA11MU | C42: =IFERROR(VLOOKUP(B42,Stock,3,FALSE),"") -> Toyota Avanza / Xenia 11-15 2nd Gen / 15-21 3rd Gen | L42: =L13 -> 5
A43: =A14 -> 4 | B43: SWR-AVANZA11MU | C43: =IFERROR(VLOOKUP(B43,Stock,3,FALSE),"") -> Toyota Avanza / Xenia 11-15 2nd Gen / 15-21 3rd Gen | L43: =L14 -> 5
C44: =IFERROR(VLOOKUP(B44,Stock,3,FALSE),"")
C45: =IFERROR(VLOOKUP(B45,Stock,3,FALSE),"")
K46: Total | L46: =SUM(L39:L45) -> 20
E47: Penerima | J47: =J18
B51: Trust the Experts, Drive Safer and Clearer | E51: ....................

Sheet  INV TTD A4 PDF
A1: SENTRA AUTOGLASS BEKASI | J1: Tanggal | L1: 45809
A2: Jalan Chairil Anwar Ruko Kalimas Blok A No. 18, Margahayu, Bekasi Timur | J2: Kepada Yth.
A3: (+62) 81281161200 | sentrakacamobil@gmail.com | J3: Ka Robbi
J4: +62 858-9479-9402
J5: Bekasi
D7: NOTA PENJUALAN
A9: INV | B9: F250001 | J9: NO POL
A10: No | B10: Kode | C10: Nama Barang | H10: Qty | J10: Harga Satuan | L10: Jumlah
A11: 1 | B11: TRW-AGYA23ASH | C11: Toyota Agya/Ayla 23- 2nd Gen | H11: 1 | I11: PC | J11: 925000 | L11: =H11*J11 -> 925000
A12: 2 | B12: OTH-SERLMB | C12: =IFERROR(VLOOKUP(B12,Stock,3,FALSE),"") -> Lembur | H12: 1 | I12: X | J12: 100000 | L12: =H12*J12 -> 100000
C13: =IFERROR(VLOOKUP(B13,Stock,3,FALSE),"") | L13: =H13*J13 -> 0
C14: =IFERROR(VLOOKUP(B14,Stock,3,FALSE),"") | L14: =H14*J14 -> 0
C15: =IFERROR(VLOOKUP(B15,Stock,3,FALSE),"") | L15: =H15*J15 -> 0
C16: =IFERROR(VLOOKUP(B16,Stock,3,FALSE),"") | L16: =H16*J16 -> 0
L17: =H17*J17 -> 0
B18: BCA 6041794388 an Alvin Wijaya | L18: =H18*J18 -> 0
K19: TOTAL | L19: =SUM(L11:L18) -> 1025000
D20: Penerima | F20: Kaca yang sudah dipesan/dipasang tidak dapat dibatalkan/dikembalikan. | K20: DEPOSIT
K21: NETTO | L21: =L19-L20 -> 1025000
K23: Ket
A24: Trust the Experts, Drive Safer and Clearer | D24: ....................

Sheet SJ POLOS
J1: Tanggal | L1: 46052
J2: Kepada Yth.
D7: SURAT JALAN
A9: SJ | B9: SJTGRA260011
A10: No | B10: Kode | C10: Nama Barang | L10: QTY
C11: =IFERROR(VLOOKUP(B11,Stock,3,FALSE),"")
C12: =IFERROR(VLOOKUP(B12,Stock,3,FALSE),"")
C13: =IFERROR(VLOOKUP(B13,Stock,3,FALSE),"")
C14: =IFERROR(VLOOKUP(B14,Stock,3,FALSE),"")
C15: =IFERROR(VLOOKUP(B15,Stock,3,FALSE),"")
C16: =IFERROR(VLOOKUP(B16,Stock,3,FALSE),"")
C17: =IFERROR(VLOOKUP(B17,Stock,3,FALSE),"")
C18: =IFERROR(VLOOKUP(B18,Stock,3,FALSE),"")
C19: =IFERROR(VLOOKUP(B19,Stock,3,FALSE),"")
C20: =IFERROR(VLOOKUP(B20,Stock,3,FALSE),"")
C21: =IFERROR(VLOOKUP(B21,Stock,3,FALSE),"")
E23: Penerima | J23: Kaca yang sudah dipesan tidak dapat dibatalkan/dikembalikan.
E27: ....................

Sheet NOTA RETUR
A1: SENTRA AUTOGLASS SURABAYA | J1: Tanggal | L1: 45448
A2: Jalan Simo Jawar No. 108, Simomulyo Baru, Sukomanunggal, Surabaya | J2: Kepada Yth.
A3: (+62) 81288009878 | sentraautoglass.sby@gmail.com | J3: PT. Tirta Jaya Trapac
J4: +62 859-4120-4572
J5: Surabaya
D7: RETUR PENJUALAN
A9: INV : | B9: E240063 | C9: RETUR NO : RTN-F240001 | J9: NO POL
A10: No | B10: Kode | C10: Nama Barang | H10: Qty | J10: Harga Satuan | L10: Jumlah
A11: 1 | B11: TRW-HIACEBLACKXYG | C11: Rear Window Toyota Hi-Ace 04-20 Tempered | H11: 1 | I11: PC | J11: 780600 | L11: =H11*J11 -> 780600
L12: =H12*J12 -> 0
L13: =H13*J13 -> 0
B14: Return to | C14: BCA 4480245542 an Tirtahamidjaja Rahardja | L14: =H14*J14 -> 0
L15: =H15*J15 -> 0
L16: =H16*J16 -> 0
L17: =H17*J17 -> 0
K18: TOTAL | L18: =SUM(L11:L17) -> 780600
D19: Penerima | F19: Kaca yang sudah dipesan/dipasang tidak dapat dibatalkan/dikembalikan. | K19: DISKON | L19: 0
K20: NETTO | L20: =L18-L19 -> 780600
K22: Ket
A23: Trust the Experts, Drive Safer and Clearer | D23: ....................
H30: ,

Sheet TANDA TERIMA
A1: SENTRA AUTOGLASS | I1: Tanggal | L1: 07/02/2025
A2: Jalan Simo Jawar No. 108, Simomulyo Baru, Sukomanunggal, Surabaya | I2: Kepada Yth.
A3: (+62) 81288009878 | sentraautoglass.sby@gmail.com | I3: PT. BGI
I4: Surabaya
D7: TANDA TERIMA BARANG
A9: NO | B9: SJB250004
A10: No | B10: Kode | C10: Nama Barang | H10: Keterangan | L10: QTY
A11: 1 | B11: LFW-ODYSSEY13XYG | C11: =IFERROR(VLOOKUP(B11,Stock,3,FALSE),"") -> Honda Odyssey 13- 5th Gen RC1/RC2 | H11: - | L11: 1
C12: =IFERROR(VLOOKUP(B12,Stock,3,FALSE),"")
C13: =IFERROR(VLOOKUP(B13,Stock,3,FALSE),"")
C14: =IFERROR(VLOOKUP(B14,Stock,3,FALSE),"")
C15: =IFERROR(VLOOKUP(B15,Stock,3,FALSE),"")
K17: total | L17: =SUM(L11:L16) -> 1
E18: Penerima | J18: Kaca yang sudah dipesan tidak dapat dibatalkan/dikembalikan.
B22: Trust the Experts, Drive Safer and Clearer | E22: ....................

Sheet Inventory Dalam
A1: No. | B1: Nama Toolkit | C1: 45456
A2: 1. | B2: Obeng Kancing | C2: 4 PC
A3: 2. | B3: Kape Plastik Doortrim | C3: 3 Set (12 PC)
A4: 3. | B4: Seling | C4: 13 PC
A5: 4. | B5: Lem G / Lem Korea | C5: 12 PC
A6: 5. | B6: Lakban Fragile | C6: 8 PC
A7: 6. | B7: Gel Sensor Besar | C7: 2 PC
A8: 7. | B8: Gel Sensor Kecil | C8: 3 PC
A9: 8. | B9: Lakban Kertas | C9: 5 PC
A10: 9. | B10: Lakban Bening | C10: 4 PC
A11: 10. | B11: Double Tape Foam Kecil | C11: 5 PC
A12: 11. | B12: Double Tape Foam Besar | C12: 1 PC
A13: 12. | B13: Isi Cutter | C13: 4 Pack
... A44: 43. | B44: Kunci T 8mm | C44: 3 PC
A45: 44 | B45: Kanebo | C45: 20 PC
A46: 45 | B46: Cutter | C46: 5 PC
A47: 46 | B47: Solder Tembak | C47: 1 PC
A48: 47 | B48: Klip | C48: 1 Bungkus
A49: 48 | B49: Sealant Boyou B501 | C49: 20 Tube
A50: 49 | B50: Sealant R 68 | C50: 1 Tube
A51: 50 | B51: Seling Boyou | C51: 1 Roll
A52: 51 | B52: No Adhesiv Tape | C52: 1 PC
A53: 52 | B53: Kop Kaca 2 kaki | C53: 1 Set
A54: 53 | B54: Fender Cover Mobil | C54: 2 Set
A55: 54 | B55: Kuas | C55: 1 PC
A56: 55 | B56: Tinta Spidol Permanent | C56: 1 PC
A57: 56 | B57: Tinta Printer Hitam | C57: 1 PC

Sheet Sheet11
A1: No | B1: Nama Toolkit | C1: BOX 1 | D1: BOX 2
A2: 1. | B2: Lakban Merah | C2: 1 PC | D2: 1 PC
A3: 2. | B3: Lakban Bening | C3: 1 PC | D3: 1 PC
A4: 3. | B4: Lakban Kertas | C4: 1 PC
A5: 4. | B5: Lakban Foam Hijau | C5: 1 PC
A6: 5. | B6: Kape Plastik Doortrim | C6: 1 Set (4 PC)
A7: 6. | B7: Seling | C7: 1 Bungkus
A8: 7. | B8: Obeng Kancing
A9: 8. | B9: Asahan
A10: 9. | B10: Kape Dodot
A11: 10. | B11: Obeng +- Pendek
A12: 11. | B12: Set Kunci Bintang
A13: 12. | B13: Dodotan
A14: 13. | B14: Kape tusuk
A15: 14. | B15: Craker
A16: 15. | B16: Lem Epoxy
A17: 16. | B17: Kacamata
A18: 17. | B18: Sarung Tangan
A19: 18. | B19: Dumpkin
... A30: 29. | B30: Kuas

Sheet SPK
A1: SURAT PERINTAH KERJA
A2: PASANG KACA / JASA PASANG / BONGKAR POLA
A3: NO SPK 1 | B3: : | E3: TGL 1 : | J3: (1=admin) (2=teknisi) (3=konsumen)
A4: NAMA KONSUMEN 3 | B4: :
A5: ALAMAT 3 | B5: : | J5: CATATAN:
A6: NO TELP/WA 3 | B6: : | J6: - SPK wajib diisi sebelum dan sesudah pemasangan kaca mobil
A7: EMAIL 3 | B7: : | J7: - SPK diisi dengan kondisi sebenar-benarnya dan disaksikan oleh pihak konsumen
A8: BARANG BERHARGA 3 | B8: : | C8: ADA / TIDAK ADA | J8: - Dokumentasikan bila perlu dan infokan ke kantor
A9: MERK & TYPE MOBIL 1 | B9: : | J9: - SPK ini ditanda-tangani oleh pihak Kaca Mobil dan Konsumen agar menjadi
A10: NO POLISI 2 | B10: : | J10: bukti sah dari segala kondisi yang ada pada mobil
A11: PART, MERK, JENIS KACA 1 | B11: : | J11: - contoh kondisi = baik / patah / retak / regas / baret / tidak ada / dll
A12: SEALANT 1 | B12: :
A13: LIST KARET 2 | B13: : | C13: GANTI / TIDAK
A14: NAMA TEKSINI 2 | B14: : | D14: &
A15: KETERANGAN | C15: SEBELUM | F15: SESUDAH | J15: KETERANGAN | K15: SEBELUM | N15: SESUDAH
A16: DEPAN/BELAKANG | C16: KONDISI | D16: TECH | E16: CUST | F16: KONDISI | G16: TECH | H16: CUST | J16: KACA SAMPING | K16: KONDISI | L16: TECH | M16: CUST | N16: KONDISI | O16: TECH | P16: CUST
A17: KACA YG AKAN DIPASANG | J17: KACA YG AKAN DIPASANG
A18: SPION DALAM | J18: BAUT BAUT
A19: TUTUP TULANG KI/KA | J19: POWER WINDOW
A20: AKSESORIS LAIN | J20: REGULATOR
A21: WIPER KANAN/KIRI | J21: DUDUKAN KACA
A22: TUTUP WIPER KA/KI | J22: KARET RUN CHANNEL
A23: TALANG/PANGGANGAN | J23: TEST TURUN NAIK PW
A24: LIST/KARET | J24: TURUN NAIK KACA
A25: BODY ATAS & SAMPING | J25: BODY DISEKITAR
A26: KAP MOBIL | J26: LAIN LAIN/KM
A27: LIST SAMPING | J27: JAM PENGERJAAN
A28: SENSOR KACA | J28: Keterangan kondisi lain : | L28: ADMIN | N28: TEKNISI | O28: CUSTOMER
A29: LAIN-LAIN/KM
A30: JAM PENGERJAAN
A32: SURAT PERINTAH KERJA
A33: PASANG KACA / JASA PASANG / BONGKAR POLA
A34: NO SPK 1 | B34: : | E34: TGL 1 : | J34: (1=admin) (2=teknisi) (3=konsumen)
A35: NAMA KONSUMEN 3 | B35: :
A36: ALAMAT 3 | B36: : | J36: CATATAN:
A37: NO TELP/WA 3 | B37: : | J37: - SPK wajib diisi sebelum dan sesudah pemasangan kaca mobil
A38: EMAIL 3 | B38: : | J38: - SPK diisi dengan kondisi sebenar-benarnya dan disaksikan oleh pihak konsumen
A39: BARANG BERHARGA 3 | B39: : | C39: ADA / TIDAK ADA | J39: - Dokumentasikan bila perlu dan infokan ke kantor
A40: MERK & TYPE MOBIL 1 | B40: : | J40: - SPK ini ditanda-tangani oleh pihak Kaca Mobil dan Konsumen agar menjadi
A41: NO POLISI 2 | B41: : | J41: bukti sah dari segala kondisi yang ada pada mobil
A42: PART, MERK, JENIS KACA 1 | B42: :
A43: SEALANT 1 | B43: :
A44: LIST KARET 2 | B44: : | C44: GANTI / TIDAK | J44: contoh kondisi = baik / patah / retak / regas / baret / tidak ada / dll
A45: NAMA TEKSINI 2 | B45: : | D45: &
A46: KETERANGAN | C46: SEBELUM | F46: SESUDAH | J46: KETERANGAN | K46: SEBELUM | N46: SESUDAH
A47: DEPAN/BELAKANG | C47: KONDISI | D47: TECH | E47: CUST | F47: KONDISI | G47: TECH | H47: CUST | J47: KACA SAMPING | K47: KONDISI | L47: TECH | M47: CUST | N47: KONDISI | O47: TECH | P47: CUST
A48: KACA YG AKAN DIPASANG | J48: KACA YG AKAN DIPASANG
A49: SPION DALAM | J49: BAUT BAUT
A50: TUTUP TULANG KI/KA | J50: POWER WINDOW
A51: AKSESORIS LAIN | J51: REGULATOR
A52: WIPER KANAN/KIRI | J52: DUDUKAN KACA
A53: TUTUP WIPER KA/KI | J53: KARET RUN CHANNEL
A54: TALANG/PANGGANGAN | J54: TEST TURUN NAIK PW
A55: LIST/KARET | J55: TURUN NAIK KACA
A56: BODY ATAS & SAMPING | J56: BODY DISEKITAR
A57: KAP MOBIL | J57: LAIN LAIN/KM
A58: LIST SAMPING | J58: JAM PENGERJAAN
A59: SENSOR KACA | J59: Keterangan kondisi lain : | L59: ADMIN | N59: TEKNISI | O59: CUSTOMER
A60: LAIN-LAIN/KM
A61: JAM PENGERJAAN

Sheet Print alamat
A2: Aulia Mandiri Otopart jember (+62 823-3968-0618) JL LETJEND SUPRAPTO XVIII/4B KEBONSARI JEMBER
G18: DIKIRIM OLEH : SENTRA AUTOGLASS +62 812-8116-1200

Sheet Copy of Print alamat
G18: DIKIRIM OLEH : TRUMP 0812 9262 2276

Sheet KAS
A1: Tanggal | B1: Nama | C1: Ket | D1: Debit | E1: Kredit | F1: Sisa | G1: Input by | H1: Terima uang | I1: Cek
A2: Juni 2024
A3: 45478 | B3: Uang Kasir | D3: 250000 | F3: =D3-E3 -> 250000 | G3: Michelle | H3: Via & Lia
A4: 45478 | B4: Tambahan Uang Kasir | D4: 101000 | F4: =F3+D4-E4 -> 351000 | G4: Michelle | H4: Via & Lia
A5: 45506 | B5: Sisa penjualan | C5: Sisa kurang tf penjualan cash | D5: 148000 | F5: =F4+D5-E5 -> 499000
A6: 45506 | B6: Hilang | C6: Uang kasir hilang | E6: 499000 | F6: =F5+D6-E6 -> 0 | H6: Maling
A7: 45514 | B7: Uang Kasir | C7: Masuk | D7: 100000 | F7: =F6+D7-E7 -> 100000 | G7: Michelle
F8: =F7+D8-E8 -> 100000
F9: =F8+D9-E9 -> 100000
F10: =F9+D10-E10 -> 100000
F11: =F10+D11-E11 -> 100000
F12: =F11+D12-E12 -> 100000
F13: =F12+D13-E13 -> 100000
F14: =F13+D14-E14 -> 100000
F15: =F14+D15-E15 -> 100000
F16: =F15+D16-E16 -> 100000
F17: =F16+D17-E17 -> 100000
F18: =F17+D18-E18 -> 100000

Sheet MEMO
B1: PT Karunia Jaya Distribusindo | D1: Jalan Simo Jawar No. 108, Simomulyo Baru, Sukomanunggal, Surabaya
D2: (+62) 81288009878
C4: MEMO PENGAMBILAN BARANG
J6: Tanggal | L6: 45694
J7: Kepada Yth.
J8: PD Jaya Baru
J9: Di- Tempat
B11: Salam Hormat,
B13: Melalui memo ini mohon untuk diberikan 3TA21M-3RWS1B0 2pc dan 3TA21M-3RWSXT0 3pc
B14: Kepada tim kami atas nama Ade
B16: Mohon untuk memberikan Nota dalam amplop kepada tim kami.
B17: Terima kasih atas perhatian dan kerjasamanya.
J19: Hormat Kami
J23: ....................

Sheet peti jangan balik
A1: JANGAN DIBALIK - PETI HADAP ATAS | J1: JANGAN DIBALIK - PETI HADAP ATAS
A14: BARANG PECAH BELAH !! | J14: BARANG PECAH BELAH !!
A16: JANGAN BANTING | J16: JANGAN BANTING
A23: JANGAN DIBALIK - PETI HADAP ATAS | J23: JANGAN DIBALIK - PETI HADAP ATAS
A36: BARANG PECAH BELAH !! | J36: BARANG PECAH BELAH !!
A38: JANGAN BANTING | J38: JANGAN BANTING

Sheet PL APR24
A1: PROMO MULIA OKT 2022 | B1: MERK | C1: KATASIKI | D1: TYPE MOBIL | J1: <--COD+UT-LO% | L1: <--COD+IT-NT% | N1: <--COD+NT-DT% | P1: <--COD+DT-UTT%
E2: ORI OKT22 | F2: PPN 11% | G2: COD OKT22+ 15RB | H2: COD+20-39% | I2: RU | J2: PRM MIN.10 | K2: COD+40-60% | L2: PRM MIN. 5 | M2: COD+60-80% | N2: PRM MIN.3 | O2: COD+80-200% | P2: PRM 1PC | Q2: 0.005 | R2: PEMBULATAN | S2: BGI GROSS | T2: SELISIH
B3: DAIHATSU | C3: GM | D3: GRANDMAX 2008- | E3: 325000 | F3: =E3*1.11 -> 360750 | G3: =(F3*1.1)+15000 -> 411825 | H3: =G3* 1.3 -> 535372.5 | I3: 536000 | J3: 516000 | K3: =G3*1.542 -> 635034.15 | L3: 612000 | M3: =G3*1.801 -> 741696.82 | N3: 715000 | O3: =G3*1.96 -> 807177 | P3: 778000 | Q3: =P3*1.05 -> 816900 | R3: 817000 | S3: 855000 | T3: =R3-P3 -> 39000
B4: DAI/TOY | C4: AX020 | D4: AVANZA1/XENIA1 2003-11/TA04 | E4: 325000 | F4: =E4*1.11 -> 360750 | G4: =(F4*1.1)+15000 -> 411825 | H4: =G4* 1.3 -> 535372.5 | I4: 536000 | J4: 516000 | K4: =G4*1.542 -> 635034.15 | L4: 612000 | M4: =G4*1.66 -> 683629.5 | N4: 659000 | O4: =G4*1.731 -> 712869.07 | P4: 687000 | Q4: =P4*1.05 -> 721350 | R4: 70 | S4: 758000 | T4: =R4-P4 -> -686930
B5: DAI/TOY | C5: AX311 | D5: AVANZA2/XENIA2 2011-15/TA11 | E5: 325000 | F5: =E5*1.11 -> 360750 | G5: =(F5*1.1)+15000 -> 411825 | H5: =G5* 1.3 -> 535372.5 | I5: 536000 | J5: 516000 | K5: =G5*1.542 -> 635034.15 | L5: 612000 | M5: =G5*1.66 -> 683629.5 | N5: 659000 | O5: =G5*1.731 -> 712869.07 | P5: 687000 | Q5: =P5*1.05 -> 721350 | R5: 729000 | S5: 758000 | T5: =R5-P5 -> 42000
B6: DAI/TOY | C6: AG40 | D6: AVANZA3/XENIA3 2015-20/TA15 | E6: 325000 | F6: =E6*1.11 -> 360750 | G6: =(F6*1.1)+15000 -> 411825 | H6: =G6* 1.3 -> 535372.5 | I6: 536000 | J6: 516000 | K6: =G6*1.542 -> 635034.15 | L6: 612000 | M6: =G6*1.66 -> 683629.5 | N6: 659000 | O6: =G6*1.731 -> 712869.07 | P6: 687000 | Q6: =P6*1.05 -> 721350 | R6: 729000 | S6: 758000 | T6: =R6-P6 -> 42000
B7: DAI/TOY | C7: AX60 | D7: AVANZA4/XENIA4 2021-/TA21 NONRS | E7: 495000 | F7: =E7*1.11 -> 549450 | G7: =(F7*1.1)+15000 -> 619395 | H7: =G7* 1.32 -> 817601.4 | I7: 818000 | J7: 798000 | K7: =G7*1.555 -> 963159.22 | L7: 940000 | M7: =G7*1.737 -> 1075889.1 | N7: 1050000 | O7: =G7*1.8 -> 1114911 | P7: 1088000 | Q7: =P7*1.05 -> 1142400 | R7: 1154000 | S7: 1190000 | T7: =R7-P7 -> 66000
B8: DAI/TOY | C8: AY50 | D8: AGYA/AYLA 2013- | E8: 277000 | F8: =E8*1.11 -> 307470 | G8: =(F8*1.1)+15000 -> 353217 | H8: =G8* 1.433 -> 506159.96 | I8: 507000 | J8: 485000 | K8: =G8*1.75 -> 618129.75 | L8: 592000 | M8: =G8*1.821 -> 643208.16 | N8: 616000 | O8: =G8*1.889 -> 667226.91 | P8: 639000 | Q8: =P8*1.05 -> 670950 | R8: 678000 | S8: 700000 | T8: =R8-P8 -> 39000
B9: DAI/TOY | C9: CS80 | D9: CALYA/SIGRA 2016- | E9: 368000 | F9: =E9*1.11 -> 408480 | G9: =(F9*1.1)+15000 -> 464328 | H9: =G9* 1.25 -> 580410 | I9: 581000 | J9: 562000 | K9: =G9*1.5 -> 696492 | L9: 674000 | M9: =G9*1.751 -> 813038.33 | N9: 787000 | O9: =G9*1.856 -> 861792.77 | P9: 834000 | Q9: =P9*1.05 -> 875700 | R9: 885000 | S9: 919000 | T9: =R9-P9 -> 51000
B10: DAI/TOY | C10: D99 | D10: RUSH1/TERIOS1 2006-17 | E10: 398000 | F10: =E10*1.11 -> 441780 | G10: =(F10*1.1)+15000 -> 500958 | H10: =G10* 1.306 -> 654251.15 | I10: 655000 | J10: 635000 | K10: =G10*1.551 -> 776985.86 | L10: 754000 | M10: =G10*1.8 -> 901724.4 | N10: 875000 | O10: =G10*1.954 -> 978871.93 | P10: 950000 | Q10: =P10*1.05 -> 997500 | R10: 1008000 | S10: 1048000 | T10: =R10-P10 -> 58000
B11: DAI/TOY | C11: RUSH | D11: RUSH2/TERIOS2 2018- | E11: 404000 | F11: =E11*1.11 -> 448440 | G11: =F11*1.1 -> 493284 | H11: =G11* 1.301 -> 641762.48 | J11: 642000 | K11: =G11*1.55 -> 764590.2 | L11: 765000 | M11: =G11*1.751 -> 863740.28 | N11: 864000 | O11: =G11*1.822 -> 898763.45 | P11: 899000
B12: HONDA | C12: MBLO | D12: MOBILIO 2014- | E12: 398000 | F12: =E12*1.11 -> 441780 | G12: =(F12*1.1)+15000 -> 500958 | H12: =G12* 1.271 -> 636717.62 | I12: 637000 | J12: 618000 | K12: =G12*1.502 -> 752438.92 | L12: 730000 | M12: =G12*1.8 -> 901724.4 | N12: 875000 | O12: =G12*1.952 -> 977870.02 | P12: 949000 | Q12: =P12*1.05 -> 996450 | R12: 1006000 | S12: 1042000 | T12: =R12-P12 -> 57000
B13: HONDA | C13: HA2708(0) | D13: JAZZ1 2001-07 | E13: 441000 | F13: =E13*1.11 -> 489510 | G13: =(F13*1.1)+15000 -> 553461 | H13: =G13* 1.251 -> 692379.71 | I13: 639000 | J13: 674000 | K13: =G13*1.6 -> 885537.6 | L13: 862000 | M13: =G13*1.8 -> 996229.8 | N13: 970000 | O13: =G13*2.039 -> 1128507 | P13: 1098000 | Q13: =P13*1.05 -> 1152900 | R13: 1164000 | T13: =R13-P13 -> 66000
B14: HONDA | C14: JAZZ | D14: JAZZ2 2008-12 | E14: 515000 | F14: =E14*1.11 -> 571650 | G14: =(F14*1.1)+15000 -> 643815 | H14: =G14* 1.251 -> 805412.56 | I14: 806000 | J14: 787000 | K14: =G14*1.501 -> 966366.31 | L14: 944000 | M14: =G14*1.749 -> 1126032.4 | N14: 1073000 | O14: =G15*1.635 -> 1120512.9 | P14: 1096000 | Q14: =P14*1.05 -> 1150800 | R14: 1162000 | T14: =R14-P14 -> 66000
B15: HONDA | C15: HJAZZ | D15: JAZZ3 2013- | E15: 549000 | F15: =E15*1.11 -> 609390 | G15: =(F15*1.1)+15000 -> 685329 | H15: =G15* 1.305 -> 894354.34 | I15: 895000 | J15: 875000 | K15: =G15*1.484 -> 1017028.2 | L15: 995000 | M15: =G15*1.6 -> 1096526.4 | N15: 1100000 | O15: =G14*2 -> 1287630 | P15: 1258000 | Q15: =P15*1.05 -> 1320900 | R15: 13 | T15: =R15-P15 -> -1257987
B16: MITSUBISHI | C16: MS146(2) | D16: PAJEROSPORT1 2006-15 | E16: 374000 | F16: =E16*1.11 -> 415140 | G16: =(F16*1.1)+15000 -> 471654 | H16: =G16* 1.46 -> 688614.84 | I16: 689000 | J16: 667000 | K16: =G16*1.898 -> 895199.29 | L16: 867000 | M16: =G16*2.097 -> 989058.44 | N16: 958000 | O16: =G16*2.397 -> 1130554.6 | P16: 1095000 | Q16: =P16*1.05 -> 1149750 | T16: =R16-P16 -> -1095000
B17: MITSUBISHI | C17: MS146(0) | D17: TRITON 2006-15 | E17: 374000 | F17: =E17*1.11 -> 415140 | G17: =(F17*1.1)+15000 -> 471654 | H17: =G17* 1.46 -> 688614.84 | I17: 689000 | J17: 667000 | K17: =G17*1.898 -> 895199.29 | L17: 867000 | M17: =G17*2.097 -> 989058.44 | N17: 958000 | O17: =G17*2.397 -> 1130554.6 | P17: 1095000 | Q17: =P17*1.05 -> 1149750 | T17: =R17-P17 -> -1095000
B18: MITSUBISHI | C18: NTRI | D18: PAJEROSPORT2 2015- | E18: 398000 | F18: =E18*1.11 -> 441780 | G18: =(F18*1.1)+15000 -> 500958 | H18: =G18* 1.382 -> 692323.96 | I18: 693000 | J18: 672000 | K18: =G18*1.701 -> 852129.56 | L18: 827000 | M18: =G18*1.901 -> 952321.16 | N18: 924000 | O18: =G18*2.201 -> 1102608.6 | P18: 1070000 | Q18: =P18*1.05 -> 1123500 | T18: =R18-P18 -> -1070000
B19: MITSUBISHI | C19: NTRI(0) | D19: TRITON2 2015- | E19: 398000 | F19: =E19*1.11 -> 441780 | G19: =(F19*1.1)+15000 -> 500958 | H19: =G19* 1.382 -> 692323.96 | I19: 693000 | J19: 672000 | K19: =G19*1.701 -> 852129.56 | L19: 827000 | M19: =G19*1.901 -> 952321.16 | N19: 924000 | O19: =G19*2.201 -> 1102608.6 | P19: 1070000 | Q19: =P19*1.05 -> 1123500 | T19: =R19-P19 -> -1070000
B20: MITSUBISHI | C20: XPAND | D20: XPANDER 2018- | E20: 551000 | F20: =E20*1.11 -> 611610 | G20: =(F20*1.1)+15000 -> 687771 | H20: =G20* 1.251 -> 860401.52 | I20: 861000 | J20: 842000 | K20: =G20*1.501 -> 1032344.3 | L20: 1010000 | M20: =G20*1.731 -> 1190531.6 | N20: 1165000 | O20: =G20*1.805 -> 1241426.7 | P20: 1215000 | Q20: =P20*1.05 -> 1275750 | T20: =R20-P20 -> -1215000
B21: NISSAN | C21: LVN | D21: LIVINA 2007-18 | E21: 453000 | F21: =E21*1.11 -> 502830 | G21: =(F21*1.1)+15000 -> 568113 | H21: =G21* 1.251 -> 710709.36 | I21: 711000 | J21: 692000 | K21: =G21*1.5 -> 852169.5 | L21: 830000 | M21: =G21*1.751 -> 994765.86 | N21: 969000 | O21: =G21*1.789 -> 1016354.2 | P21: 990000 | Q21: =P21*1.05 -> 1039500 | T21: =R21-P21 -> -990000
B22: NISSAN | C22: XPAND | D22: LIVINA 2018- | E22: 551000 | F22: =E22*1.11 -> 611610 | G22: =(F22*1.1)+15000 -> 687771 | H22: =G22* 1.251 -> 860401.52 | I22: 861000 | J22: 842000 | K22: =G22*1.501 -> 1032344.3 | L22: 1010000 | M22: =G22*1.731 -> 1190531.6 | N22: 1165000 | O22: =G22*1.805 -> 1241426.7 | P22: 1215000 | Q22: =P22*1.05 -> 1275750 | T22: =R22-P22 -> -1215000
B23: SUZUKI | C23: FTR | D23: FUTURA/T120SS 1991-18 | E23: 270000 | F23: =E23*1.11 -> 299700 | G23: =(F23*1.1)+15000 -> 344670 | H23: =G23* 1.352 -> 465993.84 | I23: 466000 | J23: 446000 | K23: =G23*1.601 -> 551816.67 | L23: 528000 | M23: =G23*1.85 -> 637639.5 | N23: 610000 | O23: =G23*2.002 -> 690029.34 | P23: 660000 | Q23: =P23*1.05 -> 693000 | T23: =R23-P23 -> -660000
B24: SUZUKI | C24: SUFTR | D24: FUTURANEW/CARRYNEW 2019- | E24: 404000 | F24: =E24*1.11 -> 448440 | G24: =(F24*1.1)+15000 -> 508284 | H24: =G24* 1.25 -> 635355 | I24: 636000 | J24: 617000 | K24: =G24*1.4 -> 711597.6 | L24: 691000 | M24: =G24*1.5 -> 762426 | N24: 740000 | O24: =G24*1.571 -> 798514.16 | P24: 775000 | Q24: =P24*1.05 -> 813750 | T24: =R24-P24 -> -775000
B25: SUZUKI | C25: SUWAG | D25: KARIMUNWAGONR | E25: 396000 | F25: =E25*1.11 -> 439560 | G25: =(F25*1.1)+15000 -> 498516 | H25: =G25* 1.35 -> 672996.6 | I25: 673000 | J25: 653000 | K25: =G25*1.549 -> 772201.28 | L25: 749000 | M25: =G25*1.801 -> 897827.32 | N25: 871000 | O25: =G25*2.006 -> 1000023.1 | P25: 970000 | Q25: =P25*1.05 -> 1018500 | T25: =R25-P25 -> -970000
B26: SUZUKI | C26: APV | D26: APV 2004- | E26: 396000 | F26: =E26*1.11 -> 439560 | G26: =(F26*1.1)+15000 -> 498516 | H26: =G26* 1.261 -> 628628.68 | I26: 629000 | J26: 610000 | K26: =G26*1.501 -> 748272.52 | L26: 726000 | M26: =G26*1.751 -> 872901.52 | N26: 847000 | O26: =G26*1.921 -> 957649.24 | P26: 929000 | Q26: =P26*1.05 -> 975450 | T26: =R26-P26 -> -929000
B27: SUZUKI | C27: ERTG | D27: ERTIGA1 2013-17 | E27: 380000 | F27: =E27*1.11 -> 421800 | G27: =(F27*1.1)+15000 -> 478980 | H27: =G27* 1.25 -> 598725 | I27: 599000 | J27: 580000 | K27: =G27*1.5 -> 718470 | L27: 696000 | M27: =G27*1.75 -> 838215 | N27: 812000 | O27: =G27*1.872 -> 896650.56 | P27: 869000 | Q27: =P27*1.05 -> 912450 | T27: =R27-P27 -> -869000
B28: SUZUKI | C28: NERTG | D28: ERTIGA2 2018- | E28: 505000 | F28: =E28*1.11 -> 560550 | G28: =(F28*1.1)+15000 -> 631605 | H28: =G28* 1.337 -> 844455.89 | I28: 845000 | J28: 825000 | K28: =G28*1.553 -> 980882.56 | L28: 958000 | M28: =G28*1.824 -> 1152047.5 | N28: 1125000 | O28: =G28*1.783 -> 1126151.7 | P28: 1100000 | Q28: =P28*1.05 -> 1155000 | T28: =R28-P28 -> -1100000
B29: TOYOTA | C29: TT738 | D29: FORTUNER1/HILUX2 2005-15 | E29: 404000 | F29: =E29*1.11 -> 448440 | G29: =(F29*1.1)+15000 -> 508284 | H29: =G29* 1.301 -> 661277.48 | I29: 662000 | J29: 642000 | K29: =G29*1.55 -> 787840.2 | L29: 765000 | M29: =G29*1.802 -> 915927.77 | N29: 889000 | O29: =G29*2.006 -> 1019617.7 | P29: 990000 | Q29: =P29*1.05 -> 1039500 | T29: =R29-P29 -> -990000
B30: TOYOTA | C30: TT739 | D30: FORTUNER2/HILUX3 2015- | E30: 429000 | F30: =E30*1.11 -> 476190 | G30: =(F30*1.1)+15000 -> 538809 | H30: =G30* 1.401 -> 754871.41 | I30: 755000 | J30: 734000 | K30: =G30*1.5 -> 808213.5 | L30: 786000 | M30: =G30*1.75 -> 942915.75 | N30: 917000 | O30: =G30*2 -> 1077618 | P30: 1048000 | Q30: =P30*1.05 -> 1100400 | T30: =R30-P30 -> -1048000
B31: TOYOTA | C31: TOVIM | D31: VIOS1 2002-07 | E31: 435000 | F31: =E31*1.11 -> 482850 | G31: =(F31*1.1)+15000 -> 546135 | H31: =G31* 1.3 -> 709975.5 | I31: 710000 | J31: 691000 | K31: =G31*1.5 -> 819202.5 | L31: 797000 | M31: =G31*1.743 -> 951913.31 | N31: 926000 | O31: =G31*1.88 -> 1026733.8 | P31: 999000 | Q31: =P31*1.05 -> 1048950 | T31: =R31-P31 -> -999000
B32: TOYOTA | C32: NVIOS | D32: VIOS2 2007-13 | E32: 453000 | F32: =E32*1.11 -> 502830 | G32: =(F32*1.1)+15000 -> 568113 | H32: =G32* 1.301 -> 739115.01 | I32: 740000 | J32: 720000 | K32: =G32*1.5 -> 852169.5 | L32: 830000 | M32: =G32*1.751 -> 994765.86 | N32: 969000 | O32: =G32*1.961 -> 1114069.6 | P32: 1085000 | Q32: =P32*1.05 -> 1139250 | T32: =R32-P32 -> -1085000
B33: TOYOTA | C33: NLIMO | D33: VIOS3 2013- | E33: 459000 | F33: =E33*1.11 -> 509490 | G33: =(F33*1.1)+15000 -> 575439 | H33: =G33* 1.302 -> 749221.58 | I33: 750000 | J33: 730000 | K33: =G33*1.552 -> 893081.33 | L33: 870000 | M33: =G33*1.802 -> 1036941.1 | N33: 1010000 | O33: =G33*2.132 -> 1226835.9 | P33: 1195000 | Q33: =P33*1.05 -> 1254750 | T33: =R33-P33 -> -1195000
B34: TOYOTA | C34: YARIS | D34: YARIS1 2005-13 | E34: 466000 | F34: =E34*1.11 -> 517260 | G34: =(F34*1.1)+15000 -> 583986 | H34: =G34* 1.3 -> 759181.8 | I34: 760000 | J34: 740000 | K34: =G34*1.55 -> 905178.3 | L34: 882000 | M34: =G34*1.801 -> 1051758.8 | N34: 1025000 | O34: =G34*1.901 -> 1110157.4 | P34: 1082000 | Q34: =P34*1.05 -> 1136100 | T34: =R34-P34 -> -1082000
B35: TOYOTA | C35: NLIMO | D35: YARIS2 2013-17 | E35: 459000 | F35: =E35*1.11 -> 509490 | G35: =(F35*1.1)+15000 -> 575439 | H35: =G35* 1.302 -> 749221.58 | I35: 750000 | J35: 730000 | K35: =G35*1.552 -> 893081.33 | L35: 870000 | M35: =G35*1.802 -> 1036941.1 | N35: 1010000 | O35: =G35*2.132 -> 1226835.9 | P35: 1195000 | Q35: =P35*1.05 -> 1254750 | T35: =R35-P35 -> -1195000
B36: TOYOTA | C36: NLIMO | D36: YARIS3 2018- | E36: 459000 | F36: =E36*1.11 -> 509490 | G36: =(F36*1.1)+15000 -> 575439 | H36: =G36* 1.302 -> 749221.58 | I36: 750000 | J36: 730000 | K36: =G36*1.552 -> 893081.33 | L36: 870000 | M36: =G36*1.802 -> 1036941.1 | N36: 1010000 | O36: =G36*2.132 -> 1226835.9 | P36: 1195000 | Q36: =P36*1.05 -> 1254750 | T36: =R36-P36 -> -1195000
B37: TOYOTA | C37: IMV | D37: INNOVA1 2005-14 | E37: 392000 | F37: =E37*1.11 -> 435120 | G37: =(F37*1.1)+15000 -> 493632 | H37: =G37* 1.351 -> 666896.83 | I37: 667000 | J37: 647000 | K37: =G37*1.6 -> 789811.2 | L37: 766000 | M37: =G37*1.851 -> 913712.83 | N37: 886000 | O37: =G37*2.085 -> 1029222.7 | P37: 998000 | Q37: =P37*1.05 -> 1047900 | T37: =R37-P37 -> -998000
B38: TOYOTA | C38: INVN | D38: INNOVA2 2015- | E38: 522000 | F38: =E38*1.11 -> 579420 | G38: =(F38*1.1)+15000 -> 652362 | H38: =G38* 1.3 -> 848070.6 | I38: 849000 | J38: 829000 | K38: =G38*1.55 -> 1011161.1 | L38: 988000 | M38: =G38*1.801 -> 1174904 | N38: 1148000 | O38: =G38*1.931 -> 1259711 | P38: 1231000 | Q38: =P38*1.05 -> 1292550 | T38: =R38-P38 -> -1231000
B39: HINO | C39: HSL | D39: TRUCK LOUHAN | E39: 679000 | F39: =E39*1.11 -> 753690 | G39: =(F39*1.1)+15000 -> 844059 | H39: =G39* 1.33 -> 1122598.5 | I39: 1123000 | J39: 1103000 | K39: =G39*1.6 -> 1350494.4 | L39: 1327000 | M39: =G39*1.682 -> 1419707.2 | N39: 1395000 | O39: =G39*1.72 -> 1451781.5 | P39: 1426000 | Q39: =P39*1.05 -> 1497300 | T39: =R39-P39 -> -1426000
B40: HINO/TOY | C40: NDYNA | D40: TRUCK DUTRO/ NEWDYNA2004- | E40: 325000 | F40: =E40*1.11 -> 360750 | G40: =(F40*1.1)+15000 -> 411825 | H40: =G40* 1.401 -> 576966.82 | I40: 577000 | J40: 556000 | K40: =G40*1.751 -> 721105.57 | L40: 695000 | M40: =G40*2 -> 823650 | N40: 794000 | O40: =G40*2.205 -> 908074.12 | P40: 875000 | Q40: =P40*1.05 -> 918750 | T40: =R40-P40 -> -875000
B41: MITSUBISHI | C41: FK40 | D41: TRUCK FIGTHER/FK40 | E41: 573000 | F41: =E41*1.11 -> 636030 | G41: =(F41*1.1)+15000 -> 714633 | H41: =G41* 1.3 -> 929022.9 | I41: 930000 | J41: 910000 | K41: =G41*1.55 -> 1107681.1 | L41: 1085000 | M41: =G41*1.8 -> 1286339.4 | N41: 1260000 | O41: =G41*1.85 -> 1322071.1 | P41: 1295000 | Q41: =P41*1.05 -> 1359750 | T41: =R41-P41 -> -1295000
B42: MITSUBISHI | C42: MS700 | D42: TRUCK FE700 | E42: 325000 | F42: =E42*1.11 -> 360750 | G42: =(F42*1.1)+15000 -> 411825 | H42: =G42* 1.35 -> 555963.75 | I42: 556000 | J42: 536000 | K42: =G42*1.6 -> 658920 | L42: 635000 | M42: =G42*1.852 -> 762699.9 | N42: 735000 | O42: =G42*1.915 -> 788644.88 | P42: 760000 | Q42: =P42*1.05 -> 798000 | T42: =R42-P42 -> -760000
B43: MITSUBISHI | C43: FE300 | D43: TRUCK FE300 1994 | E43: 340000 | F43: =E43*1.11 -> 377400 | G43: =(F43*1.1)+15000 -> 430140 | H43: =G43* 1.341 -> 576817.74 | I43: 577000 | J43: 557000 | K43: =G43*1.601 -> 688654.14 | L43: 665000 | M43: =G43*1.849 -> 795328.86 | N43: 768000 | O43: =G43*2.163 -> 930392.82 | P43: 898000 | Q43: =P43*1.05 -> 942900 | T43: =R43-P43 -> -898000
